Workbook
Name ckpj8hfcjasd9vhm: 'DIRTY ESG DATA'!$A$1:$I$6045

Sheet FINAL - WITH MOMENTUM
A1: TICKER | B1: Year | C1: ESGCombinedScore | D1: EnvironmentPillarScore | E1: GovernancePillarScore | F1: SocialPillarScore | G1: ESG Momentum | H1: ESG Mom-Env | I1: ESG Mom - Gov | J1: ESG Mom - Social
A2: AAV CN EQUITY | B2: 2021 | C2: 0.32801626 | D2: 0.27423839 | E2: 0.51237323 | F2: 0.26886706 | G2: =IF(A2<>A1,C2-0,C2-C1) -> 0.32801626 | H2: =IF(A2<>A1,D2-0,D2-D1) -> 0.27423839 | I2: =IF(A2<>A1,E2-0,E2-E1) -> 0.51237323 | J2: =IF(A2<>A1,F2-0,F2-F1) -> 0.26886706
A3: AAV CN EQUITY | B3: 2022 | C3: 0.41035629 | D3: 0.28529917 | E3: 0.56397363 | F3: 0.42706643 | G3: =IF(A3<>A2,C3-0,C3-C2) -> 0.082340022 | H3: =IF(A3<>A2,D3-0,D3-D2) -> 0.011060785 | I3: =IF(A3<>A2,E3-0,E3-E2) -> 0.051600405 | J3: =IF(A3<>A2,F3-0,F3-F2) -> 0.15819937
A4: AAV CN EQUITY | B4: 2023 | C4: 0.38751429 | D4: 0.27132183 | E4: 0.52778796 | F4: 0.40441631 | G4: =IF(A4<>A3,C4-0,C4-C3) -> -0.022841996 | H4: =IF(A4<>A3,D4-0,D4-D3) -> -0.013977347 | I4: =IF(A4<>A3,E4-0,E4-E3) -> -0.036185668 | J4: =IF(A4<>A3,F4-0,F4-F3) -> -0.022650115
A5: AAV CN EQUITY | B5: 2024 | C5: 0.375051 | D5: 0.26750334 | E5: 0.45098611 | F5: 0.42092097 | G5: =IF(A5<>A4,C5-0,C5-C4) -> -0.01246329 | H5: =IF(A5<>A4,D5-0,D5-D4) -> -0.0038184837 | I5: =IF(A5<>A4,E5-0,E5-E4) -> -0.076801851 | J5: =IF(A5<>A4,F5-0,F5-F4) -> 0.01650466
A6: AC CN EQUITY | B6: 2014 | C6: 0.47337539 | D6: 0.34599989 | E6: 0.61867288 | F6: 0.46985388 | G6: =IF(A6<>A5,C6-0,C6-C5) -> 0.47337539 | H6: =IF(A6<>A5,D6-0,D6-D5) -> 0.34599989 | I6: =IF(A6<>A5,E6-0,E6-E5) -> 0.61867288 | J6: =IF(A6<>A5,F6-0,F6-F5) -> 0.46985388
A7: AC CN EQUITY | B7: 2015 | C7: 0.44113341 | D7: 0.36070612 | E7: 0.69112079 | F7: 0.61321137 | G7: =IF(A7<>A6,C7-0,C7-C6) -> -0.032241978 | H7: =IF(A7<>A6,D7-0,D7-D6) -> 0.014706225 | I7: =IF(A7<>A6,E7-0,E7-E6) -> 0.072447912 | J7: =IF(A7<>A6,F7-0,F7-F6) -> 0.14335749
A8: AC CN EQUITY | B8: 2016 | C8: 0.5512753 | D8: 0.33358586 | E8: 0.7360353 | F8: 0.58842892 | G8: =IF(A8<>A7,C8-0,C8-C7) -> 0.11014189 | H8: =IF(A8<>A7,D8-0,D8-D7) -> -0.027120259 | I8: =IF(A8<>A7,E8-0,E8-E7) -> 0.044914504 | J8: =IF(A8<>A7,F8-0,F8-F7) -> -0.024782449
A9: AC CN EQUITY | B9: 2017 | C9: 0.61598381 | D9: 0.44964349 | E9: 0.79584639 | F9: 0.61809747 | G9: =IF(A9<>A8,C9-0,C9-C8) -> 0.064708513 | H9: =IF(A9<>A8,D9-0,D9-D8) -> 0.11605764 | I9: =IF(A9<>A8,E9-0,E9-E8) -> 0.059811099 | J9: =IF(A9<>A8,F9-0,F9-F8) -> 0.029668545
A10: AC CN EQUITY | B10: 2018 | C10: 0.40669482 | D10: 0.50891298 | E10: 0.8389932 | F10: 0.61909178 | G10: =IF(A10<>A9,C10-0,C10-C9) -> -0.209289 | H10: =IF(A10<>A9,D10-0,D10-D9) -> 0.059269488 | I10: =IF(A10<>A9,E10-0,E10-E9) -> 0.043146802 | J10: =IF(A10<>A9,F10-0,F10-F9) -> 0.00099431464
A11: AC CN EQUITY | B11: 2019 | C11: 0.49096424 | D11: 0.53867464 | E11: 0.86833679 | F11: 0.66234647 | G11: =IF(A11<>A10,C11-0,C11-C10) -> 0.084269425 | H11: =IF(A11<>A10,D11-0,D11-D10) -> 0.029761655 | I11: =IF(A11<>A10,E11-0,E11-E10) -> 0.029343595 | J11: =IF(A11<>A10,F11-0,F11-F10) -> 0.043254689
A12: AC CN EQUITY | B12: 2020 | C12: 0.61702698 | D12: 0.55796162 | E12: 0.86866569 | F12: 0.60685149 | G12: =IF(A12<>A11,C12-0,C12-C11) -> 0.12606274 | H12: =IF(A12<>A11,D12-0,D12-D11) -> 0.019286982 | I12: =IF(A12<>A11,E12-0,E12-E11) -> 0.00032889644 | J12: =IF(A12<>A11,F12-0,F12-F11) -> -0.055494985
A13: AC CN EQUITY | B13: 2021 | C13: 0.43034235 | D13: 0.63042647 | E13: 0.77109226 | F13: 0.66029355 | G13: =IF(A13<>A12,C13-0,C13-C12) -> -0.18668462 | H13: =IF(A13<>A12,D13-0,D13-D12) -> 0.072464855 | I13: =IF(A13<>A12,E13-0,E13-E12) -> -0.097573427 | J13: =IF(A13<>A12,F13-0,F13-F12) -> 0.053442065
... A290: BRE CN EQUITY | B290: 2022 | C290: 0.21300165 | D290: 0.14347436 | E290: 0.10643395 | F290: 0.37098112 | G290: =IF(A290<>A289,C290-0,C290-C289) -> -0.054933712 | H290: =IF(A290<>A289,D290-0,D290-D289) -> -0.020032824 | I290: =IF(A290<>A289,E290-0,E290-E289) -> 0.0079214409 | J290: =IF(A290<>A289,F290-0,F290-F289) -> -0.14274524
A291: BRE CN EQUITY | B291: 2024 | C291: 0.014022102 | D291: 0.010504025 | E291: 0.032847222 | F291: #N/A | G291: =IF(A291<>A290,C291-0,C291-C290) -> -0.19897955 | H291: =IF(A291<>A290,D291-0,D291-D290) -> -0.13297034 | I291: =IF(A291<>A290,E291-0,E291-E290) -> -0.073586727 | J291: =IF(A291<>A290,F291-0,F291-F290) -> #N/A
A292: BTB-U CN EQUITY | B292: 2020 | C292: 0.083188111 | D292: 0 | E292: 0.22581768 | F292: 0.034644807 | G292: =IF(A292<>A291,C292-0,C292-C291) -> 0.083188111 | H292: =IF(A292<>A291,D292-0,D292-D291) -> 0 | I292: =IF(A292<>A291,E292-0,E292-E291) -> 0.22581768 | J292: =IF(A292<>A291,F292-0,F292-F291) -> 0.034644807
A293: BTB-U CN EQUITY | B293: 2021 | C293: 0.10689827 | D293: 0.043806882 | E293: 0.22251521 | F293: 0.062153535 | G293: =IF(A293<>A292,C293-0,C293-C292) -> 0.023710155 | H293: =IF(A293<>A292,D293-0,D293-D292) -> 0.043806882 | I293: =IF(A293<>A292,E293-0,E293-E292) -> -0.0033024627 | J293: =IF(A293<>A292,F293-0,F293-F292) -> 0.027508728
A294: BTB-U CN EQUITY | B294: 2022 | C294: 0.1559515 | D294: 0.092722741 | E294: 0.31396304 | F294: 0.06622346 | G294: =IF(A294<>A293,C294-0,C294-C293) -> 0.049053232 | H294: =IF(A294<>A293,D294-0,D294-D293) -> 0.04891586 | I294: =IF(A294<>A293,E294-0,E294-E293) -> 0.091447826 | J294: =IF(A294<>A293,F294-0,F294-F293) -> 0.0040699251
A295: BTB-U CN EQUITY | B295: 2023 | C295: 0.25029394 | D295: 0.16059154 | E295: 0.30128783 | F295: 0.30744545 | G295: =IF(A295<>A294,C295-0,C295-C294) -> 0.094342446 | H295: =IF(A295<>A294,D295-0,D295-D294) -> 0.067868803 | I295: =IF(A295<>A294,E295-0,E295-E294) -> -0.012675212 | J295: =IF(A295<>A294,F295-0,F295-F294) -> 0.24122199
A296: BTB-U CN EQUITY | B296: 2024 | C296: 0.29213154 | D296: 0.22489308 | E296: 0.37315278 | F296: 0.28938747 | G296: =IF(A296<>A295,C296-0,C296-C295) -> 0.041837595 | H296: =IF(A296<>A295,D296-0,D296-D295) -> 0.064301537 | I296: =IF(A296<>A295,E296-0,E296-E295) -> 0.071864951 | J296: =IF(A296<>A295,F296-0,F296-F295) -> -0.018057979
A297: BTE CN EQUITY | B297: 2014 | C297: 0.34320423 | D297: 0.28131842 | E297: 0.34698959 | F297: 0.39197833 | G297: =IF(A297<>A296,C297-0,C297-C296) -> 0.34320423 | H297: =IF(A297<>A296,D297-0,D297-D296) -> 0.28131842 | I297: =IF(A297<>A296,E297-0,E297-E296) -> 0.34698959 | J297: =IF(A297<>A296,F297-0,F297-F296) -> 0.39197833
A298: BTE CN EQUITY | B298: 2015 | C298: 0.40157941 | D298: 0.30207565 | E298: 0.62142439 | F298: 0.36013672 | G298: =IF(A298<>A297,C298-0,C298-C297) -> 0.058375184 | H298: =IF(A298<>A297,D298-0,D298-D297) -> 0.02075723 | I298: =IF(A298<>A297,E298-0,E298-E297) -> 0.27443481 | J298: =IF(A298<>A297,F298-0,F298-F297) -> -0.031841613
A299: BTE CN EQUITY | B299: 2016 | C299: 0.38045257 | D299: 0.27024347 | E299: 0.42176893 | F299: 0.44792377 | G299: =IF(A299<>A298,C299-0,C299-C298) -> -0.021126841 | H299: =IF(A299<>A298,D299-0,D299-D298) -> -0.031832176 | I299: =IF(A299<>A298,E299-0,E299-E298) -> -0.19965546 | J299: =IF(A299<>A298,F299-0,F299-F298) -> 0.087787052
A300: BTE CN EQUITY | B300: 2017 | C300: 0.34381415 | D300: 0.28471128 | E300: 0.28918495 | F300: 0.4230553 | G300: =IF(A300<>A299,C300-0,C300-C299) -> -0.036638422 | H300: =IF(A300<>A299,D300-0,D300-D299) -> 0.014467812 | I300: =IF(A300<>A299,E300-0,E300-E299) -> -0.13258398 | J300: =IF(A300<>A299,F300-0,F300-F299) -> -0.024868469
A301: BTE CN EQUITY | B301: 2018 | C301: 0.3929047 | D301: 0.27682418 | E301: 0.61812036 | F301: 0.36208365 | G301: =IF(A301<>A300,C301-0,C301-C300) -> 0.049090556 | H301: =IF(A301<>A300,D301-0,D301-D300) -> -0.0078871061 | I301: =IF(A301<>A300,E301-0,E301-E300) -> 0.3289354 | J301: =IF(A301<>A300,F301-0,F301-F300) -> -0.060971656
A302: BTE CN EQUITY | B302: 2019 | C302: 0.41963842 | D302: 0.31908787 | E302: 0.67417062 | F302: 0.35960587 | G302: =IF(A302<>A301,C302-0,C302-C301) -> 0.026733718 | H302: =IF(A302<>A301,D302-0,D302-D301) -> 0.042263691 | I302: =IF(A302<>A301,E302-0,E302-E301) -> 0.05605026 | J302: =IF(A302<>A301,F302-0,F302-F301) -> -0.0024777798
A303: BTE CN EQUITY | B303: 2020 | C303: 0.53842405 | D303: 0.41263081 | E303: 0.93891367 | F303: 0.41730656 | G303: =IF(A303<>A302,C303-0,C303-C302) -> 0.11878563 | H303: =IF(A303<>A302,D303-0,D303-D302) -> 0.093542939 | I303: =IF(A303<>A302,E303-0,E303-E302) -> 0.26474306 | J303: =IF(A303<>A302,F303-0,F303-F302) -> 0.05770069
... A2095: XTC CN EQUITY | B2095: 2024 | C2095: 0.24393174 | D2095: 0.085651007 | E2095: 0.24609722 | F2095: 0.37258632 | G2095: =IF(A2095<>A2094,C2095-0,C2095-C2094) -> -0.017835029 | H2095: =IF(A2095<>A2094,D2095-0,D2095-D2094) -> -0.0033593059 | I2095: =IF(A2095<>A2094,E2095-0,E2095-E2094) -> -0.028701517 | J2095: =IF(A2095<>A2094,F2095-0,F2095-F2094) -> -0.023346151
G2096: =IF(A2096<>A2095,C2096-0,C2096-C2095) -> 0 | H2096: =IF(A2096<>A2095,D2096-0,D2096-D2095) -> 0 | I2096: =IF(A2096<>A2095,E2096-0,E2096-E2095) -> 0 | J2096: =IF(A2096<>A2095,F2096-0,F2096-F2095) -> 0
G2097: =IF(A2097<>A2096,C2097-0,C2097-C2096) -> 0 | H2097: =IF(A2097<>A2096,D2097-0,D2097-D2096) -> 0 | I2097: =IF(A2097<>A2096,E2097-0,E2097-E2096) -> 0 | J2097: =IF(A2097<>A2096,F2097-0,F2097-F2096) -> 0
G2098: =IF(A2098<>A2097,C2098-0,C2098-C2097) -> 0 | H2098: =IF(A2098<>A2097,D2098-0,D2098-D2097) -> 0 | I2098: =IF(A2098<>A2097,E2098-0,E2098-E2097) -> 0 | J2098: =IF(A2098<>A2097,F2098-0,F2098-F2097) -> 0
G2099: =IF(A2099<>A2098,C2099-0,C2099-C2098) -> 0 | H2099: =IF(A2099<>A2098,D2099-0,D2099-D2098) -> 0 | I2099: =IF(A2099<>A2098,E2099-0,E2099-E2098) -> 0 | J2099: =IF(A2099<>A2098,F2099-0,F2099-F2098) -> 0
G2100: =IF(A2100<>A2099,C2100-0,C2100-C2099) -> 0 | H2100: =IF(A2100<>A2099,D2100-0,D2100-D2099) -> 0 | I2100: =IF(A2100<>A2099,E2100-0,E2100-E2099) -> 0 | J2100: =IF(A2100<>A2099,F2100-0,F2100-F2099) -> 0
G2101: =IF(A2101<>A2100,C2101-0,C2101-C2100) -> 0 | H2101: =IF(A2101<>A2100,D2101-0,D2101-D2100) -> 0 | I2101: =IF(A2101<>A2100,E2101-0,E2101-E2100) -> 0 | J2101: =IF(A2101<>A2100,F2101-0,F2101-F2100) -> 0
G2102: =IF(A2102<>A2101,C2102-0,C2102-C2101) -> 0 | H2102: =IF(A2102<>A2101,D2102-0,D2102-D2101) -> 0 | I2102: =IF(A2102<>A2101,E2102-0,E2102-E2101) -> 0 | J2102: =IF(A2102<>A2101,F2102-0,F2102-F2101) -> 0
G2103: =IF(A2103<>A2102,C2103-0,C2103-C2102) -> 0 | H2103: =IF(A2103<>A2102,D2103-0,D2103-D2102) -> 0 | I2103: =IF(A2103<>A2102,E2103-0,E2103-E2102) -> 0 | J2103: =IF(A2103<>A2102,F2103-0,F2103-F2102) -> 0
G2104: =IF(A2104<>A2103,C2104-0,C2104-C2103) -> 0 | H2104: =IF(A2104<>A2103,D2104-0,D2104-D2103) -> 0 | I2104: =IF(A2104<>A2103,E2104-0,E2104-E2103) -> 0 | J2104: =IF(A2104<>A2103,F2104-0,F2104-F2103) -> 0
G2105: =IF(A2105<>A2104,C2105-0,C2105-C2104) -> 0 | H2105: =IF(A2105<>A2104,D2105-0,D2105-D2104) -> 0 | I2105: =IF(A2105<>A2104,E2105-0,E2105-E2104) -> 0 | J2105: =IF(A2105<>A2104,F2105-0,F2105-F2104) -> 0
G2106: =IF(A2106<>A2105,C2106-0,C2106-C2105) -> 0 | H2106: =IF(A2106<>A2105,D2106-0,D2106-D2105) -> 0 | I2106: =IF(A2106<>A2105,E2106-0,E2106-E2105) -> 0 | J2106: =IF(A2106<>A2105,F2106-0,F2106-F2105) -> 0
G2107: =IF(A2107<>A2106,C2107-0,C2107-C2106) -> 0 | H2107: =IF(A2107<>A2106,D2107-0,D2107-D2106) -> 0 | I2107: =IF(A2107<>A2106,E2107-0,E2107-E2106) -> 0 | J2107: =IF(A2107<>A2106,F2107-0,F2107-F2106) -> 0
... G4104: =IF(A4104<>A4103,C4104-0,C4104-C4103) -> 0 | H4104: =IF(A4104<>A4103,D4104-0,D4104-D4103) -> 0 | I4104: =IF(A4104<>A4103,E4104-0,E4104-E4103) -> 0 | J4104: =IF(A4104<>A4103,F4104-0,F4104-F4103) -> 0
H4105: =IF(A4105<>A4104,D4105-0,D4105-D4104) -> 0 | I4105: =IF(A4105<>A4104,E4105-0,E4105-E4104) -> 0 | J4105: =IF(A4105<>A4104,F4105-0,F4105-F4104) -> 0

Sheet CLEAN v1
A1: TICKER | B1: Year | C1: ESGCombinedScore | D1: EnvironmentPillarScore | E1: GovernancePillarScore | F1: SocialPillarScore | G1: ESG Momentum
A2: AC CN EQUITY | B2: 2014 | C2: {=INDEX('DIRTY ESG DATA'!$I$2:$I$8376, MATCH(1, ('DIRTY ESG DATA'!$A$2:$A$8376='CLEAN v1'!B2)* ('DIRTY ESG DATA'!$C$2:$C$8376='CLEAN v1'!A2)* ('DIRTY ESG DATA'!$G$2:$G$8376='CLEAN v1'!C$1), 0))} -> 0.47337539 | D2: {=INDEX('DIRTY ESG DATA'!$I$2:$I$8376, MATCH(1, ('DIRTY ESG DATA'!$A$2:$A$8376=B2)* ('DIRTY ESG DATA'!$C$2:$C$8376=A2)* ('DIRTY ESG DATA'!$G$2:$G$8376='CLEAN v1'!D$1), 0))} -> 0.34599989 | E2: {=INDEX('DIRTY ESG DATA'!$I$2:$I$8376, MATCH(1, ('DIRTY ESG DATA'!$A$2:$A$8376=B2)* ('DIRTY ESG DATA'!$C$2:$C$8376=A2)* ('DIRTY ESG DATA'!$G$2:$G$8376='CLEAN v1'!E$1), 0))} -> 0.61867288 | F2: {=INDEX('DIRTY ESG DATA'!$I$2:$I$8376, MATCH(1, ('DIRTY ESG DATA'!$A$2:$A$8376=B2)* ('DIRTY ESG DATA'!$C$2:$C$8376=A2)* ('DIRTY ESG DATA'!$G$2:$G$8376='CLEAN v1'!F$1), 0))} -> 0.46985388
A3: ACO/X CN EQUITY | B3: 2014 | C3: {=INDEX('DIRTY ESG DATA'!$I$2:$I$8376, MATCH(1, ('DIRTY ESG DATA'!$A$2:$A$8376='CLEAN v1'!B3)* ('DIRTY ESG DATA'!$C$2:$C$8376='CLEAN v1'!A3)* ('DIRTY ESG DATA'!$G$2:$G$8376='CLEAN v1'!C$1), 0))} -> 0.43132298 | D3: {=INDEX('DIRTY ESG DATA'!$I$2:$I$8376, MATCH(1, ('DIRTY ESG DATA'!$A$2:$A$8376=B3)* ('DIRTY ESG DATA'!$C$2:$C$8376=A3)* ('DIRTY ESG DATA'!$G$2:$G$8376='CLEAN v1'!D$1), 0))} -> 0.36314036 | E3: {=INDEX('DIRTY ESG DATA'!$I$2:$I$8376, MATCH(1, ('DIRTY ESG DATA'!$A$2:$A$8376=B3)* ('DIRTY ESG DATA'!$C$2:$C$8376=A3)* ('DIRTY ESG DATA'!$G$2:$G$8376='CLEAN v1'!E$1), 0))} -> 0.56489455 | F3: {=INDEX('DIRTY ESG DATA'!$I$2:$I$8376, MATCH(1, ('DIRTY ESG DATA'!$A$2:$A$8376=B3)* ('DIRTY ESG DATA'!$C$2:$C$8376=A3)* ('DIRTY ESG DATA'!$G$2:$G$8376='CLEAN v1'!F$1), 0))} -> 0.4237582
A4: ACQ CN EQUITY | B4: 2014 | C4: {=INDEX('DIRTY ESG DATA'!$I$2:$I$8376, MATCH(1, ('DIRTY ESG DATA'!$A$2:$A$8376='CLEAN v1'!B4)* ('DIRTY ESG DATA'!$C$2:$C$8376='CLEAN v1'!A4)* ('DIRTY ESG DATA'!$G$2:$G$8376='CLEAN v1'!C$1), 0))} -> 0.17189387 | D4: {=INDEX('DIRTY ESG DATA'!$I$2:$I$8376, MATCH(1, ('DIRTY ESG DATA'!$A$2:$A$8376=B4)* ('DIRTY ESG DATA'!$C$2:$C$8376=A4)* ('DIRTY ESG DATA'!$G$2:$G$8376='CLEAN v1'!D$1), 0))} -> 0 | E4: {=INDEX('DIRTY ESG DATA'!$I$2:$I$8376, MATCH(1, ('DIRTY ESG DATA'!$A$2:$A$8376=B4)* ('DIRTY ESG DATA'!$C$2:$C$8376=A4)* ('DIRTY ESG DATA'!$G$2:$G$8376='CLEAN v1'!E$1), 0))} -> 0.29294653 | F4: {=INDEX('DIRTY ESG DATA'!$I$2:$I$8376, MATCH(1, ('DIRTY ESG DATA'!$A$2:$A$8376=B4)* ('DIRTY ESG DATA'!$C$2:$C$8376=A4)* ('DIRTY ESG DATA'!$G$2:$G$8376='CLEAN v1'!F$1), 0))} -> 0.14029872
A5: AGF/B CN EQUITY | B5: 2014 | C5: {=INDEX('DIRTY ESG DATA'!$I$2:$I$8376, MATCH(1, ('DIRTY ESG DATA'!$A$2:$A$8376='CLEAN v1'!B5)* ('DIRTY ESG DATA'!$C$2:$C$8376='CLEAN v1'!A5)* ('DIRTY ESG DATA'!$G$2:$G$8376='CLEAN v1'!C$1), 0))} -> 0.35752508 | D5: {=INDEX('DIRTY ESG DATA'!$I$2:$I$8376, MATCH(1, ('DIRTY ESG DATA'!$A$2:$A$8376=B5)* ('DIRTY ESG DATA'!$C$2:$C$8376=A5)* ('DIRTY ESG DATA'!$G$2:$G$8376='CLEAN v1'!D$1), 0))} -> 0.31333907 | E5: {=INDEX('DIRTY ESG DATA'!$I$2:$I$8376, MATCH(1, ('DIRTY ESG DATA'!$A$2:$A$8376=B5)* ('DIRTY ESG DATA'!$C$2:$C$8376=A5)* ('DIRTY ESG DATA'!$G$2:$G$8376='CLEAN v1'!E$1), 0))} -> 0.42923777 | F5: {=INDEX('DIRTY ESG DATA'!$I$2:$I$8376, MATCH(1, ('DIRTY ESG DATA'!$A$2:$A$8376=B5)* ('DIRTY ESG DATA'!$C$2:$C$8376=A5)* ('DIRTY ESG DATA'!$G$2:$G$8376='CLEAN v1'!F$1), 0))} -> 0.35157824
A6: AIM CN EQUITY | B6: 2014 | C6: {=INDEX('DIRTY ESG DATA'!$I$2:$I$8376, MATCH(1, ('DIRTY ESG DATA'!$A$2:$A$8376='CLEAN v1'!B6)* ('DIRTY ESG DATA'!$C$2:$C$8376='CLEAN v1'!A6)* ('DIRTY ESG DATA'!$G$2:$G$8376='CLEAN v1'!C$1), 0))} -> 0.53523779 | D6: {=INDEX('DIRTY ESG DATA'!$I$2:$I$8376, MATCH(1, ('DIRTY ESG DATA'!$A$2:$A$8376=B6)* ('DIRTY ESG DATA'!$C$2:$C$8376=A6)* ('DIRTY ESG DATA'!$G$2:$G$8376='CLEAN v1'!D$1), 0))} -> 0.25952112 | E6: {=INDEX('DIRTY ESG DATA'!$I$2:$I$8376, MATCH(1, ('DIRTY ESG DATA'!$A$2:$A$8376=B6)* ('DIRTY ESG DATA'!$C$2:$C$8376=A6)* ('DIRTY ESG DATA'!$G$2:$G$8376='CLEAN v1'!E$1), 0))} -> 0.77217227 | F6: {=INDEX('DIRTY ESG DATA'!$I$2:$I$8376, MATCH(1, ('DIRTY ESG DATA'!$A$2:$A$8376=B6)* ('DIRTY ESG DATA'!$C$2:$C$8376=A6)* ('DIRTY ESG DATA'!$G$2:$G$8376='CLEAN v1'!F$1), 0))} -> 0.50085559
A7: AP-U CN EQUITY | B7: 2014 | C7: {=INDEX('DIRTY ESG DATA'!$I$2:$I$8376, MATCH(1, ('DIRTY ESG DATA'!$A$2:$A$8376='CLEAN v1'!B7)* ('DIRTY ESG DATA'!$C$2:$C$8376='CLEAN v1'!A7)* ('DIRTY ESG DATA'!$G$2:$G$8376='CLEAN v1'!C$1), 0))} -> 0.25373336 | D7: {=INDEX('DIRTY ESG DATA'!$I$2:$I$8376, MATCH(1, ('DIRTY ESG DATA'!$A$2:$A$8376=B7)* ('DIRTY ESG DATA'!$C$2:$C$8376=A7)* ('DIRTY ESG DATA'!$G$2:$G$8376='CLEAN v1'!D$1), 0))} -> 0.032409382 | E7: {=INDEX('DIRTY ESG DATA'!$I$2:$I$8376, MATCH(1, ('DIRTY ESG DATA'!$A$2:$A$8376=B7)* ('DIRTY ESG DATA'!$C$2:$C$8376=A7)* ('DIRTY ESG DATA'!$G$2:$G$8376='CLEAN v1'!E$1), 0))} -> 0.47026341 | F7: {=INDEX('DIRTY ESG DATA'!$I$2:$I$8376, MATCH(1, ('DIRTY ESG DATA'!$A$2:$A$8376=B7)* ('DIRTY ESG DATA'!$C$2:$C$8376=A7)* ('DIRTY ESG DATA'!$G$2:$G$8376='CLEAN v1'!F$1), 0))} -> 0.29812758
A8: AQN CN EQUITY | B8: 2014 | C8: {=INDEX('DIRTY ESG DATA'!$I$2:$I$8376, MATCH(1, ('DIRTY ESG DATA'!$A$2:$A$8376='CLEAN v1'!B8)* ('DIRTY ESG DATA'!$C$2:$C$8376='CLEAN v1'!A8)* ('DIRTY ESG DATA'!$G$2:$G$8376='CLEAN v1'!C$1), 0))} -> 0.24099934 | D8: {=INDEX('DIRTY ESG DATA'!$I$2:$I$8376, MATCH(1, ('DIRTY ESG DATA'!$A$2:$A$8376=B8)* ('DIRTY ESG DATA'!$C$2:$C$8376=A8)* ('DIRTY ESG DATA'!$G$2:$G$8376='CLEAN v1'!D$1), 0))} -> 0.13910611 | E8: {=INDEX('DIRTY ESG DATA'!$I$2:$I$8376, MATCH(1, ('DIRTY ESG DATA'!$A$2:$A$8376=B8)* ('DIRTY ESG DATA'!$C$2:$C$8376=A8)* ('DIRTY ESG DATA'!$G$2:$G$8376='CLEAN v1'!E$1), 0))} -> 0.56204713 | F8: {=INDEX('DIRTY ESG DATA'!$I$2:$I$8376, MATCH(1, ('DIRTY ESG DATA'!$A$2:$A$8376=B8)* ('DIRTY ESG DATA'!$C$2:$C$8376=A8)* ('DIRTY ESG DATA'!$G$2:$G$8376='CLEAN v1'!F$1), 0))} -> 0.14497146
A9: ARE CN EQUITY | B9: 2014 | C9: {=INDEX('DIRTY ESG DATA'!$I$2:$I$8376, MATCH(1, ('DIRTY ESG DATA'!$A$2:$A$8376='CLEAN v1'!B9)* ('DIRTY ESG DATA'!$C$2:$C$8376='CLEAN v1'!A9)* ('DIRTY ESG DATA'!$G$2:$G$8376='CLEAN v1'!C$1), 0))} -> 0.32827268 | D9: {=INDEX('DIRTY ESG DATA'!$I$2:$I$8376, MATCH(1, ('DIRTY ESG DATA'!$A$2:$A$8376=B9)* ('DIRTY ESG DATA'!$C$2:$C$8376=A9)* ('DIRTY ESG DATA'!$G$2:$G$8376='CLEAN v1'!D$1), 0))} -> 0.10304297 | E9: {=INDEX('DIRTY ESG DATA'!$I$2:$I$8376, MATCH(1, ('DIRTY ESG DATA'!$A$2:$A$8376=B9)* ('DIRTY ESG DATA'!$C$2:$C$8376=A9)* ('DIRTY ESG DATA'!$G$2:$G$8376='CLEAN v1'!E$1), 0))} -> 0.62202787 | F9: {=INDEX('DIRTY ESG DATA'!$I$2:$I$8376, MATCH(1, ('DIRTY ESG DATA'!$A$2:$A$8376=B9)* ('DIRTY ESG DATA'!$C$2:$C$8376=A9)* ('DIRTY ESG DATA'!$G$2:$G$8376='CLEAN v1'!F$1), 0))} -> 0.34392572
A10: ATH CN EQUITY | B10: 2014 | C10: {=INDEX('DIRTY ESG DATA'!$I$2:$I$8376, MATCH(1, ('DIRTY ESG DATA'!$A$2:$A$8376='CLEAN v1'!B10)* ('DIRTY ESG DATA'!$C$2:$C$8376='CLEAN v1'!A10)* ('DIRTY ESG DATA'!$G$2:$G$8376='CLEAN v1'!C$1), 0))} -> 0.11173973 | D10: {=INDEX('DIRTY ESG DATA'!$I$2:$I$8376, MATCH(1, ('DIRTY ESG DATA'!$A$2:$A$8376=B10)* ('DIRTY ESG DATA'!$C$2:$C$8376=A10)* ('DIRTY ESG DATA'!$G$2:$G$8376='CLEAN v1'!D$1), 0))} -> 0.086423445 | E10: {=INDEX('DIRTY ESG DATA'!$I$2:$I$8376, MATCH(1, ('DIRTY ESG DATA'!$A$2:$A$8376=B10)* ('DIRTY ESG DATA'!$C$2:$C$8376=A10)* ('DIRTY ESG DATA'!$G$2:$G$8376='CLEAN v1'!E$1), 0))} -> 0.071170255 | F10: {=INDEX('DIRTY ESG DATA'!$I$2:$I$8376, MATCH(1, ('DIRTY ESG DATA'!$A$2:$A$8376=B10)* ('DIRTY ESG DATA'!$C$2:$C$8376=A10)* ('DIRTY ESG DATA'!$G$2:$G$8376='CLEAN v1'!F$1), 0))} -> 0.15530983
A11: AX-U CN EQUITY | B11: 2014 | C11: {=INDEX('DIRTY ESG DATA'!$I$2:$I$8376, MATCH(1, ('DIRTY ESG DATA'!$A$2:$A$8376='CLEAN v1'!B11)* ('DIRTY ESG DATA'!$C$2:$C$8376='CLEAN v1'!A11)* ('DIRTY ESG DATA'!$G$2:$G$8376='CLEAN v1'!C$1), 0))} -> 0.24897136 | D11: {=INDEX('DIRTY ESG DATA'!$I$2:$I$8376, MATCH(1, ('DIRTY ESG DATA'!$A$2:$A$8376=B11)* ('DIRTY ESG DATA'!$C$2:$C$8376=A11)* ('DIRTY ESG DATA'!$G$2:$G$8376='CLEAN v1'!D$1), 0))} -> 0.032409382 | E11: {=INDEX('DIRTY ESG DATA'!$I$2:$I$8376, MATCH(1, ('DIRTY ESG DATA'!$A$2:$A$8376=B11)* ('DIRTY ESG DATA'!$C$2:$C$8376=A11)* ('DIRTY ESG DATA'!$G$2:$G$8376='CLEAN v1'!E$1), 0))} -> 0.56803185 | F11: {=INDEX('DIRTY ESG DATA'!$I$2:$I$8376, MATCH(1, ('DIRTY ESG DATA'!$A$2:$A$8376=B11)* ('DIRTY ESG DATA'!$C$2:$C$8376=A11)* ('DIRTY ESG DATA'!$G$2:$G$8376='CLEAN v1'!F$1), 0))} -> 0.17824431
A12: BB CN EQUITY | B12: 2014 | C12: {=INDEX('DIRTY ESG DATA'!$I$2:$I$8376, MATCH(1, ('DIRTY ESG DATA'!$A$2:$A$8376='CLEAN v1'!B12)* ('DIRTY ESG DATA'!$C$2:$C$8376='CLEAN v1'!A12)* ('DIRTY ESG DATA'!$G$2:$G$8376='CLEAN v1'!C$1), 0))} -> 0.55095175 | D12: {=INDEX('DIRTY ESG DATA'!$I$2:$I$8376, MATCH(1, ('DIRTY ESG DATA'!$A$2:$A$8376=B12)* ('DIRTY ESG DATA'!$C$2:$C$8376=A12)* ('DIRTY ESG DATA'!$G$2:$G$8376='CLEAN v1'!D$1), 0))} -> 0.73226958 | E12: {=INDEX('DIRTY ESG DATA'!$I$2:$I$8376, MATCH(1, ('DIRTY ESG DATA'!$A$2:$A$8376=B12)* ('DIRTY ESG DATA'!$C$2:$C$8376=A12)* ('DIRTY ESG DATA'!$G$2:$G$8376='CLEAN v1'!E$1), 0))} -> 0.4125536 | F12: {=INDEX('DIRTY ESG DATA'!$I$2:$I$8376, MATCH(1, ('DIRTY ESG DATA'!$A$2:$A$8376=B12)* ('DIRTY ESG DATA'!$C$2:$C$8376=A12)* ('DIRTY ESG DATA'!$G$2:$G$8376='CLEAN v1'!F$1), 0))} -> 0.65089197
A13: BCE CN EQUITY | B13: 2014 | C13: {=INDEX('DIRTY ESG DATA'!$I$2:$I$8376, MATCH(1, ('DIRTY ESG DATA'!$A$2:$A$8376='CLEAN v1'!B13)* ('DIRTY ESG DATA'!$C$2:$C$8376='CLEAN v1'!A13)* ('DIRTY ESG DATA'!$G$2:$G$8376='CLEAN v1'!C$1), 0))} -> 0.57561993 | D13: {=INDEX('DIRTY ESG DATA'!$I$2:$I$8376, MATCH(1, ('DIRTY ESG DATA'!$A$2:$A$8376=B13)* ('DIRTY ESG DATA'!$C$2:$C$8376=A13)* ('DIRTY ESG DATA'!$G$2:$G$8376='CLEAN v1'!D$1), 0))} -> 0.82549086 | E13: {=INDEX('DIRTY ESG DATA'!$I$2:$I$8376, MATCH(1, ('DIRTY ESG DATA'!$A$2:$A$8376=B13)* ('DIRTY ESG DATA'!$C$2:$C$8376=A13)* ('DIRTY ESG DATA'!$G$2:$G$8376='CLEAN v1'!E$1), 0))} -> 0.41014702 | F13: {=INDEX('DIRTY ESG DATA'!$I$2:$I$8376, MATCH(1, ('DIRTY ESG DATA'!$A$2:$A$8376=B13)* ('DIRTY ESG DATA'!$C$2:$C$8376=A13)* ('DIRTY ESG DATA'!$G$2:$G$8376='CLEAN v1'!F$1), 0))} -> 0.56260866
... A2095: XTC CN EQUITY | B2095: 2024 | C2095: {=INDEX('DIRTY ESG DATA'!$I$2:$I$8376, MATCH(1, ('DIRTY ESG DATA'!$A$2:$A$8376='CLEAN v1'!B2095)* ('DIRTY ESG DATA'!$C$2:$C$8376='CLEAN v1'!A2095)* ('DIRTY ESG DATA'!$G$2:$G$8376='CLEAN v1'!C$1), 0))} -> 0.24393174 | D2095: {=INDEX('DIRTY ESG DATA'!$I$2:$I$8376, MATCH(1, ('DIRTY ESG DATA'!$A$2:$A$8376=B2095)* ('DIRTY ESG DATA'!$C$2:$C$8376=A2095)* ('DIRTY ESG DATA'!$G$2:$G$8376='CLEAN v1'!D$1), 0))} -> 0.085651007 | E2095: {=INDEX('DIRTY ESG DATA'!$I$2:$I$8376, MATCH(1, ('DIRTY ESG DATA'!$A$2:$A$8376=B2095)* ('DIRTY ESG DATA'!$C$2:$C$8376=A2095)* ('DIRTY ESG DATA'!$G$2:$G$8376='CLEAN v1'!E$1), 0))} -> 0.24609722 | F2095: {=INDEX('DIRTY ESG DATA'!$I$2:$I$8376, MATCH(1, ('DIRTY ESG DATA'!$A$2:$A$8376=B2095)* ('DIRTY ESG DATA'!$C$2:$C$8376=A2095)* ('DIRTY ESG DATA'!$G$2:$G$8376='CLEAN v1'!F$1), 0))} -> 0.37258632

Sheet DIRTY ESG DATA
A1: Year | B1: CUSIP | C1: TICKER | D1: Company Name | E1: Field ID | F1: Field Pillar | G1: Field Name | H1: Value | I1: Value Score
A2: 2021 | B2: 00791P107 | C2: =VLOOKUP(B2,'REFERENCE SHEET'!B:C,2,FALSE) -> AAV CN EQUITY | D2: ADVANTAGE ENERGY LTD. | E2: 2 | F2: ESG Scores | G2: ESGCombinedScore | H2: C- | I2: 0.32801626
A3: 2021 | B3: 00791P107 | C3: =VLOOKUP(B3,'REFERENCE SHEET'!B:C,2,FALSE) -> AAV CN EQUITY | D3: ADVANTAGE ENERGY LTD. | E3: 4 | F3: ESG Scores | G3: EnvironmentPillarScore | H3: C- | I3: 0.27423839
A4: 2021 | B4: 00791P107 | C4: =VLOOKUP(B4,'REFERENCE SHEET'!B:C,2,FALSE) -> AAV CN EQUITY | D4: ADVANTAGE ENERGY LTD. | E4: 5 | F4: ESG Scores | G4: GovernancePillarScore | H4: B- | I4: 0.51237323
A5: 2021 | B5: 00791P107 | C5: =VLOOKUP(B5,'REFERENCE SHEET'!B:C,2,FALSE) -> AAV CN EQUITY | D5: ADVANTAGE ENERGY LTD. | E5: 6 | F5: ESG Scores | G5: SocialPillarScore | H5: C- | I5: 0.26886706
A6: 2022 | B6: 00791P107 | C6: =VLOOKUP(B6,'REFERENCE SHEET'!B:C,2,FALSE) -> AAV CN EQUITY | D6: ADVANTAGE ENERGY LTD. | E6: 2 | F6: ESG Scores | G6: ESGCombinedScore | H6: C | I6: 0.41035629
A7: 2022 | B7: 00791P107 | C7: =VLOOKUP(B7,'REFERENCE SHEET'!B:C,2,FALSE) -> AAV CN EQUITY | D7: ADVANTAGE ENERGY LTD. | E7: 4 | F7: ESG Scores | G7: EnvironmentPillarScore | H7: C- | I7: 0.28529917
A8: 2022 | B8: 00791P107 | C8: =VLOOKUP(B8,'REFERENCE SHEET'!B:C,2,FALSE) -> AAV CN EQUITY | D8: ADVANTAGE ENERGY LTD. | E8: 5 | F8: ESG Scores | G8: GovernancePillarScore | H8: B- | I8: 0.56397363
A9: 2022 | B9: 00791P107 | C9: =VLOOKUP(B9,'REFERENCE SHEET'!B:C,2,FALSE) -> AAV CN EQUITY | D9: ADVANTAGE ENERGY LTD. | E9: 6 | F9: ESG Scores | G9: SocialPillarScore | H9: C+ | I9: 0.42706643
A10: 2023 | B10: 00791P107 | C10: =VLOOKUP(B10,'REFERENCE SHEET'!B:C,2,FALSE) -> AAV CN EQUITY | D10: ADVANTAGE ENERGY LTD. | E10: 2 | F10: ESG Scores | G10: ESGCombinedScore | H10: C | I10: 0.38751429
A11: 2023 | B11: 00791P107 | C11: =VLOOKUP(B11,'REFERENCE SHEET'!B:C,2,FALSE) -> AAV CN EQUITY | D11: ADVANTAGE ENERGY LTD. | E11: 4 | F11: ESG Scores | G11: EnvironmentPillarScore | H11: C- | I11: 0.27132183
A12: 2023 | B12: 00791P107 | C12: =VLOOKUP(B12,'REFERENCE SHEET'!B:C,2,FALSE) -> AAV CN EQUITY | D12: ADVANTAGE ENERGY LTD. | E12: 5 | F12: ESG Scores | G12: GovernancePillarScore | H12: B- | I12: 0.52778796
A13: 2023 | B13: 00791P107 | C13: =VLOOKUP(B13,'REFERENCE SHEET'!B:C,2,FALSE) -> AAV CN EQUITY | D13: ADVANTAGE ENERGY LTD. | E13: 6 | F13: ESG Scores | G13: SocialPillarScore | H13: C | I13: 0.40441631
... A8376: 2024 | B8376: 30150P109 | C8376: =VLOOKUP(B8376,'REFERENCE SHEET'!B:C,2,FALSE) -> XTC CN EQUITY | D8376: EXCO TECHNOLOGIES LIMITED | E8376: 6 | F8376: ESG Scores | G8376: SocialPillarScore | H8376: C | I8376: 0.37258632

Sheet REFERENCE SHEET
A1: Ticker | B1: CUSIP | D1: Name | E1: 2024-Q4 | F1: 2024-Q3 | G1: 2024-Q2 | H1: 2024-Q1 | I1: 2023-Q4 | J1: 2023-Q3 | K1: 2023-Q2 | L1: 2023-Q1 | M1: 2022-Q4 | N1: 2022-Q3 | O1: 2022-Q2 | P1: 2022-Q1 | Q1: 2021-Q4 | R1: 2021-Q3 | S1: 2021-Q2 | T1: 2021-Q1 | U1: 2020-Q4 | V1: 2020-Q3 | W1: 2020-Q2 | X1: 2020-Q1 | Y1: 2019-Q4 | Z1: 2019-Q3 | AA1: 2019-Q2 | AB1: 2019-Q1 | AC1: 2018-Q4 | AD1: 2018-Q3 | AE1: 2018-Q2 | AF1: 2018-Q1 | AG1: 2017-Q4 | AH1: 2017-Q3 | AI1: 2017-Q2 | AJ1: 2017-Q1 | AK1: 2016-Q4 | AL1: 2016-Q3 | AM1: 2016-Q2 | AN1: 2016-Q1 | AO1: 2015-Q4 | AP1: 2015-Q3 | AQ1: 2015-Q2 | AR1: 2015-Q1
A2: AAV | B2: 00791P107 | C2: =A2&" CN EQUITY" -> AAV CN EQUITY | D2: Advantage Energy Ltd | E2: 1646387712 | F2: 1577886464 | G2: 1733170560 | H2: 1580187264 | I2: 1409015808 | J2: 1553945728 | K2: 1453393536 | L2: 1298478080 | M2: 1630605312 | N2: 1853482880 | O2: 1515478144 | P2: 1662120320 | Q2: 1414042752 | R2: 1221305472 | S2: 965594624 | T2: 445827328 | U2: 320753824 | V2: 328256864 | W2: 311375072 | X2: 267282512 | Y2: 514004832 | Z2: 401858336 | AA2: 304664672 | AB2: 409072704 | AC2: 368165440 | AD2: 669391680 | AE2: 765294208 | AF2: 708519744 | AG2: 1004201216 | AH2: 1454174720 | AI2: 1623263488 | AJ2: 1623166720 | AK2: 1683971072 | AL2: 1697906560 | AM2: 1332163456 | AN2: 1314780160 | AO2: 1200238592 | AP2: 1189886976 | AQ2: 1348260224 | AR2: 1161495680 | AZ2: AAV CN EQUITY
A3: ABX | B3: 06849F108 | C3: =A3&" CN EQUITY" -> ABX CN EQUITY | D3: Barrick Mining Corp | E3: 38807977984 | F3: 47092707328 | G3: 40063614976 | H3: 39552983040 | I3: 42027216896 | J3: 34635382784 | K3: 39373791232 | L3: 44041723904 | M3: 40809807872 | N3: 37830107136 | O3: 40418488320 | P3: 54305181696 | Q3: 42771628032 | R3: 40672067584 | S3: 45597442048 | T3: 44331745280 | U3: 51565649920 | V3: 66499747840 | W3: 64951975936 | X3: 45977956352 | Y3: 42880098304 | Z3: 40744468480 | AA3: 36213465088 | AB3: 32096307200 | AC3: 21518743552 | AD3: 16678699008 | AE3: 20152412160 | AF3: 18728630272 | AG3: 21202667520 | AH3: 23413340160 | AI3: 24049934336 | AJ3: 29442402304 | AK3: 25045110784 | AL3: 27070646272 | AM3: 32136636416 | AN3: 20552036352 | AO3: 11927520256 | AP3: 9888047104 | AQ3: 15548340224 | AR3: 16130674688 | AZ3: AC CN EQUITY
A4: AC | B4: 008911877 | C4: =A4&" CN EQUITY" -> AC CN EQUITY | D4: Air Canada | E4: 7779318784 | F4: 5875700224 | G4: 6417025024 | H4: 7029621760 | I4: 6699790848 | J4: 6947129344 | K4: 8957712384 | L4: 6863493120 | M4: 6962915840 | N4: 5958284288 | O4: 5741809152 | P4: 8677977088 | Q4: 7557477376 | R4: 8274573312 | S4: 9121979392 | T4: 8788898816 | U4: 7563556352 | V4: 4655280128 | W4: 5029078528 | X4: 4117028352 | Y4: 12846358528 | Z4: 11526511616 | AA4: 10641859584 | AB4: 8722577408 | AC4: 7027732480 | AD4: 7527800320 | AE4: 5788850176 | AF4: 7310460416 | AG4: 7066720768 | AH4: 7189917696 | AI4: 4717142016 | AJ4: 3760470784 | AK4: 3735870720 | AL4: 2927563520 | AM4: 2458871808 | AN4: 2523493376 | AO4: 2894456832 | AP4: 3065968384 | AQ4: 3789085440 | AR4: 3550374656 | AZ4: ACO/X CN EQUITY
A5: ACO/X | B5: 046789400 | C5: =A5&" CN EQUITY" -> ACO/X CN EQUITY | D5: Atco Ltd/Canada | E5: 5356498432 | F5: 5438578688 | G5: 4408354816 | H5: 4251751936 | I5: 4357063680 | J5: 3918804224 | K5: 4473836544 | L5: 4942422528 | M5: 4803340288 | N5: 4836183040 | O5: 5043595776 | P5: 4898488320 | Q5: 4888135680 | R5: 4650233344 | S5: 5050794496 | T5: 4790389248 | U5: 4201691648 | V5: 4416777728 | W5: 4600962560 | X5: 4468485120 | Y5: 5708773888 | Z5: 5564491776 | AA5: 5058420736 | AB5: 5159705600 | AC5: 4430725632 | AD5: 4332813824 | AE5: 4656373760 | AF5: 4748883456 | AG5: 5159636992 | AH5: 5252987904 | AI5: 5815187968 | AJ5: 5930008576 | AK5: 5122024960 | AL5: 5346150400 | AM5: 5192025600 | AN5: 4518471680 | AO5: 4107735808 | AP5: 4514950144 | AQ5: 4546976768 | AR5: 5197527552 | AZ5: ACQ CN EQUITY
A6: AEM | B6: 008474108 | C6: =A6&" CN EQUITY" -> AEM CN EQUITY | D6: Agnico Eagle Mines Ltd | E6: 56443891712 | F6: 54646591488 | G6: 44764639232 | H6: 40299433984 | I6: 36073746432 | J6: 30578929664 | K6: 32715147264 | L6: 31490955264 | M6: 32076687360 | N6: 26591344640 | O6: 26859173888 | P6: 34790236160 | Q6: 16452568064 | R6: 16057384960 | S6: 18287462400 | T6: 17688954880 | U6: 21762924544 | V6: 25655674880 | W6: 21053421568 | X6: 13530664960 | Y6: 19183237120 | Z6: 16999652352 | AA6: 15823868928 | AB6: 13658712064 | AC6: 12926810112 | AD6: 10335356928 | AE6: 14079306752 | AF6: 12637274112 | AG6: 13488970752 | AH6: 13082985472 | AI6: 13550573568 | AJ6: 12744101888 | AK6: 12717728768 | AL6: 15931622400 | AM6: 15424679936 | AN6: 10380139520 | AO6: 7916745216 | AP6: 7354202112 | AQ6: 7666540544 | AR6: 7615286784 | AZ6: ADEN CN EQUITY
A7: AG | B7: 32076V103 | C7: =A7&" CN EQUITY" -> AG CN EQUITY | D7: First Majestic Silver Corp | E7: 2383937280 | F7: 2449124864 | G7: 2351210752 | H7: 2282816512 | I7: 2332766208 | J7: 1997036544 | K7: 2126761216 | L7: 2676179456 | M7: 3026874112 | N7: 2776702464 | O7: 2426123008 | P7: 4274784768 | Q7: 3610731264 | R7: 3677938176 | S7: 4930934272 | T7: 4364550144 | U7: 3779883776 | V7: 2728916992 | W7: 2829510144 | X7: 1814737280 | Y7: 3226195200 | Z7: 2440404992 | AA7: 2089173248 | AB7: 1728342912 | AC7: 1553197312 | AD7: 1415606144 | AE7: 1936780800 | AF7: 1309354624 | AG7: 1405099264 | AH7: 1411037952 | AI7: 1776939136 | AJ7: 1774540288 | AK7: 1687144832 | AL7: 2213533952 | AM7: 2847280384 | AN7: 1310686848 | AO7: 701422144 | AP7: 522668032 | AQ7: 739398528 | AR7: 801995456 | AZ7: ADN CN EQUITY
A8: AGI | B8: 011532108 | C8: =A8&" CN EQUITY" -> AGI CN EQUITY | D8: Alamos Gold Inc | E8: 11142990848 | F8: 11315946496 | G8: 8559896064 | H8: 7924278272 | I8: 7070629888 | J8: 6068656640 | K8: 6250302976 | L8: 6500131840 | M8: 5383944704 | N8: 4016207104 | O8: 3545876224 | P8: 4114842112 | Q8: 3815324672 | R8: 3574255616 | S8: 3719620352 | T8: 3857068288 | U8: 4367131648 | V8: 4594193920 | W8: 4954233856 | X8: 2769891584 | Y8: 3062084608 | Z8: 3011848960 | AA8: 3081672960 | AB8: 2636103936 | AC8: 1921017216 | AD8: 2311550208 | AE8: 2914751232 | AF8: 2607320832 | AG8: 3186339072 | AH8: 2534509824 | AI8: 2749072128 | AJ8: 3191288832 | AK8: 2491526144 | AL8: 2876170752 | AM8: 2948805120 | AN8: 1844908672 | AO8: 1167923456 | AP8: 1262198016 | AQ8: 904238144 | AR8: 944992512 | AZ8: ADW/A CN EQUITY
A9: AIF | B9: 02215R107 | C9: =A9&" CN EQUITY" -> AIF CN EQUITY | D9: Altus Group Ltd/Canada | E9: 2586639872 | F9: 2534984448 | G9: 2331340288 | H9: 2386389760 | I9: 1932735104 | J9: 2158483456 | K9: 2015424000 | L9: 2613003520 | M9: 2451339776 | N9: 2028156160 | O9: 2017189120 | P9: 2264322560 | Q9: 3172848128 | R9: 2585094400 | S9: 2395868160 | T9: 2473533184 | U9: 2004295040 | V9: 2244134912 | W9: 1652837120 | X9: 1470111360 | Y9: 1524445952 | Z9: 1602520320 | AA9: 1270935168 | AB9: 1026608960 | AC9: 930303872 | AD9: 1200637440 | AE9: 1144430976 | AF9: 1266111616 | AG9: 1429149184 | AH9: 1227808256 | AI9: 1081707136 | AJ9: 1101388928 | AK9: 1158704128 | AL9: 1089304064 | AM9: 826008064 | AN9: 766711360 | AO9: 708210112 | AP9: 682053312 | AQ9: 578221632 | AR9: 632991104 | AZ9: AGF/B CN EQUITY
A10: ALA | B10: 021361100 | C10: =A10&" CN EQUITY" -> ALA CN EQUITY | D10: AltaGas Ltd | E10: 9971879936 | F10: 9966685184 | G10: 9166783488 | H10: 8836188160 | I10: 8194971136 | J10: 7339083264 | K10: 6704039936 | L10: 6344253440 | M10: 6581919232 | N10: 7441016832 | O10: 7622471168 | P10: 7852406272 | Q10: 7651362816 | R10: 7001172992 | S10: 7283146752 | T10: 5853430272 | U10: 5231352320 | V10: 4493476864 | W10: 4373315584 | X10: 3562669824 | Y10: 5511896576 | Z10: 5391819264 | AA10: 5465117184 | AB10: 4847395328 | AC10: 3791446016 | AD10: 5468099072 | AE10: 7151847424 | AF10: 6280448000 | AG10: 7304140288 | AH10: 7250946048 | AI10: 7411161088 | AJ10: 7626598400 | AK10: 5636426752 | AL10: 5525857792 | AM10: 5104321024 | AN10: 4907148800 | AO10: 4549060096 | AP10: 4758144512 | AQ10: 5129059328 | AR10: 5678100480 | AZ10: AI CN EQUITY
A11: AP-U | B11: 019456102 | C11: =A11&" CN EQUITY" -> AP-U CN EQUITY | D11: Allied Properties Real Estate | E11: 2194445056 | F11: 2587269888 | G11: 1959006080 | H11: 2248611072 | I11: 2568023296 | J11: 2281697536 | K11: 2763997184 | L11: 3099952640 | M11: 3257750016 | N11: 3481720320 | O11: 4223621888 | P11: 5933940736 | Q11: 5592894976 | R11: 5118230528 | S11: 5732876288 | T11: 5171678208 | U11: 4814089216 | V11: 4562122240 | W11: 5042698240 | X11: 5495291904 | Y11: 6395615744 | Z11: 6228705280 | AA11: 5507816960 | AB11: 5362827776 | AC11: 4600924160 | AD11: 4474274304 | AE11: 4195988480 | AF11: 3761268992 | AG11: 3902223872 | AH11: 3694500864 | AI11: 3295697664 | AJ11: 3056056832 | AK11: 3044201728 | AL11: 3190695936 | AM11: 2989293312 | AN11: 2702574592 | AO11: 2439813632 | AP11: 2699483392 | AQ11: 2738897408 | AR11: 3112945664 | AZ11: AIF CN EQUITY
A12: AQN | B12: 015857105 | C12: =A12&" CN EQUITY" -> AQN CN EQUITY | D12: Algonquin Power & Utilities Co | E12: 4895110144 | F12: 5668532736 | G12: 5543098880 | H12: 5901607936 | I12: 5761210880 | J12: 5538054144 | K12: 7540876800 | L12: 7750265856 | M12: 6062156800 | N12: 10194551808 | O12: 11687590912 | P12: 13028030464 | Q12: 12275508224 | R12: 11499719680 | S12: 11300712448 | T12: 11886893056 | U12: 12507805696 | V12: 11454545920 | W12: 9255700480 | X12: 9934031872 | Y12: 9544770560 | Z12: 8951825408 | AA12: 7796688384 | AB12: 7122724864 | AC12: 6506654208 | AD12: 6308524032 | AE12: 5977105920 | AF12: 5513651200 | AG12: 6068597760 | AH12: 5044759552 | AI12: 5220695040 | AJ12: 4736491520 | AK12: 3112865280 | AL12: 3211252480 | AM12: 3086951168 | AN12: 2744537600 | AO12: 2754637056 | AP12: 2247969536 | AQ12: 2228918784 | AR12: 2228918784 | AZ12: AIM CN EQUITY
A13: ARE | B13: 00762V109 | C13: =A13&" CN EQUITY" -> ARE CN EQUITY | D13: Aecon Group Inc | E13: 1697589760 | F13: 1307172224 | G13: 1057283520 | H13: 1059151488 | I13: 807557248 | J13: 701163456 | K13: 763145664 | L13: 844885696 | M13: 555817728 | N13: 580832576 | O13: 799964096 | P13: 1032164416 | Q13: 1018221312 | R13: 1156356736 | S13: 1085723392 | T13: 1171319680 | U13: 979629184 | V13: 819107904 | W13: 883774272 | X13: 758210752 | Y13: 1061183104 | Z13: 1108290816 | AA13: 1151260160 | AB13: 1046676032 | AC13: 1055079808 | AD13: 972319936 | AE13: 923766080 | AF13: 1093209344 | AG13: 1174446464 | AH13: 1033082304 | AI13: 945496384 | AJ13: 1000904640 | AK13: 876374464 | AL13: 1039578176 | AM13: 1007718336 | AN13: 922963392 | AO13: 869642432 | AP13: 767387584 | AQ13: 719708352 | AR13: 633343360 | AZ13: ALS CN EQUITY
A14: ARX | B14: 00208D408 | C14: =A14&" CN EQUITY" -> ARX CN EQUITY | D14: ARC Resources Ltd | E14: 15429603328 | F14: 13611326464 | G14: 14585907200 | H14: 14436017152 | I14: 11817239552 | J14: 13177922560 | K14: 10782667776 | L14: 9495879680 | M14: 11421119488 | N14: 10864626688 | O14: 10912884736 | P14: 11547301888 | Q14: 8034594304 | R14: 8605234176 | S14: 7635851264 | T14: 2735747328 | U14: 2124921600 | V14: 2107213952 | W14: 1614940416 | X14: 1434322176 | Y14: 2896976640 | Z14: 2234709248 | AA14: 2268476160 | AB14: 3227535616 | AC14: 2866668544 | AD14: 5096299520 | AE14: 4804002816 | AF14: 4966730240 | AG14: 5217854464 | AH14: 6080831488 | AI14: 5997367296 | AJ14: 6739075584 | AK14: 8160606208 | AL14: 8345443840 | AM14: 7755399168 | AN14: 6580125184 | AO14: 5779362816 | AP14: 6055498240 | AQ14: 7263007744 | AR14: 7367747584 | AZ14: AND CN EQUITY
A15: ASTL | B15: 15658107 | C15: =A15&" CN EQUITY" -> ASTL CN EQUITY | D15: Algoma Steel Group Inc | E15: 1474472064 | F15: 1447303808 | G15: 988127936 | H15: 1202390528 | I15: 1381052032 | J15: 954186048 | K15: 969395392 | L15: 1134068352 | M15: 886839232 | N15: 937696704 | O15: 1701514624 | P15: 1573530368 | Q15: 1521966208 | R15: -- | S15: -- | T15: -- | U15: -- | V15: -- | W15: -- | X15: -- | Y15: -- | Z15: -- | AA15: -- | AB15: -- | AC15: -- | AD15: -- | AE15: -- | AF15: -- | AG15: -- | AH15: -- | AI15: -- | AJ15: -- | AK15: -- | AL15: -- | AM15: -- | AN15: -- | AO15: -- | AP15: -- | AQ15: -- | AR15: -- | AZ15: APR-U CN EQUITY
A16: ATD | B16: 01626P148 | C16: =A16&" CN EQUITY" -> ATD CN EQUITY | D16: Alimentation Couche-Tard Inc | E16: 75558395904 | F16: 70880894976 | G16: 73444433920 | H16: 74355777536 | I16: 75187961856 | J16: 66640760832 | K16: 66502021120 | L16: 66952843264 | M16: 59886936064 | N16: 56837222400 | O16: 51509608448 | P16: 58808741888 | Q16: 56287309824 | R16: 52039499776 | S16: 49006710784 | T16: 44091064320 | U16: 48310153216 | V16: 51617562624 | W16: 47666987008 | X16: 37258641408 | Y16: 46330957824 | Z16: 45748342784 | AA16: 46503993344 | AB16: 44454727680 | AC16: 38328074240 | AD16: 36487589888 | AE16: 32300642304 | AF16: 32479109120 | AG16: 36855721984 | AH16: 32420294656 | AI16: 35355680768 | AJ16: 34423926784 | AK16: 34978963456 | AL16: 36170809344 | AM16: 31551803392 | AN16: 33026658304 | AO16: 34668249088 | AP16: 34958462976 | AQ16: 30412279808 | AR16: 28787920896 | AZ16: AP-U CN EQUITY
A17: ATH | B17: 04682R107 | C17: =A17&" CN EQUITY" -> ATH CN EQUITY | D17: Athabasca Oil Corp | E17: 2793556736 | F17: 2580307200 | G17: 2872803584 | H17: 2966092032 | I17: 2416014592 | J17: 2527933696 | K17: 1698880384 | L17: 1894919296 | M17: 1413438464 | N17: 1246526080 | O17: 1445492992 | P17: 1077703168 | Q17: 631705088 | R17: 488221344 | S17: 520061888 | T17: 281257952 | U17: 90214816 | V17: 68987800 | W17: 95521568 | X17: 75923296 | Y17: 308833792 | Z17: 334853984 | AA17: 382096224 | AB17: 438569824 | AC17: 510705728 | AD17: 820115072 | AE17: 927252032 | AF17: 607085312 | AG17: 545465152 | AH17: 570905152 | AI17: 514023904 | AJ17: 775165824 | AK17: 833090496 | AL17: 523829952 | AM17: 579702400 | AN17: 416717472 | AO17: 617558976 | AP17: 512335392 | AQ17: 822005248 | AR17: 849367680 | AZ17: AQN CN EQUITY
A18: ATRL | B18: 04764T104 | C18: =A18&" CN EQUITY" -> ATRL CN EQUITY | D18: AtkinsRealis Group Inc | E18: 13307099136 | F18: 9623729152 | G18: 10379665408 | H18: 9725705216 | I18: 7489144320 | J18: 7954363392 | K18: 6100510208 | L18: 5831912448 | M18: 4188724480 | N18: 4037747712 | O18: 3886771200 | P18: 5284183040 | Q18: 5426381824 | R18: 6175998464 | S18: 5661624832 | T18: 4722409472 | U18: 3814793984 | V18: 3748083200 | W18: 4021947904 | X18: 3644506368 | Y18: 5257849856 | Z18: 3275842304 | AA18: 4648676352 | AB18: 5954800128 | AC18: 8061451264 | AD18: 9246442496 | AE18: 10191333376 | AF18: 9929096192 | AG18: 10010983424 | AH18: 9892482048 | AI18: 9396936704 | AJ18: 7847200768 | AK18: 8685224960 | AL18: 7740161536 | AM18: 8143421440 | AN18: 7106723328 | AO18: 6158466560 | AP18: 5687970304 | AQ18: 6383876096 | AR18: 5996510720 | AZ18: ARE CN EQUITY
A19: ATS | B19: 00217Y104 | C19: =A19&" CN EQUITY" -> ATS CN EQUITY | D19: ATS Corp | E19: 4293112064 | F19: 3842648576 | G19: 4335091200 | H19: 4509460992 | I19: 5648172544 | J19: 5725241856 | K19: 6024563200 | L19: 5194683904 | M19: 3862636032 | N19: 3345015040 | O19: 3241583872 | P19: 4160936192 | Q19: 4634822144 | R19: 3705853696 | S19: 3276103424 | T19: 2437281024 | U19: 2056299904 | V19: 1599625472 | W19: 1761543808 | X19: 1518985984 | Y19: 1975765120 | Z19: 1665746816 | AA19: 1957670528 | AB19: 1830841984 | AC19: 1354661632 | AD19: 2259861760 | AE19: 1853425280 | AF19: 1661912576 | AG19: 1459590144 | AH19: 1241471104 | AI19: 1244077184 | AJ19: 1256128896 | AK19: 1158921472 | AL19: 1015939200 | AM19: 897115776 | AN19: 975747904 | AO19: 1053123200 | AP19: 1194227712 | AQ19: 1401017472 | AR19: 1244195072 | AZ19: ARIS CN EQUITY
A20: ATZ | B20: 04045U102 | C20: =A20&" CN EQUITY" -> ATZ CN EQUITY | D20: Aritzia Inc | E20: 6032571904 | F20: 5729277952 | G20: 4333110272 | H20: 4143386880 | I20: 3049657600 | J20: 2621653248 | K20: 4134684672 | L20: 4857106432 | M20: 5291279360 | N20: 4981030912 | O20: 3844553216 | P20: 5792592384 | Q20: 5936025088 | R20: 4555462144 | S20: 4081010176 | T20: 3210651392 | U20: 2823394048 | V20: 1907240192 | W20: 2078703744 | X20: 1333765376 | Y20: 2056904704 | Z20: 2151201024 | AA20: 2330675968 | AB20: 2466418688 | AC20: 1964058496 | AD20: 1932424576 | AE20: 1753467520 | AF20: 1347300864 | AG20: 1411837952 | AH20: 1636499712 | AI20: 1638474496 | AJ20: 1689236352 | AK20: 1871906688 | AL20: -- | AM20: -- | AN20: -- | AO20: -- | AP20: -- | AQ20: -- | AR20: -- | AZ20: ATH CN EQUITY
A21: AYA | B21: 05466C109 | C21: =A21&" CN EQUITY" -> AYA CN EQUITY | D21: Aya Gold & Silver Inc | E21: 1403046400 | F21: 2295978496 | G21: 1767660672 | H21: 1516343424 | I21: 1188287488 | J21: 852561600 | K21: 996763904 | L21: 1263948544 | M21: 946734720 | N21: 840725632 | O21: 688534336 | P21: 933738048 | Q21: 999685888 | R21: 811713792 | S21: 886323712 | T21: 466110112 | U21: 354899584 | V21: 240594272 | W21: 113747376 | X21: 77196232 | Y21: 155255296 | Z21: 139370160 | AA21: 149661248 | AB21: 172384688 | AC21: 148894192 | AD21: 180711392 | AE21: 199540208 | AF21: 128069064 | AG21: 88561944 | AH21: 81589704 | AI21: 39012444 | AJ21: 29522930 | AK21: 27907546 | AL21: 33887736 | AM21: 29301140 | AN21: 26213546 | AO21: 18824054 | AP21: 28236080 | AQ21: 31213850 | AR21: 29939816 | AZ21: ATS CN EQUITY
A22: BAM | B22: 113004105 | C22: =A22&" CN EQUITY" -> BAM CN EQUITY | D22: Brookfield Asset Management Lt | E22: 34540109824 | F22: 28370855936 | G22: 23110426624 | H22: 23509430272 | I22: 21964765184 | J22: 18675122176 | K22: 17834174464 | L22: 18256191488 | M22: 63499468800 | N22: -- | O22: -- | P22: -- | Q22: -- | R22: -- | S22: -- | T22: -- | U22: -- | V22: -- | W22: -- | X22: -- | Y22: -- | Z22: -- | AA22: -- | AB22: -- | AC22: -- | AD22: -- | AE22: -- | AF22: -- | AG22: -- | AH22: -- | AI22: -- | AJ22: -- | AK22: -- | AL22: -- | AM22: -- | AN22: -- | AO22: -- | AP22: -- | AQ22: -- | AR22: -- | AZ22: ATZ CN EQUITY
A23: BB | B23: 09228F103 | C23: =A23&" CN EQUITY" -> BB CN EQUITY | D23: BlackBerry Ltd | E23: 3230044160 | F23: 2102991616 | G23: 2018386304 | H23: 2186052608 | I23: 2698442240 | J23: 3753091072 | K23: 4280980224 | L23: 3609374720 | M23: 2559327744 | N23: 3758977536 | O23: 4005552384 | P23: 5341632512 | Q23: 6780739584 | R23: 6991048192 | S23: 8578220032 | T23: 5960425984 | U23: 4743413760 | V23: 3400018432 | W23: 3694890240 | X23: 3197728256 | Y23: 4610301952 | Z23: 3805451264 | AA23: 5347258368 | AB23: 7372897280 | AC23: 5249024000 | AD23: 7862163968 | AE23: 6810575872 | AF23: 7948834816 | AG23: 7529755136 | AH23: 7399238656 | AI23: 6887924224 | AJ23: 5464121344 | AK23: 4896849920 | AL23: 5468687872 | AM23: 4530219520 | AN23: 5493122560 | AO23: 6749996544 | AP23: 4293288960 | AQ23: 5405492224 | AR23: 5970178048 | AZ23: AX-U CN EQUITY
A24: BBD/B | B24: 097751861 | C24: =A24&" CN EQUITY" -> BBD/B CN EQUITY | D24: Bombardier Inc | E24: 9768412160 | F24: 10286349312 | G24: 8760404992 | H24: 5793561600 | I24: 5297312256 | J24: 4707893760 | K24: 6467159552 | L24: 7276578304 | M24: 5108203008 | N24: 2439795200 | O24: 1933459200 | P24: 3541554176 | Q24: 4117212672 | R24: 5291314176 | S24: 2983207936 | T24: 2416227840 | U24: 1274648448 | V24: 827308800 | W24: 1094477568 | X24: 1193630336 | Y24: 4703885824 | Z24: 4371474432 | AA24: 5360430080 | AB24: 6275293696 | AC24: 4956424192 | AD24: 11128473600 | AE24: 12563041280 | AF24: 8418777088 | AG24: 6810583552 | AH24: 5092957696 | AI24: 5317615616 | AJ24: 4633240064 | AK24: 4925295104 | AL24: 4115937024 | AM24: 4446145024 | AN24: 2983606528 | AO24: 3054138112 | AP24: 3757637120 | AQ24: 5114784768 | AR24: 5647144448 | AZ24: AYA CN EQUITY
A25: BBU-U | B25: G16234109 | C25: =A25&" CN EQUITY" -> BBU-U CN EQUITY | D25: Brookfield Business Partners L | E25: 4881168384 | F25: 4565836288 | G25: 3730710016 | H25: 4319618048 | I25: 3945631488 | J25: 2975849984 | K25: 3320768512 | L25: 3594973696 | M25: 3303400704 | N25: 3905199872 | O25: 3963250688 | P25: 5632005120 | Q25: 8565309952 | R25: 8571139584 | S25: 8501852160 | T25: 7527044096 | U25: 7225088512 | V25: 6094448640 | W25: 6001179136 | X25: 5124467200 | Y25: 7747236864 | Z25: 7483372544 | AA25: 6592053248 | AB25: 6845444608 | AC25: 5375516160 | AD25: 7654745600 | AE25: 6514484224 | AF25: 6003823104 | AG25: 5596587008 | AH25: 3995844352 | AI25: 3787412480 | AJ25: 3558461440 | AK25: 3161479936 | AL25: 3104999936 | AM25: 2205900032 | AN25: -- | AO25: -- | AP25: -- | AQ25: -- | AR25: -- | AZ25: BB CN EQUITY
A26: BCE | B26: 05534B760 | C26: =A26&" CN EQUITY" -> BCE CN EQUITY | D26: BCE Inc | E26: 30397272064 | F26: 42895552512 | G26: 40423264256 | H26: 41992036352 | I26: 47593349120 | J26: 47302213632 | K26: 55102255104 | L26: 55221215232 | M26: 54179221504 | N26: 52819214336 | O26: 57696374784 | P26: 63046504448 | Q26: 59811401728 | R26: 57555828736 | S26: 55308185600 | T26: 51315638272 | U26: 49225105408 | V26: 49936977920 | W26: 51203035136 | X26: 52201984000 | Y26: 54370328576 | Z26: 57677279232 | AA26: 53606068224 | AB26: 53311856640 | AC26: 48432807936 | AD26: 46992797696 | AE26: 47808401408 | AF26: 49954467840 | AG26: 54381891584 | AH26: 52634619904 | AI26: 52529074176 | AJ26: 52900503552 | AK26: 50516602880 | AL26: 52695031808 | AM26: 53150429184 | AN26: 51375751168 | AO26: 46264786944 | AP26: 46371414016 | AQ26: 44993060864 | AR26: 45069574144 | AZ26: BBD/B CN EQUITY
A27: BDGI | B27: 056533102 | C27: =A27&" CN EQUITY" -> BDGI CN EQUITY | D27: Badger Infrastructure Solution | E27: 1232156416 | F27: 1267360384 | G27: 1419960960 | H27: 1730566528 | I27: 1403413632 | J27: 1195883520 | K27: 927335488 | L27: 1126592000 | M27: 919061888 | N27: 970427264 | O27: 973529920 | P27: 1084534400 | Q27: 1095910656 | R27: 1166925824 | S27: 1309734144 | T27: 1494184064 | U27: 1325491456 | V27: 1327234176 | W27: 1035856064 | X27: 794188864 | Y27: 1231085568 | Z27: 1450954112 | AA27: 1714319488 | AB27: 1457422720 | AC27: 1196497024 | AD27: 1098180096 | AE27: 1174978560 | AF27: 956084544 | AG27: 1008396480 | AH27: 985765120 | AI27: 987620160 | AJ27: 1296668800 | AK27: 1190931840 | AL27: 1051804352 | AM27: 834765312 | AN27: 815843968 | AO27: 905998656 | AP27: 722392960 | AQ27: 970229312 | AR27: 1001718208 | AZ27: BCE CN EQUITY
A28: BDT | B28: 09076P104 | C28: =A28&" CN EQUITY" -> BDT CN EQUITY | D28: Bird Construction Inc | E28: 1443276544 | F28: 1337495424 | G28: 1445380992 | H28: 1004545152 | I28: 774354816 | J28: 553341056 | K28: 453857952 | L28: 488811456 | M28: 436005792 | N28: 320023936 | O28: 401103840 | P28: 490238016 | Q28: 527287776 | R28: 528361696 | S28: 468333728 | T28: 474698400 | U28: 424311424 | V28: 341040256 | W28: 252975280 | X28: 193876848 | Y28: 303995488 | Z28: 241495728 | AA28: 240220224 | AB28: 335032800 | AC28: 259777968 | AD28: 335457984 | AE28: 308672352 | AF28: 363519104 | AG28: 431120896 | AH28: 423042688 | AI28: 362243584 | AJ28: 425593696 | AK28: 385202720 | AL28: 482566304 | AM28: 568450304 | AN28: 471086720 | AO28: 552719104 | AP28: 510202240 | AQ28: 473637760 | AR28: 400933920 | AZ28: BDGI CN EQUITY
A29: BEI-U | B29: 096631106 | C29: =A29&" CN EQUITY" -> BEI-U CN EQUITY | D29: Boardwalk Real Estate Investme | E29: 3512735232 | F29: 4683282432 | G29: 3853347584 | H29: 4268861696 | I29: 3900366336 | J29: 3403053824 | K29: 3167728128 | L29: 2808627200 | M29: 2517780992 | N29: 2356312832 | O29: 2133211904 | P29: 2994544640 | Q29: 2792836864 | R29: 2408777216 | S29: 2082275712 | T29: 1849496832 | U29: 1718590464 | V29: 1398201216 | W29: 1513317248 | X29: 1158154880 | Y29: 2321870592 | Z29: 2245030912 | AA29: 2014006656 | AB29: 2061525888 | AC29: 1911385344 | AD29: 2536212736 | AE29: 2308727040 | AF29: 2237953536 | AG29: 2178301952 | AH29: 1921495808 | AI29: 2403765504 | AJ29: 2384555520 | AK29: 2527558912 | AL29: 2688619520 | AM29: 2990472192 | AN29: 2690697728 | AO29: 2465217280 | AP29: 2848118272 | AQ29: 2942155008 | AR29: 3062688256 | AZ29: BDT CN EQUITY
A30: BEP-U | B30: N/A | C30: =A30&" CN EQUITY" -> BEP-U CN EQUITY | D30: Brookfield Renewable Partners | E30: 21579894784 | F30: 25139193856 | G30: 22311528448 | H30: 20831242240 | I30: 23024877568 | J30: 14260872192 | K30: 18355118080 | L30: 20015509504 | M30: 16103885824 | N30: 20268904448 | O30: 21007316992 | P30: 24093843456 | Q30: 21272969216 | R30: 21969442816 | S30: 22483159040 | T30: 21701414912 | U30: 22225080320 | V30: 21895790592 | W30: 20063913984 | X30: 18268190720 | Y30: 18608826368 | Z30: 16600801280 | AA30: 13975518208 | AB30: 13140388864 | AC30: 10938591232 | AD30: 12130399232 | AE30: 12237450240 | AF30: 12420482048 | AG30: 13579982848 | AH30: 12956984320 | AI30: 12264250368 | AJ30: 11682019328 | AK30: 11811981312 | AL30: 11945080832 | AM30: 11393988608 | AN30: 5621567488 | AO30: 5194257920 | AP30: 5260904448 | AQ30: 5325898240 | AR30: 5734274048 | AZ30: BEI-U CN EQUITY
A31: BHC | B31: 071734107 | C31: =A31&" CN EQUITY" -> BHC CN EQUITY | D31: Bausch Health Cos Inc | E31: 4202151168 | F31: 3989100032 | G31: 3499240704 | H31: 5243661312 | I31: 3882023424 | J31: 4080543744 | K31: 3855473152 | L31: 3964307200 | M31: 3075879168 | N31: 3450889728 | O31: 3889521664 | P31: 10271504384 | Q31: 12555016192 | R31: 12673125376 | S31: 13038433280 | T31: 14180221952 | U31: 9379537920 | V31: 7348358656 | W31: 8811429888 | X31: 7706696704 | Y31: 13595064320 | Z31: 10107984896 | AA31: 11555979264 | AB31: 11531496448 | AC31: 8831370240 | AD31: 11596721152 | AE31: 10670482432 | AF31: 7154718208 | AG31: 9124427776 | AH31: 6210264576 | AI31: 7690444800 | AJ31: 5012095488 | AK31: 6642988032 | AL31: 10982937600 | AM31: 8888025088 | AN31: 11617552384 | AO31: 47425544192 | AP31: 81271693312 | AQ31: 94578049024 | AR31: 85286240256 | AZ31: BHC CN EQUITY
A32: BIR | B32: 090697103 | C32: =A32&" CN EQUITY" -> BIR CN EQUITY | D32: Birchcliff Energy Ltd | E32: 1465057792 | F32: 1535390464 | G32: 1616449280 | H32: 1433702656 | I32: 1540620544 | J32: 2062201600 | K32: 2086199040 | L32: 2042483840 | M32: 2507785728 | N32: 2601390592 | O32: 2321688064 | P32: 2223447296 | Q32: 1713037056 | R32: 1861889152 | S32: 1383495808 | T32: 694355008 | U32: 470705344 | V32: 406880896 | W32: 303166176 | X32: 207429472 | Y32: 688772224 | Z32: 569101376 | AA32: 691403328 | AB32: 946644480 | AC32: 808370560 | AD32: 1382603904 | AE32: 1281265408 | AF32: 991421696 | AG32: 1169483520 | AH32: 1605827072 | AI32: 1621683456 | AJ32: 2007341568 | AK32: 2466674944 | AL32: 2413155072 | AM32: 1047875904 | AN32: 805706880 | AO32: 615322496 | AP32: 971696576 | AQ32: 1061461568 | AR32: 1032441728 | AZ32: BIR CN EQUITY
A33: BLX | B33: 09950M300 | C33: =A33&" CN EQUITY" -> BLX CN EQUITY | D33: Boralex Inc | E33: 2950414848 | F33: 3697524480 | G33: 3443692032 | H33: 2941165824 | I33: 3461162496 | J33: 2998714880 | K33: 3706773248 | L33: 4228825088 | M33: 4112569344 | N33: 4508206080 | O33: 4404535808 | P33: 4158109696 | Q33: 3558816512 | R33: 3837939456 | S33: 3873856000 | T33: 4055491072 | U33: 4844643840 | V33: 3946991360 | W33: 2980759040 | X33: 2411611392 | Y33: 2356172288 | Z33: 2019772032 | AA33: 1756115328 | AB33: 1690931968 | AC33: 1501564928 | AD33: 1607230080 | AE33: 1607276032 | AF33: 1705835776 | AG33: 1791820032 | AH33: 1635582336 | AI33: 1666187136 | AJ33: 1625110144 | AK33: 1448215552 | AL33: 1221076992 | AM33: 1270153728 | AN33: 1048702272 | AO33: 937428928 | AP33: 611554880 | AQ33: 636734848 | AR33: 636627328 | AZ33: BLDP CN EQUITY
A34: BMO | B34: 063671101 | C34: =A34&" CN EQUITY" -> BMO CN EQUITY | D34: Bank of Montreal | E34: 101824733184 | F34: 89017958400 | G34: 83743760384 | H34: 96434372608 | I34: 96082706432 | J34: 82597347328 | K34: 85753184256 | L34: 86131032064 | M34: 86252838912 | N34: 81996111872 | O34: 83472424960 | P34: 98775031808 | Q34: 88286445568 | R34: 81930592256 | S34: 82238578688 | T34: 72483643392 | U34: 62571487232 | V34: 50052005888 | W34: 46462717952 | X34: 45452005376 | Y34: 64325668864 | Z34: 62347444224 | AA34: 63186227200 | AB34: 63833980928 | AC34: 57021808640 | AD34: 68178124800 | AE34: 65102888960 | AF34: 62822809600 | AG34: 65166413824 | AH34: 61257621504 | AI34: 62143553536 | AJ34: 64728539136 | AK34: 62573797376 | AL34: 55438409728 | AM34: 52753158144 | AN34: 50735632384 | AO34: 50172903424 | AP34: 46747967488 | AQ34: 47694241792 | AR34: 49122926592 | AZ34: BLX CN EQUITY
A35: BN | B35: 11271J107 | C35: =A35&" CN EQUITY" -> BN CN EQUITY | D35: Brookfield Corp | E35: 136088051712 | F35: 118175293440 | G35: 93528629248 | H35: 85826363392 | I35: 87132307456 | J35: 69575475200 | K35: 73055068160 | L35: 72165679104 | M35: 69743304704 | N35: 88254849024 | O35: 93991280640 | P35: 110846091264 | Q35: 119800979456 | R35: 106435616768 | S35: 99787628544 | T35: 84435189760 | U35: 82881200128 | V35: 69342814208 | W35: 70279823360 | X35: 62968913920 | Y35: 78628151296 | Z35: 69971222528 | AA35: 62293467136 | AB35: 61842223104 | AC35: 51992440832 | AD35: 57047818240 | AE35: 52900311040 | AF35: 49715200000 | AG35: 54130814976 | AH35: 50940960768 | AI35: 50284101632 | AJ35: 47873687552 | AK35: 43750924288 | AL35: 45545762816 | AM35: 42193850368 | AN35: 44578361344 | AO35: 42826743808 | AP35: 41226108928 | AQ35: 42778300416 | AR35: 42847125504 | AZ35: BMO CN EQUITY
A36: BNS | B36: 064149107 | C36: =A36&" CN EQUITY" -> BNS CN EQUITY | D36: Bank of Nova Scotia/The | E36: 96107962368 | F36: 91179737088 | G36: 76946628608 | H36: 85636816896 | I36: 78306205696 | J36: 73381396480 | K36: 79415238656 | L36: 81134870528 | M36: 79088025600 | N36: 78270201856 | O36: 91120304128 | P36: 107822759936 | Q36: 108878938112 | R36: 94732427264 | S36: 97839628288 | T36: 95342108672 | U36: 83348447232 | V36: 67016228864 | W36: 68054503424 | X36: 69439946752 | Y36: 89193775104 | Z36: 91836203008 | AA36: 85982740480 | AB36: 85930418176 | AC36: 83500679168 | AD36: 94831009792 | AE36: 91748442112 | AF36: 95073230848 | AG36: 97313292288 | AH36: 96102490112 | AI36: 93761978368 | AJ36: 94080827392 | AK36: 90345447424 | AL36: 83759710208 | AM36: 76162138112 | AN36: 76310020096 | AO36: 67340046336 | AP36: 71038173184 | AQ36: 77994139648 | AR36: 76861440000 | AZ36: BN CN EQUITY
A37: BTE | B37: 07317Q105 | C37: =A37&" CN EQUITY" -> BTE CN EQUITY | D37: Baytex Energy Corp | E37: 2880359168 | F37: 3200988672 | G37: 3844379648 | H37: 4018018304 | I37: 3742175488 | J37: 5107334656 | K37: 3701906944 | L37: 2762795520 | M37: 3318009600 | N37: 3226009856 | O37: 3537859840 | P37: 3074961152 | Q37: 2206073088 | R37: 1946535040 | S37: 1348225152 | T37: 735207872 | U37: 387202208 | V37: 257850816 | W37: 386776224 | X37: 187755264 | Y37: 1043894912 | Z37: 1093524736 | AA37: 1129781888 | AB37: 1261711488 | AC37: 1335236864 | AD37: 2075828864 | AE37: 1033846336 | AF37: 835120704 | AG37: 887649856 | AH37: 880607360 | AI37: 737742912 | AJ37: 1063286528 | AK37: 1531425408 | AL37: 1173681280 | AM37: 1580360704 | AN37: 1080833792 | AO37: 941983808 | AP37: 889422144 | AQ37: 3996853504 | AR37: 3381658880 | AZ37: BNE CN EQUITY
... A58: CRT-U | B58: 126462100 | C58: =A58&" CN EQUITY" -> CRT-U CN EQUITY | D58: CT Real Estate Investment Trus | E58: 3368365568 | F58: 3745509376 | G58: 3106722048 | H58: 3363651328 | I58: 3441017600 | J58: 3215531008 | K58: 3551411968 | L58: 3719106304 | M58: 3617022464 | N58: 3482457088 | O58: 3844391424 | P58: 4101921536 | Q58: 4018398208 | R58: 3951115520 | S58: 3722534912 | T58: 3715717120 | U58: 3561179648 | V58: 3174835968 | W58: 3086204160 | X58: 2658953472 | Y58: 3667992320 | Z58: 3292231936 | AA58: 3114806272 | AB58: 3145472512 | AC58: 2525577728 | AD58: 2435382016 | AE58: 2444858112 | AF58: 2520667904 | AG58: 2748096512 | AH58: 2632486912 | AI58: 2725353472 | AJ58: 2850439424 | AK58: 2842858496 | AL58: 2918667776 | AM58: 2804953600 | AN58: 2738626560 | AO58: 2463810560 | AP58: 2437277184 | AQ58: 2290803200 | AR58: 2401419776 | AZ58: CHP-U CN EQUITY
A59: CS | B59: 14071L108 | C59: =A59&" CN EQUITY" -> CS CN EQUITY | D59: Capstone Copper Corp | E59: 6773049856 | F59: 8036252672 | G59: 7311205888 | H59: 6490013184 | I59: 4480161280 | J59: 4000624640 | K59: 4174262784 | L59: 4224392448 | M59: 3416378368 | N59: 2248458496 | O59: 2241561344 | P59: 2925462016 | Q59: -- | R59: -- | S59: -- | T59: -- | U59: -- | V59: -- | W59: -- | X59: -- | Y59: -- | Z59: -- | AA59: -- | AB59: -- | AC59: -- | AD59: -- | AE59: -- | AF59: -- | AG59: -- | AH59: -- | AI59: -- | AJ59: -- | AK59: -- | AL59: -- | AM59: -- | AN59: -- | AO59: -- | AP59: -- | AQ59: -- | AR59: -- | AZ59: CIGI CN EQUITY
A60: CSH-U | B60: 16141A103 | C60: =A60&" CN EQUITY" -> CSH-U CN EQUITY | D60: Chartwell Retirement Residence | E60: 4102958592 | F60: 4238998272 | G60: 3483450880 | H60: 2867942400 | I60: 2719440640 | J60: 2385311488 | K60: 2197363712 | L60: 1983892224 | M60: 1958368512 | N60: 2155597568 | O60: 2587181056 | P60: 2877223936 | Q60: 2742643968 | R60: 2798332160 | S60: 2788822016 | T60: 2464687104 | U60: 2355238912 | V60: 2125819008 | W60: 1972170624 | X60: 1883770240 | Y60: 2925632000 | Z60: 3098223360 | AA60: 3203461888 | AB60: 3152947200 | AC60: 2877222400 | AD60: 3081385216 | AE60: 3226614272 | AF60: 3293967104 | AG60: 3422358016 | AH60: 2844364032 | AI60: 2956993280 | AJ60: 2976082944 | AK60: 2796639744 | AL60: 3016171264 | AM60: 2746574848 | AN60: 2455719936 | AO60: 2211889664 | AP60: 2140482176 | AQ60: 1999408896 | AR60: 2152673536 | AZ60: CJ CN EQUITY
A61: CSU | B61: 21037X100 | C61: =A61&" CN EQUITY" -> CSU CN EQUITY | D61: Constellation Software Inc/Can | E61: 94194442240 | F61: 93242728448 | G61: 83534471168 | H61: 77984833536 | I61: 69619900416 | J61: 59422531584 | K61: 58165665792 | L61: 53845770240 | M61: 44798046208 | N61: 40732028928 | O61: 40494260224 | P61: 45286297600 | Q61: 49735249920 | R61: 43972849664 | S61: 39785189376 | T61: 37191983104 | U61: 35027902464 | V61: 31355623424 | W61: 32484284416 | X61: 27104391168 | Y61: 26725910528 | Z61: 28039573504 | AA61: 26155644928 | AB61: 23999408128 | AC61: 18518429696 | AD61: 20129198080 | AE61: 21605824512 | AF61: 18524575744 | AG61: 16148369408 | AH61: 14425922560 | AI61: 14375486464 | AJ61: 13848665088 | AK61: 12929376256 | AL61: 12533094400 | AM61: 10595977216 | AN61: 11269443584 | AO61: 12224969728 | AP61: 11853481984 | AQ61: 10508032000 | AR61: 9276804096 | AZ61: CJT CN EQUITY
A62: CTC/A | B62: 136681202 | C62: =A62&" CN EQUITY" -> CTC/A CN EQUITY | D62: Canadian Tire Corp Ltd | E62: 8569640448 | F62: 9214227456 | G62: 7811085824 | H62: 7897531392 | I62: 8302108160 | J62: 8561821696 | K62: 10567449600 | L62: 10518343680 | M62: 8664607744 | N62: 9128472576 | O62: 10022731776 | P62: 11846567936 | Q62: 11454157824 | R62: 11026538496 | S62: 12119428096 | T62: 10959507456 | U62: 10286731264 | V62: 8399982592 | W62: 7503766016 | X62: 5572677632 | Y62: 8733616128 | Z62: 9390615552 | AA62: 9095933952 | AB62: 9341266944 | AC62: 9341231104 | AD62: 10021190656 | AE62: 11547355136 | AF62: 11476426752 | AG62: 11241613312 | AH62: 10869873664 | AI62: 10480175104 | AJ62: 11265765376 | AK62: 10065374208 | AL62: 9696525312 | AM62: 10446338048 | AN62: 10175785984 | AO62: 9157234688 | AP62: 9472537600 | AQ62: 10603462656 | AR62: 10355876864 | AZ62: CLS CN EQUITY
A63: CU | B63: 136717832 | C63: =A63&" CN EQUITY" -> CU CN EQUITY | D63: Canadian Utilities Ltd | E63: 9525522432 | F63: 9815126016 | G63: 8068053504 | H63: 8412577280 | I63: 8801395712 | J63: 7761846784 | K63: 9256853504 | L63: 10185342976 | M63: 9883213824 | N63: 9699207168 | O63: 10341209088 | P63: 10335266816 | Q63: 9877970944 | R63: 9190374400 | S63: 9317373952 | T63: 9225354240 | U63: 8412517888 | V63: 8691602432 | W63: 9183868928 | X63: 9218519040 | Y63: 10690094080 | Z63: 10666741760 | AA63: 10091143168 | AB63: 9965676544 | AC63: 8533787136 | AD63: 8631492608 | AE63: 9014359040 | AF63: 9327646720 | AG63: 10115846144 | AH63: 10472545280 | AI63: 11225876480 | AJ63: 10462190592 | AK63: 9708345344 | AL63: 9929278464 | AM63: 10004930560 | AN63: 9720982528 | AO63: 8499457024 | AP63: 9569776640 | AQ63: 9506328576 | AR63: 10477035520 | AZ63: CM CN EQUITY
A64: CVE | B64: 15135U109 | C64: =A64&" CN EQUITY" -> CVE CN EQUITY | D64: Cenovus Energy Inc | E64: 39772246016 | F64: 41557524480 | G64: 49979944960 | H64: 50483478528 | I64: 41414766592 | J64: 53407502336 | K64: 42715103232 | L64: 44980989952 | M64: 50371678208 | N64: 40975835136 | O64: 48236056576 | P64: 41316782080 | Q64: 31292762112 | R64: 25763739648 | S64: 23926581248 | T64: 19043688448 | U64: 9523034112 | V64: 6377360896 | W64: 7802744320 | X64: 3489613056 | Y64: 16219327488 | Z64: 15272883200 | AA64: 14191617024 | AB64: 14252903424 | AC64: 11795506176 | AD64: 15936220160 | AE64: 16771735552 | AF64: 13479824384 | AG64: 14105446400 | AH64: 15371004928 | AI64: 11746339840 | AJ64: 12539597824 | AK64: 16913858560 | AL64: 15689051136 | AM64: 14889184256 | AN64: 14080985088 | AO64: 14580897792 | AP64: 16863849472 | AQ64: 16548003840 | AR64: 17594945536 | AZ64: CMG CN EQUITY
A65: CWB | B65: 13677F101 | C65: =A65&" CN EQUITY" -> CWB CN EQUITY | D65: Canadian Western Bank | E65: 5683631104 | F65: 5205165056 | G65: 4188116992 | H65: 2720866816 | I65: 2976918528 | J65: 2712062976 | K65: 2380728832 | L65: 2382763520 | M65: 2269486336 | N65: 2091290880 | O65: 2383548416 | P65: 3278934784 | Q65: 3248862208 | R65: 3195176704 | S65: 3031680512 | T65: 2786323712 | U65: 2492797184 | V65: 2338630400 | W65: 2059911040 | X65: 1690316032 | Y65: 2781601536 | Z65: 2900296960 | AA65: 2605830656 | AB65: 2461077504 | AC65: 2316312576 | AD65: 3032480512 | AE65: 3077993472 | AF65: 2931879936 | AG65: 3473403392 | AH65: 2978654464 | AI65: 2417660928 | AJ65: 2597352704 | AK65: 2673786112 | AL65: 2223419392 | AM65: 2018394240 | AN65: 1975748608 | AO65: 1882699520 | AP65: 1889806208 | AQ65: 2314579200 | AR65: 2229765888 | AZ65: CNQ CN EQUITY
A66: CXB | B66: 13000C205 | C66: =A66&" CN EQUITY" -> CXB CN EQUITY | D66: Calibre Mining Corp | E66: 1800023296 | F66: 2055945728 | G66: 1417893632 | H66: 1197678720 | I66: 630579968 | J66: 592245248 | K66: 633246848 | L66: 594484800 | M66: 405069792 | N66: 427069088 | O66: 434890560 | P66: 662051904 | Q66: 455884576 | R66: 458285376 | S66: 549788480 | T66: 539792320 | U66: 799265984 | V66: 604403648 | W66: 449389120 | X66: 198452848 | Y66: 308264128 | Z66: 25996516 | AA66: 25996516 | AB66: 22410788 | AC66: 15629876 | AD66: 17270262 | AE66: 17196928 | AF66: 25013714 | AG66: 40647284 | AH66: 43774000 | AI66: 46900712 | AJ66: 70328568 | AK66: 40440528 | AL66: 44259408 | AM66: 36672084 | AN66: 31207528 | AO66: 15603764 | AP66: 22291092 | AQ66: 31207528 | AR66: 27863864 | AZ66: CNR CN EQUITY
A67: DFY | B67: 24477T100 | C67: =A67&" CN EQUITY" -> DFY CN EQUITY | D67: Definity Financial Corp | E67: 6773928448 | F67: 6317310976 | G67: 5212853760 | H67: 4999610880 | I67: 4350611968 | J67: 4345976320 | K67: 4073628416 | L67: 4087535616 | M67: 4459551232 | N67: 4498954752 | O67: 3855750144 | P67: 3700453888 | Q67: 3422311424 | R67: -- | S67: -- | T67: -- | U67: -- | V67: -- | W67: -- | X67: -- | Y67: -- | Z67: -- | AA67: -- | AB67: -- | AC67: -- | AD67: -- | AE67: -- | AF67: -- | AG67: -- | AH67: -- | AI67: -- | AJ67: -- | AK67: -- | AL67: -- | AM67: -- | AN67: -- | AO67: -- | AP67: -- | AQ67: -- | AR67: -- | AZ67: CP CN EQUITY
A68: DIR-U | B68: 26153W109 | C68: =A68&" CN EQUITY" -> DIR-U CN EQUITY | D68: Dream Industrial Real Estate I | E68: 3403561728 | F68: 4161509632 | G68: 3651407872 | H68: 3771505408 | I68: 3991843584 | J68: 3674213120 | K68: 3851220480 | L68: 4012256768 | M68: 3190699264 | N68: 2928674304 | O68: 3297146880 | P68: 4206145280 | Q68: 4244614656 | R68: 3693484032 | S68: 3156148992 | T68: 2569537024 | U68: 2242051072 | V68: 1928334464 | W68: 1820920576 | X68: 1600977920 | Y68: 2003913856 | Z68: 1800327168 | AA68: 1605734016 | AB68: 1253244160 | AC68: 868698112 | AD68: 915370176 | AE68: 927926592 | AF68: 718673600 | AG68: 656935808 | AH68: 529991712 | AI68: 506695392 | AJ68: 478739808 | AK68: 496794432 | AL68: 457190656 | AM68: 508442592 | AN68: 468256416 | AO68: 418169280 | AP68: 458355488 | AQ68: 476410144 | AR68: 496118368 | AZ68: CPX CN EQUITY
A69: DML | B69: 248356107 | C69: =A69&" CN EQUITY" -> DML CN EQUITY | D69: Denison Mines Corp | E69: 2337781504 | F69: 2195788544 | G69: 2444807680 | H69: 2361140480 | I69: 2066795648 | J69: 1874472704 | K69: 1387381248 | L69: 1227965824 | M69: 1277150720 | N69: 1317849088 | O69: 1038274752 | P69: 1661995008 | Q69: 1404810752 | R69: 1482567936 | S69: 1215033856 | T69: 1086598272 | U69: 570149824 | V69: 350592000 | W69: 300507424 | X69: 220961104 | Y69: 322483776 | Z69: 377738496 | AA69: 412687264 | AB69: 400607648 | AC69: 371180320 | AD69: 475305728 | AE69: 357877248 | AF69: 324326272 | AG69: 385768224 | AH69: 324268960 | AI69: 313087264 | AJ69: 458438144 | AK69: 373393280 | AL69: 325385600 | AM69: 378832192 | AN69: 378460224 | AO69: 362907072 | AP69: 259219328 | AQ69: 466594784 | AR69: 511503040 | AZ69: CRDL CN EQUITY
A70: DOL | B70: 25675T107 | C70: =A70&" CN EQUITY" -> DOL CN EQUITY | D70: Dollarama Inc | E70: 39353491456 | F70: 39037349888 | G70: 35447115776 | H70: 28765302784 | I70: 26855763968 | J70: 26451705856 | K70: 25606664192 | L70: 22979520512 | M70: 22747238400 | N70: 22853500928 | O70: 21628858368 | P70: 20760481792 | Q70: 18854285312 | R70: 16640269312 | S70: 17339695104 | T70: 17225992192 | U70: 16144056320 | V70: 15879832576 | W70: 14018636800 | X70: 12111419392 | Y70: 13934418944 | Z70: 14930022400 | AA70: 14500116480 | AB70: 11218530304 | AC70: 10388619264 | AD70: 13298573312 | AE70: 16701583360 | AF70: 17118242816 | AG70: 17539588096 | AH70: 15337324544 | AI70: 14077144064 | AJ70: 12626290688 | AK70: 11546369024 | AL70: 12171290624 | AM70: 10803297280 | AN70: 11170152448 | AO70: 9976368128 | AP70: 11521564672 | AQ70: 9792235520 | AR70: 9173778432 | AZ70: CRON CN EQUITY
A71: DOO | B71: 05577W200 | C71: =A71&" CN EQUITY" -> DOO CN EQUITY | D71: BRP Inc | E71: 5345073664 | F71: 5875975680 | G71: 6633540608 | H71: 7014782464 | I71: 7187983360 | J71: 7889257472 | K71: 8741353472 | L71: 8345173504 | M71: 8129008128 | N71: 6747694080 | O71: 6278613504 | P71: 8294761984 | Q71: 9086111744 | R71: 9458239488 | S71: 8147047936 | T71: 9361402880 | U71: 7393334272 | V71: 6160522752 | W71: 5054594560 | X71: 2130297600 | Y71: 5246333440 | Z71: 4644616704 | AA71: 4512220160 | AB71: 3602003456 | AC71: 3432673024 | AD71: 6856965120 | AE71: 7290829824 | AF71: 5805546496 | AG71: 5490922496 | AH71: 4416009216 | AI71: 4248201728 | AJ71: 3496844032 | AK71: 3163585792 | AL71: 2887603712 | AM71: 2353289216 | AN71: 2233376768 | AO71: 2299960576 | AP71: 2962044672 | AQ71: 3451366144 | AR71: 2870619904 | AZ71: CRR-U CN EQUITY
A72: DPM | B72: 26139R109 | C72: =A72&" CN EQUITY" -> DPM CN EQUITY | D72: DPM Metals Inc | E72: 2323778560 | F72: 2458155776 | G72: 1943069056 | H72: 1868684416 | I72: 1634024960 | J72: 1618609664 | K72: 1686051712 | L72: 1894158720 | M72: 1254422528 | N72: 1183126656 | O72: 1235153280 | P72: 1437479552 | Q72: 1506848512 | R72: 1468310144 | S72: 1456600832 | T72: 1431570816 | U72: 1707806080 | V72: 1780597760 | W72: 1668610560 | X72: 795828224 | Y72: 1000162496 | Z72: 799413056 | AA72: 871147392 | AB72: 790816128 | AC72: 642649728 | AD72: 542681984 | AE72: 560366144 | AF72: 549658560 | AG72: 535381696 | AH72: 478221056 | AI72: 431826496 | AJ72: 503176064 | AK72: 361323264 | AL72: 520305472 | AM72: 432778016 | AN72: 295075936 | AO72: 179855808 | AP72: 306316896 | AQ72: 356901344 | AR72: 382193568 | AZ72: CRT-U CN EQUITY
A73: DSG | B73: 249906108 | C73: =A73&" CN EQUITY" -> DSG CN EQUITY | D73: Descartes Systems Group Inc/Th | E73: 13963799552 | F73: 11884973056 | G73: 11307637760 | H73: 10554229760 | I73: 9466679296 | J73: 8475804160 | K73: 9020594176 | L73: 9252467712 | M73: 8005970432 | N73: 7436978688 | O73: 6781677056 | P73: 7755193344 | Q73: 8855873536 | R73: 8724895744 | S73: 7245424128 | T73: 6478412288 | U73: 6289832448 | V73: 6407236608 | W73: 6031641088 | X73: 4074007296 | Y73: 4670404096 | Z73: 4499056128 | AA73: 4075757312 | AB73: 3748498176 | AC73: 2769430272 | AD73: 3367436544 | AE73: 3289977856 | AF73: 2826800128 | AG73: 2743884800 | AH73: 2611019776 | AI73: 2396831232 | AJ73: 2311901696 | AK73: 2170688768 | AL73: 2140234368 | AM73: 1872083584 | AN73: 1915242752 | AO73: 2109163520 | AP73: 1784831488 | AQ73: 1513674624 | AR73: 1441677440 | AZ73: CSH-U CN EQUITY
A74: EFN | B74: 286181201 | C74: =A74&" CN EQUITY" -> EFN CN EQUITY | D74: Element Fleet Management Corp | E74: 11767254016 | F74: 11607781376 | G74: 9683081216 | H74: 8534470144 | I74: 8388237824 | J74: 7590664192 | K74: 7871742976 | L74: 6964645888 | M74: 7241244160 | N74: 6429122560 | O74: 5332774400 | P74: 4837142528 | Q74: 5287262208 | R74: 5385560576 | S74: 6235172352 | T74: 6021674496 | U74: 5891606016 | V74: 4852516352 | W74: 4433722880 | X74: 3911121664 | Y74: 4826550784 | Z74: 4613294592 | AA74: 4157134336 | AB74: 3665961472 | AC74: 2993437184 | AD74: 2530662656 | AE74: 2350599168 | AF74: 1578476672 | AG74: 3610200320 | AH74: 3586173952 | AI74: 3462304512 | AJ74: 4765406208 | AK74: 4823338496 | AL74: 6350423552 | AM74: 5293072384 | AN74: 5405883904 | AO74: 6442829312 | AP74: 6995360256 | AQ74: 5218020352 | AR74: 4520785920 | AZ74: CSU CN EQUITY
A75: EFR | B75: 292671708 | C75: =A75&" CN EQUITY" -> EFR CN EQUITY | D75: Energy Fuels Inc/Canada | E75: 1457680000 | F75: 1205744384 | G75: 1336947968 | H75: 1365976960 | I75: 1524583424 | J75: 1767177728 | K75: 1302337024 | L75: 1188336000 | M75: 1319728384 | N75: 1317466752 | O75: 990834944 | P75: 1798818688 | Q75: 1503295488 | R75: 1190181120 | S75: 1006146304 | T75: 961816768 | U75: 684863808 | V75: 278795456 | W75: 234530800 | X75: 183830208 | Y75: 245018944 | Z75: 249069184 | AA75: 380619744 | AB75: 405368288 | AC75: 346560608 | AD75: 370390528 | AE75: 232753248 | AF75: 164217808 | AG75: 168069024 | AH75: 142723936 | AI75: 145121600 | AJ75: 191254832 | AK75: 147272896 | AL75: 139973312 | AM75: 167833648 | AN75: 156746192 | AO75: 185582992 | AP75: 176167824 | AQ75: 246755664 | AR75: 111802120 | AZ75: CSW/A CN EQUITY
A76: EFX | B76: 29269R105 | C76: =A76&" CN EQUITY" -> EFX CN EQUITY | D76: Enerflex Ltd | E76: 1775931520 | F76: 999801152 | G76: 915450688 | H76: 976780096 | I76: 759739904 | J76: 966299712 | K76: 1116672256 | L76: 996099136 | M76: 1056517760 | N76: 531808128 | O76: 545260288 | P76: 718344512 | Q76: 686939968 | R76: 832219712 | S76: 752405504 | T76: 727295424 | U76: 588293248 | V76: 414316256 | W76: 460949248 | X76: 522827680 | Y76: 1096527360 | Z76: 1041835456 | AA76: 1526263808 | AB76: 1704823680 | AC76: 1419427072 | AD76: 1464660608 | AE76: 1252891776 | AF76: 1359980544 | AG76: 1358209664 | AH76: 1628959360 | AI76: 1666142080 | AJ76: 1675873536 | AK76: 1504035328 | AL76: 1240266112 | AM76: 845823360 | AN76: 808480320 | AO76: 1051309120 | AP76: 1042687680 | AQ76: 1066482496 | AR76: 1208643456 | AZ76: CTC/A CN EQUITY
A77: EIF | B77: 301283107 | C77: =A77&" CN EQUITY" -> EIF CN EQUITY | D77: Exchange Income Corp | E77: 2847026176 | F77: 2446656000 | G77: 2131518208 | H77: 2299478528 | I77: 2094657152 | J77: 2082581504 | K77: 2434168064 | L77: 2267228928 | M77: 2228277504 | N77: 1754509184 | O77: 1607330560 | P77: 1631741824 | Q77: 1607330560 | R77: 1676618496 | S77: 1507557248 | T77: 1423703424 | U77: 1260193536 | V77: 1044543680 | W77: 920037632 | X77: 610492288 | Y77: 1537064704 | Z77: 1306939776 | AA77: 1205337984 | AB77: 1044100416 | AC77: 891697728 | AD77: 1043469376 | AE77: 994734464 | AF77: 958099456 | AG77: 1106502400 | AH77: 1075638400 | AI77: 1018053440 | AJ77: 1202202240 | AK77: 1153686784 | AL77: 972689280 | AM77: 862709056 | AN77: 766269120 | AO77: 742098624 | AP77: 632514816 | AQ77: 465270560 | AR77: 491272352 | AZ77: CTS CN EQUITY
A78: ELD | B78: 284902509 | C78: =A78&" CN EQUITY" -> ELD CN EQUITY | D78: Eldorado Gold Corp | E78: 4381101056 | F78: 4815821824 | G78: 4136322560 | H78: 3869880832 | I78: 3519816448 | J78: 2477483776 | K78: 2720048384 | L78: 2587207936 | M78: 2093457664 | N78: 1542324096 | O78: 1516256000 | P78: 2567146752 | Q78: 2166336000 | R78: 1789422080 | S78: 2245211392 | T78: 2390657536 | U78: 2948857088 | V78: 2446501376 | W78: 2194374144 | X78: 1443429120 | Y78: 1656699648 | Z78: 1629473920 | AA78: 1208481152 | AB78: 979806656 | AC78: 635208576 | AD78: 897232064 | AE78: 1056034176 | AF78: 857531520 | AG78: 1445099392 | AH78: 2175589376 | AI78: 2458726144 | AJ78: 3260471552 | AK78: 3095656448 | AL78: 3697589504 | AM78: 4163371264 | AN78: 2923675648 | AO78: 2938007296 | AP78: 3066993152 | AQ78: 3711921408 | AR78: 4163371264 | AZ78: CU CN EQUITY
A79: EMA | B79: 290876101 | C79: =A79&" CN EQUITY" -> EMA CN EQUITY | D79: Emera Inc | E79: 15854921728 | F79: 15493142528 | G79: 13151012864 | H79: 13626455040 | I79: 13993465856 | J79: 13007181824 | K79: 14889816064 | L79: 15067392000 | M79: 13955172352 | N79: 14934337536 | O79: 15987106816 | P79: 16248732672 | Q79: 16431545344 | R79: 14807433216 | S79: 14270458880 | T79: 14132684800 | U79: 13581103104 | V79: 13546866688 | W79: 13073105920 | X79: 13462237184 | Y79: 13450780672 | Z79: 13988206592 | AA79: 12620336128 | AB79: 11785388032 | AC79: 10183107584 | AD79: 9311603712 | AE79: 9869323264 | AF79: 9395371008 | AG79: 10703022080 | AH79: 10025543680 | AI79: 10174572544 | AJ79: 9914984448 | AK79: 9529314304 | AL79: 9484761088 | AM79: 7205317120 | AN79: 7044147712 | AO79: 6143021568 | AP79: 6290806272 | AQ79: 5590248960 | AR79: 5854556672 | AZ79: CWB CN EQUITY
... A84: EQX | B84: 29446Y502 | C84: =A84&" CN EQUITY" -> EQX CN EQUITY | D84: Equinox Gold Corp | E84: 3295870720 | F84: 3543916544 | G84: 3059192576 | H84: 2647748096 | I84: 2015715200 | J84: 1786926720 | K84: 1899394176 | L84: 2166210816 | M84: 1351455872 | N84: 1528329472 | O84: 1740966784 | P84: 3118488064 | Q84: 2573426944 | R84: 2511752960 | S84: 2573295872 | T84: 2431082496 | U84: 3187229184 | V84: 3748070912 | W84: 3373910016 | X84: 2029748864 | Y84: 1133148288 | Z84: 797213248 | AA84: 739807168 | AB84: 776702592 | AC84: 597996352 | AD84: 429126656 | AE84: 414802208 | AF84: 469827008 | AG84: 453051360 | AH84: 179510096 | AI84: 199060704 | AJ84: 166812992 | AK84: 28335820 | AL84: 34645208 | AM84: 33138894 | AN84: 28117850 | AO84: 11462639 | AP84: 18984996 | AQ84: 23283486 | AR84: 23641694 | AZ84: DML CN EQUITY
A85: ERO | B85: 296006109 | C85: =A85&" CN EQUITY" -> ERO CN EQUITY | D85: ERO Copper Corp | E85: 2002039680 | F85: 3107836928 | G85: 3018038784 | H85: 2684087296 | I85: 2146276736 | J85: 2188167424 | K85: 2485741056 | L85: 2205943808 | M85: 1713268864 | N85: 1385552512 | O85: 983659392 | P85: 1652191488 | Q85: 1713254784 | R85: 1984895232 | S85: 2292896256 | T85: 1905644288 | U85: 1773325696 | V85: 1675043328 | W85: 1687659264 | X85: 906451264 | Y85: 2020393728 | Z85: 1655850112 | AA85: 1885602688 | AB85: 1353808512 | AC85: 830305152 | AD85: 1030761536 | AE85: 827665344 | AF85: 666803264 | AG85: 565453056 | AH85: -- | AI85: -- | AJ85: -- | AK85: -- | AL85: -- | AM85: -- | AN85: -- | AO85: -- | AP85: -- | AQ85: -- | AR85: -- | AZ85: DND CN EQUITY
A86: FCR-U | B86: 31890B103 | C86: =A86&" CN EQUITY" -> FCR-U CN EQUITY | D86: First Capital Real Estate Inve | E86: 3602285824 | F86: 3982479872 | G86: 3122264320 | H86: 3336787200 | I86: 3258199552 | J86: 2824905728 | K86: 3105272320 | L86: 3447343872 | M86: 3684033536 | N86: 3313657856 | O86: 3282975744 | P86: 3933872896 | Q86: 4133306112 | R86: 3835252224 | S86: 3857167872 | T86: 3613903360 | U86: 2969580800 | V86: 2840278016 | W86: 3041902848 | X86: 2987113472 | Y86: 4529980416 | Z86: 4835377152 | AA86: 4788977664 | AB86: 5456065536 | AC86: 4803044352 | AD86: 4968637440 | AE86: 5059417600 | AF86: 4974684160 | AG86: 5057326592 | AH86: 4800151552 | AI86: 4824393728 | AJ86: 4877798912 | AK86: 5029232128 | AL86: 5337139200 | AM86: 5201892864 | AN86: 4651050496 | AO86: 4136291584 | AP86: 4196864000 | AQ86: 3970176768 | AR86: 4374793216 | AZ86: DOL CN EQUITY
A87: FFH | B87: 303901102 | C87: =A87&" CN EQUITY" -> FFH CN EQUITY | D87: Fairfax Financial Holdings Ltd | E87: 49466580992 | F87: 42448531456 | G87: 39036051456 | H87: 37567676416 | I87: 31612874752 | J87: 28719067136 | K87: 25766432768 | L87: 23438426112 | M87: 21033381888 | N87: 16643822592 | O87: 18054483968 | P87: 18097100800 | Q87: 17755101184 | R87: 14589806592 | S87: 15511175168 | T87: 15678749696 | U87: 12443559936 | V87: 11288276992 | W87: 12150801408 | X87: 12518356992 | Y87: 17692194816 | Z87: 16945323008 | AA87: 18650300416 | AB87: 17960882176 | AC87: 17619220480 | AD87: 20573249536 | AE87: 21666048000 | AF87: 18601347072 | AG87: 19750488064 | AH87: 19238414336 | AI87: 13798586368 | AJ87: 14858995712 | AK87: 15922106368 | AL87: 18897395712 | AM87: 17105546240 | AN87: 17873516544 | AO87: 15491868672 | AP87: 13470948352 | AQ87: 13651377152 | AR87: 15737607168 | AZ87: DOO CN EQUITY
A88: FIL | B88: 31729R105 | C88: =A88&" CN EQUITY" -> FIL CN EQUITY | D88: Filo Corp | E88: 4318508032 | F88: 4340918272 | G88: 3285262592 | H88: 3091839488 | I88: 2759777280 | J88: 2651675648 | K88: 3358573568 | L88: 2871713280 | M88: 2860375040 | N88: 2032628736 | O88: 2161838592 | P88: 2327792640 | Q88: 1464118016 | R88: 1018424576 | S88: 1163198464 | T88: 348927936 | U88: 213787584 | V88: 206033632 | W88: 172908160 | X88: 110273064 | Y88: 172025984 | Z88: 220383120 | AA88: 206149776 | AB88: 174135440 | AC88: 159665424 | AD88: 163161072 | AE88: 173313312 | AF88: 149538688 | AG88: 150027808 | AH88: 155483632 | AI88: 130238744 | AJ88: 113809432 | AK88: 104771976 | AL88: 87160616 | AM88: -- | AN88: -- | AO88: -- | AP88: -- | AQ88: -- | AR88: -- | AZ88: DRM CN EQUITY
A89: FM | B89: 335934105 | C89: =A89&" CN EQUITY" -> FM CN EQUITY | D89: First Quantum Minerals Ltd | E89: 15457840128 | F89: 15382761472 | G89: 14928839680 | H89: 12136213504 | I89: 7525756928 | J89: 22251012096 | K89: 21717753856 | L89: 21516132352 | M89: 19590967296 | N89: 16222424064 | O89: 16893035520 | P89: 29913159680 | Q89: 20917751808 | R89: 16204810240 | S89: 19725148160 | T89: 16534925312 | U89: 15753036800 | V89: 8183258624 | W89: 7459318784 | X89: 4956793344 | Y89: 9079324672 | Z89: 7672960512 | AA89: 8576018432 | AB89: 10444267520 | AC89: 7610871808 | AD89: 10140870656 | AE89: 13353374720 | AF89: 12470962176 | AG89: 12140058624 | AH89: 9658208256 | AI89: 7465980928 | AJ89: 9740852224 | AK89: 9207999488 | AL89: 7486135296 | AM89: 6252232704 | AN89: 4715024384 | AO89: 3563841536 | AP89: 3369049344 | AQ89: 11243943936 | AR89: 9217763328 | AZ89: D-U CN EQUITY
A90: FNV | B90: 351858105 | C90: =A90&" CN EQUITY" -> FNV CN EQUITY | D90: Franco-Nevada Corp | E90: 32515876864 | F90: 32323835904 | G90: 31170791424 | H90: 31017052160 | I90: 28197365760 | J90: 34825441280 | K90: 36243701760 | L90: 37827805184 | M90: 35355557888 | N90: 31606802432 | O90: 32421685248 | P90: 38064062464 | Q90: 33704636416 | R90: 31446433792 | S90: 34363199488 | T90: 30073735168 | U90: 30456745984 | V90: 35462799360 | W90: 36023160832 | X90: 26630369280 | Y90: 25289373696 | Z90: 22623963136 | AA90: 20808826880 | AB90: 18743527424 | AC90: 17840529408 | AD90: 15043224576 | AE90: 17850920960 | AF90: 16343276544 | AG90: 18658207744 | AH90: 17265985536 | AI90: 16714031104 | AJ90: 15444838400 | AK90: 14232226816 | AL90: 16249700352 | AM90: 17416218624 | AN90: 14140040192 | AO90: 9905197056 | AP90: 9226073088 | AQ90: 9321526272 | AR90: 9604755456 | AZ90: DXT CN EQUITY
A91: FRU | B91: 356500108 | C91: =A91&" CN EQUITY" -> FRU CN EQUITY | D91: Freehold Royalties Ltd | E91: 2097052672 | F91: 2117185152 | G91: 2050590848 | H91: 2196631552 | I91: 2061129856 | J91: 2213192704 | K91: 2023490560 | L91: 2187598080 | M91: 2383322624 | N91: 2165014528 | O91: 1918100480 | P91: 2154475520 | Q91: 1753992960 | R91: 1367213440 | S91: 1256445568 | T91: 932367552 | U91: 667900928 | V91: 436499936 | W91: 416390176 | X91: 347780448 | Y91: 862353536 | Z91: 889560832 | AA91: 1001938880 | AB91: 994841344 | AC91: 978280384 | AD91: 1317780352 | AE91: 1464783104 | AF91: 1458876672 | AG91: 1659693696 | AH91: 1738115328 | AI91: 1538833536 | AJ91: 1589538304 | AK91: 1664796160 | AL91: 1486215296 | AM91: 1399274752 | AN91: 1032814656 | AO91: 1064171456 | AP91: 1060251840 | AQ91: 1581558656 | AR91: 1328611712 | AZ91: ECN CN EQUITY
A92: FSV | B92: 33767E202 | C92: =A92&" CN EQUITY" -> FSV CN EQUITY | D92: FirstService Corp | E92: 12130896896 | F92: 11470063616 | G92: 9640676352 | H92: 10382120960 | I92: 9864953856 | J92: 9076809728 | K92: 9367478272 | L92: 8735378432 | M92: 7552593408 | N92: 7486436352 | O92: 7107215872 | P92: 8198601728 | Q92: 11250200576 | R92: 10349477888 | S92: 9600914432 | T92: 8420303360 | U92: 7821754880 | V92: 7870922240 | W92: 6118059520 | X92: 4647005696 | Y92: 5166252544 | Z92: 5507587584 | AA92: 4925031936 | AB92: 4289990144 | AC92: 3370279936 | AD92: 3923908352 | AE92: 3591558400 | AF92: 3390865664 | AG92: 3156789504 | AH92: 2946674432 | AI92: 2990406144 | AJ92: 2882104576 | AK92: 2293939712 | AL92: 2196049408 | AM92: 2127946752 | AN92: 1849474688 | AO92: 1937930752 | AP92: 1494526080 | AQ92: 1202871424 | AR92: -- | AZ92: EDR CN EQUITY
A93: FTS | B93: 349553107 | C93: =A93&" CN EQUITY" -> FTS CN EQUITY | D93: Fortis Inc/Canada | E93: 29710055424 | F93: 30435891200 | G93: 26213992448 | H93: 26385614848 | I93: 26622019584 | J93: 25096118272 | K93: 27661459456 | L93: 27699996672 | M93: 26023112704 | N93: 25121777664 | O93: 29033068544 | P93: 29361172480 | Q93: 28860844032 | R93: 26479874048 | S93: 25757257728 | T93: 25452990464 | U93: 24181340160 | V93: 25294180352 | W93: 23971796992 | X93: 25150760960 | Y93: 24876193792 | Z93: 24462931968 | AA93: 22345500672 | AB93: 21167466496 | AC93: 19420108800 | AD93: 17792186368 | AE93: 17776510976 | AF93: 18398349312 | AG93: 19347701760 | AH93: 18713241600 | AI93: 18959661056 | AJ93: 18236987392 | AK93: 16577115136 | AL93: 12001773568 | AM93: 12363799552 | AN93: 11477805056 | AO93: 10484008960 | AP93: 10637632512 | AQ93: 9728902144 | AR93: 10661809152 | AZ93: EFN CN EQUITY
A94: FTT | B94: 318071404 | C94: =A94&" CN EQUITY" -> FTT CN EQUITY | D94: Finning International Inc | E94: 5241908736 | F94: 6144524288 | G94: 5683639808 | H94: 5707958272 | I94: 5537752064 | J94: 5832213504 | K94: 6047952384 | L94: 5071512064 | M94: 5105164800 | N94: 3729926400 | O94: 4216468992 | P94: 5936850944 | Q94: 5095540736 | R94: 5010958336 | S94: 5272785408 | T94: 5186979840 | U94: 4381657600 | V94: 3300427264 | W94: 3000535808 | X94: 2454027008 | Y94: 4131750656 | Z94: 3787165440 | AA94: 3898208512 | AB94: 3883846400 | AC94: 4002941184 | AD94: 5307229696 | AE94: 5464616960 | AF94: 5228042752 | AG94: 5333333504 | AH94: 4795817984 | AI94: 4272953600 | AJ94: 4177273344 | AK94: 4420722688 | AL94: 4101680640 | AM94: 3536859136 | AN94: 3204368128 | AO94: 3161792000 | AP94: 3339281920 | AQ94: 4042165248 | AR94: 4061124864 | AZ94: EFR CN EQUITY
A95: FVI | B95: 349942102 | C95: =A95&" CN EQUITY" -> FVI CN EQUITY | D95: Fortuna Mining Corp | E95: 1894363904 | F95: 1970850944 | G95: 2047902976 | H95: 1542135808 | I95: 1563596928 | J95: 1133902976 | K95: 1253704192 | L95: 1494863872 | M95: 1477024256 | N95: 1008446656 | O95: 1068640512 | P95: 1384764288 | Q95: 1440154880 | R95: 1451299584 | S95: 1280540160 | T95: 1501195136 | U95: 1926687360 | V95: 1558345344 | W95: 1268132096 | X95: 519344640 | Y95: 847942336 | Z95: 657195392 | AA95: 597446592 | AB95: 711731200 | AC95: 799597952 | AD95: 901273792 | AE95: 1194084608 | AF95: 1072760512 | AG95: 1047218624 | AH95: 870667328 | AI95: 1011069184 | AJ95: 1099255296 | AK95: 1114691456 | AL95: 1382063232 | AM95: 1180348160 | AN95: 653982272 | AO95: 401440576 | AP95: 378206048 | AQ95: 586248576 | AR95: 615883136 | AZ95: EFX CN EQUITY
A96: GEI | B96: 374825206 | C96: =A96&" CN EQUITY" -> GEI CN EQUITY | D96: Gibson Energy Inc | E96: 3991487488 | F96: 3614857472 | G96: 3778675712 | H96: 3729271040 | I96: 3254102528 | J96: 3140890112 | K96: 3385378560 | L96: 3070713088 | M96: 3401521920 | N96: 3216941056 | O96: 3495792128 | P96: 3667325696 | Q96: 3285431296 | R96: 3408201216 | S96: 3479010816 | T96: 3244040192 | U96: 3007957504 | V96: 3156338176 | W96: 3089390080 | X96: 2367226624 | Y96: 3868504064 | Z96: 3309089280 | AA96: 3392066304 | AB96: 3321005568 | AC96: 2693788160 | AD96: 2943176960 | AE96: 2521776640 | AF96: 2378624768 | AG96: 2598679296 | AH96: 2528008192 | AI96: 2390457088 | AJ96: 2707100928 | AK96: 2690008832 | AL96: 2497138688 | AM96: 2120393984 | AN96: 2170603520 | AO96: 1743080960 | AP96: 2109855360 | AQ96: 2832636928 | AR96: 3245490432 | AZ96: EIF CN EQUITY
A97: GFL | B97: 36168Q104 | C97: =A97&" CN EQUITY" -> GFL CN EQUITY | D97: GFL Environmental Inc | E97: 25208008704 | F97: 20316045312 | G97: 20062007296 | H97: 17359767552 | I97: 16912013312 | J97: 15922187264 | K97: 18967431168 | L97: 16325914624 | M97: 13578196992 | N97: 11978336256 | O97: 11369575424 | P97: 13754989568 | Q97: 15927661568 | R97: 15577959424 | S97: 12987389952 | T97: 14327352320 | U97: 12111380480 | V97: 9239689216 | W97: 8320464896 | X97: 7106179584 | Y97: -- | Z97: -- | AA97: -- | AB97: -- | AC97: -- | AD97: -- | AE97: -- | AF97: -- | AG97: -- | AH97: -- | AI97: -- | AJ97: -- | AK97: -- | AL97: -- | AM97: -- | AN97: -- | AO97: -- | AP97: -- | AQ97: -- | AR97: -- | AZ97: ELD CN EQUITY
A98: GIB/A | B98: 12532H104 | C98: =A98&" CN EQUITY" -> GIB/A CN EQUITY | D98: CGI Inc | E98: 35763511296 | F98: 35448639488 | G98: 31436994560 | H98: 34791419904 | I98: 33015418880 | J98: 31526590464 | K98: 32872241152 | L98: 30646837248 | M98: 27795421184 | N98: 24746506240 | O98: 24512915456 | P98: 24258500608 | Q98: 27302307840 | R98: 26685585408 | S98: 27983820800 | T98: 26086569984 | U98: 26034667520 | V98: 23456768000 | W98: 22169610240 | X98: 20516491264 | Y98: 29244602368 | Z98: 28226695168 | AA98: 27634690048 | AB98: 25178259456 | AC98: 23176960000 | AD98: 23643387904 | AE98: 23865495552 | AF98: 21430364160 | AG98: 19676489728 | AH98: 19014985728 | AI98: 19653480448 | AJ98: 19094931456 | AK98: 19678152704 | AL98: 19021654016 | AM98: 16773814272 | AN98: 19235538944 | AO98: 17181915136 | AP98: 14966930432 | AQ98: 15379124224 | AR98: 16911358976 | AZ98: EMA CN EQUITY
A99: GIL | B99: 375916103 | C99: =A99&" CN EQUITY" -> GIL CN EQUITY | D99: Gildan Activewear Inc | E99: 10343832576 | F99: 10146657280 | G99: 8744525824 | H99: 8474587136 | I99: 7473541632 | J99: 6650505728 | K99: 7573828096 | L99: 8069687808 | M99: 6663729664 | N99: 7091514368 | O99: 6851954688 | P99: 8889885696 | Q99: 10397535232 | R99: 9120201728 | S99: 9078264832 | T99: 7631346176 | U99: 7061275136 | V99: 5203310592 | W99: 4168394496 | X99: 3570267904 | Y99: 7653981184 | Z99: 9577485312 | AA99: 10336283648 | AB99: 9925949440 | AC99: 8566913536 | AD99: 8166166528 | AE99: 7837863424 | AF99: 8156723712 | AG99: 8901627904 | AH99: 8672088064 | AI99: 8971023360 | AJ99: 8272883712 | AK99: 7902486016 | AL99: 8491477504 | AM99: 8855565312 | AN99: 9647006720 | AO99: 9592529920 | AP99: 9792708608 | AQ99: 10059334656 | AR99: 9050743808 | AZ99: EMP/A CN EQUITY
A100: GRT-U | B100: 387437205 | C100: =A100&" CN EQUITY" -> GRT-U CN EQUITY | D100: Granite Real Estate Investment | E100: 4395181056 | F100: 5171731456 | G100: 4294887680 | H100: 4898034688 | I100: 4862379008 | J100: 4594655232 | K100: 4996236288 | L100: 5331714560 | M100: 4400748544 | N100: 4361605120 | O100: 5200374272 | P100: 6331592192 | Q100: 6924130816 | R100: 5916858368 | S100: 5417656320 | T100: 4714211328 | U100: 4805510144 | V100: 4469735424 | W100: 4052143616 | X100: 3141525504 | Y100: 3565763840 | Z100: 3171774976 | AA100: 2980924672 | AB100: 2916987136 | AC100: 2501599744 | AD100: 2607850752 | AE100: 2520875520 | AF100: 2388766976 | AG100: 2315425536 | AH100: 2353976832 | AI100: 2411333376 | AJ100: 2187078144 | AK100: 2107624960 | AL100: 1884309760 | AM100: 1821781504 | AN100: 1758783232 | AO100: 1784640768 | AP100: 1766775552 | AQ100: 2019709312 | AR100: 2091170176 | AZ100: ENB CN EQUITY
A101: GSY | B101: 380355107 | C101: =A101&" CN EQUITY" -> GSY CN EQUITY | D101: goeasy Ltd | E101: 2788807424 | F101: 3040041984 | G101: 3305978112 | H101: 2666620928 | I101: 2618905600 | J101: 1766567296 | K101: 1828664064 | L101: 1578698496 | M101: 1748287616 | N101: 1705581696 | O101: 1549091840 | P101: 2237420800 | Q101: 2927310848 | R101: 3334078208 | S101: 2602908928 | T101: 1861763584 | U101: 1430532992 | V101: 913129664 | W101: 783429440 | X101: 522358880 | Y101: 997813632 | Z101: 857290880 | AA101: 762768832 | AB101: 592740800 | AC101: 529427904 | AD101: 698614400 | AE101: 545724928 | AF101: 511829376 | AG101: 500644064 | AH101: 386772320 | AI101: 369615296 | AJ101: 408600000 | AK101: 325056000 | AL101: 336379680 | AM101: 248055408 | AN101: 262074864 | AO101: 253808240 | AP101: 208136144 | AQ101: 261978784 | AR101: 273506912 | AZ101: ENGH CN EQUITY
A102: GWO | B102: 39138C106 | C102: =A102&" CN EQUITY" -> GWO CN EQUITY | D102: Great-West Lifeco Inc | E102: 44433571840 | F102: 42929020928 | G102: 37213102080 | H102: 40414670848 | I102: 40882216960 | J102: 36242681856 | K102: 35776344064 | L102: 33393647616 | M102: 29166598144 | N102: 27786825728 | O102: 29285732352 | P102: 34292873216 | Q102: 35330514944 | R102: 35830747136 | S102: 34195146752 | T102: 31042985984 | U102: 28156506112 | V102: 24138360832 | W102: 22078781440 | X102: 22542204928 | Y102: 30866911232 | Z102: 29521240064 | AA102: 27980679168 | AB102: 31963590656 | AC102: 27852646400 | AD102: 30981601280 | AE102: 31952265216 | AF102: 32509200384 | AG102: 34720735232 | AH102: 35542028288 | AI102: 34799341568 | AJ102: 36348776448 | AK102: 34679799808 | AL102: 32059545600 | AM102: 33836769280 | AN102: 35496939520 | AO102: 34416029696 | AP102: 31864477696 | AQ102: 36239986688 | AR102: 36499128320 | AZ102: EQB CN EQUITY
A103: H | B103: 448811208 | C103: =A103&" CN EQUITY" -> H CN EQUITY | D103: Hydro One Ltd | E103: 26536994816 | F103: 28101521408 | G103: 23887095808 | H103: 23663544320 | I103: 23783360512 | J103: 20716083200 | K103: 22663069696 | L103: 23038541824 | M103: 21715382272 | N103: 20224577536 | O103: 20721504256 | P103: 20151627776 | Q103: 19687331840 | R103: 17910626304 | S103: 17922586624 | T103: 17492097024 | U103: 17120030720 | V103: 16863080448 | W103: 15255650304 | X103: 15129420800 | Y103: 14965362688 | Z103: 14610857984 | AA103: 13623480320 | AB103: 12371732480 | AC103: 12066619392 | AD103: 11703131136 | AE103: 11941484544 | AF103: 12455489536 | AG103: 13336659968 | AH103: 13527183360 | AI103: 13830801408 | AJ103: 14428749824 | AK103: 14030099456 | AL103: 15428349952 | AM103: 15446200320 | AN103: 14464449536 | AO103: 13262550016 | AP103: -- | AQ103: -- | AR103: -- | AZ103: EQX CN EQUITY
A104: HBM | B104: 443628102 | C104: =A104&" CN EQUITY" -> HBM CN EQUITY | D104: Hudbay Minerals Inc | E104: 4593405440 | F104: 4896471040 | G104: 4872602112 | H104: 3325350912 | I104: 2560240896 | J104: 2306235392 | K104: 2198504704 | L104: 1857762048 | M104: 1792215808 | N104: 1456181504 | O104: 1372293376 | P104: 2568929536 | Q104: 2395805184 | R104: 2065989376 | S104: 2157027072 | T104: 2246940416 | U104: 2327934976 | V104: 1470962176 | W104: 1073828480 | X104: 694983936 | Y104: 1405644160 | Z104: 1248880896 | AA104: 1852419584 | AB104: 2495149056 | AC104: 1687818112 | AD104: 1708719872 | AE104: 1915117824 | AF104: 2382793216 | AG104: 2907948288 | AH104: 2416758528 | AI104: 1779533952 | AJ104: 2073750144 | AK104: 1814259328 | AL104: 1226042496 | AM104: 1457549568 | AN104: 1119702784 | AO104: 1249080320 | AP104: 1159692288 | AQ104: 2444558336 | AR104: 2420332800 | AZ104: ERE-U CN EQUITY
A105: HR-U | B105: 403925407 | C105: =A105&" CN EQUITY" -> HR-U CN EQUITY | D105: H&R Real Estate Investment Tru | E105: 2549563648 | F105: 3142996736 | G105: 2458900224 | H105: 2541321472 | I105: 2719900928 | J105: 2535826688 | K105: 2816059136 | L105: 3461692160 | M105: 3327070720 | N105: 2876501248 | O105: 3420481536 | P105: 3743563264 | Q105: 4661524992 | R105: 4483670016 | S105: 4589809152 | T105: 4089309696 | U105: 3811144704 | V105: 2773045248 | W105: 2798854400 | X105: 2551102976 | Y105: 6027801600 | Z105: 6607727616 | AA105: 6524881408 | AB105: 6687158272 | AC105: 5898753536 | AD105: 5675943424 | AE105: 5747356672 | AF105: 6095740416 | AG105: 6218942464 | AH105: 6250335744 | AI105: 6357846528 | AJ105: 6605888000 | AK105: 6371310080 | AL105: 6346673664 | AM105: 6346643456 | AN105: 5889696768 | AO105: 5596635648 | AP105: 5705375744 | AQ105: 6195399168 | AR105: 6422863872 | AZ105: ERO CN EQUITY
A106: HWX | B106: 422096107 | C106: =A106&" CN EQUITY" -> HWX CN EQUITY | D106: Headwater Exploration Inc | E106: 1570965888 | F106: 1504352512 | G106: 1721783936 | H106: 1815284736 | I106: 1477424000 | J106: 1692510208 | K106: 1498756736 | L106: 1476815616 | M106: 1381644160 | N106: 1209332992 | O106: 1235477376 | P106: 1483311232 | Q106: 1043198400 | R106: 920399104 | S106: 857026240 | T106: 763631872 | U106: 466156352 | V106: 203062288 | W106: 178328880 | X106: 166066128 | Y106: 63465844 | Z106: 59058492 | AA106: 58615452 | AB106: 62247124 | AC106: 70993568 | AD106: 60285604 | AE106: 58512496 | AF106: 62058708 | AG106: 54079732 | AH106: 53193180 | AI106: 43884372 | AJ106: 35891896 | AK106: 49628300 | AL106: 38993664 | AM106: 39879884 | AN106: 49628300 | AO106: 39879884 | AP106: 38107444 | AQ106: 60262936 | AR106: 73556232 | AZ106: ESI CN EQUITY
A107: IAG | B107: 45075E104 | C107: =A107&" CN EQUITY" -> IAG CN EQUITY | D107: iA Financial Corp Inc | E107: 12535168000 | F107: 10523375616 | G107: 8262406144 | H107: 8335313920 | I107: 9038095360 | J107: 8692560896 | K107: 9295569920 | L107: 8908897280 | M107: 8332383744 | N107: 7416946688 | O107: 6855213056 | P107: 8186799616 | Q107: 7791712768 | R107: 7731595264 | S107: 7252119552 | T107: 7324359680 | U107: 5907782144 | V107: 4960785920 | W107: 4864621056 | X107: 4737758720 | Y107: 7624620544 | Z107: 6410442752 | AA107: 5682504704 | AB107: 5285827072 | AC107: 4764595712 | AD107: 5663053824 | AE107: 5561875456 | AF107: 5804724736 | AG107: 6380811776 | AH107: 6019558400 | AI107: 5986015744 | AJ107: 6124045824 | AK107: 5642281472 | AL107: 4845464576 | AM107: 4166065664 | AN107: 4018428928 | AO107: 4497651200 | AP107: 4040964608 | AQ107: 4250329088 | AR107: 4274377728 | AZ107: EXE CN EQUITY
A108: IFC | B108: 45823T106 | C108: =A108&" CN EQUITY" -> IFC CN EQUITY | D108: Intact Financial Corp | E108: 46683201536 | F108: 46321123328 | G108: 40653561856 | H108: 39256211456 | I108: 36352901120 | J108: 35311493120 | K108: 35847061504 | L108: 33898203136 | M108: 34159335424 | N108: 34271287296 | O108: 31901583360 | P108: 32520124416 | Q108: 28951396352 | R108: 29490206720 | S108: 25647181824 | T108: 22024792064 | U108: 21555693568 | V108: 20391526400 | W108: 18479372288 | X108: 17395296256 | Y108: 19544868864 | Z108: 19067539456 | AA108: 16844608512 | AB108: 15739450368 | AC108: 13806120960 | AD108: 14948858880 | AE108: 12979340288 | AF108: 13474851840 | AG108: 14613414912 | AH108: 13963783168 | AI108: 13263027200 | AJ108: 12392792064 | AK108: 12598415360 | AL108: 12438658048 | AM108: 12112789504 | AN108: 11951632384 | AO108: 11665245184 | AP108: 12328222720 | AQ108: 11416629248 | AR108: 12551845888 | AZ108: FC CN EQUITY
A109: IFP | B109: 45868C109 | C109: =A109&" CN EQUITY" -> IFP CN EQUITY | D109: Interfor Corp | E109: 863908224 | F109: 1044370112 | G109: 849901184 | H109: 1088614400 | I109: 1207923968 | J109: 1036612800 | K109: 1285016192 | L109: 1132748544 | M109: 1080132736 | N109: 1324836736 | O109: 1421191424 | P109: 2062179968 | Q109: 2462714624 | R109: 1979788800 | S109: 2027376640 | T109: 1869713024 | U109: 1599123840 | V109: 1001050176 | W109: 769453952 | X109: 421047328 | Y109: 986703616 | Z109: 941541632 | AA109: 937506432 | AB109: 1055596672 | AC109: 992622016 | AD109: 1336179200 | AE109: 1768463616 | AF109: 1645015424 | AG109: 1479043200 | AH109: 1385202432 | AI109: 1301165824 | AJ109: 1203123200 | AK109: 1052557696 | AL109: 1042053184 | AM109: 775237120 | AN109: 1006337664 | AO109: 983227584 | AP109: 659686912 | AQ109: 1434924032 | AR109: 1277888128 | AZ109: FEC CN EQUITY
A110: IGM | B110: 449586106 | C110: =A110&" CN EQUITY" -> IGM CN EQUITY | D110: IGM Financial Inc | E110: 10928349184 | F110: 9594279936 | G110: 8953529344 | H110: 8315324416 | I110: 8336992256 | J110: 8203483136 | K110: 9600230400 | L110: 9607717888 | M110: 8983853056 | N110: 8180141056 | O110: 8223820800 | P110: 10591357952 | Q110: 10932658176 | R110: 10813556736 | S110: 10448537600 | T110: 9127357440 | U110: 8224018944 | V110: 7275551744 | W110: 7861790208 | X110: 5564498432 | Y110: 8883463168 | Z110: 8963549184 | AA110: 8908583936 | AB110: 8286402048 | AC110: 7474026496 | AD110: 8549625344 | AE110: 9177210880 | AF110: 9070989312 | AG110: 10623876096 | AH110: 10090376192 | AI110: 9676446720 | AJ110: 9540612096 | AK110: 9187564544 | AL110: 8518125056 | AM110: 8467917824 | AN110: 9492376576 | AO110: 8682256384 | AP110: 8359447040 | AQ110: 9924720640 | AR110: 11315688448 | AZ110: FFH CN EQUITY
A111: IIP-U | B111: 46071W205 | C111: =A111&" CN EQUITY" -> IIP-U CN EQUITY | D111: InterRent Real Estate Investme | E111: 1494312576 | F111: 1869730944 | G111: 1753424896 | H111: 1996342656 | I111: 1925713792 | J111: 1818001920 | K111: 1866035584 | L111: 1912584064 | M111: 1828310400 | N111: 1638337536 | O111: 1712612608 | P111: 2283959552 | Q111: 2472504064 | R111: 2358073088 | S111: 2376396288 | T111: 2084632320 | U111: 1929588736 | V111: 1775954560 | W111: 2019795968 | X111: 1655247616 | Y111: 1945009152 | Z111: 2034549248 | AA111: 1504343040 | AB111: 1585010688 | AC111: 1422585216 | AD111: 1280871808 | AE111: 1023982848 | AF111: 942064256 | AG111: 758560128 | AH111: 668829056 | AI111: 672152384 | AJ111: 637256960 | AK111: 526556928 | AL111: 548438016 | AM111: 559731456 | AN111: 518086848 | AO111: 463031296 | AP111: 458796256 | AQ111: 446091136 | AR111: 456795552 | AZ111: FM CN EQUITY
A112: IMG | B112: 450913108 | C112: =A112&" CN EQUITY" -> IMG CN EQUITY | D112: IAMGOLD Corp | E112: 4244873216 | F112: 4039933952 | G112: 2926102272 | H112: 2239522560 | I112: 1607052928 | J112: 1409730560 | K112: 1673493760 | L112: 1743470848 | M112: 1662045056 | N112: 713652928 | O112: 991450688 | P112: 2070124672 | Q112: 1879093376 | R112: 1368088832 | S112: 1739787136 | T112: 1777777664 | U112: 2219689216 | V112: 2421341696 | W112: 2550199808 | X112: 1504938240 | Y112: 2274769152 | Z112: 2115282816 | AA112: 2073108096 | AB112: 2166702080 | AC112: 2342720256 | AD112: 2216194048 | AE112: 3573810432 | AF112: 3115748864 | AG112: 3414885888 | AH112: 3545818112 | AI112: 3108279296 | AJ112: 2471755776 | AK112: 2354881280 | AL112: 2388518144 | AM112: 2171850240 | AN112: 1160971264 | AO112: 775022656 | AP112: 853248064 | AQ112: 978339136 | AR112: 923546880 | AZ112: FNV CN EQUITY
A113: IMO | B113: 453038408 | C113: =A113&" CN EQUITY" -> IMO CN EQUITY | D113: Imperial Oil Ltd | E113: 45408686080 | F113: 50281099264 | G113: 49982857216 | H113: 50063233024 | I113: 40444960768 | J113: 48183631872 | K113: 39593869312 | L113: 40148815872 | M113: 38524870656 | N113: 37173432320 | O113: 38633508864 | P113: 40483192832 | Q113: 31280508928 | R113: 27964973056 | S113: 27208069120 | T113: 22345295872 | U113: 17735294976 | V113: 11701183488 | W113: 16032236544 | X113: 11733749760 | Y113: 25633394688 | Z113: 26084317184 | AA113: 27763187712 | AB113: 28418816000 | AC113: 27163543552 | AD113: 33262782464 | AE113: 35505602560 | AF113: 28361988096 | AG113: 32718868480 | AH113: 33499793408 | AI113: 32039241728 | AJ113: 34344712192 | AK113: 39591350272 | AL113: 34785464320 | AM113: 34649845760 | AN113: 36777320448 | AO113: 38209761280 | AP113: 35836485632 | AQ113: 40896651264 | AR113: 42846130176 | AZ113: FOM CN EQUITY
A114: INE | B114: 45790B104 | C114: =A114&" CN EQUITY" -> INE CN EQUITY | D114: Innergex Energie Renouvelable | E114: 1635156480 | F114: 2130197248 | G114: 2081367552 | H114: 1630876800 | I114: 1877713536 | J114: 2077613056 | K114: 2520025856 | L114: 2997077760 | M114: 3306951936 | N114: 3549593088 | O114: 3530993408 | P114: 4056949504 | Q114: 3586165248 | R114: 3913697280 | S114: 3763208448 | T114: 3837985280 | U114: 4778277376 | V114: 4197408000 | W114: 3327881472 | X114: 3333141504 | Y114: 2350382336 | Z114: 2043013760 | AA114: 1861825920 | AB114: 1873461376 | AC114: 1667655040 | AD114: 1723737600 | AE114: 1830743680 | AF114: 1747567360 | AG114: 1563956352 | AH114: 1561168128 | AI114: 1546407040 | AJ114: 1549764736 | AK114: 1517787648 | AL114: 1581444736 | AM114: 1564515968 | AN114: 1467536000 | AO114: 1177624704 | AP114: 1096456576 | AQ114: 1075475584 | AR114: 1130411648 | AZ114: FRU CN EQUITY
A115: IPCO | B115: 46016U108 | C115: =A115&" CN EQUITY" -> IPCO CN EQUITY | D115: International Petroleum Corp | E115: 2015228160 | F115: 1939930752 | G115: 2251224064 | H115: 2020424704 | I115: 2022105472 | J115: 1683678976 | K115: 1429348096 | L115: 1734863232 | M115: 2119062528 | N115: 1517822080 | O115: 1855372288 | P115: 1810336896 | Q115: 1098450304 | R115: 1002122048 | S115: 893364608 | T115: 646329856 | U115: 436513152 | V115: 372822624 | W115: 380589760 | X115: 248548416 | Y115: 936478784 | Z115: 756386688 | AA115: 954488000 | AB115: 1022431808 | AC115: 382460032 | AD115: 742060352 | AE115: 790417408 | AF115: 476536416 | AG115: 484449376 | AH115: 483570144 | AI115: 345189312 | AJ115: -- | AK115: -- | AL115: -- | AM115: -- | AN115: -- | AO115: -- | AP115: -- | AQ115: -- | AR115: -- | AZ115: FSV CN EQUITY
A116: IVN | B116: 46579R104 | C116: =A116&" CN EQUITY" -> IVN CN EQUITY | D116: Ivanhoe Mines Ltd | E116: 23055237120 | F116: 27180308480 | G116: 22667335680 | H116: 20515465216 | I116: 16313151488 | J116: 14207361024 | K116: 14736574464 | L116: 14864689152 | M116: 12990566400 | N116: 10792218624 | O116: 8976540672 | P116: 14115396608 | Q116: 12482972672 | R116: 9789803520 | S116: 10816009216 | T116: 7815382016 | U116: 8258371072 | V116: 5826606080 | W116: 4619441664 | X116: 2802042368 | Y116: 5065293312 | Z116: 4099392000 | AA116: 4238982144 | AB116: 3255864576 | AC116: 2395141376 | AD116: 2777948672 | AE116: 2154947072 | AF116: 2168296448 | AG116: 3367001856 | AH116: 3151129344 | AI116: 3307442944 | AJ116: 3674320896 | AK116: 2002449920 | AL116: 1791488256 | AM116: 793597824 | AN116: 660021952 | AO116: 475165472 | AP116: 506323872 | AQ116: 702542080 | AR116: 646740992 | AZ116: FSZ CN EQUITY
A117: JWEL | B117: 470748104 | C117: =A117&" CN EQUITY" -> JWEL CN EQUITY | D117: Jamieson Wellness Inc | E117: 1537939584 | F117: 1460440320 | G117: 1202640000 | H117: 1104642688 | I117: 1328390912 | J117: 1024505664 | K117: 1257827456 | L117: 1402638336 | M117: 1462619392 | N117: 1396587136 | O117: 1448786432 | P117: 1409424640 | Q117: 1620818048 | R117: 1460736640 | S117: 1354051968 | T117: 1466269952 | U117: 1439715584 | V117: 1679250560 | W117: 1410656640 | X117: 1010794432 | Y117: 1001985984 | Z117: 905484032 | AA117: 770538688 | AB117: 721365504 | AC117: 812268992 | AD117: 1015241024 | AE117: 1012024512 | AF117: 869521280 | AG117: 843114304 | AH117: 749933824 | AI117: -- | AJ117: -- | AK117: -- | AL117: -- | AM117: -- | AN117: -- | AO117: -- | AP117: -- | AQ117: -- | AR117: -- | AZ117: FTS CN EQUITY
A118: K | B118: 496902404 | C118: =A118&" CN EQUITY" -> K CN EQUITY | D118: Kinross Gold Corp | E118: 16408604672 | F118: 15572040704 | G118: 13998604288 | H118: 10203333632 | I118: 9847121920 | J118: 7599088640 | K118: 7770473984 | L118: 7805178880 | M118: 6832171520 | N118: 6799338496 | O118: 5966452736 | P118: 9505948672 | Q118: 9199624192 | R118: 8568528896 | S118: 9916381184 | T118: 10553098240 | U118: 11752406016 | V118: 14784747520 | W118: 12327363584 | X118: 7103076352 | Y118: 7720922112 | Z118: 7645718528 | AA118: 6336604672 | AB118: 5760221184 | AC118: 5501006848 | AD118: 4400805376 | AE118: 6188417536 | AF118: 6347405312 | AG118: 6758761472 | AH118: 6596596736 | AI118: 6571053568 | AJ118: 5847255552 | AK118: 5216732160 | AL118: 6883364864 | AM118: 7888359936 | AN118: 5511386624 | AO118: 2877767936 | AP118: 2659616256 | AQ118: 3335473152 | AR118: 3232305152 | AZ118: FTT CN EQUITY
A119: KEL | B119: 488295106 | C119: =A119&" CN EQUITY" -> KEL CN EQUITY | D119: Kelt Exploration Ltd | E119: 1381129216 | F119: 1229142016 | G119: 1246001024 | H119: 1177260288 | I119: 1112457088 | J119: 1404808576 | K119: 1076542080 | L119: 881368896 | M119: 961956928 | N119: 1000024960 | O119: 1170393856 | P119: 1276144768 | Q119: 911771776 | R119: 858812032 | S119: 665995328 | T119: 501634784 | U119: 339308576 | V119: 269338720 | W119: 263067856 | X119: 206573248 | Y119: 914517120 | Z119: 641287808 | AA119: 718107712 | AB119: 1013892800 | AC119: 853698304 | AD119: 1547185152 | AE119: 1639036800 | AF119: 1240167552 | AG119: 1285192832 | AH119: 1255064832 | AI119: 1105048192 | AJ119: 1173715712 | AK119: 1188876032 | AL119: 1010748416 | AM119: 823677952 | AN119: 668022656 | AO119: 714859136 | AP119: 962699392 | AQ119: 1337097216 | AR119: 990273152 | AZ119: FVI CN EQUITY
A120: KEY | B120: 493271100 | C120: =A120&" CN EQUITY" -> KEY CN EQUITY | D120: Keyera Corp | E120: 10073582592 | F120: 9663397888 | G120: 8682620928 | H120: 7995161088 | I120: 7339782656 | J120: 7307701248 | K120: 7000635392 | L120: 6780648448 | M120: 6780648448 | N120: 6089765376 | O120: 6288903680 | P120: 6785677312 | Q120: 6109037056 | R120: 6824220160 | S120: 7132562944 | T120: 5592991232 | U120: 4843547648 | V120: 4303948288 | W120: 4426000384 | X120: 2800778240 | Y120: 7284593152 | Z120: 6888458240 | AA120: 7156811776 | AB120: 6673735680 | AC120: 5401451008 | AD120: 7176270336 | AE120: 7549350400 | AF120: 6839777280 | AG120: 7229630464 | AH120: 7112336384 | AI120: 7612102144 | AJ120: 7274573312 | AK120: 7389361664 | AL120: 7747323904 | AM120: 7217686016 | AN120: 6655349760 | AO120: 6797168128 | AP120: 6204568576 | AQ120: 7040286208 | AR120: 7112039424 | AZ120: GAU CN EQUITY
A121: KMP-U | B121: 49410M102 | C121: =A121&" CN EQUITY" -> KMP-U CN EQUITY | D121: Killam Apartment Real Estate I | E121: 1960436352 | F121: 2406406912 | G121: 1953557504 | H121: 2130111488 | I121: 2059031296 | J121: 1997122816 | K121: 2024637696 | L121: 1967315072 | M121: 1858401920 | N121: 1748342272 | O121: 1966168576 | P121: 2455704320 | Q121: 2593140224 | R121: 2327139584 | S121: 2219817472 | T121: 1892668800 | U121: 1749517184 | V121: 1775079936 | W121: 1710700544 | X121: 1540802176 | Y121: 1849353216 | Z121: 1801236224 | AA121: 1689726848 | AB121: 1744582272 | AC121: 1352962048 | AD121: 1369088896 | AE121: 1271478656 | AF121: 1115112704 | AG121: 1142428160 | AH121: 973869568 | AI121: 940644288 | AJ121: 936214272 | AK121: 793956672 | AL121: 803931072 | AM121: 843828352 | AN121: 681226880 | AO121: 659269504 | AP121: 622840960 | AQ121: 631487872 | AR121: 670261632 | AZ121: GEI CN EQUITY
A122: KNT | B122: 499113108 | C122: =A122&" CN EQUITY" -> KNT CN EQUITY | D122: K92 Mining Inc | E122: 2065031168 | F122: 1857705088 | G122: 1857705088 | H122: 1476231552 | I122: 1525439232 | J122: 1351842688 | K122: 1342784768 | L122: 1793493376 | M122: 1747854976 | N122: 1800267776 | O122: 1724192896 | P122: 2033435136 | Q122: 1599606016 | R122: 1354577408 | S122: 1964032896 | T122: 1391920640 | U122: 1668112768 | V122: 1478530176 | W122: 858570112 | X122: 630612288 | Y122: 613568704 | Z122: 452990496 | AA122: 354633728 | AB122: 286015968 | AC122: 152419024 | AD122: 155783152 | AE122: 161194512 | AF122: 114524416 | AG122: 88960800 | AH122: 72466232 | AI122: 122877520 | AJ122: 99635344 | AK122: 115843736 | AL122: 145391200 | AM122: 82894024 | AN122: 2643866.8 | AO122: 2643866.8 | AP122: 2643866.8 | AQ122: 2643866.8 | AR122: 2643866.8 | AZ122: GFL CN EQUITY
A123: KXS | B123: 49448Q109 | C123: =A123&" CN EQUITY" -> KXS CN EQUITY | D123: Kinaxis Inc | E123: 4878597120 | F123: 4527539712 | G123: 4469142016 | H123: 4362896896 | I123: 4220455680 | J123: 4363582976 | K123: 5365341184 | L123: 5206459904 | M123: 4236460800 | N123: 3801235712 | O123: 3834152448 | P123: 4495947264 | Q123: 4854803456 | R123: 4990554624 | S123: 4438624768 | T123: 3972538112 | U123: 4862825472 | V123: 5282585600 | W123: 5148007936 | X123: 2875531520 | Y123: 2623218944 | Z123: 2257890048 | AA123: 2136011904 | AB123: 2033803136 | AC123: 1715335168 | AD123: 2525734144 | AE123: 2278846208 | AF123: 2113076224 | AG123: 1954208640 | AH123: 1873803136 | AI123: 2041870976 | AJ123: 1857940992 | AK123: 1554507392 | AL123: 1649689216 | AM123: 1278192640 | AN123: 1055404416 | AO123: 1142143360 | AP123: 987789824 | AQ123: 662806528 | AR123: 629713664 | AZ123: GGD CN EQUITY
A124: L | B124: 539481101 | C124: =A124&" CN EQUITY" -> L CN EQUITY | D124: Loblaw Cos Ltd | E124: 57155334144 | F124: 54876508160 | G124: 48562663424 | H124: 46535155712 | I124: 40167710720 | J124: 36378628096 | K124: 38748831744 | L124: 39710281728 | M124: 38875267072 | N124: 35595468800 | O124: 38092611584 | P124: 37420929024 | Q124: 34570465280 | R124: 29393946624 | S124: 26151907328 | T124: 24384776192 | U124: 22162130944 | V124: 24832057344 | W124: 23653226496 | X124: 26130352128 | Y124: 24387487744 | Z124: 27466864640 | AA124: 24640964608 | AB124: 24321411072 | AC124: 22931425280 | AD124: 24882395136 | AE124: 25372248064 | AF124: 24941443072 | AG124: 26479644672 | AH124: 26920103936 | AI124: 28575977472 | AJ124: 28925216768 | AK124: 28585961472 | AL124: 27373979648 | AM124: 28159557632 | AN124: 29827012608 | AO124: 26916007936 | AP124: 28343357440 | AQ124: 26028574720 | AR124: 25540816896 | AZ124: GIB/A CN EQUITY
...
