Workbook

Sheet FINAL
A1: Security | B1: Name | C1: Sector | D1: INDUSTRY | E1: Year | F1: Quarter | G1: Index | H1: Closing Stock Price | I1: SP Volatility | J1: MC RAW | K1: Log MCap | L1: PB RAW | M1: Book to Mkt | N1: ROA | O1: Total Assets | P1: Asset Growth | Q1: ESGCombinedScore | R1: EnvironmentPillarScore | S1: GovernancePillarScore | T1: SocialPillarScore | U1: ESG Momentum | V1: ESG Mom-Env | W1: ESG Mom - Gov | X1: ESG Mom - Social
A2: AAV CN EQUITY | B2: Advantage Energy Ltd | C2: Energy | D2: =VLOOKUP(C2,INDUSTRY!A:B,2,FALSE) -> Natural Resources | E2: 2015 | F2: Q1 | G2: 2015-Q1 | H2: 6.82 | I2: 0.43338782 | J2: 1161495680 | K2: 20.872974 | L2: 0.86407202 | M2: 1.1573109 | N2: 0.97533798 | O2: 1454.767 | P2: 0.088701862 | Q2: 0 | R2: 0 | S2: 0 | T2: 0 | U2: 0 | V2: 0 | W2: 0 | X2: 0
A3: AAV CN EQUITY | B3: Advantage Energy Ltd | C3: Energy | D3: =VLOOKUP(C3,INDUSTRY!A:B,2,FALSE) -> Natural Resources | E3: 2015 | F3: Q2 | G3: 2015-Q2 | H3: 7.9 | I3: 0.11026483 | J3: 1348260224 | K3: 21.022081 | L3: 1.0568269 | M3: 0.94622871 | N3: 6.8927059 | O3: 1508.438 | P3: 0.036893221 | Q3: 0 | R3: 0 | S3: 0 | T3: 0 | U3: 0 | V3: 0 | W3: 0 | X3: 0
A4: AAV CN EQUITY | B4: Advantage Energy Ltd | C4: Energy | D4: =VLOOKUP(C4,INDUSTRY!A:B,2,FALSE) -> Natural Resources | E4: 2015 | F4: Q3 | G4: 2015-Q3 | H4: 6.97 | I4: 1.0395672 | J4: 1189886976 | K4: 20.897124 | L4: 1.226446 | M4: 0.81536405 | N4: 5.0444198 | O4: 1493.8691 | P4: -0.0096583087 | Q4: 0 | R4: 0 | S4: 0 | T4: 0 | U4: 0 | V4: 0 | W4: 0 | X4: 0
A5: AAV CN EQUITY | B5: Advantage Energy Ltd | C5: Energy | D5: =VLOOKUP(C5,INDUSTRY!A:B,2,FALSE) -> Natural Resources | E5: 2015 | F5: Q4 | G5: 2015-Q4 | H5: 7.03 | I5: 1.1470942 | J5: 1200238592 | K5: 20.905786 | L5: 1.0742 | M5: 0.93092531 | N5: 4.388618 | O5: 1518.964 | P5: 0.016798602 | Q5: 0 | R5: 0 | S5: 0 | T5: 0 | U5: 0 | V5: 0 | W5: 0 | X5: 0
A6: AAV CN EQUITY | B6: Advantage Energy Ltd | C6: Energy | D6: =VLOOKUP(C6,INDUSTRY!A:B,2,FALSE) -> Natural Resources | E6: 2016 | F6: Q1 | G6: 2016-Q1 | H6: 7.13 | I6: 0.92477024 | J6: 1314780160 | K6: 20.996935 | L6: 1.070385 | M6: 0.9342433 | N6: 1.438526 | O6: 1517.4429 | P6: -0.0010013562 | Q6: 0 | R6: 0 | S6: 0 | T6: 0 | U6: 0 | V6: 0 | W6: 0 | X6: 0
A7: AAV CN EQUITY | B7: Advantage Energy Ltd | C7: Energy | D7: =VLOOKUP(C7,INDUSTRY!A:B,2,FALSE) -> Natural Resources | E7: 2016 | F7: Q2 | G7: 2016-Q2 | H7: 7.22 | I7: 0.22470351 | J7: 1332163456 | K7: 21.01007 | L7: 1.065817 | M7: 0.93824737 | N7: 2.089612 | O7: 1554.14 | P7: 0.024183504 | Q7: 0 | R7: 0 | S7: 0 | T7: 0 | U7: 0 | V7: 0 | W7: 0 | X7: 0
A8: AAV CN EQUITY | B8: Advantage Energy Ltd | C8: Energy | D8: =VLOOKUP(C8,INDUSTRY!A:B,2,FALSE) -> Natural Resources | E8: 2016 | F8: Q3 | G8: 2016-Q3 | H8: 9.2 | I8: 0.5591884 | J8: 1697906560 | K8: 21.252662 | L8: 1.1047651 | M8: 0.90516983 | N8: 0.286286 | O8: 1505.225 | P8: -0.031474044 | Q8: 0 | R8: 0 | S8: 0 | T8: 0 | U8: 0 | V8: 0 | W8: 0 | X8: 0
A9: AAV CN EQUITY | B9: Advantage Energy Ltd | C9: Energy | D9: =VLOOKUP(C9,INDUSTRY!A:B,2,FALSE) -> Natural Resources | E9: 2016 | F9: Q4 | G9: 2016-Q4 | H9: 9.12 | I9: 1.5932645 | J9: 1683971072 | K9: 21.244421 | L9: 1.397257 | M9: 0.71568797 | N9: 0.36416301 | O9: 1512.0931 | P9: 0.0045628369 | Q9: 0 | R9: 0 | S9: 0 | T9: 0 | U9: 0 | V9: 0 | W9: 0 | X9: 0
A10: AAV CN EQUITY | B10: Advantage Energy Ltd | C10: Energy | D10: =VLOOKUP(C10,INDUSTRY!A:B,2,FALSE) -> Natural Resources | E10: 2017 | F10: Q1 | G10: 2017-Q1 | H10: 8.78 | I10: 2.2606341 | J10: 1623166720 | K10: 21.207645 | L10: 1.393764 | M10: 0.71748157 | N10: -1.044095 | O10: 1496.459 | P10: -0.010339343 | Q10: 0 | R10: 0 | S10: 0 | T10: 0 | U10: 0 | V10: 0 | W10: 0 | X10: 0
A11: AAV CN EQUITY | B11: Advantage Energy Ltd | C11: Energy | D11: =VLOOKUP(C11,INDUSTRY!A:B,2,FALSE) -> Natural Resources | E11: 2017 | F11: Q2 | G11: 2017-Q2 | H11: 8.77 | I11: 1.8253493 | J11: 1623263488 | K11: 21.207704 | L11: 1.297083 | M11: 0.77096067 | N11: 0.76613802 | O11: 1532.51 | P11: 0.024090833 | Q11: 0 | R11: 0 | S11: 0 | T11: 0 | U11: 0 | V11: 0 | W11: 0 | X11: 0
A12: AAV CN EQUITY | B12: Advantage Energy Ltd | C12: Energy | D12: =VLOOKUP(C12,INDUSTRY!A:B,2,FALSE) -> Natural Resources | E12: 2017 | F12: Q3 | G12: 2017-Q3 | H12: 7.82 | I12: 0.807589 | J12: 1454174720 | K12: 21.097704 | L12: 1.281309 | M12: 0.78045186 | N12: 3.9336181 | O12: 1541.7411 | P12: 0.0060235198 | Q12: 0 | R12: 0 | S12: 0 | T12: 0 | U12: 0 | V12: 0 | W12: 0 | X12: 0
A13: AAV CN EQUITY | B13: Advantage Energy Ltd | C13: Energy | D13: =VLOOKUP(C13,INDUSTRY!A:B,2,FALSE) -> Natural Resources | E13: 2017 | F13: Q4 | G13: 2017-Q4 | H13: 5.4 | I13: 0.95325757 | J13: 1004201216 | K13: 20.727458 | L13: 1.128872 | M13: 0.88584 | N13: 4.1560621 | O13: 1604.752 | P13: 0.040869992 | Q13: 0 | R13: 0 | S13: 0 | T13: 0 | U13: 0 | V13: 0 | W13: 0 | X13: 0
... A37: AAV CN EQUITY | B37: Advantage Energy Ltd | C37: Energy | D37: =VLOOKUP(C37,INDUSTRY!A:B,2,FALSE) -> Natural Resources | E37: 2023 | F37: Q4 | G37: 2023-Q4 | H37: 8.53 | I37: 0.38064638 | J37: 1409015808 | K37: 21.066157 | L37: 0.99283201 | M37: 1.0072197 | N37: 7.7911472 | O37: 2283.7189 | P37: 0.023283405 | Q37: 0.38751429 | R37: 0.27132183 | S37: 0.52778796 | T37: 0.40441631 | U37: -0.022841996 | V37: -0.013977347 | W37: -0.036185668 | X37: -0.022650115
A38: AAV CN EQUITY | B38: Advantage Energy Ltd | C38: Energy | D38: =VLOOKUP(C38,INDUSTRY!A:B,2,FALSE) -> Natural Resources | E38: 2024 | F38: Q1 | G38: 2024-Q1 | H38: 9.88 | I38: n/a | J38: 1580187264 | K38: 21.180809 | L38: 0.88915098 | M38: 1.1246684 | N38: 4.4994378 | O38: 2299.028 | P38: 0.0067035641 | Q38: 0.375051 | R38: 0.26750334 | S38: 0.45098611 | T38: 0.42092097 | U38: -0.01246329 | V38: -0.0038184837 | W38: -0.076801851 | X38: 0.01650466
A39: AAV CN EQUITY | B39: Advantage Energy Ltd | C39: Energy | D39: =VLOOKUP(C39,INDUSTRY!A:B,2,FALSE) -> Natural Resources | E39: 2024 | F39: Q2 | G39: 2024-Q2 | H39: 10.38 | I39: n/a | J39: 1733170560 | K39: 21.273218 | L39: 1.014098 | M39: 0.98609794 | N39: 4.1665492 | O39: 2342.176 | P39: 0.018767946 | Q39: 0.375051 | R39: 0.26750334 | S39: 0.45098611 | T39: 0.42092097 | U39: -0.01246329 | V39: -0.0038184837 | W39: -0.076801851 | X39: 0.01650466
A40: AAV CN EQUITY | B40: Advantage Energy Ltd | C40: Energy | D40: =VLOOKUP(C40,INDUSTRY!A:B,2,FALSE) -> Natural Resources | E40: 2024 | F40: Q3 | G40: 2024-Q3 | H40: 9.45 | I40: n/a | J40: 1577886464 | K40: 21.179352 | L40: 1.068455 | M40: 0.93593087 | N40: 3.184761 | O40: 2818.4819 | P40: 0.20336043 | Q40: 0.375051 | R40: 0.26750334 | S40: 0.45098611 | T40: 0.42092097 | U40: -0.01246329 | V40: -0.0038184837 | W40: -0.076801851 | X40: 0.01650466
A41: AAV CN EQUITY | B41: Advantage Energy Ltd | C41: Energy | D41: =VLOOKUP(C41,INDUSTRY!A:B,2,FALSE) -> Natural Resources | E41: 2024 | F41: Q4 | G41: 2024-Q4 | H41: 9.86 | I41: n/a | J41: 1646387712 | K41: 21.221849 | L41: 0.97480702 | M41: 1.0258441 | N41: 1.77763 | O41: 2848.394 | P41: 0.010612828 | Q41: 0.375051 | R41: 0.26750334 | S41: 0.45098611 | T41: 0.42092097 | U41: -0.01246329 | V41: -0.0038184837 | W41: -0.076801851 | X41: 0.01650466
A42: ACQ CN EQUITY | B42: AutoCanada Inc | C42: Consumer Discretionary | D42: =VLOOKUP(C42,INDUSTRY!A:B,2,FALSE) -> Service | E42: 2015 | F42: Q1 | G42: 2015-Q1 | H42: 31.67 | I42: 9.8389579 | J42: 776221696 | K42: 20.469949 | L42: 2.8477969 | M42: 0.35114863 | N42: 5.374836 | O42: 1357.9869 | P42: 0.12088868 | Q42: 0.27490535 | R42: 0 | S42: 0.52746401 | T42: 0.17130996 | U42: 0.10301148 | V42: 0 | W42: 0.23451748 | X42: 0.031011237
A43: ACQ CN EQUITY | B43: AutoCanada Inc | C43: Consumer Discretionary | D43: =VLOOKUP(C43,INDUSTRY!A:B,2,FALSE) -> Service | E43: 2015 | F43: Q2 | G43: 2015-Q2 | H43: 41.3 | I43: 3.2871923 | J43: 1012249920 | K43: 20.735441 | L43: 2.032541 | M43: 0.49199499 | N43: 4.7069578 | O43: 1449.2131 | P43: 0.067177459 | Q43: 0.27490535 | R43: 0 | S43: 0.52746401 | T43: 0.17130996 | U43: 0.10301148 | V43: 0 | W43: 0.23451748 | X43: 0.031011237
A44: ACQ CN EQUITY | B44: AutoCanada Inc | C44: Consumer Discretionary | D44: =VLOOKUP(C44,INDUSTRY!A:B,2,FALSE) -> Service | E44: 2015 | F44: Q3 | G44: 2015-Q3 | H44: 25.86 | I44: 2.484195 | J44: 633820416 | K44: 20.267276 | L44: 2.6015649 | M44: 0.38438403 | N44: 4.3450532 | O44: 1517.978 | P44: 0.04744984 | Q44: 0.27490535 | R44: 0 | S44: 0.52746401 | T44: 0.17130996 | U44: 0.10301148 | V44: 0 | W44: 0.23451748 | X44: 0.031011237
A45: ACQ CN EQUITY | B45: AutoCanada Inc | C45: Consumer Discretionary | D45: =VLOOKUP(C45,INDUSTRY!A:B,2,FALSE) -> Service | E45: 2015 | F45: Q4 | G45: 2015-Q4 | H45: 24.15 | I45: 2.1752701 | J45: 663151360 | K45: 20.312514 | L45: 1.605267 | M45: 0.62294931 | N45: 3.4335761 | O45: 1508.028 | P45: -0.0065547407 | Q45: 0.27490535 | R45: 0 | S45: 0.52746401 | T45: 0.17130996 | U45: 0.10301148 | V45: 0 | W45: 0.23451748 | X45: 0.031011237
A46: ACQ CN EQUITY | B46: AutoCanada Inc | C46: Consumer Discretionary | D46: =VLOOKUP(C46,INDUSTRY!A:B,2,FALSE) -> Service | E46: 2016 | F46: Q1 | G46: 2016-Q1 | H46: 18.22 | I46: 0.45756602 | J46: 500315424 | K46: 20.030749 | L46: 1.463537 | M46: 0.68327621 | N46: 1.736092 | O46: 1532.182 | P46: 0.016016933 | Q46: 0.22123307 | R46: 0 | S46: 0.42600849 | T46: 0.13649007 | U46: -0.053672279 | V46: 0 | W46: -0.10145552 | X46: -0.03481989
A47: ACQ CN EQUITY | B47: AutoCanada Inc | C47: Consumer Discretionary | D47: =VLOOKUP(C47,INDUSTRY!A:B,2,FALSE) -> Service | E47: 2016 | F47: Q2 | G47: 2016-Q2 | H47: 22.15 | I47: 1.7917287 | J47: 608231936 | K47: 20.226067 | L47: 1.108619 | M47: 0.90202317 | N47: 1.809517 | O47: 1578.225 | P47: 0.030050612 | Q47: 0.22123307 | R47: 0 | S47: 0.42600849 | T47: 0.13649007 | U47: -0.053672279 | V47: 0 | W47: -0.10145552 | X47: -0.03481989
A48: ACQ CN EQUITY | B48: AutoCanada Inc | C48: Consumer Discretionary | D48: =VLOOKUP(C48,INDUSTRY!A:B,2,FALSE) -> Service | E48: 2016 | F48: Q3 | G48: 2016-Q3 | H48: 22.15 | I48: 2.0976078 | J48: 608231936 | K48: 20.226067 | L48: 1.3082221 | M48: 0.76439622 | N48: 1.679831 | O48: 1548.879 | P48: -0.018594337 | Q48: 0.22123307 | R48: 0 | S48: 0.42600849 | T48: 0.13649007 | U48: -0.053672279 | V48: 0 | W48: -0.10145552 | X48: -0.03481989
A49: ACQ CN EQUITY | B49: AutoCanada Inc | C49: Consumer Discretionary | D49: =VLOOKUP(C49,INDUSTRY!A:B,2,FALSE) -> Service | E49: 2016 | F49: Q4 | G49: 2016-Q4 | H49: 23.12 | I49: 2.0335089 | J49: 634867904 | K49: 20.268928 | L49: 1.413289 | M49: 0.70756939 | N49: -1.214255 | O49: 1547.344 | P49: -0.00099102385 | Q49: 0.22123307 | R49: 0 | S49: 0.42600849 | T49: 0.13649007 | U49: -0.053672279 | V49: 0 | W49: -0.10145552 | X49: -0.03481989
A50: ACQ CN EQUITY | B50: AutoCanada Inc | C50: Consumer Discretionary | D50: =VLOOKUP(C50,INDUSTRY!A:B,2,FALSE) -> Service | E50: 2017 | F50: Q1 | G50: 2017-Q1 | H50: 22.44 | I50: 2.0212599 | J50: 616195328 | K50: 20.239075 | L50: 1.437192 | M50: 0.69580127 | N50: 0.16573 | O50: 1600.615 | P50: 0.034427406 | Q50: 0.26669986 | R50: 0 | S50: 0.55621735 | T50: 0.12614907 | U50: 0.045466796 | V50: 0 | W50: 0.13020885 | X50: -0.010340998
A51: ACQ CN EQUITY | B51: AutoCanada Inc | C51: Consumer Discretionary | D51: =VLOOKUP(C51,INDUSTRY!A:B,2,FALSE) -> Service | E51: 2017 | F51: Q2 | G51: 2017-Q2 | H51: 19.08 | I51: 3.0177751 | J51: 523930752 | K51: 20.07687 | L51: 0.69552898 | M51: 1.4377546 | N51: -0.060756002 | O51: 1707.063 | P51: 0.066504436 | Q51: 0.26669986 | R51: 0 | S51: 0.55621735 | T51: 0.12614907 | U51: 0.045466796 | V51: 0 | W51: 0.13020885 | X51: -0.010340998
A52: ACQ CN EQUITY | B52: AutoCanada Inc | C52: Consumer Discretionary | D52: =VLOOKUP(C52,INDUSTRY!A:B,2,FALSE) -> Service | E52: 2017 | F52: Q3 | G52: 2017-Q3 | H52: 23.81 | I52: 4.3392242 | J52: 653815040 | K52: 20.298335 | L52: 1.126552 | M52: 0.88766432 | N52: 0.604958 | O52: 1698.29 | P52: -0.0051392314 | Q52: 0.26669986 | R52: 0 | S52: 0.55621735 | T52: 0.12614907 | U52: 0.045466796 | V52: 0 | W52: 0.13020885 | X52: -0.010340998
A53: ACQ CN EQUITY | B53: AutoCanada Inc | C53: Consumer Discretionary | D53: =VLOOKUP(C53,INDUSTRY!A:B,2,FALSE) -> Service | E53: 2017 | F53: Q4 | G53: 2017-Q4 | H53: 22.64 | I53: 4.732296 | J53: 621687232 | K53: 20.247948 | L53: 1.375158 | M53: 0.72718919 | N53: 3.3658171 | O53: 1693.5331 | P53: -0.002801048 | Q53: 0.26669986 | R53: 0 | S53: 0.55621735 | T53: 0.12614907 | U53: 0.045466796 | V53: 0 | W53: 0.13020885 | X53: -0.010340998
... A77: ACQ CN EQUITY | B77: AutoCanada Inc | C77: Consumer Discretionary | D77: =VLOOKUP(C77,INDUSTRY!A:B,2,FALSE) -> Service | E77: 2023 | F77: Q4 | G77: 2023-Q4 | H77: 22.9 | I77: 4.8404227 | J77: 540695936 | K77: 20.108368 | L77: 1.061255 | M77: 0.94228062 | N77: 2.89101 | O77: 3065.3381 | P77: 0.05421292 | Q77: 0.45576793 | R77: 0.084677419 | S77: 0.52546742 | T77: 0.56002912 | U77: 0.18854959 | V77: -0.0099727864 | W77: 0.1320738 | X77: 0.32871288
A78: ACQ CN EQUITY | B78: AutoCanada Inc | C78: Consumer Discretionary | D78: =VLOOKUP(C78,INDUSTRY!A:B,2,FALSE) -> Service | E78: 2024 | F78: Q1 | G78: 2024-Q1 | H78: 26.88 | I78: n/a | J78: 634668416 | K78: 20.268613 | L78: 0.58389503 | M78: 1.7126366 | N78: 1.67803 | O78: 3159.4391 | P78: 0.030698405 | Q78: 0.46061779 | R78: 0.07312253 | S78: 0.58279167 | T78: 0.52503417 | U78: 0.0048498607 | V78: -0.01155489 | W78: 0.057324245 | X78: -0.034994947
A79: ACQ CN EQUITY | B79: AutoCanada Inc | C79: Consumer Discretionary | D79: =VLOOKUP(C79,INDUSTRY!A:B,2,FALSE) -> Service | E79: 2024 | F79: Q2 | G79: 2024-Q2 | H79: 19.23 | I79: n/a | J79: 448930752 | K79: 19.922379 | L79: 1.182011 | M79: 0.84601581 | N79: 1.325309 | O79: 3173.0921 | P79: 0.0043213341 | Q79: 0.46061779 | R79: 0.07312253 | S79: 0.58279167 | T79: 0.52503417 | U79: 0.0048498607 | V79: -0.01155489 | W79: 0.057324245 | X79: -0.034994947
A80: ACQ CN EQUITY | B80: AutoCanada Inc | C80: Consumer Discretionary | D80: =VLOOKUP(C80,INDUSTRY!A:B,2,FALSE) -> Service | E80: 2024 | F80: Q3 | G80: 2024-Q3 | H80: 16.09 | I80: n/a | J80: 372487264 | K80: 19.735713 | L80: 0.90373999 | M80: 1.1065129 | N80: -1.197926 | O80: 3197.515 | P80: 0.0076968809 | Q80: 0.46061779 | R80: 0.07312253 | S80: 0.58279167 | T80: 0.52503417 | U80: 0.0048498607 | V80: -0.01155489 | W80: 0.057324245 | X80: -0.034994947
A81: ACQ CN EQUITY | B81: AutoCanada Inc | C81: Consumer Discretionary | D81: =VLOOKUP(C81,INDUSTRY!A:B,2,FALSE) -> Service | E81: 2024 | F81: Q4 | G81: 2024-Q4 | H81: 17.33 | I81: n/a | J81: 401193536 | K81: 19.809955 | L81: 0.76310599 | M81: 1.310434 | N81: -1.635744 | O81: 3105.922 | P81: -0.028645045 | Q81: 0.46061779 | R81: 0.07312253 | S81: 0.58279167 | T81: 0.52503417 | U81: 0.0048498607 | V81: -0.01155489 | W81: 0.057324245 | X81: -0.034994947
A82: ADEN CN EQUITY | B82: ADENTRA Inc | C82: Industrials | D82: =VLOOKUP(C82,INDUSTRY!A:B,2,FALSE) -> Manufacturing | E82: 2015 | F82: Q1 | G82: 2015-Q1 | H82: 12.88 | I82: 0.9954689 | J82: 214470224 | K82: 19.183681 | L82: 1.768145 | M82: 0.56556449 | N82: 9.6963778 | O82: 138.45286 | P82: -0.048764052 | Q82: 0 | R82: 0 | S82: 0 | T82: 0 | U82: 0 | V82: 0 | W82: 0 | X82: 0
A83: ADEN CN EQUITY | B83: ADENTRA Inc | C83: Industrials | D83: =VLOOKUP(C83,INDUSTRY!A:B,2,FALSE) -> Manufacturing | E83: 2015 | F83: Q2 | G83: 2015-Q2 | H83: 16.84 | I83: 1.2664221 | J83: 280409824 | K83: 19.451763 | L83: 1.790699 | M83: 0.55844114 | N83: 9.5147266 | O83: 147.03581 | P83: 0.061991813 | Q83: 0 | R83: 0 | S83: 0 | T83: 0 | U83: 0 | V83: 0 | W83: 0 | X83: 0
A84: ADEN CN EQUITY | B84: ADENTRA Inc | C84: Industrials | D84: =VLOOKUP(C84,INDUSTRY!A:B,2,FALSE) -> Manufacturing | E84: 2015 | F84: Q3 | G84: 2015-Q3 | H84: 15.95 | I84: 1.3131641 | J84: 265590064 | K84: 19.397465 | L84: 2.2789409 | M84: 0.43880032 | N84: 9.6708918 | O84: 151.8353 | P84: 0.032641627 | Q84: 0 | R84: 0 | S84: 0 | T84: 0 | U84: 0 | V84: 0 | W84: 0 | X84: 0
A85: ADEN CN EQUITY | B85: ADENTRA Inc | C85: Industrials | D85: =VLOOKUP(C85,INDUSTRY!A:B,2,FALSE) -> Manufacturing | E85: 2015 | F85: Q4 | G85: 2015-Q4 | H85: 17.98 | I85: 1.305 | J85: 299392448 | K85: 19.517266 | L85: 1.969663 | M85: 0.50770106 | N85: 10.219131 | O85: 148.37738 | P85: -0.022774151 | Q85: 0 | R85: 0 | S85: 0 | T85: 0 | U85: 0 | V85: 0 | W85: 0 | X85: 0
A86: ADEN CN EQUITY | B86: ADENTRA Inc | C86: Industrials | D86: =VLOOKUP(C86,INDUSTRY!A:B,2,FALSE) -> Manufacturing | E86: 2016 | F86: Q1 | G86: 2016-Q1 | H86: 18.02 | I86: 1.3790667 | J86: 302052544 | K86: 19.526112 | L86: 2.1083331 | M86: 0.47430835 | N86: 11.48519 | O86: 137.40526 | P86: -0.073947338 | Q86: 0 | R86: 0 | S86: 0 | T86: 0 | U86: 0 | V86: 0 | W86: 0 | X86: 0
A87: ADEN CN EQUITY | B87: ADENTRA Inc | C87: Industrials | D87: =VLOOKUP(C87,INDUSTRY!A:B,2,FALSE) -> Manufacturing | E87: 2016 | F87: Q2 | G87: 2016-Q2 | H87: 15.68 | I87: 1.0825433 | J87: 263091024 | K87: 19.388011 | L87: 2.160917 | M87: 0.46276649 | N87: 10.597122 | O87: 148.03253 | P87: 0.077342481 | Q87: 0 | R87: 0 | S87: 0 | T87: 0 | U87: 0 | V87: 0 | W87: 0 | X87: 0
A88: ADEN CN EQUITY | B88: ADENTRA Inc | C88: Industrials | D88: =VLOOKUP(C88,INDUSTRY!A:B,2,FALSE) -> Manufacturing | E88: 2016 | F88: Q3 | G88: 2016-Q3 | H88: 18.68 | I88: 1.6016346 | J88: 398045760 | K88: 19.802078 | L88: 1.825158 | M88: 0.54789777 | N88: 9.3335352 | O88: 190.98235 | P88: 0.29013775 | Q88: 0 | R88: 0 | S88: 0 | T88: 0 | U88: 0 | V88: 0 | W88: 0 | X88: 0
A89: ADEN CN EQUITY | B89: ADENTRA Inc | C89: Industrials | D89: =VLOOKUP(C89,INDUSTRY!A:B,2,FALSE) -> Manufacturing | E89: 2016 | F89: Q4 | G89: 2016-Q4 | H89: 17.89 | I89: 1.8267891 | J89: 381244896 | K89: 19.758952 | L89: 1.839568 | M89: 0.54360588 | N89: 7.7034121 | O89: 278.8633 | P89: 0.46015217 | Q89: 0 | R89: 0 | S89: 0 | T89: 0 | U89: 0 | V89: 0 | W89: 0 | X89: 0
A90: ADEN CN EQUITY | B90: ADENTRA Inc | C90: Industrials | D90: =VLOOKUP(C90,INDUSTRY!A:B,2,FALSE) -> Manufacturing | E90: 2017 | F90: Q1 | G90: 2017-Q1 | H90: 16.34 | I90: 0.87313134 | J90: 348868320 | K90: 19.670205 | L90: 1.690104 | M90: 0.59167956 | N90: 8.5057392 | O90: 275.89293 | P90: -0.010651699 | Q90: 0 | R90: 0 | S90: 0 | T90: 0 | U90: 0 | V90: 0 | W90: 0 | X90: 0
A91: ADEN CN EQUITY | B91: ADENTRA Inc | C91: Industrials | D91: =VLOOKUP(C91,INDUSTRY!A:B,2,FALSE) -> Manufacturing | E91: 2017 | F91: Q2 | G91: 2017-Q2 | H91: 18.59 | I91: 1.4862341 | J91: 397149440 | K91: 19.799823 | L91: 1.5122941 | M91: 0.66124706 | N91: 9.3750267 | O91: 291.41245 | P91: 0.056251967 | Q91: 0 | R91: 0 | S91: 0 | T91: 0 | U91: 0 | V91: 0 | W91: 0 | X91: 0
A92: ADEN CN EQUITY | B92: ADENTRA Inc | C92: Industrials | D92: =VLOOKUP(C92,INDUSTRY!A:B,2,FALSE) -> Manufacturing | E92: 2017 | F92: Q3 | G92: 2017-Q3 | H92: 20.2 | I92: 1.5069478 | J92: 431544832 | K92: 19.882882 | L92: 1.691373 | M92: 0.59123564 | N92: 9.9771519 | O92: 296.35133 | P92: 0.016948075 | Q92: 0 | R92: 0 | S92: 0 | T92: 0 | U92: 0 | V92: 0 | W92: 0 | X92: 0
A93: ADEN CN EQUITY | B93: ADENTRA Inc | C93: Industrials | D93: =VLOOKUP(C93,INDUSTRY!A:B,2,FALSE) -> Manufacturing | E93: 2017 | F93: Q4 | G93: 2017-Q4 | H93: 20.2 | I93: 3.4299951 | J93: 431544832 | K93: 19.882882 | L93: 1.848387 | M93: 0.54101224 | N93: 8.4122076 | O93: 308.55094 | P93: 0.041166058 | Q93: 0 | R93: 0 | S93: 0 | T93: 0 | U93: 0 | V93: 0 | W93: 0 | X93: 0
... A117: ADEN CN EQUITY | B117: ADENTRA Inc | C117: Industrials | D117: =VLOOKUP(C117,INDUSTRY!A:B,2,FALSE) -> Manufacturing | E117: 2023 | F117: Q4 | G117: 2023-Q4 | H117: 31.97 | I117: 2.6664521 | J117: 714392256 | K117: 20.386943 | L117: 0.96791399 | M117: 1.0331497 | N117: 2.887594 | O117: 1289.545 | P117: -0.014341431 | Q117: 0.19686677 | R117: 0.037080216 | S117: 0.57495374 | T117: 0.0881235 | U117: 0.19686677 | V117: 0.037080216 | W117: 0.57495374 | X117: 0.0881235
A118: ADEN CN EQUITY | B118: ADENTRA Inc | C118: Industrials | D118: =VLOOKUP(C118,INDUSTRY!A:B,2,FALSE) -> Manufacturing | E118: 2024 | F118: Q1 | G118: 2024-Q1 | H118: 41.01 | I118: n/a | J118: 919878272 | K118: 20.639752 | L118: 1.030571 | M118: 0.97033588 | N118: 2.7092631 | O118: 1232.119 | P118: -0.044531925 | Q118: 0.16328353 | R118: 0.044106245 | S118: 0.44904167 | T118: 0.079776508 | U118: -0.033583239 | V118: 0.0070260289 | W118: -0.12591207 | X118: -0.0083469925
A119: ADEN CN EQUITY | B119: ADENTRA Inc | C119: Industrials | D119: =VLOOKUP(C119,INDUSTRY!A:B,2,FALSE) -> Manufacturing | E119: 2024 | F119: Q2 | G119: 2024-Q2 | H119: 37.27 | I119: n/a | J119: 932443904 | K119: 20.65332 | L119: 1.2614501 | M119: 0.79273848 | N119: 2.839154 | O119: 1262.0189 | P119: 0.024267058 | Q119: 0.16328353 | R119: 0.044106245 | S119: 0.44904167 | T119: 0.079776508 | U119: -0.033583239 | V119: 0.0070260289 | W119: -0.12591207 | X119: -0.0083469925
A120: ADEN CN EQUITY | B120: ADENTRA Inc | C120: Industrials | D120: =VLOOKUP(C120,INDUSTRY!A:B,2,FALSE) -> Manufacturing | E120: 2024 | F120: Q3 | G120: 2024-Q3 | H120: 42.41 | I120: n/a | J120: 1061051968 | K120: 20.782527 | L120: 1.092648 | M120: 0.9152078 | N120: 3.4435551 | O120: 1291.9119 | P120: 0.023686643 | Q120: 0.16328353 | R120: 0.044106245 | S120: 0.44904167 | T120: 0.079776508 | U120: -0.033583239 | V120: 0.0070260289 | W120: -0.12591207 | X120: -0.0083469925
A121: ADEN CN EQUITY | B121: ADENTRA Inc | C121: Industrials | D121: =VLOOKUP(C121,INDUSTRY!A:B,2,FALSE) -> Manufacturing | E121: 2024 | F121: Q4 | G121: 2024-Q4 | H121: 37.13 | I121: n/a | J121: 928952128 | K121: 20.649568 | L121: 1.248587 | M121: 0.80090534 | N121: 3.480083 | O121: 1416.54 | P121: 0.09646795 | Q121: 0.16328353 | R121: 0.044106245 | S121: 0.44904167 | T121: 0.079776508 | U121: -0.033583239 | V121: 0.0070260289 | W121: -0.12591207 | X121: -0.0083469925
A122: ADN CN EQUITY | B122: Acadian Timber Corp | C122: Materials | D122: =VLOOKUP(C122,INDUSTRY!A:B,2,FALSE) -> Natural Resources | E122: 2015 | F122: Q1 | G122: 2015-Q1 | H122: 18.15 | I122: 0.59179811 | J122: 303671584 | K122: 19.531457 | L122: 1.016207 | M122: 0.9840515 | N122: 12.308104 | O122: 406.42598 | P122: 0.31825088 | Q122: 0 | R122: 0 | S122: 0 | T122: 0 | U122: 0 | V122: 0 | W122: 0 | X122: 0
A123: ADN CN EQUITY | B123: Acadian Timber Corp | C123: Materials | D123: =VLOOKUP(C123,INDUSTRY!A:B,2,FALSE) -> Natural Resources | E123: 2015 | F123: Q2 | G123: 2015-Q2 | H123: 18.9 | I123: 1.7517111 | J123: 316220000 | K123: 19.571949 | L123: 1.198284 | M123: 0.83452669 | N123: 10.875058 | O123: 424.928 | P123: 0.045523704 | Q123: 0 | R123: 0 | S123: 0 | T123: 0 | U123: 0 | V123: 0 | W123: 0 | X123: 0
A124: ADN CN EQUITY | B124: Acadian Timber Corp | C124: Materials | D124: =VLOOKUP(C124,INDUSTRY!A:B,2,FALSE) -> Natural Resources | E124: 2015 | F124: Q3 | G124: 2015-Q3 | H124: 20.07 | I124: 1.7046896 | J124: 335795520 | K124: 19.632013 | L124: 1.265533 | M124: 0.79018091 | N124: 11.362474 | O124: 418.22301 | P124: -0.015779125 | Q124: 0 | R124: 0 | S124: 0 | T124: 0 | U124: 0 | V124: 0 | W124: 0 | X124: 0
A125: ADN CN EQUITY | B125: Acadian Timber Corp | C125: Materials | D125: =VLOOKUP(C125,INDUSTRY!A:B,2,FALSE) -> Natural Resources | E125: 2015 | F125: Q4 | G125: 2015-Q4 | H125: 20.1 | I125: 1.4337916 | J125: 336297440 | K125: 19.633507 | L125: 1.327588 | M125: 0.75324576 | N125: 10.242769 | O125: 438.288 | P125: 0.047976777 | Q125: 0 | R125: 0 | S125: 0 | T125: 0 | U125: 0 | V125: 0 | W125: 0 | X125: 0
A126: ADN CN EQUITY | B126: Acadian Timber Corp | C126: Materials | D126: =VLOOKUP(C126,INDUSTRY!A:B,2,FALSE) -> Natural Resources | E126: 2016 | F126: Q1 | G126: 2016-Q1 | H126: 20.08 | I126: 0.85351723 | J126: 335962816 | K126: 19.632511 | L126: 1.259324 | M126: 0.79407685 | N126: 3.1863899 | O126: 449.77798 | P126: 0.026215603 | Q126: 0 | R126: 0 | S126: 0 | T126: 0 | U126: 0 | V126: 0 | W126: 0 | X126: 0
A127: ADN CN EQUITY | B127: Acadian Timber Corp | C127: Materials | D127: =VLOOKUP(C127,INDUSTRY!A:B,2,FALSE) -> Natural Resources | E127: 2016 | F127: Q2 | G127: 2016-Q2 | H127: 16.58 | I127: 0.30474033 | J127: 277403584 | K127: 19.440984 | L127: 1.28406 | M127: 0.77877981 | N127: 4.8027811 | O127: 445.65101 | P127: -0.0091755847 | Q127: 0 | R127: 0 | S127: 0 | T127: 0 | U127: 0 | V127: 0 | W127: 0 | X127: 0
A128: ADN CN EQUITY | B128: Acadian Timber Corp | C128: Materials | D128: =VLOOKUP(C128,INDUSTRY!A:B,2,FALSE) -> Natural Resources | E128: 2016 | F128: Q3 | G128: 2016-Q3 | H128: 18.1 | I128: 0.51012253 | J128: 302835008 | K128: 19.528699 | L128: 1.0577019 | M128: 0.94544593 | N128: 4.9102869 | O128: 440.62701 | P128: -0.011273395 | Q128: 0 | R128: 0 | S128: 0 | T128: 0 | U128: 0 | V128: 0 | W128: 0 | X128: 0
A129: ADN CN EQUITY | B129: Acadian Timber Corp | C129: Materials | D129: =VLOOKUP(C129,INDUSTRY!A:B,2,FALSE) -> Natural Resources | E129: 2016 | F129: Q4 | G129: 2016-Q4 | H129: 18.35 | I129: 0.53845458 | J129: 307017824 | K129: 19.542416 | L129: 1.182677 | M129: 0.84553938 | N129: 6.0312171 | O129: 447.636 | P129: 0.01590686 | Q129: 0 | R129: 0 | S129: 0 | T129: 0 | U129: 0 | V129: 0 | W129: 0 | X129: 0
A130: ADN CN EQUITY | B130: Acadian Timber Corp | C130: Materials | D130: =VLOOKUP(C130,INDUSTRY!A:B,2,FALSE) -> Natural Resources | E130: 2017 | F130: Q1 | G130: 2017-Q1 | H130: 18.36 | I130: 0.30116441 | J130: 307185120 | K130: 19.542961 | L130: 1.146226 | M130: 0.87242826 | N130: 3.554352 | O130: 454.57798 | P130: 0.0155081 | Q130: 0 | R130: 0 | S130: 0 | T130: 0 | U130: 0 | V130: 0 | W130: 0 | X130: 0
A131: ADN CN EQUITY | B131: Acadian Timber Corp | C131: Materials | D131: =VLOOKUP(C131,INDUSTRY!A:B,2,FALSE) -> Natural Resources | E131: 2017 | F131: Q2 | G131: 2017-Q2 | H131: 18.83 | I131: 0.2844146 | J131: 315048800 | K131: 19.568238 | L131: 1.14782 | M131: 0.87121674 | N131: 3.6282101 | O131: 463.22701 | P131: 0.019026491 | Q131: 0 | R131: 0 | S131: 0 | T131: 0 | U131: 0 | V131: 0 | W131: 0 | X131: 0
A132: ADN CN EQUITY | B132: Acadian Timber Corp | C132: Materials | D132: =VLOOKUP(C132,INDUSTRY!A:B,2,FALSE) -> Natural Resources | E132: 2017 | F132: Q3 | G132: 2017-Q3 | H132: 19.43 | I132: 0.71656588 | J132: 325087520 | K132: 19.599605 | L132: 1.191125 | M132: 0.83954242 | N132: 3.2770591 | O132: 454.62701 | P132: -0.018565411 | Q132: 0 | R132: 0 | S132: 0 | T132: 0 | U132: 0 | V132: 0 | W132: 0 | X132: 0
A133: ADN CN EQUITY | B133: Acadian Timber Corp | C133: Materials | D133: =VLOOKUP(C133,INDUSTRY!A:B,2,FALSE) -> Natural Resources | E133: 2017 | F133: Q4 | G133: 2017-Q4 | H133: 19.5 | I133: 2.107801 | J133: 326258720 | K133: 19.603201 | L133: 1.234347 | M133: 0.81014497 | N133: 4.8020158 | O133: 451.65299 | P133: -0.0065416615 | Q133: 0 | R133: 0 | S133: 0 | T133: 0 | U133: 0 | V133: 0 | W133: 0 | X133: 0
... A157: ADN CN EQUITY | B157: Acadian Timber Corp | C157: Materials | D157: =VLOOKUP(C157,INDUSTRY!A:B,2,FALSE) -> Natural Resources | E157: 2023 | F157: Q4 | G157: 2023-Q4 | H157: 17.01 | I157: 0.14384598 | J157: 292275296 | K157: 19.493207 | L157: 0.95504397 | M157: 1.0470722 | N157: 7.2631221 | O157: 560.04198 | P157: 0.026750296 | Q157: 0.2468288 | R157: 0.21679021 | S157: 0.49948477 | T157: 0.092421426 | U157: 0.0095946625 | V157: 0.03403788 | W157: -0.043553759 | X157: 0.014889117
A158: ADN CN EQUITY | B158: Acadian Timber Corp | C158: Materials | D158: =VLOOKUP(C158,INDUSTRY!A:B,2,FALSE) -> Natural Resources | E158: 2024 | F158: Q1 | G158: 2024-Q1 | H158: 17.38 | I158: n/a | J158: 299888384 | K158: 19.518921 | L158: 0.91627502 | M158: 1.0913754 | N158: 5.2760868 | O158: 567.95302 | P158: 0.014125798 | Q158: 0.22124697 | R158: 0.18272417 | S158: 0.47834722 | T158: 0.076057275 | U158: -0.025581828 | V158: -0.034066043 | W158: -0.021137543 | X158: -0.016364151
A159: ADN CN EQUITY | B159: Acadian Timber Corp | C159: Materials | D159: =VLOOKUP(C159,INDUSTRY!A:B,2,FALSE) -> Natural Resources | E159: 2024 | F159: Q2 | G159: 2024-Q2 | H159: 17.13 | I159: n/a | J159: 297935808 | K159: 19.512389 | L159: 0.92826903 | M159: 1.0772739 | N159: 5.2337971 | O159: 585.49101 | P159: 0.030879286 | Q159: 0.22124697 | R159: 0.18272417 | S159: 0.47834722 | T159: 0.076057275 | U159: -0.025581828 | V159: -0.034066043 | W159: -0.021137543 | X159: -0.016364151
A160: ADN CN EQUITY | B160: Acadian Timber Corp | C160: Materials | D160: =VLOOKUP(C160,INDUSTRY!A:B,2,FALSE) -> Natural Resources | E160: 2024 | F160: Q3 | G160: 2024-Q3 | H160: 17.44 | I160: n/a | J160: 305842048 | K160: 19.538579 | L160: 0.90584701 | M160: 1.1039392 | N160: 5.6606898 | O160: 582.99802 | P160: -0.004257951 | Q160: 0.22124697 | R160: 0.18272417 | S160: 0.47834722 | T160: 0.076057275 | U160: -0.025581828 | V160: -0.034066043 | W160: -0.021137543 | X160: -0.016364151
A161: ADN CN EQUITY | B161: Acadian Timber Corp | C161: Materials | D161: =VLOOKUP(C161,INDUSTRY!A:B,2,FALSE) -> Natural Resources | E161: 2024 | F161: Q4 | G161: 2024-Q4 | H161: 17.42 | I161: n/a | J161: 307910464 | K161: 19.54532 | L161: 0.92724299 | M161: 1.078466 | N161: 4.8444619 | O161: 585.43098 | P161: 0.0041731874 | Q161: 0.22124697 | R161: 0.18272417 | S161: 0.47834722 | T161: 0.076057275 | U161: -0.025581828 | V161: -0.034066043 | W161: -0.021137543 | X161: -0.016364151
A162: ADW/A CN EQUITY | B162: Andrew Peller Ltd | C162: Consumer Staples | D162: =VLOOKUP(C162,INDUSTRY!A:B,2,FALSE) -> Manufacturing | E162: 2015 | F162: Q1 | G162: 2015-Q1 | H162: 5.3333 | I162: 1.8166345 | J162: 245137936 | K162: 19.317332 | L162: 1.456845 | M162: 0.6864148 | N162: 4.7202301 | O162: 301.45501 | P162: 0.0081634702 | Q162: 0 | R162: 0 | S162: 0 | T162: 0 | U162: 0 | V162: 0 | W162: 0 | X162: 0
A163: ADW/A CN EQUITY | B163: Andrew Peller Ltd | C163: Consumer Staples | D163: =VLOOKUP(C163,INDUSTRY!A:B,2,FALSE) -> Manufacturing | E163: 2015 | F163: Q2 | G163: 2015-Q2 | H163: 5.95 | I163: 1.8432333 | J163: 265881328 | K163: 19.398561 | L163: 1.552271 | M163: 0.6442174 | N163: 5.0533252 | O163: 301.51901 | P163: 0.00021230365 | Q163: 0 | R163: 0 | S163: 0 | T163: 0 | U163: 0 | V163: 0 | W163: 0 | X163: 0
A164: ADW/A CN EQUITY | B164: Andrew Peller Ltd | C164: Consumer Staples | D164: =VLOOKUP(C164,INDUSTRY!A:B,2,FALSE) -> Manufacturing | E164: 2015 | F164: Q3 | G164: 2015-Q3 | H164: 6.0333 | I164: 1.864985 | J164: 268464448 | K164: 19.408229 | L164: 1.663291 | M164: 0.60121771 | N164: 6.0107369 | O164: 298.236 | P164: -0.010888229 | Q164: 0 | R164: 0 | S164: 0 | T164: 0 | U164: 0 | V164: 0 | W164: 0 | X164: 0
A165: ADW/A CN EQUITY | B165: Andrew Peller Ltd | C165: Consumer Staples | D165: =VLOOKUP(C165,INDUSTRY!A:B,2,FALSE) -> Manufacturing | E165: 2015 | F165: Q4 | G165: 2015-Q4 | H165: 6.83 | I165: 1.1608027 | J165: 307412800 | K165: 19.543702 | L165: 1.633021 | M165: 0.612362 | N165: 6.5155921 | O165: 308.544 | P165: 0.034563232 | Q165: 0 | R165: 0 | S165: 0 | T165: 0 | U165: 0 | V165: 0 | W165: 0 | X165: 0
A166: ADW/A CN EQUITY | B166: Andrew Peller Ltd | C166: Consumer Staples | D166: =VLOOKUP(C166,INDUSTRY!A:B,2,FALSE) -> Manufacturing | E166: 2016 | F166: Q1 | G166: 2016-Q1 | H166: 9.8167 | I166: 1.0882859 | J166: 425758560 | K166: 19.869383 | L166: 1.789362 | M166: 0.55885842 | N166: 6.963789 | O166: 309.04602 | P166: 0.0016270483 | Q166: 0 | R166: 0 | S166: 0 | T166: 0 | U166: 0 | V166: 0 | W166: 0 | X166: 0
A167: ADW/A CN EQUITY | B167: Andrew Peller Ltd | C167: Consumer Staples | D167: =VLOOKUP(C167,INDUSTRY!A:B,2,FALSE) -> Manufacturing | E167: 2016 | F167: Q2 | G167: 2016-Q2 | H167: 9.2867 | I167: 0.30732294 | J167: 398646816 | K167: 19.803586 | L167: 2.650804 | M167: 0.37724403 | N167: 6.2965298 | O167: 308.30899 | P167: -0.0023848358 | Q167: 0 | R167: 0 | S167: 0 | T167: 0 | U167: 0 | V167: 0 | W167: 0 | X167: 0
A168: ADW/A CN EQUITY | B168: Andrew Peller Ltd | C168: Consumer Staples | D168: =VLOOKUP(C168,INDUSTRY!A:B,2,FALSE) -> Manufacturing | E168: 2016 | F168: Q3 | G168: 2016-Q3 | H168: 11.3167 | I168: 0.46700286 | J168: 485171936 | K168: 20.000014 | L168: 2.4183209 | M168: 0.41351005 | N168: 6.9326768 | O168: 309.98499 | P168: 0.0054361048 | Q168: 0 | R168: 0 | S168: 0 | T168: 0 | U168: 0 | V168: 0 | W168: 0 | X168: 0
A169: ADW/A CN EQUITY | B169: Andrew Peller Ltd | C169: Consumer Staples | D169: =VLOOKUP(C169,INDUSTRY!A:B,2,FALSE) -> Manufacturing | E169: 2016 | F169: Q4 | G169: 2016-Q4 | H169: 11.7 | I169: 2.1170656 | J169: 498525472 | K169: 20.027165 | L169: 2.8505559 | M169: 0.35080877 | N169: 6.9060049 | O169: 319.60499 | P169: 0.03103376 | Q169: 0 | R169: 0 | S169: 0 | T169: 0 | U169: 0 | V169: 0 | W169: 0 | X169: 0
A170: ADW/A CN EQUITY | B170: Andrew Peller Ltd | C170: Consumer Staples | D170: =VLOOKUP(C170,INDUSTRY!A:B,2,FALSE) -> Manufacturing | E170: 2017 | F170: Q1 | G170: 2017-Q1 | H170: 11.27 | I170: 3.3014681 | J170: 479939872 | K170: 19.989171 | L170: 2.814111 | M170: 0.35535201 | N170: 7.0750108 | O170: 332.112 | P170: 0.039132705 | Q170: 0 | R170: 0 | S170: 0 | T170: 0 | U170: 0 | V170: 0 | W170: 0 | X170: 0
A171: ADW/A CN EQUITY | B171: Andrew Peller Ltd | C171: Consumer Staples | D171: =VLOOKUP(C171,INDUSTRY!A:B,2,FALSE) -> Manufacturing | E171: 2017 | F171: Q2 | G171: 2017-Q2 | H171: 10.95 | I171: 2.6717083 | J171: 470725856 | K171: 19.969786 | L171: 2.707185 | M171: 0.36938739 | N171: 8.2889404 | O171: 327.47802 | P171: -0.013953076 | Q171: 0 | R171: 0 | S171: 0 | T171: 0 | U171: 0 | V171: 0 | W171: 0 | X171: 0
A172: ADW/A CN EQUITY | B172: Andrew Peller Ltd | C172: Consumer Staples | D172: =VLOOKUP(C172,INDUSTRY!A:B,2,FALSE) -> Manufacturing | E172: 2017 | F172: Q3 | G172: 2017-Q3 | H172: 12.01 | I172: 1.0889253 | J172: 520020640 | K172: 20.069379 | L172: 2.554091 | M172: 0.39152873 | N172: 8.1345606 | O172: 328.476 | P172: 0.003047484 | Q172: 0 | R172: 0 | S172: 0 | T172: 0 | U172: 0 | V172: 0 | W172: 0 | X172: 0
A173: ADW/A CN EQUITY | B173: Andrew Peller Ltd | C173: Consumer Staples | D173: =VLOOKUP(C173,INDUSTRY!A:B,2,FALSE) -> Manufacturing | E173: 2017 | F173: Q4 | G173: 2017-Q4 | H173: 15.55 | I173: 1.8950879 | J173: 695365888 | K173: 20.359949 | L173: 2.679363 | M173: 0.37322304 | N173: 7.8809228 | O173: 379.90701 | P173: 0.15657463 | Q173: 0 | R173: 0 | S173: 0 | T173: 0 | U173: 0 | V173: 0 | W173: 0 | X173: 0
... A197: ADW/A CN EQUITY | B197: Andrew Peller Ltd | C197: Consumer Staples | D197: =VLOOKUP(C197,INDUSTRY!A:B,2,FALSE) -> Manufacturing | E197: 2023 | F197: Q4 | G197: 2023-Q4 | H197: 4.58 | I197: 0.12919623 | J197: 208241056 | K197: 19.154207 | L197: 0.71633297 | M197: 1.3959988 | N197: -0.29785001 | O197: 565.43398 | P197: 0.021987482 | Q197: 0.095857113 | R197: 0 | S197: 0.12279614 | T197: 0.14376077 | U197: 0.067770569 | V197: 0 | W197: 0.0474368 | X197: 0.12305311
A198: ADW/A CN EQUITY | B198: Andrew Peller Ltd | C198: Consumer Staples | D198: =VLOOKUP(C198,INDUSTRY!A:B,2,FALSE) -> Manufacturing | E198: 2024 | F198: Q1 | G198: 2024-Q1 | H198: 3.99 | I198: n/a | J198: 180446304 | K198: 19.010944 | L198: 0.791812 | M198: 1.262926 | N198: -1.069329 | O198: 545.07398 | P198: -0.03600774 | Q198: 0.13720767 | R198: 0.0096618357 | S198: 0.25548611 | T198: 0.1561194 | U198: 0.041350559 | V198: 0.0096618357 | W198: 0.13268997 | X198: 0.012358628
A199: ADW/A CN EQUITY | B199: Andrew Peller Ltd | C199: Consumer Staples | D199: =VLOOKUP(C199,INDUSTRY!A:B,2,FALSE) -> Manufacturing | E199: 2024 | F199: Q2 | G199: 2024-Q2 | H199: 3.82 | I199: n/a | J199: 175130752 | K199: 18.981043 | L199: 0.71702898 | M199: 1.3946438 | N199: -0.50931001 | O199: 553.19898 | P199: 0.014906219 | Q199: 0.13720767 | R199: 0.0096618357 | S199: 0.25548611 | T199: 0.1561194 | U199: 0.041350559 | V199: 0.0096618357 | W199: 0.13268997 | X199: 0.012358628
A200: ADW/A CN EQUITY | B200: Andrew Peller Ltd | C200: Consumer Staples | D200: =VLOOKUP(C200,INDUSTRY!A:B,2,FALSE) -> Manufacturing | E200: 2024 | F200: Q3 | G200: 2024-Q3 | H200: 3.93 | I200: n/a | J200: 178364608 | K200: 18.99934 | L200: 0.69393498 | M200: 1.4410572 | N200: -0.41724601 | O200: 547.28102 | P200: -0.010697692 | Q200: 0.13720767 | R200: 0.0096618357 | S200: 0.25548611 | T200: 0.1561194 | U200: 0.041350559 | V200: 0.0096618357 | W200: 0.13268997 | X200: 0.012358628
A201: ADW/A CN EQUITY | B201: Andrew Peller Ltd | C201: Consumer Staples | D201: =VLOOKUP(C201,INDUSTRY!A:B,2,FALSE) -> Manufacturing | E201: 2024 | F201: Q4 | G201: 2024-Q4 | H201: 4.13 | I201: n/a | J201: 187899376 | K201: 19.051417 | L201: 0.70566398 | M201: 1.4171051 | N201: -0.56376201 | O201: 543.90003 | P201: -0.0061777987 | Q201: 0.13720767 | R201: 0.0096618357 | S201: 0.25548611 | T201: 0.1561194 | U201: 0.041350559 | V201: 0.0096618357 | W201: 0.13268997 | X201: 0.012358628
A202: AGF/B CN EQUITY | B202: AGF Management Ltd | C202: Financials | D202: =VLOOKUP(C202,INDUSTRY!A:B,2,FALSE) -> Service | E202: 2015 | F202: Q1 | G202: 2015-Q1 | H202: 8.34 | I202: 0.3307945 | J202: 716926400 | K202: 20.390484 | L202: 0.91869903 | M202: 1.0884958 | N202: 3.9091859 | O202: 1511.423 | P202: 0.0021682257 | Q202: 0.36096696 | R202: 0.29107154 | S202: 0.44418605 | T202: 0.35073407 | U202: 0.0034418881 | V202: -0.022267526 | W202: 0.014948276 | X202: -0.00084416844
A203: AGF/B CN EQUITY | B203: AGF Management Ltd | C203: Financials | D203: =VLOOKUP(C203,INDUSTRY!A:B,2,FALSE) -> Service | E203: 2015 | F203: Q2 | G203: 2015-Q2 | H203: 5.86 | I203: 0.12175796 | J203: 503739680 | K203: 20.03757 | L203: 0.76349002 | M203: 1.3097748 | N203: 3.750978 | O203: 1406.64 | P203: -0.069327367 | Q203: 0.36096696 | R203: 0.29107154 | S203: 0.44418605 | T203: 0.35073407 | U203: 0.0034418881 | V203: -0.022267526 | W203: 0.014948276 | X203: -0.00084416844
A204: AGF/B CN EQUITY | B204: AGF Management Ltd | C204: Financials | D204: =VLOOKUP(C204,INDUSTRY!A:B,2,FALSE) -> Service | E204: 2015 | F204: Q3 | G204: 2015-Q3 | H204: 5.29 | I204: 0.093585968 | J204: 454741088 | K204: 19.935239 | L204: 0.63351798 | M204: 1.5784872 | N204: 3.7449341 | O204: 1424.359 | P204: 0.012596713 | Q204: 0.36096696 | R204: 0.29107154 | S204: 0.44418605 | T204: 0.35073407 | U204: 0.0034418881 | V204: -0.022267526 | W204: 0.014948276 | X204: -0.00084416844
A205: AGF/B CN EQUITY | B205: AGF Management Ltd | C205: Financials | D205: =VLOOKUP(C205,INDUSTRY!A:B,2,FALSE) -> Service | E205: 2015 | F205: Q4 | G205: 2015-Q4 | H205: 5.2 | I205: 0.60964471 | J205: 419721728 | K205: 19.855102 | L205: 0.55089003 | M205: 1.8152443 | N205: 3.545279 | O205: 1425.551 | P205: 0.00083682272 | Q205: 0.36096696 | R205: 0.29107154 | S205: 0.44418605 | T205: 0.35073407 | U205: 0.0034418881 | V205: -0.022267526 | W205: 0.014948276 | X205: -0.00084416844
A206: AGF/B CN EQUITY | B206: AGF Management Ltd | C206: Financials | D206: =VLOOKUP(C206,INDUSTRY!A:B,2,FALSE) -> Service | E206: 2016 | F206: Q1 | G206: 2016-Q1 | H206: 5.14 | I206: 0.69438222 | J206: 414878784 | K206: 19.843497 | L206: 0.447092 | M206: 2.2366761 | N206: 3.2495489 | O206: 1436.9251 | P206: 0.0079787256 | Q206: 0.43603344 | R206: 0.30464413 | S206: 0.58142251 | T206: 0.37283782 | U206: 0.075066479 | V206: 0.013572589 | W206: 0.13723646 | X206: 0.022103754
A207: AGF/B CN EQUITY | B207: AGF Management Ltd | C207: Financials | D207: =VLOOKUP(C207,INDUSTRY!A:B,2,FALSE) -> Service | E207: 2016 | F207: Q2 | G207: 2016-Q2 | H207: 5 | I207: 0.72502874 | J207: 403578592 | K207: 19.815882 | L207: 0.421974 | M207: 2.3698142 | N207: 3.159013 | O207: 1412.848 | P207: -0.016755958 | Q207: 0.43603344 | R207: 0.30464413 | S207: 0.58142251 | T207: 0.37283782 | U207: 0.075066479 | V207: 0.013572589 | W207: 0.13723646 | X207: 0.022103754
A208: AGF/B CN EQUITY | B208: AGF Management Ltd | C208: Financials | D208: =VLOOKUP(C208,INDUSTRY!A:B,2,FALSE) -> Service | E208: 2016 | F208: Q3 | G208: 2016-Q3 | H208: 5.03 | I208: 0.88643481 | J208: 406000064 | K208: 19.821864 | L208: 0.45903 | M208: 2.1785068 | N208: 2.8033891 | O208: 1386.881 | P208: -0.018379172 | Q208: 0.43603344 | R208: 0.30464413 | S208: 0.58142251 | T208: 0.37283782 | U208: 0.075066479 | V208: 0.013572589 | W208: 0.13723646 | X208: 0.022103754
A209: AGF/B CN EQUITY | B209: AGF Management Ltd | C209: Financials | D209: =VLOOKUP(C209,INDUSTRY!A:B,2,FALSE) -> Service | E209: 2016 | F209: Q4 | G209: 2016-Q4 | H209: 6.27 | I209: 1.0019107 | J209: 506087552 | K209: 20.04222 | L209: 0.43629801 | M209: 2.2920114 | N209: 2.5325661 | O209: 1388.512 | P209: 0.0011760028 | Q209: 0.43603344 | R209: 0.30464413 | S209: 0.58142251 | T209: 0.37283782 | U209: 0.075066479 | V209: 0.013572589 | W209: 0.13723646 | X209: 0.022103754
A210: AGF/B CN EQUITY | B210: AGF Management Ltd | C210: Financials | D210: =VLOOKUP(C210,INDUSTRY!A:B,2,FALSE) -> Service | E210: 2017 | F210: Q1 | G210: 2017-Q1 | H210: 6.16 | I210: 0.86129263 | J210: 497208800 | K210: 20.024521 | L210: 0.46694401 | M210: 2.1415844 | N210: 3.0312099 | O210: 1362.881 | P210: -0.018459312 | Q210: 0.48186808 | R210: 0.48937192 | S210: 0.56018809 | T210: 0.48325359 | U210: 0.045834639 | V210: 0.18472779 | W210: -0.021234418 | X210: 0.11041577
A211: AGF/B CN EQUITY | B211: AGF Management Ltd | C211: Financials | D211: =VLOOKUP(C211,INDUSTRY!A:B,2,FALSE) -> Service | E211: 2017 | F211: Q2 | G211: 2017-Q2 | H211: 6.74 | I211: 0.81131067 | J211: 536507328 | K211: 20.100591 | L211: 0.52792501 | M211: 1.8942084 | N211: 3.022167 | O211: 1333.2611 | P211: -0.021733348 | Q211: 0.48186808 | R211: 0.48937192 | S211: 0.56018809 | T211: 0.48325359 | U211: 0.045834639 | V211: 0.18472779 | W211: -0.021234418 | X211: 0.11041577
A212: AGF/B CN EQUITY | B212: AGF Management Ltd | C212: Financials | D212: =VLOOKUP(C212,INDUSTRY!A:B,2,FALSE) -> Service | E212: 2017 | F212: Q3 | G212: 2017-Q3 | H212: 8.09 | I212: 0.88894601 | J212: 643968000 | K212: 20.28316 | L212: 0.55813903 | M212: 1.7916683 | N212: 3.3186281 | O212: 1331.471 | P212: -0.0013426328 | Q212: 0.48186808 | R212: 0.48937192 | S212: 0.56018809 | T212: 0.48325359 | U212: 0.045834639 | V212: 0.18472779 | W212: -0.021234418 | X212: 0.11041577
A213: AGF/B CN EQUITY | B213: AGF Management Ltd | C213: Financials | D213: =VLOOKUP(C213,INDUSTRY!A:B,2,FALSE) -> Service | E213: 2017 | F213: Q4 | G213: 2017-Q4 | H213: 8.18 | I213: 0.92899139 | J213: 651602752 | K213: 20.294946 | L213: 0.67073101 | M213: 1.4909106 | N213: 3.652416 | O213: 1312.604 | P213: -0.01417 | Q213: 0.48186808 | R213: 0.48937192 | S213: 0.56018809 | T213: 0.48325359 | U213: 0.045834639 | V213: 0.18472779 | W213: -0.021234418 | X213: 0.11041577
... A237: AGF/B CN EQUITY | B237: AGF Management Ltd | C237: Financials | D237: =VLOOKUP(C237,INDUSTRY!A:B,2,FALSE) -> Service | E237: 2023 | F237: Q4 | G237: 2023-Q4 | H237: 7.71 | I237: 1.1103565 | J237: 519264768 | K237: 20.067924 | L237: 0.471964 | M237: 2.1188057 | N237: 6.7347841 | O237: 1401.521 | P237: 0.010164954 | Q237: 0.37507708 | R237: 0.20156129 | S237: 0.36409291 | T237: 0.44972843 | U237: -0.037077011 | V237: -0.045027172 | W237: -0.041041959 | X237: -0.029557278
A238: AGF/B CN EQUITY | B238: AGF Management Ltd | C238: Financials | D238: =VLOOKUP(C238,INDUSTRY!A:B,2,FALSE) -> Service | E238: 2024 | F238: Q1 | G238: 2024-Q1 | H238: 8.2 | I238: n/a | J238: 552265984 | K238: 20.12954 | L238: 0.42890099 | M238: 2.3315404 | N238: 6.2883902 | O238: 1420.278 | P238: 0.013383311 | Q238: 0.36625021 | R238: 0.19758137 | S238: 0.35545833 | T238: 0.43895188 | U238: -0.0088268789 | V238: -0.0039799195 | W238: -0.008634578 | X238: -0.01077655
...

Sheet INDUSTRY
A1: Sector | B1: Canadian Industry
A2: Energy | B2: Natural Resources
A3: Materials | B3: Natural Resources
A4: Industrials | B4: Manufacturing
A5: Utilities | B5: Service
A6: Real Estate | B6: Service
A7: Consumer Staples | B7: Manufacturing
A8: Information Technology | B8: Service
A9: Communication Services | B9: Service
A10: Health Care | B10: Service
A11: Financials | B11: Service
A12: Consumer Discretionary | B12: Service
