Workbook

Sheet Sheet3
A2: things to fix
A3: - | B3: price to book --> those highlighted in red are missing values
A4: - | B4: pull total assets for all companies
A5: - | B5: pull the ibsn numbers or whatever for each company for easier extraction of ESG scores
A6: - | B6: need to get all numbers (minus stock prices) for companies that didn’t start on mar 31 2015
A7: - | B7: roa - those in red are missing values
L8: AAV CN EQUITY
L9: ACQ CN EQUITY
L10: ADEN CN EQUITY
L11: ADN CN EQUITY
L12: ADW/A CN EQUITY
L13: AGF/B CN EQUITY
L14: AI CN EQUITY
L15: AIF CN EQUITY
L16: AIM CN EQUITY
L17: ALS CN EQUITY
L18: AND CN EQUITY
L19: APR-U CN EQUITY
... L247: WRN CN EQUITY

Sheet COMBINED DATA
A1: Security | C1: Name | D1: Sector | E1: Year | F1: Quarter | G1: Index | H1: Closing Stock Price | I1: SP Volatility | J1: MC RAW (million's) | K1: Log MCap | L1: PB RAW | M1: Book to Mkt | N1: ROA | O1: Total Assets (mil) | P1: Asset Growth | Q1: ESGScore | R1: ESG Momentum | S1: EnvironmentPillarScore | T1: GovernancePillarScore | U1: SocialPillarScore
A2: AAV CN Equity | B2: =VLOOKUP(A2,Sheet3!L:L,1,FALSE) -> AAV CN EQUITY | C2: =VLOOKUP(A2,'ALL - prices'!B:C,2,FALSE) -> Advantage Energy Ltd | D2: =VLOOKUP(A2,'ALL - prices'!B:I,8,FALSE) -> Energy | E2: 2015 | F2: Q1 | G2: =E2&"-"&F2 -> 2015-Q1 | H2: =INDEX('ALL - prices'!$J$3:$DY$219,MATCH('COMBINED DATA'!A2,'ALL - prices'!$B$3:$B$219,0),MATCH('COMBINED DATA'!G2,'ALL - prices'!$J$1:$DY$1,0)) -> 6.82 | I2: =STDEV(H3:H6) -> 0.43338782 | J2: =INDEX('market cap'!$B$3:$DQ$219,MATCH(A2,'market cap'!$A$3:$A$219,0),MATCH(G2,'market cap'!$B$1:$DQ$1,0)) -> 1161.4957 | K2: =LN(J2) -> 7.0574639 | L2: =INDEX('PB2'!$D$2:$AQ$224,MATCH(A2,'PB2'!$B$2:$B$224,0),MATCH(G2,'PB2'!$D$1:$AQ$1,0)) -> 1.0568269 | M2: =1/L2 -> 0.94622871 | N2: =INDEX('ROA2'!$D$2:$AQ$224,MATCH(A2,'ROA2'!$B$2:$B$224,0),MATCH(G2,'ROA2'!$D$1:$AQ$1,0)) -> 0.97533798 | O2: 1454.767 | P2: 0.088701862
A3: AAV CN Equity | B3: =VLOOKUP(A3,Sheet3!L:L,1,FALSE) -> AAV CN EQUITY | C3: =VLOOKUP(A3,'ALL - prices'!B:C,2,FALSE) -> Advantage Energy Ltd | D3: =VLOOKUP(A3,'ALL - prices'!B:I,8,FALSE) -> Energy | E3: 2015 | F3: Q2 | G3: =E3&"-"&F3 -> 2015-Q2 | H3: =INDEX('ALL - prices'!$J$3:$DY$219,MATCH('COMBINED DATA'!A3,'ALL - prices'!$B$3:$B$219,0),MATCH('COMBINED DATA'!G3,'ALL - prices'!$J$1:$DY$1,0)) -> 7.9 | I3: =STDEV(H4:H7) -> 0.11026483 | J3: =INDEX('market cap'!$B$3:$DQ$219,MATCH(A3,'market cap'!$A$3:$A$219,0),MATCH(G3,'market cap'!$B$1:$DQ$1,0)) -> 1348.2602 | K3: =LN(J3) -> 7.2065703 | L3: =INDEX('PB2'!$D$2:$AQ$224,MATCH(A3,'PB2'!$B$2:$B$224,0),MATCH(G3,'PB2'!$D$1:$AQ$1,0)) -> 1.226446 | M3: =1/L3 -> 0.81536405 | N3: =INDEX('ROA2'!$D$2:$AQ$224,MATCH(A3,'ROA2'!$B$2:$B$224,0),MATCH(G3,'ROA2'!$D$1:$AQ$1,0)) -> 6.8927059 | O3: 1508.438 | P3: 0.036893221
A4: AAV CN Equity | B4: =VLOOKUP(A4,Sheet3!L:L,1,FALSE) -> AAV CN EQUITY | C4: =VLOOKUP(A4,'ALL - prices'!B:C,2,FALSE) -> Advantage Energy Ltd | D4: =VLOOKUP(A4,'ALL - prices'!B:I,8,FALSE) -> Energy | E4: 2015 | F4: Q3 | G4: =E4&"-"&F4 -> 2015-Q3 | H4: =INDEX('ALL - prices'!$J$3:$DY$219,MATCH('COMBINED DATA'!A4,'ALL - prices'!$B$3:$B$219,0),MATCH('COMBINED DATA'!G4,'ALL - prices'!$J$1:$DY$1,0)) -> 6.97 | I4: =STDEV(H5:H8) -> 1.0395672 | J4: =INDEX('market cap'!$B$3:$DQ$219,MATCH(A4,'market cap'!$A$3:$A$219,0),MATCH(G4,'market cap'!$B$1:$DQ$1,0)) -> 1189.8869 | K4: =LN(J4) -> 7.0816135 | L4: =INDEX('PB2'!$D$2:$AQ$224,MATCH(A4,'PB2'!$B$2:$B$224,0),MATCH(G4,'PB2'!$D$1:$AQ$1,0)) -> 1.0742 | M4: =1/L4 -> 0.93092531 | N4: =INDEX('ROA2'!$D$2:$AQ$224,MATCH(A4,'ROA2'!$B$2:$B$224,0),MATCH(G4,'ROA2'!$D$1:$AQ$1,0)) -> 5.0444198 | O4: 1493.8691 | P4: -0.0096583087
A5: AAV CN Equity | B5: =VLOOKUP(A5,Sheet3!L:L,1,FALSE) -> AAV CN EQUITY | C5: =VLOOKUP(A5,'ALL - prices'!B:C,2,FALSE) -> Advantage Energy Ltd | D5: =VLOOKUP(A5,'ALL - prices'!B:I,8,FALSE) -> Energy | E5: 2015 | F5: Q4 | G5: =E5&"-"&F5 -> 2015-Q4 | H5: =INDEX('ALL - prices'!$J$3:$DY$219,MATCH('COMBINED DATA'!A5,'ALL - prices'!$B$3:$B$219,0),MATCH('COMBINED DATA'!G5,'ALL - prices'!$J$1:$DY$1,0)) -> 7.03 | I5: =STDEV(H6:H9) -> 1.1470942 | J5: =INDEX('market cap'!$B$3:$DQ$219,MATCH(A5,'market cap'!$A$3:$A$219,0),MATCH(G5,'market cap'!$B$1:$DQ$1,0)) -> 1200.2386 | K5: =LN(J5) -> 7.0902756 | L5: =INDEX('PB2'!$D$2:$AQ$224,MATCH(A5,'PB2'!$B$2:$B$224,0),MATCH(G5,'PB2'!$D$1:$AQ$1,0)) -> 1.070385 | M5: =1/L5 -> 0.9342433 | N5: =INDEX('ROA2'!$D$2:$AQ$224,MATCH(A5,'ROA2'!$B$2:$B$224,0),MATCH(G5,'ROA2'!$D$1:$AQ$1,0)) -> 4.388618 | O5: 1518.964 | P5: 0.016798602
A6: AAV CN Equity | B6: =VLOOKUP(A6,Sheet3!L:L,1,FALSE) -> AAV CN EQUITY | C6: =VLOOKUP(A6,'ALL - prices'!B:C,2,FALSE) -> Advantage Energy Ltd | D6: =VLOOKUP(A6,'ALL - prices'!B:I,8,FALSE) -> Energy | E6: 2016 | F6: Q1 | G6: =E6&"-"&F6 -> 2016-Q1 | H6: =INDEX('ALL - prices'!$J$3:$DY$219,MATCH('COMBINED DATA'!A6,'ALL - prices'!$B$3:$B$219,0),MATCH('COMBINED DATA'!G6,'ALL - prices'!$J$1:$DY$1,0)) -> 7.13 | I6: =STDEV(H7:H10) -> 0.92477024 | J6: =INDEX('market cap'!$B$3:$DQ$219,MATCH(A6,'market cap'!$A$3:$A$219,0),MATCH(G6,'market cap'!$B$1:$DQ$1,0)) -> 1314.7801 | K6: =LN(J6) -> 7.1814247 | L6: =INDEX('PB2'!$D$2:$AQ$224,MATCH(A6,'PB2'!$B$2:$B$224,0),MATCH(G6,'PB2'!$D$1:$AQ$1,0)) -> 1.065817 | M6: =1/L6 -> 0.93824737 | N6: =INDEX('ROA2'!$D$2:$AQ$224,MATCH(A6,'ROA2'!$B$2:$B$224,0),MATCH(G6,'ROA2'!$D$1:$AQ$1,0)) -> 1.438526 | O6: 1517.4429 | P6: -0.0010013562
A7: AAV CN Equity | B7: =VLOOKUP(A7,Sheet3!L:L,1,FALSE) -> AAV CN EQUITY | C7: =VLOOKUP(A7,'ALL - prices'!B:C,2,FALSE) -> Advantage Energy Ltd | D7: =VLOOKUP(A7,'ALL - prices'!B:I,8,FALSE) -> Energy | E7: 2016 | F7: Q2 | G7: =E7&"-"&F7 -> 2016-Q2 | H7: =INDEX('ALL - prices'!$J$3:$DY$219,MATCH('COMBINED DATA'!A7,'ALL - prices'!$B$3:$B$219,0),MATCH('COMBINED DATA'!G7,'ALL - prices'!$J$1:$DY$1,0)) -> 7.22 | I7: =STDEV(H8:H11) -> 0.22470351 | J7: =INDEX('market cap'!$B$3:$DQ$219,MATCH(A7,'market cap'!$A$3:$A$219,0),MATCH(G7,'market cap'!$B$1:$DQ$1,0)) -> 1332.1635 | K7: =LN(J7) -> 7.1945596 | L7: =INDEX('PB2'!$D$2:$AQ$224,MATCH(A7,'PB2'!$B$2:$B$224,0),MATCH(G7,'PB2'!$D$1:$AQ$1,0)) -> 1.1047651 | M7: =1/L7 -> 0.90516983 | N7: =INDEX('ROA2'!$D$2:$AQ$224,MATCH(A7,'ROA2'!$B$2:$B$224,0),MATCH(G7,'ROA2'!$D$1:$AQ$1,0)) -> 2.089612 | O7: 1554.14 | P7: 0.024183504
A8: AAV CN Equity | B8: =VLOOKUP(A8,Sheet3!L:L,1,FALSE) -> AAV CN EQUITY | C8: =VLOOKUP(A8,'ALL - prices'!B:C,2,FALSE) -> Advantage Energy Ltd | D8: =VLOOKUP(A8,'ALL - prices'!B:I,8,FALSE) -> Energy | E8: 2016 | F8: Q3 | G8: =E8&"-"&F8 -> 2016-Q3 | H8: =INDEX('ALL - prices'!$J$3:$DY$219,MATCH('COMBINED DATA'!A8,'ALL - prices'!$B$3:$B$219,0),MATCH('COMBINED DATA'!G8,'ALL - prices'!$J$1:$DY$1,0)) -> 9.2 | I8: =STDEV(H9:H12) -> 0.5591884 | J8: =INDEX('market cap'!$B$3:$DQ$219,MATCH(A8,'market cap'!$A$3:$A$219,0),MATCH(G8,'market cap'!$B$1:$DQ$1,0)) -> 1697.9066 | K8: =LN(J8) -> 7.4371514 | L8: =INDEX('PB2'!$D$2:$AQ$224,MATCH(A8,'PB2'!$B$2:$B$224,0),MATCH(G8,'PB2'!$D$1:$AQ$1,0)) -> 1.397257 | M8: =1/L8 -> 0.71568797 | N8: =INDEX('ROA2'!$D$2:$AQ$224,MATCH(A8,'ROA2'!$B$2:$B$224,0),MATCH(G8,'ROA2'!$D$1:$AQ$1,0)) -> 0.286286 | O8: 1505.225 | P8: -0.031474044
A9: AAV CN Equity | B9: =VLOOKUP(A9,Sheet3!L:L,1,FALSE) -> AAV CN EQUITY | C9: =VLOOKUP(A9,'ALL - prices'!B:C,2,FALSE) -> Advantage Energy Ltd | D9: =VLOOKUP(A9,'ALL - prices'!B:I,8,FALSE) -> Energy | E9: 2016 | F9: Q4 | G9: =E9&"-"&F9 -> 2016-Q4 | H9: =INDEX('ALL - prices'!$J$3:$DY$219,MATCH('COMBINED DATA'!A9,'ALL - prices'!$B$3:$B$219,0),MATCH('COMBINED DATA'!G9,'ALL - prices'!$J$1:$DY$1,0)) -> 9.12 | I9: =STDEV(H10:H13) -> 1.5932645 | J9: =INDEX('market cap'!$B$3:$DQ$219,MATCH(A9,'market cap'!$A$3:$A$219,0),MATCH(G9,'market cap'!$B$1:$DQ$1,0)) -> 1683.9711 | K9: =LN(J9) -> 7.42891 | L9: =INDEX('PB2'!$D$2:$AQ$224,MATCH(A9,'PB2'!$B$2:$B$224,0),MATCH(G9,'PB2'!$D$1:$AQ$1,0)) -> 1.393764 | M9: =1/L9 -> 0.71748157 | N9: =INDEX('ROA2'!$D$2:$AQ$224,MATCH(A9,'ROA2'!$B$2:$B$224,0),MATCH(G9,'ROA2'!$D$1:$AQ$1,0)) -> 0.36416301 | O9: 1512.0931 | P9: 0.0045628369
A10: AAV CN Equity | B10: =VLOOKUP(A10,Sheet3!L:L,1,FALSE) -> AAV CN EQUITY | C10: =VLOOKUP(A10,'ALL - prices'!B:C,2,FALSE) -> Advantage Energy Ltd | D10: =VLOOKUP(A10,'ALL - prices'!B:I,8,FALSE) -> Energy | E10: 2017 | F10: Q1 | G10: =E10&"-"&F10 -> 2017-Q1 | H10: =INDEX('ALL - prices'!$J$3:$DY$219,MATCH('COMBINED DATA'!A10,'ALL - prices'!$B$3:$B$219,0),MATCH('COMBINED DATA'!G10,'ALL - prices'!$J$1:$DY$1,0)) -> 8.78 | I10: =STDEV(H11:H14) -> 2.2606341 | J10: =INDEX('market cap'!$B$3:$DQ$219,MATCH(A10,'market cap'!$A$3:$A$219,0),MATCH(G10,'market cap'!$B$1:$DQ$1,0)) -> 1623.1667 | K10: =LN(J10) -> 7.3921343 | L10: =INDEX('PB2'!$D$2:$AQ$224,MATCH(A10,'PB2'!$B$2:$B$224,0),MATCH(G10,'PB2'!$D$1:$AQ$1,0)) -> 1.297083 | M10: =1/L10 -> 0.77096067 | N10: =INDEX('ROA2'!$D$2:$AQ$224,MATCH(A10,'ROA2'!$B$2:$B$224,0),MATCH(G10,'ROA2'!$D$1:$AQ$1,0)) -> -1.044095 | O10: 1496.459 | P10: -0.010339343
A11: AAV CN Equity | B11: =VLOOKUP(A11,Sheet3!L:L,1,FALSE) -> AAV CN EQUITY | C11: =VLOOKUP(A11,'ALL - prices'!B:C,2,FALSE) -> Advantage Energy Ltd | D11: =VLOOKUP(A11,'ALL - prices'!B:I,8,FALSE) -> Energy | E11: 2017 | F11: Q2 | G11: =E11&"-"&F11 -> 2017-Q2 | H11: =INDEX('ALL - prices'!$J$3:$DY$219,MATCH('COMBINED DATA'!A11,'ALL - prices'!$B$3:$B$219,0),MATCH('COMBINED DATA'!G11,'ALL - prices'!$J$1:$DY$1,0)) -> 8.77 | I11: =STDEV(H12:H15) -> 1.8253493 | J11: =INDEX('market cap'!$B$3:$DQ$219,MATCH(A11,'market cap'!$A$3:$A$219,0),MATCH(G11,'market cap'!$B$1:$DQ$1,0)) -> 1623.2635 | K11: =LN(J11) -> 7.3921939 | L11: =INDEX('PB2'!$D$2:$AQ$224,MATCH(A11,'PB2'!$B$2:$B$224,0),MATCH(G11,'PB2'!$D$1:$AQ$1,0)) -> 1.281309 | M11: =1/L11 -> 0.78045186 | N11: =INDEX('ROA2'!$D$2:$AQ$224,MATCH(A11,'ROA2'!$B$2:$B$224,0),MATCH(G11,'ROA2'!$D$1:$AQ$1,0)) -> 0.76613802 | O11: 1532.51 | P11: 0.024090833
A12: AAV CN Equity | B12: =VLOOKUP(A12,Sheet3!L:L,1,FALSE) -> AAV CN EQUITY | C12: =VLOOKUP(A12,'ALL - prices'!B:C,2,FALSE) -> Advantage Energy Ltd | D12: =VLOOKUP(A12,'ALL - prices'!B:I,8,FALSE) -> Energy | E12: 2017 | F12: Q3 | G12: =E12&"-"&F12 -> 2017-Q3 | H12: =INDEX('ALL - prices'!$J$3:$DY$219,MATCH('COMBINED DATA'!A12,'ALL - prices'!$B$3:$B$219,0),MATCH('COMBINED DATA'!G12,'ALL - prices'!$J$1:$DY$1,0)) -> 7.82 | I12: =STDEV(H13:H16) -> 0.807589 | J12: =INDEX('market cap'!$B$3:$DQ$219,MATCH(A12,'market cap'!$A$3:$A$219,0),MATCH(G12,'market cap'!$B$1:$DQ$1,0)) -> 1454.1747 | K12: =LN(J12) -> 7.2821938 | L12: =INDEX('PB2'!$D$2:$AQ$224,MATCH(A12,'PB2'!$B$2:$B$224,0),MATCH(G12,'PB2'!$D$1:$AQ$1,0)) -> 1.128872 | M12: =1/L12 -> 0.88584 | N12: =INDEX('ROA2'!$D$2:$AQ$224,MATCH(A12,'ROA2'!$B$2:$B$224,0),MATCH(G12,'ROA2'!$D$1:$AQ$1,0)) -> 3.9336181 | O12: 1541.7411 | P12: 0.0060235198
A13: AAV CN Equity | B13: =VLOOKUP(A13,Sheet3!L:L,1,FALSE) -> AAV CN EQUITY | C13: =VLOOKUP(A13,'ALL - prices'!B:C,2,FALSE) -> Advantage Energy Ltd | D13: =VLOOKUP(A13,'ALL - prices'!B:I,8,FALSE) -> Energy | E13: 2017 | F13: Q4 | G13: =E13&"-"&F13 -> 2017-Q4 | H13: =INDEX('ALL - prices'!$J$3:$DY$219,MATCH('COMBINED DATA'!A13,'ALL - prices'!$B$3:$B$219,0),MATCH('COMBINED DATA'!G13,'ALL - prices'!$J$1:$DY$1,0)) -> 5.4 | I13: =STDEV(H14:H17) -> 0.95325757 | J13: =INDEX('market cap'!$B$3:$DQ$219,MATCH(A13,'market cap'!$A$3:$A$219,0),MATCH(G13,'market cap'!$B$1:$DQ$1,0)) -> 1004.2012 | K13: =LN(J13) -> 6.9119477 | L13: =INDEX('PB2'!$D$2:$AQ$224,MATCH(A13,'PB2'!$B$2:$B$224,0),MATCH(G13,'PB2'!$D$1:$AQ$1,0)) -> 0.76558602 | M13: =1/L13 -> 1.306189 | N13: =INDEX('ROA2'!$D$2:$AQ$224,MATCH(A13,'ROA2'!$B$2:$B$224,0),MATCH(G13,'ROA2'!$D$1:$AQ$1,0)) -> 4.1560621 | O13: 1604.752 | P13: 0.040869992
... A37: AAV CN Equity | B37: =VLOOKUP(A37,Sheet3!L:L,1,FALSE) -> AAV CN EQUITY | C37: =VLOOKUP(A37,'ALL - prices'!B:C,2,FALSE) -> Advantage Energy Ltd | D37: =VLOOKUP(A37,'ALL - prices'!B:I,8,FALSE) -> Energy | E37: 2023 | F37: Q4 | G37: =E37&"-"&F37 -> 2023-Q4 | H37: =INDEX('ALL - prices'!$J$3:$DY$219,MATCH('COMBINED DATA'!A37,'ALL - prices'!$B$3:$B$219,0),MATCH('COMBINED DATA'!G37,'ALL - prices'!$J$1:$DY$1,0)) -> 8.53 | I37: =STDEV(H38:H41) -> 0.38064638 | J37: =INDEX('market cap'!$B$3:$DQ$219,MATCH(A37,'market cap'!$A$3:$A$219,0),MATCH(G37,'market cap'!$B$1:$DQ$1,0)) -> 1409.0158 | K37: =LN(J37) -> 7.2506467 | L37: =INDEX('PB2'!$D$2:$AQ$224,MATCH(A37,'PB2'!$B$2:$B$224,0),MATCH(G37,'PB2'!$D$1:$AQ$1,0)) -> 0.88915098 | M37: =1/L37 -> 1.1246684 | N37: =INDEX('ROA2'!$D$2:$AQ$224,MATCH(A37,'ROA2'!$B$2:$B$224,0),MATCH(G37,'ROA2'!$D$1:$AQ$1,0)) -> 7.7911472 | O37: 2283.7189 | P37: 0.023283405
A38: AAV CN Equity | B38: =VLOOKUP(A38,Sheet3!L:L,1,FALSE) -> AAV CN EQUITY | C38: =VLOOKUP(A38,'ALL - prices'!B:C,2,FALSE) -> Advantage Energy Ltd | D38: =VLOOKUP(A38,'ALL - prices'!B:I,8,FALSE) -> Energy | E38: 2024 | F38: Q1 | G38: =E38&"-"&F38 -> 2024-Q1 | H38: =INDEX('ALL - prices'!$J$3:$DY$219,MATCH('COMBINED DATA'!A38,'ALL - prices'!$B$3:$B$219,0),MATCH('COMBINED DATA'!G38,'ALL - prices'!$J$1:$DY$1,0)) -> 9.88 | I38: N/A | J38: =INDEX('market cap'!$B$3:$DQ$219,MATCH(A38,'market cap'!$A$3:$A$219,0),MATCH(G38,'market cap'!$B$1:$DQ$1,0)) -> 1580.1872 | K38: =LN(J38) -> 7.3652986 | L38: =INDEX('PB2'!$D$2:$AQ$224,MATCH(A38,'PB2'!$B$2:$B$224,0),MATCH(G38,'PB2'!$D$1:$AQ$1,0)) -> 1.014098 | M38: =1/L38 -> 0.98609794 | N38: =INDEX('ROA2'!$D$2:$AQ$224,MATCH(A38,'ROA2'!$B$2:$B$224,0),MATCH(G38,'ROA2'!$D$1:$AQ$1,0)) -> 4.4994378 | O38: 2299.028 | P38: 0.0067035641
A39: AAV CN Equity | B39: =VLOOKUP(A39,Sheet3!L:L,1,FALSE) -> AAV CN EQUITY | C39: =VLOOKUP(A39,'ALL - prices'!B:C,2,FALSE) -> Advantage Energy Ltd | D39: =VLOOKUP(A39,'ALL - prices'!B:I,8,FALSE) -> Energy | E39: 2024 | F39: Q2 | G39: =E39&"-"&F39 -> 2024-Q2 | H39: =INDEX('ALL - prices'!$J$3:$DY$219,MATCH('COMBINED DATA'!A39,'ALL - prices'!$B$3:$B$219,0),MATCH('COMBINED DATA'!G39,'ALL - prices'!$J$1:$DY$1,0)) -> 10.38 | I39: N/A | J39: =INDEX('market cap'!$B$3:$DQ$219,MATCH(A39,'market cap'!$A$3:$A$219,0),MATCH(G39,'market cap'!$B$1:$DQ$1,0)) -> 1733.1706 | K39: =LN(J39) -> 7.4577077 | L39: =INDEX('PB2'!$D$2:$AQ$224,MATCH(A39,'PB2'!$B$2:$B$224,0),MATCH(G39,'PB2'!$D$1:$AQ$1,0)) -> 1.068455 | M39: =1/L39 -> 0.93593087 | N39: =INDEX('ROA2'!$D$2:$AQ$224,MATCH(A39,'ROA2'!$B$2:$B$224,0),MATCH(G39,'ROA2'!$D$1:$AQ$1,0)) -> 4.1665492 | O39: 2342.176 | P39: 0.018767946
A40: AAV CN Equity | B40: =VLOOKUP(A40,Sheet3!L:L,1,FALSE) -> AAV CN EQUITY | C40: =VLOOKUP(A40,'ALL - prices'!B:C,2,FALSE) -> Advantage Energy Ltd | D40: =VLOOKUP(A40,'ALL - prices'!B:I,8,FALSE) -> Energy | E40: 2024 | F40: Q3 | G40: =E40&"-"&F40 -> 2024-Q3 | H40: =INDEX('ALL - prices'!$J$3:$DY$219,MATCH('COMBINED DATA'!A40,'ALL - prices'!$B$3:$B$219,0),MATCH('COMBINED DATA'!G40,'ALL - prices'!$J$1:$DY$1,0)) -> 9.45 | I40: N/A | J40: =INDEX('market cap'!$B$3:$DQ$219,MATCH(A40,'market cap'!$A$3:$A$219,0),MATCH(G40,'market cap'!$B$1:$DQ$1,0)) -> 1577.8865 | K40: =LN(J40) -> 7.3638416 | L40: =INDEX('PB2'!$D$2:$AQ$224,MATCH(A40,'PB2'!$B$2:$B$224,0),MATCH(G40,'PB2'!$D$1:$AQ$1,0)) -> 0.97480702 | M40: =1/L40 -> 1.0258441 | N40: =INDEX('ROA2'!$D$2:$AQ$224,MATCH(A40,'ROA2'!$B$2:$B$224,0),MATCH(G40,'ROA2'!$D$1:$AQ$1,0)) -> 3.184761 | O40: 2818.4819 | P40: 0.20336043
A41: AAV CN Equity | B41: =VLOOKUP(A41,Sheet3!L:L,1,FALSE) -> AAV CN EQUITY | C41: =VLOOKUP(A41,'ALL - prices'!B:C,2,FALSE) -> Advantage Energy Ltd | D41: =VLOOKUP(A41,'ALL - prices'!B:I,8,FALSE) -> Energy | E41: 2024 | F41: Q4 | G41: =E41&"-"&F41 -> 2024-Q4 | H41: =INDEX('ALL - prices'!$J$3:$DY$219,MATCH('COMBINED DATA'!A41,'ALL - prices'!$B$3:$B$219,0),MATCH('COMBINED DATA'!G41,'ALL - prices'!$J$1:$DY$1,0)) -> 9.86 | I41: N/A | J41: =INDEX('market cap'!$B$3:$DQ$219,MATCH(A41,'market cap'!$A$3:$A$219,0),MATCH(G41,'market cap'!$B$1:$DQ$1,0)) -> 1646.3877 | K41: =LN(J41) -> 7.4063389 | L41: =INDEX('PB2'!$D$2:$AQ$224,MATCH(A41,'PB2'!$B$2:$B$224,0),MATCH(G41,'PB2'!$D$1:$AQ$1,0)) -> 1.0170997 | M41: =1/L41 -> 0.98318777 | N41: =INDEX('ROA2'!$D$2:$AQ$224,MATCH(A41,'ROA2'!$B$2:$B$224,0),MATCH(G41,'ROA2'!$D$1:$AQ$1,0)) -> 1.77763 | O41: 2848.394 | P41: 0.010612828
A42: ABX CN Equity | B42: =VLOOKUP(A42,Sheet3!L:L,1,FALSE) -> #N/A | C42: =VLOOKUP(A42,'ALL - prices'!B:C,2,FALSE) -> Barrick Mining Corp | D42: =VLOOKUP(A42,'ALL - prices'!B:I,8,FALSE) -> Materials | E42: 2015 | F42: Q1 | G42: =E42&"-"&F42 -> 2015-Q1 | H42: =INDEX('ALL - prices'!$J$3:$DY$219,MATCH('COMBINED DATA'!A42,'ALL - prices'!$B$3:$B$219,0),MATCH('COMBINED DATA'!G42,'ALL - prices'!$J$1:$DY$1,0)) -> 11.5543 | I42: =STDEV(H43:H46) -> 3.392744 | J42: =INDEX(MarketCap2!$E$2:$AR$224,MATCH(A42,MarketCap2!$B$2:$B$224,0),MATCH(G42,MarketCap2!$E$1:$AR$1,0)) -> 16130674688 | K42: =LN(J42) -> 23.503989 | L42: =INDEX('PB2'!$D$2:$AQ$224,MATCH(A42,'PB2'!$B$2:$B$224,0),MATCH(G42,'PB2'!$D$1:$AQ$1,0)) -> 1.249226 | M42: =1/L42 -> 0.80049568 | N42: =INDEX('ROA2'!$D$2:$AQ$224,MATCH(A42,'ROA2'!$B$2:$B$224,0),MATCH(G42,'ROA2'!$D$1:$AQ$1,0)) -> -8.1511908 | O42: 33878.999 | P42: -0.096319041
A43: ABX CN Equity | B43: =VLOOKUP(A43,Sheet3!L:L,1,FALSE) -> #N/A | C43: =VLOOKUP(A43,'ALL - prices'!B:C,2,FALSE) -> Barrick Mining Corp | D43: =VLOOKUP(A43,'ALL - prices'!B:I,8,FALSE) -> Materials | E43: 2015 | F43: Q2 | G43: =E43&"-"&F43 -> 2015-Q2 | H43: =INDEX('ALL - prices'!$J$3:$DY$219,MATCH('COMBINED DATA'!A43,'ALL - prices'!$B$3:$B$219,0),MATCH('COMBINED DATA'!G43,'ALL - prices'!$J$1:$DY$1,0)) -> 11.1849 | I43: =STDEV(H44:H47) -> 7.3544072 | J43: =INDEX(MarketCap2!$E$2:$AR$224,MATCH(A43,MarketCap2!$B$2:$B$224,0),MATCH(G43,MarketCap2!$E$1:$AR$1,0)) -> 15548340224 | K43: =LN(J43) -> 23.46722 | L43: =INDEX('PB2'!$D$2:$AQ$224,MATCH(A43,'PB2'!$B$2:$B$224,0),MATCH(G43,'PB2'!$D$1:$AQ$1,0)) -> 1.224861 | M43: =1/L43 -> 0.81641915 | N43: =INDEX('ROA2'!$D$2:$AQ$224,MATCH(A43,'ROA2'!$B$2:$B$224,0),MATCH(G43,'ROA2'!$D$1:$AQ$1,0)) -> -8.2381153 | O43: 33517.001 | P43: -0.010685036
A44: ABX CN Equity | B44: =VLOOKUP(A44,Sheet3!L:L,1,FALSE) -> #N/A | C44: =VLOOKUP(A44,'ALL - prices'!B:C,2,FALSE) -> Barrick Mining Corp | D44: =VLOOKUP(A44,'ALL - prices'!B:I,8,FALSE) -> Materials | E44: 2015 | F44: Q3 | G44: =E44&"-"&F44 -> 2015-Q3 | H44: =INDEX('ALL - prices'!$J$3:$DY$219,MATCH('COMBINED DATA'!A44,'ALL - prices'!$B$3:$B$219,0),MATCH('COMBINED DATA'!G44,'ALL - prices'!$J$1:$DY$1,0)) -> 7.1349 | I44: =STDEV(H45:H48) -> 6.3429034 | J44: =INDEX(MarketCap2!$E$2:$AR$224,MATCH(A44,MarketCap2!$B$2:$B$224,0),MATCH(G44,MarketCap2!$E$1:$AR$1,0)) -> 9888047104 | K44: =LN(J44) -> 23.014593 | L44: =INDEX('PB2'!$D$2:$AQ$224,MATCH(A44,'PB2'!$B$2:$B$224,0),MATCH(G44,'PB2'!$D$1:$AQ$1,0)) -> 0.75509399 | M44: =1/L44 -> 1.3243384 | N44: =INDEX('ROA2'!$D$2:$AQ$224,MATCH(A44,'ROA2'!$B$2:$B$224,0),MATCH(G44,'ROA2'!$D$1:$AQ$1,0)) -> -7.583395 | O44: 33193.001 | P44: -0.0096667284
A45: ABX CN Equity | B45: =VLOOKUP(A45,Sheet3!L:L,1,FALSE) -> #N/A | C45: =VLOOKUP(A45,'ALL - prices'!B:C,2,FALSE) -> Barrick Mining Corp | D45: =VLOOKUP(A45,'ALL - prices'!B:I,8,FALSE) -> Materials | E45: 2015 | F45: Q4 | G45: =E45&"-"&F45 -> 2015-Q4 | H45: =INDEX('ALL - prices'!$J$3:$DY$219,MATCH('COMBINED DATA'!A45,'ALL - prices'!$B$3:$B$219,0),MATCH('COMBINED DATA'!G45,'ALL - prices'!$J$1:$DY$1,0)) -> 8.6289 | I45: =STDEV(H46:H49) -> 3.4876187 | J45: =INDEX(MarketCap2!$E$2:$AR$224,MATCH(A45,MarketCap2!$B$2:$B$224,0),MATCH(G45,MarketCap2!$E$1:$AR$1,0)) -> 11927520256 | K45: =LN(J45) -> 23.202114 | L45: =INDEX('PB2'!$D$2:$AQ$224,MATCH(A45,'PB2'!$B$2:$B$224,0),MATCH(G45,'PB2'!$D$1:$AQ$1,0)) -> 1.201969 | M45: =1/L45 -> 0.83196819 | N45: =INDEX('ROA2'!$D$2:$AQ$224,MATCH(A45,'ROA2'!$B$2:$B$224,0),MATCH(G45,'ROA2'!$D$1:$AQ$1,0)) -> -8.7770262 | O45: 32397.001 | P45: -0.023980967
A46: ABX CN Equity | B46: =VLOOKUP(A46,Sheet3!L:L,1,FALSE) -> #N/A | C46: =VLOOKUP(A46,'ALL - prices'!B:C,2,FALSE) -> Barrick Mining Corp | D46: =VLOOKUP(A46,'ALL - prices'!B:I,8,FALSE) -> Materials | E46: 2016 | F46: Q1 | G46: =E46&"-"&F46 -> 2016-Q1 | H46: =INDEX('ALL - prices'!$J$3:$DY$219,MATCH('COMBINED DATA'!A46,'ALL - prices'!$B$3:$B$219,0),MATCH('COMBINED DATA'!G46,'ALL - prices'!$J$1:$DY$1,0)) -> 14.8869 | I46: =STDEV(H47:H50) -> 2.2089316 | J46: =INDEX(MarketCap2!$E$2:$AR$224,MATCH(A46,MarketCap2!$B$2:$B$224,0),MATCH(G46,MarketCap2!$E$1:$AR$1,0)) -> 20552036352 | K46: =LN(J46) -> 23.746226 | L46: =INDEX('PB2'!$D$2:$AQ$224,MATCH(A46,'PB2'!$B$2:$B$224,0),MATCH(G46,'PB2'!$D$1:$AQ$1,0)) -> 2.2083249 | M46: =1/L46 -> 0.45283192 | N46: =INDEX('ROA2'!$D$2:$AQ$224,MATCH(A46,'ROA2'!$B$2:$B$224,0),MATCH(G46,'ROA2'!$D$1:$AQ$1,0)) -> -9.4306078 | O46: 26308 | P46: -0.18794953
A47: ABX CN Equity | B47: =VLOOKUP(A47,Sheet3!L:L,1,FALSE) -> #N/A | C47: =VLOOKUP(A47,'ALL - prices'!B:C,2,FALSE) -> Barrick Mining Corp | D47: =VLOOKUP(A47,'ALL - prices'!B:I,8,FALSE) -> Materials | E47: 2016 | F47: Q2 | G47: =E47&"-"&F47 -> 2016-Q2 | H47: =INDEX('ALL - prices'!$J$3:$DY$219,MATCH('COMBINED DATA'!A47,'ALL - prices'!$B$3:$B$219,0),MATCH('COMBINED DATA'!G47,'ALL - prices'!$J$1:$DY$1,0)) -> 23.3029 | I47: =STDEV(H48:H51) -> 1.7264674 | J47: =INDEX(MarketCap2!$E$2:$AR$224,MATCH(A47,MarketCap2!$B$2:$B$224,0),MATCH(G47,MarketCap2!$E$1:$AR$1,0)) -> 32136636416 | K47: =LN(J47) -> 24.193263 | L47: =INDEX('PB2'!$D$2:$AQ$224,MATCH(A47,'PB2'!$B$2:$B$224,0),MATCH(G47,'PB2'!$D$1:$AQ$1,0)) -> 3.3727789 | M47: =1/L47 -> 0.29649142 | N47: =INDEX('ROA2'!$D$2:$AQ$224,MATCH(A47,'ROA2'!$B$2:$B$224,0),MATCH(G47,'ROA2'!$D$1:$AQ$1,0)) -> -10.114974 | O47: 25366 | P47: -0.035806604
A48: ABX CN Equity | B48: =VLOOKUP(A48,Sheet3!L:L,1,FALSE) -> #N/A | C48: =VLOOKUP(A48,'ALL - prices'!B:C,2,FALSE) -> Barrick Mining Corp | D48: =VLOOKUP(A48,'ALL - prices'!B:I,8,FALSE) -> Materials | E48: 2016 | F48: Q3 | G48: =E48&"-"&F48 -> 2016-Q3 | H48: =INDEX('ALL - prices'!$J$3:$DY$219,MATCH('COMBINED DATA'!A48,'ALL - prices'!$B$3:$B$219,0),MATCH('COMBINED DATA'!G48,'ALL - prices'!$J$1:$DY$1,0)) -> 19.649 | I48: =STDEV(H49:H52) -> 1.9628205 | J48: =INDEX(MarketCap2!$E$2:$AR$224,MATCH(A48,MarketCap2!$B$2:$B$224,0),MATCH(G48,MarketCap2!$E$1:$AR$1,0)) -> 27070646272 | K48: =LN(J48) -> 24.021716 | L48: =INDEX('PB2'!$D$2:$AQ$224,MATCH(A48,'PB2'!$B$2:$B$224,0),MATCH(G48,'PB2'!$D$1:$AQ$1,0)) -> 2.745357 | M48: =1/L48 -> 0.36425135 | N48: =INDEX('ROA2'!$D$2:$AQ$224,MATCH(A48,'ROA2'!$B$2:$B$224,0),MATCH(G48,'ROA2'!$D$1:$AQ$1,0)) -> -9.6297426 | O48: 25604 | P48: 0.0093826434
A49: ABX CN Equity | B49: =VLOOKUP(A49,Sheet3!L:L,1,FALSE) -> #N/A | C49: =VLOOKUP(A49,'ALL - prices'!B:C,2,FALSE) -> Barrick Mining Corp | D49: =VLOOKUP(A49,'ALL - prices'!B:I,8,FALSE) -> Materials | E49: 2016 | F49: Q4 | G49: =E49&"-"&F49 -> 2016-Q4 | H49: =INDEX('ALL - prices'!$J$3:$DY$219,MATCH('COMBINED DATA'!A49,'ALL - prices'!$B$3:$B$219,0),MATCH('COMBINED DATA'!G49,'ALL - prices'!$J$1:$DY$1,0)) -> 18.2018 | I49: =STDEV(H50:H53) -> 2.5129984 | J49: =INDEX(MarketCap2!$E$2:$AR$224,MATCH(A49,MarketCap2!$B$2:$B$224,0),MATCH(G49,MarketCap2!$E$1:$AR$1,0)) -> 25045110784 | K49: =LN(J49) -> 23.943944 | L49: =INDEX('PB2'!$D$2:$AQ$224,MATCH(A49,'PB2'!$B$2:$B$224,0),MATCH(G49,'PB2'!$D$1:$AQ$1,0)) -> 2.3469679 | M49: =1/L49 -> 0.42608166 | N49: =INDEX('ROA2'!$D$2:$AQ$224,MATCH(A49,'ROA2'!$B$2:$B$224,0),MATCH(G49,'ROA2'!$D$1:$AQ$1,0)) -> -8.2447224 | O49: 25628 | P49: 0.00093737354
A50: ABX CN Equity | B50: =VLOOKUP(A50,Sheet3!L:L,1,FALSE) -> #N/A | C50: =VLOOKUP(A50,'ALL - prices'!B:C,2,FALSE) -> Barrick Mining Corp | D50: =VLOOKUP(A50,'ALL - prices'!B:I,8,FALSE) -> Materials | E50: 2017 | F50: Q1 | G50: =E50&"-"&F50 -> 2017-Q1 | H50: =INDEX('ALL - prices'!$J$3:$DY$219,MATCH('COMBINED DATA'!A50,'ALL - prices'!$B$3:$B$219,0),MATCH('COMBINED DATA'!G50,'ALL - prices'!$J$1:$DY$1,0)) -> 21.4276 | I50: =STDEV(H51:H54) -> 1.7274331 | J50: =INDEX(MarketCap2!$E$2:$AR$224,MATCH(A50,MarketCap2!$B$2:$B$224,0),MATCH(G50,MarketCap2!$E$1:$AR$1,0)) -> 29442402304 | K50: =LN(J50) -> 24.105702 | L50: =INDEX('PB2'!$D$2:$AQ$224,MATCH(A50,'PB2'!$B$2:$B$224,0),MATCH(G50,'PB2'!$D$1:$AQ$1,0)) -> 2.578748 | M50: =1/L50 -> 0.38778508 | N50: =INDEX('ROA2'!$D$2:$AQ$224,MATCH(A50,'ROA2'!$B$2:$B$224,0),MATCH(G50,'ROA2'!$D$1:$AQ$1,0)) -> 2.540138 | O50: 25264.001 | P50: -0.014203185
A51: ABX CN Equity | B51: =VLOOKUP(A51,Sheet3!L:L,1,FALSE) -> #N/A | C51: =VLOOKUP(A51,'ALL - prices'!B:C,2,FALSE) -> Barrick Mining Corp | D51: =VLOOKUP(A51,'ALL - prices'!B:I,8,FALSE) -> Materials | E51: 2017 | F51: Q2 | G51: =E51&"-"&F51 -> 2017-Q2 | H51: =INDEX('ALL - prices'!$J$3:$DY$219,MATCH('COMBINED DATA'!A51,'ALL - prices'!$B$3:$B$219,0),MATCH('COMBINED DATA'!G51,'ALL - prices'!$J$1:$DY$1,0)) -> 17.5321 | I51: =STDEV(H52:H55) -> 1.4125527 | J51: =INDEX(MarketCap2!$E$2:$AR$224,MATCH(A51,MarketCap2!$B$2:$B$224,0),MATCH(G51,MarketCap2!$E$1:$AR$1,0)) -> 24049934336 | K51: =LN(J51) -> 23.903398 | L51: =INDEX('PB2'!$D$2:$AQ$224,MATCH(A51,'PB2'!$B$2:$B$224,0),MATCH(G51,'PB2'!$D$1:$AQ$1,0)) -> 1.92039 | M51: =1/L51 -> 0.52072756 | N51: =INDEX('ROA2'!$D$2:$AQ$224,MATCH(A51,'ROA2'!$B$2:$B$224,0),MATCH(G51,'ROA2'!$D$1:$AQ$1,0)) -> 5.4734731 | O51: 26411 | P51: 0.04540052
A52: ABX CN Equity | B52: =VLOOKUP(A52,Sheet3!L:L,1,FALSE) -> #N/A | C52: =VLOOKUP(A52,'ALL - prices'!B:C,2,FALSE) -> Barrick Mining Corp | D52: =VLOOKUP(A52,'ALL - prices'!B:I,8,FALSE) -> Materials | E52: 2017 | F52: Q3 | G52: =E52&"-"&F52 -> 2017-Q3 | H52: =INDEX('ALL - prices'!$J$3:$DY$219,MATCH('COMBINED DATA'!A52,'ALL - prices'!$B$3:$B$219,0),MATCH('COMBINED DATA'!G52,'ALL - prices'!$J$1:$DY$1,0)) -> 17.0937 | I52: =STDEV(H53:H56) -> 1.4046691 | J52: =INDEX(MarketCap2!$E$2:$AR$224,MATCH(A52,MarketCap2!$B$2:$B$224,0),MATCH(G52,MarketCap2!$E$1:$AR$1,0)) -> 23413340160 | K52: =LN(J52) -> 23.876572 | L52: =INDEX('PB2'!$D$2:$AQ$224,MATCH(A52,'PB2'!$B$2:$B$224,0),MATCH(G52,'PB2'!$D$1:$AQ$1,0)) -> 1.951203 | M52: =1/L52 -> 0.51250434 | N52: =INDEX('ROA2'!$D$2:$AQ$224,MATCH(A52,'ROA2'!$B$2:$B$224,0),MATCH(G52,'ROA2'!$D$1:$AQ$1,0)) -> 9.192585 | O52: 25807 | P52: -0.022869269
A53: ABX CN Equity | B53: =VLOOKUP(A53,Sheet3!L:L,1,FALSE) -> #N/A | C53: =VLOOKUP(A53,'ALL - prices'!B:C,2,FALSE) -> Barrick Mining Corp | D53: =VLOOKUP(A53,'ALL - prices'!B:I,8,FALSE) -> Materials | E53: 2017 | F53: Q4 | G53: =E53&"-"&F53 -> 2017-Q4 | H53: =INDEX('ALL - prices'!$J$3:$DY$219,MATCH('COMBINED DATA'!A53,'ALL - prices'!$B$3:$B$219,0),MATCH('COMBINED DATA'!G53,'ALL - prices'!$J$1:$DY$1,0)) -> 15.5091 | I53: =STDEV(H54:H57) -> 1.5661405 | J53: =INDEX(MarketCap2!$E$2:$AR$224,MATCH(A53,MarketCap2!$B$2:$B$224,0),MATCH(G53,MarketCap2!$E$1:$AR$1,0)) -> 21202667520 | K53: =LN(J53) -> 23.777393 | L53: =INDEX('PB2'!$D$2:$AQ$224,MATCH(A53,'PB2'!$B$2:$B$224,0),MATCH(G53,'PB2'!$D$1:$AQ$1,0)) -> 1.8231879 | M53: =1/L53 -> 0.5484898 | N53: =INDEX('ROA2'!$D$2:$AQ$224,MATCH(A53,'ROA2'!$B$2:$B$224,0),MATCH(G53,'ROA2'!$D$1:$AQ$1,0)) -> 8.5877714 | O53: 25072.001 | P53: -0.028480588
... A77: ABX CN Equity | B77: =VLOOKUP(A77,Sheet3!L:L,1,FALSE) -> #N/A | C77: =VLOOKUP(A77,'ALL - prices'!B:C,2,FALSE) -> Barrick Mining Corp | D77: =VLOOKUP(A77,'ALL - prices'!B:I,8,FALSE) -> Materials | E77: 2023 | F77: Q4 | G77: =E77&"-"&F77 -> 2023-Q4 | H77: =INDEX('ALL - prices'!$J$3:$DY$219,MATCH('COMBINED DATA'!A77,'ALL - prices'!$B$3:$B$219,0),MATCH('COMBINED DATA'!G77,'ALL - prices'!$J$1:$DY$1,0)) -> 22.903 | I77: =STDEV(H78:H81) -> 2.1581346 | J77: =INDEX(MarketCap2!$E$2:$AR$224,MATCH(A77,MarketCap2!$B$2:$B$224,0),MATCH(G77,MarketCap2!$E$1:$AR$1,0)) -> 42027216896 | K77: =LN(J77) -> 24.461583 | L77: =INDEX('PB2'!$D$2:$AQ$224,MATCH(A77,'PB2'!$B$2:$B$224,0),MATCH(G77,'PB2'!$D$1:$AQ$1,0)) -> 1.363385 | M77: =1/L77 -> 0.73346856 | N77: =INDEX('ROA2'!$D$2:$AQ$224,MATCH(A77,'ROA2'!$B$2:$B$224,0),MATCH(G77,'ROA2'!$D$1:$AQ$1,0)) -> 0.126036 | O77: 45595.001 | P77: 0.0068233505
A78: ABX CN Equity | B78: =VLOOKUP(A78,Sheet3!L:L,1,FALSE) -> #N/A | C78: =VLOOKUP(A78,'ALL - prices'!B:C,2,FALSE) -> Barrick Mining Corp | D78: =VLOOKUP(A78,'ALL - prices'!B:I,8,FALSE) -> Materials | E78: 2024 | F78: Q1 | G78: =E78&"-"&F78 -> 2024-Q1 | H78: =INDEX('ALL - prices'!$J$3:$DY$219,MATCH('COMBINED DATA'!A78,'ALL - prices'!$B$3:$B$219,0),MATCH('COMBINED DATA'!G78,'ALL - prices'!$J$1:$DY$1,0)) -> 21.7035 | I78: N/A | J78: =INDEX(MarketCap2!$E$2:$AR$224,MATCH(A78,MarketCap2!$B$2:$B$224,0),MATCH(G78,MarketCap2!$E$1:$AR$1,0)) -> 39552983040 | K78: =LN(J78) -> 24.400907 | L78: =INDEX('PB2'!$D$2:$AQ$224,MATCH(A78,'PB2'!$B$2:$B$224,0),MATCH(G78,'PB2'!$D$1:$AQ$1,0)) -> 1.245345 | M78: =1/L78 -> 0.80299034 | N78: =INDEX('ROA2'!$D$2:$AQ$224,MATCH(A78,'ROA2'!$B$2:$B$224,0),MATCH(G78,'ROA2'!$D$1:$AQ$1,0)) -> 2.7719669 | O78: 45810.999 | P78: 0.0047373278
A79: ABX CN Equity | B79: =VLOOKUP(A79,Sheet3!L:L,1,FALSE) -> #N/A | C79: =VLOOKUP(A79,'ALL - prices'!B:C,2,FALSE) -> Barrick Mining Corp | D79: =VLOOKUP(A79,'ALL - prices'!B:I,8,FALSE) -> Materials | E79: 2024 | F79: Q2 | G79: =E79&"-"&F79 -> 2024-Q2 | H79: =INDEX('ALL - prices'!$J$3:$DY$219,MATCH('COMBINED DATA'!A79,'ALL - prices'!$B$3:$B$219,0),MATCH('COMBINED DATA'!G79,'ALL - prices'!$J$1:$DY$1,0)) -> 22.1118 | I79: N/A | J79: =INDEX(MarketCap2!$E$2:$AR$224,MATCH(A79,MarketCap2!$B$2:$B$224,0),MATCH(G79,MarketCap2!$E$1:$AR$1,0)) -> 40063614976 | K79: =LN(J79) -> 24.413734 | L79: =INDEX('PB2'!$D$2:$AQ$224,MATCH(A79,'PB2'!$B$2:$B$224,0),MATCH(G79,'PB2'!$D$1:$AQ$1,0)) -> 1.238506 | M79: =1/L79 -> 0.80742446 | N79: =INDEX('ROA2'!$D$2:$AQ$224,MATCH(A79,'ROA2'!$B$2:$B$224,0),MATCH(G79,'ROA2'!$D$1:$AQ$1,0)) -> 3.145823 | O79: 45843.001 | P79: 0.00069856691
A80: ABX CN Equity | B80: =VLOOKUP(A80,Sheet3!L:L,1,FALSE) -> #N/A | C80: =VLOOKUP(A80,'ALL - prices'!B:C,2,FALSE) -> Barrick Mining Corp | D80: =VLOOKUP(A80,'ALL - prices'!B:I,8,FALSE) -> Materials | E80: 2024 | F80: Q3 | G80: =E80&"-"&F80 -> 2024-Q3 | H80: =INDEX('ALL - prices'!$J$3:$DY$219,MATCH('COMBINED DATA'!A80,'ALL - prices'!$B$3:$B$219,0),MATCH('COMBINED DATA'!G80,'ALL - prices'!$J$1:$DY$1,0)) -> 26.1841 | I80: N/A | J80: =INDEX(MarketCap2!$E$2:$AR$224,MATCH(A80,MarketCap2!$B$2:$B$224,0),MATCH(G80,MarketCap2!$E$1:$AR$1,0)) -> 47092707328 | K80: =LN(J80) -> 24.575384 | L80: =INDEX('PB2'!$D$2:$AQ$224,MATCH(A80,'PB2'!$B$2:$B$224,0),MATCH(G80,'PB2'!$D$1:$AQ$1,0)) -> 1.460304 | M80: =1/L80 -> 0.68478891 | N80: =INDEX('ROA2'!$D$2:$AQ$224,MATCH(A80,'ROA2'!$B$2:$B$224,0),MATCH(G80,'ROA2'!$D$1:$AQ$1,0)) -> 3.3047371 | O80: 46219.002 | P80: 0.0082019174
A81: ABX CN Equity | B81: =VLOOKUP(A81,Sheet3!L:L,1,FALSE) -> #N/A | C81: =VLOOKUP(A81,'ALL - prices'!B:C,2,FALSE) -> Barrick Mining Corp | D81: =VLOOKUP(A81,'ALL - prices'!B:I,8,FALSE) -> Materials | E81: 2024 | F81: Q4 | G81: =E81&"-"&F81 -> 2024-Q4 | H81: =INDEX('ALL - prices'!$J$3:$DY$219,MATCH('COMBINED DATA'!A81,'ALL - prices'!$B$3:$B$219,0),MATCH('COMBINED DATA'!G81,'ALL - prices'!$J$1:$DY$1,0)) -> 21.8288 | I81: N/A | J81: =INDEX(MarketCap2!$E$2:$AR$224,MATCH(A81,MarketCap2!$B$2:$B$224,0),MATCH(G81,MarketCap2!$E$1:$AR$1,0)) -> 38807977984 | K81: =LN(J81) -> 24.381892 | L81: =INDEX('PB2'!$D$2:$AQ$224,MATCH(A81,'PB2'!$B$2:$B$224,0),MATCH(G81,'PB2'!$D$1:$AQ$1,0)) -> 1.1362153 | M81: =1/L81 -> 0.88011486 | N81: =INDEX('ROA2'!$D$2:$AQ$224,MATCH(A81,'ROA2'!$B$2:$B$224,0),MATCH(G81,'ROA2'!$D$1:$AQ$1,0)) -> 3.500845 | O81: 47353.999 | P81: 0.024556945
A82: AC CN Equity | B82: =VLOOKUP(A82,Sheet3!L:L,1,FALSE) -> #N/A | C82: =VLOOKUP(A82,'ALL - prices'!B:C,2,FALSE) -> Air Canada | D82: =VLOOKUP(A82,'ALL - prices'!B:I,8,FALSE) -> Industrials | E82: 2015 | F82: Q1 | G82: =E82&"-"&F82 -> 2015-Q1 | H82: =INDEX('ALL - prices'!$J$3:$DY$219,MATCH('COMBINED DATA'!A82,'ALL - prices'!$B$3:$B$219,0),MATCH('COMBINED DATA'!G82,'ALL - prices'!$J$1:$DY$1,0)) -> 12.39 | I82: =STDEV(H83:H86) -> 1.7836923 | J82: =INDEX(MarketCap2!$E$2:$AR$224,MATCH(A82,MarketCap2!$B$2:$B$224,0),MATCH(G82,MarketCap2!$E$1:$AR$1,0)) -> 3550374656 | K82: =LN(J82) -> 21.990319 | L82: =INDEX('PB2'!$D$2:$AQ$224,MATCH(A82,'PB2'!$B$2:$B$224,0),MATCH(G82,'PB2'!$D$1:$AQ$1,0)) -> -- | M82: =1/L82 -> #VALUE! | N82: =INDEX('ROA2'!$D$2:$AQ$224,MATCH(A82,'ROA2'!$B$2:$B$224,0),MATCH(G82,'ROA2'!$D$1:$AQ$1,0)) -> 0.99413502 | O82: 10648.001 | P82: 0.0097676681
A83: AC CN Equity | B83: =VLOOKUP(A83,Sheet3!L:L,1,FALSE) -> #N/A | C83: =VLOOKUP(A83,'ALL - prices'!B:C,2,FALSE) -> Air Canada | D83: =VLOOKUP(A83,'ALL - prices'!B:I,8,FALSE) -> Industrials | E83: 2015 | F83: Q2 | G83: =E83&"-"&F83 -> 2015-Q2 | H83: =INDEX('ALL - prices'!$J$3:$DY$219,MATCH('COMBINED DATA'!A83,'ALL - prices'!$B$3:$B$219,0),MATCH('COMBINED DATA'!G83,'ALL - prices'!$J$1:$DY$1,0)) -> 13.21 | I83: =STDEV(H84:H87) -> 0.91736489 | J83: =INDEX(MarketCap2!$E$2:$AR$224,MATCH(A83,MarketCap2!$B$2:$B$224,0),MATCH(G83,MarketCap2!$E$1:$AR$1,0)) -> 3789085440 | K83: =LN(J83) -> 22.055391 | L83: =INDEX('PB2'!$D$2:$AQ$224,MATCH(A83,'PB2'!$B$2:$B$224,0),MATCH(G83,'PB2'!$D$1:$AQ$1,0)) -> -- | M83: =1/L83 -> #VALUE! | N83: =INDEX('ROA2'!$D$2:$AQ$224,MATCH(A83,'ROA2'!$B$2:$B$224,0),MATCH(G83,'ROA2'!$D$1:$AQ$1,0)) -> 1.225342 | O83: 11581 | P83: 0.087622006
A84: AC CN Equity | B84: =VLOOKUP(A84,Sheet3!L:L,1,FALSE) -> #N/A | C84: =VLOOKUP(A84,'ALL - prices'!B:C,2,FALSE) -> Air Canada | D84: =VLOOKUP(A84,'ALL - prices'!B:I,8,FALSE) -> Industrials | E84: 2015 | F84: Q3 | G84: =E84&"-"&F84 -> 2015-Q3 | H84: =INDEX('ALL - prices'!$J$3:$DY$219,MATCH('COMBINED DATA'!A84,'ALL - prices'!$B$3:$B$219,0),MATCH('COMBINED DATA'!G84,'ALL - prices'!$J$1:$DY$1,0)) -> 10.73 | I84: =STDEV(H85:H88) -> 0.8696551 | J84: =INDEX(MarketCap2!$E$2:$AR$224,MATCH(A84,MarketCap2!$B$2:$B$224,0),MATCH(G84,MarketCap2!$E$1:$AR$1,0)) -> 3065968384 | K84: =LN(J84) -> 21.843629 | L84: =INDEX('PB2'!$D$2:$AQ$224,MATCH(A84,'PB2'!$B$2:$B$224,0),MATCH(G84,'PB2'!$D$1:$AQ$1,0)) -> -- | M84: =1/L84 -> #VALUE! | N84: =INDEX('ROA2'!$D$2:$AQ$224,MATCH(A84,'ROA2'!$B$2:$B$224,0),MATCH(G84,'ROA2'!$D$1:$AQ$1,0)) -> 1.790706 | O84: 12374 | P84: 0.068474221
A85: AC CN Equity | B85: =VLOOKUP(A85,Sheet3!L:L,1,FALSE) -> #N/A | C85: =VLOOKUP(A85,'ALL - prices'!B:C,2,FALSE) -> Air Canada | D85: =VLOOKUP(A85,'ALL - prices'!B:I,8,FALSE) -> Industrials | E85: 2015 | F85: Q4 | G85: =E85&"-"&F85 -> 2015-Q4 | H85: =INDEX('ALL - prices'!$J$3:$DY$219,MATCH('COMBINED DATA'!A85,'ALL - prices'!$B$3:$B$219,0),MATCH('COMBINED DATA'!G85,'ALL - prices'!$J$1:$DY$1,0)) -> 10.21 | I85: =STDEV(H86:H89) -> 2.2374837 | J85: =INDEX(MarketCap2!$E$2:$AR$224,MATCH(A85,MarketCap2!$B$2:$B$224,0),MATCH(G85,MarketCap2!$E$1:$AR$1,0)) -> 2894456832 | K85: =LN(J85) -> 21.786063 | L85: =INDEX('PB2'!$D$2:$AQ$224,MATCH(A85,'PB2'!$B$2:$B$224,0),MATCH(G85,'PB2'!$D$1:$AQ$1,0)) -> 222.09277 | M85: =1/L85 -> 0.0045026229 | N85: =INDEX('ROA2'!$D$2:$AQ$224,MATCH(A85,'ROA2'!$B$2:$B$224,0),MATCH(G85,'ROA2'!$D$1:$AQ$1,0)) -> 2.7381971 | O85: 12755 | P85: 0.030790425
A86: AC CN Equity | B86: =VLOOKUP(A86,Sheet3!L:L,1,FALSE) -> #N/A | C86: =VLOOKUP(A86,'ALL - prices'!B:C,2,FALSE) -> Air Canada | D86: =VLOOKUP(A86,'ALL - prices'!B:I,8,FALSE) -> Industrials | E86: 2016 | F86: Q1 | G86: =E86&"-"&F86 -> 2016-Q1 | H86: =INDEX('ALL - prices'!$J$3:$DY$219,MATCH('COMBINED DATA'!A86,'ALL - prices'!$B$3:$B$219,0),MATCH('COMBINED DATA'!G86,'ALL - prices'!$J$1:$DY$1,0)) -> 8.96 | I86: =STDEV(H87:H90) -> 2.4076683 | J86: =INDEX(MarketCap2!$E$2:$AR$224,MATCH(A86,MarketCap2!$B$2:$B$224,0),MATCH(G86,MarketCap2!$E$1:$AR$1,0)) -> 2523493376 | K86: =LN(J86) -> 21.64891 | L86: =INDEX('PB2'!$D$2:$AQ$224,MATCH(A86,'PB2'!$B$2:$B$224,0),MATCH(G86,'PB2'!$D$1:$AQ$1,0)) -> -- | M86: =1/L86 -> #VALUE! | N86: =INDEX('ROA2'!$D$2:$AQ$224,MATCH(A86,'ROA2'!$B$2:$B$224,0),MATCH(G86,'ROA2'!$D$1:$AQ$1,0)) -> 2.5488961 | O86: 13127 | P86: 0.029165013
A87: AC CN Equity | B87: =VLOOKUP(A87,Sheet3!L:L,1,FALSE) -> #N/A | C87: =VLOOKUP(A87,'ALL - prices'!B:C,2,FALSE) -> Air Canada | D87: =VLOOKUP(A87,'ALL - prices'!B:I,8,FALSE) -> Industrials | E87: 2016 | F87: Q2 | G87: =E87&"-"&F87 -> 2016-Q2 | H87: =INDEX('ALL - prices'!$J$3:$DY$219,MATCH('COMBINED DATA'!A87,'ALL - prices'!$B$3:$B$219,0),MATCH('COMBINED DATA'!G87,'ALL - prices'!$J$1:$DY$1,0)) -> 8.89 | I87: =STDEV(H88:H91) -> 2.7723441 | J87: =INDEX(MarketCap2!$E$2:$AR$224,MATCH(A87,MarketCap2!$B$2:$B$224,0),MATCH(G87,MarketCap2!$E$1:$AR$1,0)) -> 2458871808 | K87: =LN(J87) -> 21.622968 | L87: =INDEX('PB2'!$D$2:$AQ$224,MATCH(A87,'PB2'!$B$2:$B$224,0),MATCH(G87,'PB2'!$D$1:$AQ$1,0)) -> -- | M87: =1/L87 -> #VALUE! | N87: =INDEX('ROA2'!$D$2:$AQ$224,MATCH(A87,'ROA2'!$B$2:$B$224,0),MATCH(G87,'ROA2'!$D$1:$AQ$1,0)) -> 5.692872 | O87: 13503 | P87: 0.028643215
A88: AC CN Equity | B88: =VLOOKUP(A88,Sheet3!L:L,1,FALSE) -> #N/A | C88: =VLOOKUP(A88,'ALL - prices'!B:C,2,FALSE) -> Air Canada | D88: =VLOOKUP(A88,'ALL - prices'!B:I,8,FALSE) -> Industrials | E88: 2016 | F88: Q3 | G88: =E88&"-"&F88 -> 2016-Q3 | H88: =INDEX('ALL - prices'!$J$3:$DY$219,MATCH('COMBINED DATA'!A88,'ALL - prices'!$B$3:$B$219,0),MATCH('COMBINED DATA'!G88,'ALL - prices'!$J$1:$DY$1,0)) -> 10.6 | I88: =STDEV(H89:H92) -> 5.9009568 | J88: =INDEX(MarketCap2!$E$2:$AR$224,MATCH(A88,MarketCap2!$B$2:$B$224,0),MATCH(G88,MarketCap2!$E$1:$AR$1,0)) -> 2927563520 | K88: =LN(J88) -> 21.797436 | L88: =INDEX('PB2'!$D$2:$AQ$224,MATCH(A88,'PB2'!$B$2:$B$224,0),MATCH(G88,'PB2'!$D$1:$AQ$1,0)) -> 17.960733 | M88: =1/L88 -> 0.055677014 | N88: =INDEX('ROA2'!$D$2:$AQ$224,MATCH(A88,'ROA2'!$B$2:$B$224,0),MATCH(G88,'ROA2'!$D$1:$AQ$1,0)) -> 4.4959679 | O88: 14539 | P88: 0.076723713
A89: AC CN Equity | B89: =VLOOKUP(A89,Sheet3!L:L,1,FALSE) -> #N/A | C89: =VLOOKUP(A89,'ALL - prices'!B:C,2,FALSE) -> Air Canada | D89: =VLOOKUP(A89,'ALL - prices'!B:I,8,FALSE) -> Industrials | E89: 2016 | F89: Q4 | G89: =E89&"-"&F89 -> 2016-Q4 | H89: =INDEX('ALL - prices'!$J$3:$DY$219,MATCH('COMBINED DATA'!A89,'ALL - prices'!$B$3:$B$219,0),MATCH('COMBINED DATA'!G89,'ALL - prices'!$J$1:$DY$1,0)) -> 13.67 | I89: =STDEV(H90:H93) -> 6.220769 | J89: =INDEX(MarketCap2!$E$2:$AR$224,MATCH(A89,MarketCap2!$B$2:$B$224,0),MATCH(G89,MarketCap2!$E$1:$AR$1,0)) -> 3735870720 | K89: =LN(J89) -> 22.041247 | L89: =INDEX('PB2'!$D$2:$AQ$224,MATCH(A89,'PB2'!$B$2:$B$224,0),MATCH(G89,'PB2'!$D$1:$AQ$1,0)) -> 3.063838 | M89: =1/L89 -> 0.32638801 | N89: =INDEX('ROA2'!$D$2:$AQ$224,MATCH(A89,'ROA2'!$B$2:$B$224,0),MATCH(G89,'ROA2'!$D$1:$AQ$1,0)) -> 6.7958698 | O89: 14850 | P89: 0.021390747
A90: AC CN Equity | B90: =VLOOKUP(A90,Sheet3!L:L,1,FALSE) -> #N/A | C90: =VLOOKUP(A90,'ALL - prices'!B:C,2,FALSE) -> Air Canada | D90: =VLOOKUP(A90,'ALL - prices'!B:I,8,FALSE) -> Industrials | E90: 2017 | F90: Q1 | G90: =E90&"-"&F90 -> 2017-Q1 | H90: =INDEX('ALL - prices'!$J$3:$DY$219,MATCH('COMBINED DATA'!A90,'ALL - prices'!$B$3:$B$219,0),MATCH('COMBINED DATA'!G90,'ALL - prices'!$J$1:$DY$1,0)) -> 13.8 | I90: =STDEV(H91:H94) -> 4.4732939 | J90: =INDEX(MarketCap2!$E$2:$AR$224,MATCH(A90,MarketCap2!$B$2:$B$224,0),MATCH(G90,MarketCap2!$E$1:$AR$1,0)) -> 3760470784 | K90: =LN(J90) -> 22.04781 | L90: =INDEX('PB2'!$D$2:$AQ$224,MATCH(A90,'PB2'!$B$2:$B$224,0),MATCH(G90,'PB2'!$D$1:$AQ$1,0)) -> 4.072865 | M90: =1/L90 -> 0.24552741 | N90: =INDEX('ROA2'!$D$2:$AQ$224,MATCH(A90,'ROA2'!$B$2:$B$224,0),MATCH(G90,'ROA2'!$D$1:$AQ$1,0)) -> 6.2037458 | O90: 15114 | P90: 0.017777812
A91: AC CN Equity | B91: =VLOOKUP(A91,Sheet3!L:L,1,FALSE) -> #N/A | C91: =VLOOKUP(A91,'ALL - prices'!B:C,2,FALSE) -> Air Canada | D91: =VLOOKUP(A91,'ALL - prices'!B:I,8,FALSE) -> Industrials | E91: 2017 | F91: Q2 | G91: =E91&"-"&F91 -> 2017-Q2 | H91: =INDEX('ALL - prices'!$J$3:$DY$219,MATCH('COMBINED DATA'!A91,'ALL - prices'!$B$3:$B$219,0),MATCH('COMBINED DATA'!G91,'ALL - prices'!$J$1:$DY$1,0)) -> 17.38 | I91: =STDEV(H92:H95) -> 2.5496732 | J91: =INDEX(MarketCap2!$E$2:$AR$224,MATCH(A91,MarketCap2!$B$2:$B$224,0),MATCH(G91,MarketCap2!$E$1:$AR$1,0)) -> 4717142016 | K91: =LN(J91) -> 22.274469 | L91: =INDEX('PB2'!$D$2:$AQ$224,MATCH(A91,'PB2'!$B$2:$B$224,0),MATCH(G91,'PB2'!$D$1:$AQ$1,0)) -> 3.9436829 | M91: =1/L91 -> 0.25357008 | N91: =INDEX('ROA2'!$D$2:$AQ$224,MATCH(A91,'ROA2'!$B$2:$B$224,0),MATCH(G91,'ROA2'!$D$1:$AQ$1,0)) -> 5.1894979 | O91: 15864.001 | P91: 0.049622873
A92: AC CN Equity | B92: =VLOOKUP(A92,Sheet3!L:L,1,FALSE) -> #N/A | C92: =VLOOKUP(A92,'ALL - prices'!B:C,2,FALSE) -> Air Canada | D92: =VLOOKUP(A92,'ALL - prices'!B:I,8,FALSE) -> Industrials | E92: 2017 | F92: Q3 | G92: =E92&"-"&F92 -> 2017-Q3 | H92: =INDEX('ALL - prices'!$J$3:$DY$219,MATCH('COMBINED DATA'!A92,'ALL - prices'!$B$3:$B$219,0),MATCH('COMBINED DATA'!G92,'ALL - prices'!$J$1:$DY$1,0)) -> 26.24 | I92: =STDEV(H93:H96) -> 2.8382683 | J92: =INDEX(MarketCap2!$E$2:$AR$224,MATCH(A92,MarketCap2!$B$2:$B$224,0),MATCH(G92,MarketCap2!$E$1:$AR$1,0)) -> 7189917696 | K92: =LN(J92) -> 22.695946 | L92: =INDEX('PB2'!$D$2:$AQ$224,MATCH(A92,'PB2'!$B$2:$B$224,0),MATCH(G92,'PB2'!$D$1:$AQ$1,0)) -> 2.344523 | M92: =1/L92 -> 0.426526 | N92: =INDEX('ROA2'!$D$2:$AQ$224,MATCH(A92,'ROA2'!$B$2:$B$224,0),MATCH(G92,'ROA2'!$D$1:$AQ$1,0)) -> 5.6864438 | O92: 16658 | P92: 0.050050387
A93: AC CN Equity | B93: =VLOOKUP(A93,Sheet3!L:L,1,FALSE) -> #N/A | C93: =VLOOKUP(A93,'ALL - prices'!B:C,2,FALSE) -> Air Canada | D93: =VLOOKUP(A93,'ALL - prices'!B:I,8,FALSE) -> Industrials | E93: 2017 | F93: Q4 | G93: =E93&"-"&F93 -> 2017-Q4 | H93: =INDEX('ALL - prices'!$J$3:$DY$219,MATCH('COMBINED DATA'!A93,'ALL - prices'!$B$3:$B$219,0),MATCH('COMBINED DATA'!G93,'ALL - prices'!$J$1:$DY$1,0)) -> 25.88 | I93: =STDEV(H94:H97) -> 2.8432903 | J93: =INDEX(MarketCap2!$E$2:$AR$224,MATCH(A93,MarketCap2!$B$2:$B$224,0),MATCH(G93,MarketCap2!$E$1:$AR$1,0)) -> 7066720768 | K93: =LN(J93) -> 22.678662 | L93: =INDEX('PB2'!$D$2:$AQ$224,MATCH(A93,'PB2'!$B$2:$B$224,0),MATCH(G93,'PB2'!$D$1:$AQ$1,0)) -> 2.065232 | M93: =1/L93 -> 0.48420709 | N93: =INDEX('ROA2'!$D$2:$AQ$224,MATCH(A93,'ROA2'!$B$2:$B$224,0),MATCH(G93,'ROA2'!$D$1:$AQ$1,0)) -> 11.415822 | O93: 17421.001 | P93: 0.045803868
... A117: AC CN Equity | B117: =VLOOKUP(A117,Sheet3!L:L,1,FALSE) -> #N/A | C117: =VLOOKUP(A117,'ALL - prices'!B:C,2,FALSE) -> Air Canada | D117: =VLOOKUP(A117,'ALL - prices'!B:I,8,FALSE) -> Industrials | E117: 2023 | F117: Q4 | G117: =E117&"-"&F117 -> 2023-Q4 | H117: =INDEX('ALL - prices'!$J$3:$DY$219,MATCH('COMBINED DATA'!A117,'ALL - prices'!$B$3:$B$219,0),MATCH('COMBINED DATA'!G117,'ALL - prices'!$J$1:$DY$1,0)) -> 18.69 | I117: =STDEV(H118:H121) -> 2.5176312 | J117: =INDEX(MarketCap2!$E$2:$AR$224,MATCH(A117,MarketCap2!$B$2:$B$224,0),MATCH(G117,MarketCap2!$E$1:$AR$1,0)) -> 6699790848 | K117: =LN(J117) -> 22.625342 | L117: =INDEX('PB2'!$D$2:$AQ$224,MATCH(A117,'PB2'!$B$2:$B$224,0),MATCH(G117,'PB2'!$D$1:$AQ$1,0)) -> 8.4168234 | M117: =1/L117 -> 0.11880967 | N117: =INDEX('ROA2'!$D$2:$AQ$224,MATCH(A117,'ROA2'!$B$2:$B$224,0),MATCH(G117,'ROA2'!$D$1:$AQ$1,0)) -> 7.6029 | O117: 29696.999 | P117: -0.035279249
A118: AC CN Equity | B118: =VLOOKUP(A118,Sheet3!L:L,1,FALSE) -> #N/A | C118: =VLOOKUP(A118,'ALL - prices'!B:C,2,FALSE) -> Air Canada | D118: =VLOOKUP(A118,'ALL - prices'!B:I,8,FALSE) -> Industrials | E118: 2024 | F118: Q1 | G118: =E118&"-"&F118 -> 2024-Q1 | H118: =INDEX('ALL - prices'!$J$3:$DY$219,MATCH('COMBINED DATA'!A118,'ALL - prices'!$B$3:$B$219,0),MATCH('COMBINED DATA'!G118,'ALL - prices'!$J$1:$DY$1,0)) -> 19.61 | I118: N/A | J118: =INDEX(MarketCap2!$E$2:$AR$224,MATCH(A118,MarketCap2!$B$2:$B$224,0),MATCH(G118,MarketCap2!$E$1:$AR$1,0)) -> 7029621760 | K118: =LN(J118) -> 22.673399 | L118: =INDEX('PB2'!$D$2:$AQ$224,MATCH(A118,'PB2'!$B$2:$B$224,0),MATCH(G118,'PB2'!$D$1:$AQ$1,0)) -> 9.9712238 | M118: =1/L118 -> 0.10028859 | N118: =INDEX('ROA2'!$D$2:$AQ$224,MATCH(A118,'ROA2'!$B$2:$B$224,0),MATCH(G118,'ROA2'!$D$1:$AQ$1,0)) -> 7.62428 | O118: 30197 | P118: 0.016836744
A119: AC CN Equity | B119: =VLOOKUP(A119,Sheet3!L:L,1,FALSE) -> #N/A | C119: =VLOOKUP(A119,'ALL - prices'!B:C,2,FALSE) -> Air Canada | D119: =VLOOKUP(A119,'ALL - prices'!B:I,8,FALSE) -> Industrials | E119: 2024 | F119: Q2 | G119: =E119&"-"&F119 -> 2024-Q2 | H119: =INDEX('ALL - prices'!$J$3:$DY$219,MATCH('COMBINED DATA'!A119,'ALL - prices'!$B$3:$B$219,0),MATCH('COMBINED DATA'!G119,'ALL - prices'!$J$1:$DY$1,0)) -> 17.9 | I119: N/A | J119: =INDEX(MarketCap2!$E$2:$AR$224,MATCH(A119,MarketCap2!$B$2:$B$224,0),MATCH(G119,MarketCap2!$E$1:$AR$1,0)) -> 6417025024 | K119: =LN(J119) -> 22.58222 | L119: =INDEX('PB2'!$D$2:$AQ$224,MATCH(A119,'PB2'!$B$2:$B$224,0),MATCH(G119,'PB2'!$D$1:$AQ$1,0)) -> 5.5081758 | M119: =1/L119 -> 0.18154831 | N119: =INDEX('ROA2'!$D$2:$AQ$224,MATCH(A119,'ROA2'!$B$2:$B$224,0),MATCH(G119,'ROA2'!$D$1:$AQ$1,0)) -> 7.2802792 | O119: 29714 | P119: -0.015994977
A120: AC CN Equity | B120: =VLOOKUP(A120,Sheet3!L:L,1,FALSE) -> #N/A | C120: =VLOOKUP(A120,'ALL - prices'!B:C,2,FALSE) -> Air Canada | D120: =VLOOKUP(A120,'ALL - prices'!B:I,8,FALSE) -> Industrials | E120: 2024 | F120: Q3 | G120: =E120&"-"&F120 -> 2024-Q3 | H120: =INDEX('ALL - prices'!$J$3:$DY$219,MATCH('COMBINED DATA'!A120,'ALL - prices'!$B$3:$B$219,0),MATCH('COMBINED DATA'!G120,'ALL - prices'!$J$1:$DY$1,0)) -> 16.39 | I120: N/A | J120: =INDEX(MarketCap2!$E$2:$AR$224,MATCH(A120,MarketCap2!$B$2:$B$224,0),MATCH(G120,MarketCap2!$E$1:$AR$1,0)) -> 5875700224 | K120: =LN(J120) -> 22.494091 | L120: =INDEX('PB2'!$D$2:$AQ$224,MATCH(A120,'PB2'!$B$2:$B$224,0),MATCH(G120,'PB2'!$D$1:$AQ$1,0)) -> 1.900291 | M120: =1/L120 -> 0.5262352 | N120: =INDEX('ROA2'!$D$2:$AQ$224,MATCH(A120,'ROA2'!$B$2:$B$224,0),MATCH(G120,'ROA2'!$D$1:$AQ$1,0)) -> 5.7680349 | O120: 30347 | P120: 0.021303087
A121: AC CN Equity | B121: =VLOOKUP(A121,Sheet3!L:L,1,FALSE) -> #N/A | C121: =VLOOKUP(A121,'ALL - prices'!B:C,2,FALSE) -> Air Canada | D121: =VLOOKUP(A121,'ALL - prices'!B:I,8,FALSE) -> Industrials | E121: 2024 | F121: Q4 | G121: =E121&"-"&F121 -> 2024-Q4 | H121: =INDEX('ALL - prices'!$J$3:$DY$219,MATCH('COMBINED DATA'!A121,'ALL - prices'!$B$3:$B$219,0),MATCH('COMBINED DATA'!G121,'ALL - prices'!$J$1:$DY$1,0)) -> 22.26 | I121: N/A | J121: =INDEX(MarketCap2!$E$2:$AR$224,MATCH(A121,MarketCap2!$B$2:$B$224,0),MATCH(G121,MarketCap2!$E$1:$AR$1,0)) -> 7779318784 | K121: =LN(J121) -> 22.774735 | L121: =INDEX('PB2'!$D$2:$AQ$224,MATCH(A121,'PB2'!$B$2:$B$224,0),MATCH(G121,'PB2'!$D$1:$AQ$1,0)) -> 2.5808713 | M121: =1/L121 -> 0.38746605 | N121: =INDEX('ROA2'!$D$2:$AQ$224,MATCH(A121,'ROA2'!$B$2:$B$224,0),MATCH(G121,'ROA2'!$D$1:$AQ$1,0)) -> 8.3277502 | O121: 31495.999 | P121: 0.037862052
A122: ACO/X CN Equity | B122: =VLOOKUP(A122,Sheet3!L:L,1,FALSE) -> #N/A | C122: =VLOOKUP(A122,'ALL - prices'!B:C,2,FALSE) -> Atco Ltd/Canada | D122: =VLOOKUP(A122,'ALL - prices'!B:I,8,FALSE) -> Utilities | E122: 2015 | F122: Q1 | G122: =E122&"-"&F122 -> 2015-Q1 | H122: =INDEX('ALL - prices'!$J$3:$DY$219,MATCH('COMBINED DATA'!A122,'ALL - prices'!$B$3:$B$219,0),MATCH('COMBINED DATA'!G122,'ALL - prices'!$J$1:$DY$1,0)) -> 30.0313 | I122: =STDEV(H123:H126) -> 1.1905714 | J122: =INDEX(MarketCap2!$E$2:$AR$224,MATCH(A122,MarketCap2!$B$2:$B$224,0),MATCH(G122,MarketCap2!$E$1:$AR$1,0)) -> 5197527552 | K122: =LN(J122) -> 22.371449 | L122: =INDEX('PB2'!$D$2:$AQ$224,MATCH(A122,'PB2'!$B$2:$B$224,0),MATCH(G122,'PB2'!$D$1:$AQ$1,0)) -> 1.596087 | M122: =1/L122 -> 0.62653227 | N122: =INDEX('ROA2'!$D$2:$AQ$224,MATCH(A122,'ROA2'!$B$2:$B$224,0),MATCH(G122,'ROA2'!$D$1:$AQ$1,0)) -> 2.492656 | O122: 17689 | P122: 0.010107381
A123: ACO/X CN Equity | B123: =VLOOKUP(A123,Sheet3!L:L,1,FALSE) -> #N/A | C123: =VLOOKUP(A123,'ALL - prices'!B:C,2,FALSE) -> Atco Ltd/Canada | D123: =VLOOKUP(A123,'ALL - prices'!B:I,8,FALSE) -> Utilities | E123: 2015 | F123: Q2 | G123: =E123&"-"&F123 -> 2015-Q2 | H123: =INDEX('ALL - prices'!$J$3:$DY$219,MATCH('COMBINED DATA'!A123,'ALL - prices'!$B$3:$B$219,0),MATCH('COMBINED DATA'!G123,'ALL - prices'!$J$1:$DY$1,0)) -> 26.4378 | I123: =STDEV(H124:H127) -> 2.9162521 | J123: =INDEX(MarketCap2!$E$2:$AR$224,MATCH(A123,MarketCap2!$B$2:$B$224,0),MATCH(G123,MarketCap2!$E$1:$AR$1,0)) -> 4546976768 | K123: =LN(J123) -> 22.237728 | L123: =INDEX('PB2'!$D$2:$AQ$224,MATCH(A123,'PB2'!$B$2:$B$224,0),MATCH(G123,'PB2'!$D$1:$AQ$1,0)) -> 1.396966 | M123: =1/L123 -> 0.71583705 | N123: =INDEX('ROA2'!$D$2:$AQ$224,MATCH(A123,'ROA2'!$B$2:$B$224,0),MATCH(G123,'ROA2'!$D$1:$AQ$1,0)) -> 2.2500651 | O123: 17955 | P123: 0.015037616
A124: ACO/X CN Equity | B124: =VLOOKUP(A124,Sheet3!L:L,1,FALSE) -> #N/A | C124: =VLOOKUP(A124,'ALL - prices'!B:C,2,FALSE) -> Atco Ltd/Canada | D124: =VLOOKUP(A124,'ALL - prices'!B:I,8,FALSE) -> Utilities | E124: 2015 | F124: Q3 | G124: =E124&"-"&F124 -> 2015-Q3 | H124: =INDEX('ALL - prices'!$J$3:$DY$219,MATCH('COMBINED DATA'!A124,'ALL - prices'!$B$3:$B$219,0),MATCH('COMBINED DATA'!G124,'ALL - prices'!$J$1:$DY$1,0)) -> 26.4174 | I124: =STDEV(H125:H128) -> 3.7587453 | J124: =INDEX(MarketCap2!$E$2:$AR$224,MATCH(A124,MarketCap2!$B$2:$B$224,0),MATCH(G124,MarketCap2!$E$1:$AR$1,0)) -> 4514950144 | K124: =LN(J124) -> 22.23066 | L124: =INDEX('PB2'!$D$2:$AQ$224,MATCH(A124,'PB2'!$B$2:$B$224,0),MATCH(G124,'PB2'!$D$1:$AQ$1,0)) -> 1.365258 | M124: =1/L124 -> 0.7324623 | N124: =INDEX('ROA2'!$D$2:$AQ$224,MATCH(A124,'ROA2'!$B$2:$B$224,0),MATCH(G124,'ROA2'!$D$1:$AQ$1,0)) -> 1.8853329 | O124: 18148 | P124: 0.010749063
A125: ACO/X CN Equity | B125: =VLOOKUP(A125,Sheet3!L:L,1,FALSE) -> #N/A | C125: =VLOOKUP(A125,'ALL - prices'!B:C,2,FALSE) -> Atco Ltd/Canada | D125: =VLOOKUP(A125,'ALL - prices'!B:I,8,FALSE) -> Utilities | E125: 2015 | F125: Q4 | G125: =E125&"-"&F125 -> 2015-Q4 | H125: =INDEX('ALL - prices'!$J$3:$DY$219,MATCH('COMBINED DATA'!A125,'ALL - prices'!$B$3:$B$219,0),MATCH('COMBINED DATA'!G125,'ALL - prices'!$J$1:$DY$1,0)) -> 24.2275 | I125: =STDEV(H126:H129) -> 2.3936508 | J125: =INDEX(MarketCap2!$E$2:$AR$224,MATCH(A125,MarketCap2!$B$2:$B$224,0),MATCH(G125,MarketCap2!$E$1:$AR$1,0)) -> 4107735808 | K125: =LN(J125) -> 22.136138 | L125: =INDEX('PB2'!$D$2:$AQ$224,MATCH(A125,'PB2'!$B$2:$B$224,0),MATCH(G125,'PB2'!$D$1:$AQ$1,0)) -> 1.2235889 | M125: =1/L125 -> 0.81726793 | N125: =INDEX('ROA2'!$D$2:$AQ$224,MATCH(A125,'ROA2'!$B$2:$B$224,0),MATCH(G125,'ROA2'!$D$1:$AQ$1,0)) -> 1.3766789 | O125: 18662.001 | P125: 0.02832273
A126: ACO/X CN Equity | B126: =VLOOKUP(A126,Sheet3!L:L,1,FALSE) -> #N/A | C126: =VLOOKUP(A126,'ALL - prices'!B:C,2,FALSE) -> Atco Ltd/Canada | D126: =VLOOKUP(A126,'ALL - prices'!B:I,8,FALSE) -> Utilities | E126: 2016 | F126: Q1 | G126: =E126&"-"&F126 -> 2016-Q1 | H126: =INDEX('ALL - prices'!$J$3:$DY$219,MATCH('COMBINED DATA'!A126,'ALL - prices'!$B$3:$B$219,0),MATCH('COMBINED DATA'!G126,'ALL - prices'!$J$1:$DY$1,0)) -> 26.8634 | I126: =STDEV(H127:H130) -> 2.4394693 | J126: =INDEX(MarketCap2!$E$2:$AR$224,MATCH(A126,MarketCap2!$B$2:$B$224,0),MATCH(G126,MarketCap2!$E$1:$AR$1,0)) -> 4518471680 | K126: =LN(J126) -> 22.23144 | L126: =INDEX('PB2'!$D$2:$AQ$224,MATCH(A126,'PB2'!$B$2:$B$224,0),MATCH(G126,'PB2'!$D$1:$AQ$1,0)) -> 1.3414561 | M126: =1/L126 -> 0.74545863 | N126: =INDEX('ROA2'!$D$2:$AQ$224,MATCH(A126,'ROA2'!$B$2:$B$224,0),MATCH(G126,'ROA2'!$D$1:$AQ$1,0)) -> 0.83823198 | O126: 19055 | P126: 0.021058777
A127: ACO/X CN Equity | B127: =VLOOKUP(A127,Sheet3!L:L,1,FALSE) -> #N/A | C127: =VLOOKUP(A127,'ALL - prices'!B:C,2,FALSE) -> Atco Ltd/Canada | D127: =VLOOKUP(A127,'ALL - prices'!B:I,8,FALSE) -> Utilities | E127: 2016 | F127: Q2 | G127: =E127&"-"&F127 -> 2016-Q2 | H127: =INDEX('ALL - prices'!$J$3:$DY$219,MATCH('COMBINED DATA'!A127,'ALL - prices'!$B$3:$B$219,0),MATCH('COMBINED DATA'!G127,'ALL - prices'!$J$1:$DY$1,0)) -> 31.1943 | I127: =STDEV(H128:H131) -> 2.5665167 | J127: =INDEX(MarketCap2!$E$2:$AR$224,MATCH(A127,MarketCap2!$B$2:$B$224,0),MATCH(G127,MarketCap2!$E$1:$AR$1,0)) -> 5192025600 | K127: =LN(J127) -> 22.37039 | L127: =INDEX('PB2'!$D$2:$AQ$224,MATCH(A127,'PB2'!$B$2:$B$224,0),MATCH(G127,'PB2'!$D$1:$AQ$1,0)) -> 1.5478669 | M127: =1/L127 -> 0.64605036 | N127: =INDEX('ROA2'!$D$2:$AQ$224,MATCH(A127,'ROA2'!$B$2:$B$224,0),MATCH(G127,'ROA2'!$D$1:$AQ$1,0)) -> 0.91208398 | O127: 19103.001 | P127: 0.0025190777
A128: ACO/X CN Equity | B128: =VLOOKUP(A128,Sheet3!L:L,1,FALSE) -> #N/A | C128: =VLOOKUP(A128,'ALL - prices'!B:C,2,FALSE) -> Atco Ltd/Canada | D128: =VLOOKUP(A128,'ALL - prices'!B:I,8,FALSE) -> Utilities | E128: 2016 | F128: Q3 | G128: =E128&"-"&F128 -> 2016-Q3 | H128: =INDEX('ALL - prices'!$J$3:$DY$219,MATCH('COMBINED DATA'!A128,'ALL - prices'!$B$3:$B$219,0),MATCH('COMBINED DATA'!G128,'ALL - prices'!$J$1:$DY$1,0)) -> 32.2778 | I128: =STDEV(H129:H132) -> 2.5054701 | J128: =INDEX(MarketCap2!$E$2:$AR$224,MATCH(A128,MarketCap2!$B$2:$B$224,0),MATCH(G128,MarketCap2!$E$1:$AR$1,0)) -> 5346150400 | K128: =LN(J128) -> 22.399643 | L128: =INDEX('PB2'!$D$2:$AQ$224,MATCH(A128,'PB2'!$B$2:$B$224,0),MATCH(G128,'PB2'!$D$1:$AQ$1,0)) -> 1.574877 | M128: =1/L128 -> 0.63497021 | N128: =INDEX('ROA2'!$D$2:$AQ$224,MATCH(A128,'ROA2'!$B$2:$B$224,0),MATCH(G128,'ROA2'!$D$1:$AQ$1,0)) -> 1.182707 | O128: 19392.999 | P128: 0.015180801
A129: ACO/X CN Equity | B129: =VLOOKUP(A129,Sheet3!L:L,1,FALSE) -> #N/A | C129: =VLOOKUP(A129,'ALL - prices'!B:C,2,FALSE) -> Atco Ltd/Canada | D129: =VLOOKUP(A129,'ALL - prices'!B:I,8,FALSE) -> Utilities | E129: 2016 | F129: Q4 | G129: =E129&"-"&F129 -> 2016-Q4 | H129: =INDEX('ALL - prices'!$J$3:$DY$219,MATCH('COMBINED DATA'!A129,'ALL - prices'!$B$3:$B$219,0),MATCH('COMBINED DATA'!G129,'ALL - prices'!$J$1:$DY$1,0)) -> 31.1272 | I129: =STDEV(H130:H133) -> 2.1138513 | J129: =INDEX(MarketCap2!$E$2:$AR$224,MATCH(A129,MarketCap2!$B$2:$B$224,0),MATCH(G129,MarketCap2!$E$1:$AR$1,0)) -> 5122024960 | K129: =LN(J129) -> 22.356816 | L129: =INDEX('PB2'!$D$2:$AQ$224,MATCH(A129,'PB2'!$B$2:$B$224,0),MATCH(G129,'PB2'!$D$1:$AQ$1,0)) -> 1.443997 | M129: =1/L129 -> 0.6925222 | N129: =INDEX('ROA2'!$D$2:$AQ$224,MATCH(A129,'ROA2'!$B$2:$B$224,0),MATCH(G129,'ROA2'!$D$1:$AQ$1,0)) -> 1.25144 | O129: 19534 | P129: 0.0072707012
A130: ACO/X CN Equity | B130: =VLOOKUP(A130,Sheet3!L:L,1,FALSE) -> #N/A | C130: =VLOOKUP(A130,'ALL - prices'!B:C,2,FALSE) -> Atco Ltd/Canada | D130: =VLOOKUP(A130,'ALL - prices'!B:I,8,FALSE) -> Utilities | E130: 2017 | F130: Q1 | G130: =E130&"-"&F130 -> 2017-Q1 | H130: =INDEX('ALL - prices'!$J$3:$DY$219,MATCH('COMBINED DATA'!A130,'ALL - prices'!$B$3:$B$219,0),MATCH('COMBINED DATA'!G130,'ALL - prices'!$J$1:$DY$1,0)) -> 36.2967 | I130: =STDEV(H131:H134) -> 2.4262514 | J130: =INDEX(MarketCap2!$E$2:$AR$224,MATCH(A130,MarketCap2!$B$2:$B$224,0),MATCH(G130,MarketCap2!$E$1:$AR$1,0)) -> 5930008576 | K130: =LN(J130) -> 22.503291 | L130: =INDEX('PB2'!$D$2:$AQ$224,MATCH(A130,'PB2'!$B$2:$B$224,0),MATCH(G130,'PB2'!$D$1:$AQ$1,0)) -> 1.646889 | M130: =1/L130 -> 0.60720547 | N130: =INDEX('ROA2'!$D$2:$AQ$224,MATCH(A130,'ROA2'!$B$2:$B$224,0),MATCH(G130,'ROA2'!$D$1:$AQ$1,0)) -> 1.753526 | O130: 19723.999 | P130: 0.0097265846
A131: ACO/X CN Equity | B131: =VLOOKUP(A131,Sheet3!L:L,1,FALSE) -> #N/A | C131: =VLOOKUP(A131,'ALL - prices'!B:C,2,FALSE) -> Atco Ltd/Canada | D131: =VLOOKUP(A131,'ALL - prices'!B:I,8,FALSE) -> Utilities | E131: 2017 | F131: Q2 | G131: =E131&"-"&F131 -> 2017-Q2 | H131: =INDEX('ALL - prices'!$J$3:$DY$219,MATCH('COMBINED DATA'!A131,'ALL - prices'!$B$3:$B$219,0),MATCH('COMBINED DATA'!G131,'ALL - prices'!$J$1:$DY$1,0)) -> 35.8231 | I131: =STDEV(H132:H135) -> 1.5369104 | J131: =INDEX(MarketCap2!$E$2:$AR$224,MATCH(A131,MarketCap2!$B$2:$B$224,0),MATCH(G131,MarketCap2!$E$1:$AR$1,0)) -> 5815187968 | K131: =LN(J131) -> 22.483739 | L131: =INDEX('PB2'!$D$2:$AQ$224,MATCH(A131,'PB2'!$B$2:$B$224,0),MATCH(G131,'PB2'!$D$1:$AQ$1,0)) -> 1.621366 | M131: =1/L131 -> 0.61676388 | N131: =INDEX('ROA2'!$D$2:$AQ$224,MATCH(A131,'ROA2'!$B$2:$B$224,0),MATCH(G131,'ROA2'!$D$1:$AQ$1,0)) -> 1.691797 | O131: 20027.001 | P131: 0.015362077
A132: ACO/X CN Equity | B132: =VLOOKUP(A132,Sheet3!L:L,1,FALSE) -> #N/A | C132: =VLOOKUP(A132,'ALL - prices'!B:C,2,FALSE) -> Atco Ltd/Canada | D132: =VLOOKUP(A132,'ALL - prices'!B:I,8,FALSE) -> Utilities | E132: 2017 | F132: Q3 | G132: =E132&"-"&F132 -> 2017-Q3 | H132: =INDEX('ALL - prices'!$J$3:$DY$219,MATCH('COMBINED DATA'!A132,'ALL - prices'!$B$3:$B$219,0),MATCH('COMBINED DATA'!G132,'ALL - prices'!$J$1:$DY$1,0)) -> 32.5903 | I132: =STDEV(H133:H136) -> 1.8124175 | J132: =INDEX(MarketCap2!$E$2:$AR$224,MATCH(A132,MarketCap2!$B$2:$B$224,0),MATCH(G132,MarketCap2!$E$1:$AR$1,0)) -> 5252987904 | K132: =LN(J132) -> 22.382063 | L132: =INDEX('PB2'!$D$2:$AQ$224,MATCH(A132,'PB2'!$B$2:$B$224,0),MATCH(G132,'PB2'!$D$1:$AQ$1,0)) -> 1.452633 | M132: =1/L132 -> 0.68840511 | N132: =INDEX('ROA2'!$D$2:$AQ$224,MATCH(A132,'ROA2'!$B$2:$B$224,0),MATCH(G132,'ROA2'!$D$1:$AQ$1,0)) -> 1.579267 | O132: 20118.999 | P132: 0.0045937087
A133: ACO/X CN Equity | B133: =VLOOKUP(A133,Sheet3!L:L,1,FALSE) -> #N/A | C133: =VLOOKUP(A133,'ALL - prices'!B:C,2,FALSE) -> Atco Ltd/Canada | D133: =VLOOKUP(A133,'ALL - prices'!B:I,8,FALSE) -> Utilities | E133: 2017 | F133: Q4 | G133: =E133&"-"&F133 -> 2017-Q4 | H133: =INDEX('ALL - prices'!$J$3:$DY$219,MATCH('COMBINED DATA'!A133,'ALL - prices'!$B$3:$B$219,0),MATCH('COMBINED DATA'!G133,'ALL - prices'!$J$1:$DY$1,0)) -> 32.2532 | I133: =STDEV(H134:H137) -> 0.94303776 | J133: =INDEX(MarketCap2!$E$2:$AR$224,MATCH(A133,MarketCap2!$B$2:$B$224,0),MATCH(G133,MarketCap2!$E$1:$AR$1,0)) -> 5159636992 | K133: =LN(J133) -> 22.364132 | L133: =INDEX('PB2'!$D$2:$AQ$224,MATCH(A133,'PB2'!$B$2:$B$224,0),MATCH(G133,'PB2'!$D$1:$AQ$1,0)) -> 1.37555 | M133: =1/L133 -> 0.72698192 | N133: =INDEX('ROA2'!$D$2:$AQ$224,MATCH(A133,'ROA2'!$B$2:$B$224,0),MATCH(G133,'ROA2'!$D$1:$AQ$1,0)) -> 1.430993 | O133: 20578.001 | P133: 0.022814349
... A157: ACO/X CN Equity | B157: =VLOOKUP(A157,Sheet3!L:L,1,FALSE) -> #N/A | C157: =VLOOKUP(A157,'ALL - prices'!B:C,2,FALSE) -> Atco Ltd/Canada | D157: =VLOOKUP(A157,'ALL - prices'!B:I,8,FALSE) -> Utilities | E157: 2023 | F157: Q4 | G157: =E157&"-"&F157 -> 2023-Q4 | H157: =INDEX('ALL - prices'!$J$3:$DY$219,MATCH('COMBINED DATA'!A157,'ALL - prices'!$B$3:$B$219,0),MATCH('COMBINED DATA'!G157,'ALL - prices'!$J$1:$DY$1,0)) -> 35.4947 | I157: =STDEV(H158:H161) -> 5.6830271 | J157: =INDEX(MarketCap2!$E$2:$AR$224,MATCH(A157,MarketCap2!$B$2:$B$224,0),MATCH(G157,MarketCap2!$E$1:$AR$1,0)) -> 4357063680 | K157: =LN(J157) -> 22.195064 | L157: =INDEX('PB2'!$D$2:$AQ$224,MATCH(A157,'PB2'!$B$2:$B$224,0),MATCH(G157,'PB2'!$D$1:$AQ$1,0)) -> 0.98059797 | M157: =1/L157 -> 1.0197859 | N157: =INDEX('ROA2'!$D$2:$AQ$224,MATCH(A157,'ROA2'!$B$2:$B$224,0),MATCH(G157,'ROA2'!$D$1:$AQ$1,0)) -> 1.715716 | O157: 25094.001 | P157: 0.012303862
A158: ACO/X CN Equity | B158: =VLOOKUP(A158,Sheet3!L:L,1,FALSE) -> #N/A | C158: =VLOOKUP(A158,'ALL - prices'!B:C,2,FALSE) -> Atco Ltd/Canada | D158: =VLOOKUP(A158,'ALL - prices'!B:I,8,FALSE) -> Utilities | E158: 2024 | F158: Q1 | G158: =E158&"-"&F158 -> 2024-Q1 | H158: =INDEX('ALL - prices'!$J$3:$DY$219,MATCH('COMBINED DATA'!A158,'ALL - prices'!$B$3:$B$219,0),MATCH('COMBINED DATA'!G158,'ALL - prices'!$J$1:$DY$1,0)) -> 35.0713 | I158: N/A | J158: =INDEX(MarketCap2!$E$2:$AR$224,MATCH(A158,MarketCap2!$B$2:$B$224,0),MATCH(G158,MarketCap2!$E$1:$AR$1,0)) -> 4251751936 | K158: =LN(J158) -> 22.170597 | L158: =INDEX('PB2'!$D$2:$AQ$224,MATCH(A158,'PB2'!$B$2:$B$224,0),MATCH(G158,'PB2'!$D$1:$AQ$1,0)) -> 0.938223 | M158: =1/L158 -> 1.0658447 | N158: =INDEX('ROA2'!$D$2:$AQ$224,MATCH(A158,'ROA2'!$B$2:$B$224,0),MATCH(G158,'ROA2'!$D$1:$AQ$1,0)) -> 1.7455601 | O158: 25358 | P158: 0.010520422
A159: ACO/X CN Equity | B159: =VLOOKUP(A159,Sheet3!L:L,1,FALSE) -> #N/A | C159: =VLOOKUP(A159,'ALL - prices'!B:C,2,FALSE) -> Atco Ltd/Canada | D159: =VLOOKUP(A159,'ALL - prices'!B:I,8,FALSE) -> Utilities | E159: 2024 | F159: Q2 | G159: =E159&"-"&F159 -> 2024-Q2 | H159: =INDEX('ALL - prices'!$J$3:$DY$219,MATCH('COMBINED DATA'!A159,'ALL - prices'!$B$3:$B$219,0),MATCH('COMBINED DATA'!G159,'ALL - prices'!$J$1:$DY$1,0)) -> 36.6957 | I159: N/A | J159: =INDEX(MarketCap2!$E$2:$AR$224,MATCH(A159,MarketCap2!$B$2:$B$224,0),MATCH(G159,MarketCap2!$E$1:$AR$1,0)) -> 4408354816 | K159: =LN(J159) -> 22.206767 | L159: =INDEX('PB2'!$D$2:$AQ$224,MATCH(A159,'PB2'!$B$2:$B$224,0),MATCH(G159,'PB2'!$D$1:$AQ$1,0)) -> 0.96957201 | M159: =1/L159 -> 1.0313829 | N159: =INDEX('ROA2'!$D$2:$AQ$224,MATCH(A159,'ROA2'!$B$2:$B$224,0),MATCH(G159,'ROA2'!$D$1:$AQ$1,0)) -> 1.634694 | O159: 25347 | P159: -0.00043378058
A160: ACO/X CN Equity | B160: =VLOOKUP(A160,Sheet3!L:L,1,FALSE) -> #N/A | C160: =VLOOKUP(A160,'ALL - prices'!B:C,2,FALSE) -> Atco Ltd/Canada | D160: =VLOOKUP(A160,'ALL - prices'!B:I,8,FALSE) -> Utilities | E160: 2024 | F160: Q3 | G160: =E160&"-"&F160 -> 2024-Q3 | H160: =INDEX('ALL - prices'!$J$3:$DY$219,MATCH('COMBINED DATA'!A160,'ALL - prices'!$B$3:$B$219,0),MATCH('COMBINED DATA'!G160,'ALL - prices'!$J$1:$DY$1,0)) -> 45.5895 | I160: N/A | J160: =INDEX(MarketCap2!$E$2:$AR$224,MATCH(A160,MarketCap2!$B$2:$B$224,0),MATCH(G160,MarketCap2!$E$1:$AR$1,0)) -> 5438578688 | K160: =LN(J160) -> 22.416784 | L160: =INDEX('PB2'!$D$2:$AQ$224,MATCH(A160,'PB2'!$B$2:$B$224,0),MATCH(G160,'PB2'!$D$1:$AQ$1,0)) -> 1.1949821 | M160: =1/L160 -> 0.83683265 | N160: =INDEX('ROA2'!$D$2:$AQ$224,MATCH(A160,'ROA2'!$B$2:$B$224,0),MATCH(G160,'ROA2'!$D$1:$AQ$1,0)) -> 1.5306931 | O160: 25515 | P160: 0.006627983
A161: ACO/X CN Equity | B161: =VLOOKUP(A161,Sheet3!L:L,1,FALSE) -> #N/A | C161: =VLOOKUP(A161,'ALL - prices'!B:C,2,FALSE) -> Atco Ltd/Canada | D161: =VLOOKUP(A161,'ALL - prices'!B:I,8,FALSE) -> Utilities | E161: 2024 | F161: Q4 | G161: =E161&"-"&F161 -> 2024-Q4 | H161: =INDEX('ALL - prices'!$J$3:$DY$219,MATCH('COMBINED DATA'!A161,'ALL - prices'!$B$3:$B$219,0),MATCH('COMBINED DATA'!G161,'ALL - prices'!$J$1:$DY$1,0)) -> 45.7286 | I161: N/A | J161: =INDEX(MarketCap2!$E$2:$AR$224,MATCH(A161,MarketCap2!$B$2:$B$224,0),MATCH(G161,MarketCap2!$E$1:$AR$1,0)) -> 5356498432 | K161: =LN(J161) -> 22.401576 | L161: =INDEX('PB2'!$D$2:$AQ$224,MATCH(A161,'PB2'!$B$2:$B$224,0),MATCH(G161,'PB2'!$D$1:$AQ$1,0)) -> 1.1869991 | M161: =1/L161 -> 0.84246063 | N161: =INDEX('ROA2'!$D$2:$AQ$224,MATCH(A161,'ROA2'!$B$2:$B$224,0),MATCH(G161,'ROA2'!$D$1:$AQ$1,0)) -> 1.513315 | O161: 26052 | P161: 0.021046441
A162: AEM CN Equity | B162: =VLOOKUP(A162,Sheet3!L:L,1,FALSE) -> #N/A | C162: =VLOOKUP(A162,'ALL - prices'!B:C,2,FALSE) -> Agnico Eagle Mines Ltd | D162: =VLOOKUP(A162,'ALL - prices'!B:I,8,FALSE) -> Materials | E162: 2015 | F162: Q1 | G162: =E162&"-"&F162 -> 2015-Q1 | H162: =INDEX('ALL - prices'!$J$3:$DY$219,MATCH('COMBINED DATA'!A162,'ALL - prices'!$B$3:$B$219,0),MATCH('COMBINED DATA'!G162,'ALL - prices'!$J$1:$DY$1,0)) -> 29.2018 | I162: =STDEV(H163:H166) -> 5.0867011 | J162: =INDEX(MarketCap2!$E$2:$AR$224,MATCH(A162,MarketCap2!$B$2:$B$224,0),MATCH(G162,MarketCap2!$E$1:$AR$1,0)) -> 7615286784 | K162: =LN(J162) -> 22.753423 | L162: =INDEX('PB2'!$D$2:$AQ$224,MATCH(A162,'PB2'!$B$2:$B$224,0),MATCH(G162,'PB2'!$D$1:$AQ$1,0)) -> 1.4585429 | M162: =1/L162 -> 0.68561574 | N162: =INDEX('ROA2'!$D$2:$AQ$224,MATCH(A162,'ROA2'!$B$2:$B$224,0),MATCH(G162,'ROA2'!$D$1:$AQ$1,0)) -> 1.662555 | O162: 6809.2549 | P162: 0.020133078
A163: AEM CN Equity | B163: =VLOOKUP(A163,Sheet3!L:L,1,FALSE) -> #N/A | C163: =VLOOKUP(A163,'ALL - prices'!B:C,2,FALSE) -> Agnico Eagle Mines Ltd | D163: =VLOOKUP(A163,'ALL - prices'!B:I,8,FALSE) -> Materials | E163: 2015 | F163: Q2 | G163: =E163&"-"&F163 -> 2015-Q2 | H163: =INDEX('ALL - prices'!$J$3:$DY$219,MATCH('COMBINED DATA'!A163,'ALL - prices'!$B$3:$B$219,0),MATCH('COMBINED DATA'!G163,'ALL - prices'!$J$1:$DY$1,0)) -> 29.4344 | I163: =STDEV(H164:H167) -> 13.567619 | J163: =INDEX(MarketCap2!$E$2:$AR$224,MATCH(A163,MarketCap2!$B$2:$B$224,0),MATCH(G163,MarketCap2!$E$1:$AR$1,0)) -> 7666540544 | K163: =LN(J163) -> 22.760131 | L163: =INDEX('PB2'!$D$2:$AQ$224,MATCH(A163,'PB2'!$B$2:$B$224,0),MATCH(G163,'PB2'!$D$1:$AQ$1,0)) -> 1.482096 | M163: =1/L163 -> 0.67472015 | N163: =INDEX('ROA2'!$D$2:$AQ$224,MATCH(A163,'ROA2'!$B$2:$B$224,0),MATCH(G163,'ROA2'!$D$1:$AQ$1,0)) -> 0.24770799 | O163: 6767.125 | P163: -0.0061871556
A164: AEM CN Equity | B164: =VLOOKUP(A164,Sheet3!L:L,1,FALSE) -> #N/A | C164: =VLOOKUP(A164,'ALL - prices'!B:C,2,FALSE) -> Agnico Eagle Mines Ltd | D164: =VLOOKUP(A164,'ALL - prices'!B:I,8,FALSE) -> Materials | E164: 2015 | F164: Q3 | G164: =E164&"-"&F164 -> 2015-Q3 | H164: =INDEX('ALL - prices'!$J$3:$DY$219,MATCH('COMBINED DATA'!A164,'ALL - prices'!$B$3:$B$219,0),MATCH('COMBINED DATA'!G164,'ALL - prices'!$J$1:$DY$1,0)) -> 28.1766 | I164: =STDEV(H165:H168) -> 14.315902 | J164: =INDEX(MarketCap2!$E$2:$AR$224,MATCH(A164,MarketCap2!$B$2:$B$224,0),MATCH(G164,MarketCap2!$E$1:$AR$1,0)) -> 7354202112 | K164: =LN(J164) -> 22.718538 | L164: =INDEX('PB2'!$D$2:$AQ$224,MATCH(A164,'PB2'!$B$2:$B$224,0),MATCH(G164,'PB2'!$D$1:$AQ$1,0)) -> 1.321147 | M164: =1/L164 -> 0.75691806 | N164: =INDEX('ROA2'!$D$2:$AQ$224,MATCH(A164,'ROA2'!$B$2:$B$224,0),MATCH(G164,'ROA2'!$D$1:$AQ$1,0)) -> 0.037048001 | O164: 6749.8148 | P164: -0.0025579856
A165: AEM CN Equity | B165: =VLOOKUP(A165,Sheet3!L:L,1,FALSE) -> #N/A | C165: =VLOOKUP(A165,'ALL - prices'!B:C,2,FALSE) -> Agnico Eagle Mines Ltd | D165: =VLOOKUP(A165,'ALL - prices'!B:I,8,FALSE) -> Materials | E165: 2015 | F165: Q4 | G165: =E165&"-"&F165 -> 2015-Q4 | H165: =INDEX('ALL - prices'!$J$3:$DY$219,MATCH('COMBINED DATA'!A165,'ALL - prices'!$B$3:$B$219,0),MATCH('COMBINED DATA'!G165,'ALL - prices'!$J$1:$DY$1,0)) -> 30.3825 | I165: =STDEV(H166:H169) -> 9.5039459 | J165: =INDEX(MarketCap2!$E$2:$AR$224,MATCH(A165,MarketCap2!$B$2:$B$224,0),MATCH(G165,MarketCap2!$E$1:$AR$1,0)) -> 7916745216 | K165: =LN(J165) -> 22.792246 | L165: =INDEX('PB2'!$D$2:$AQ$224,MATCH(A165,'PB2'!$B$2:$B$224,0),MATCH(G165,'PB2'!$D$1:$AQ$1,0)) -> 1.38241 | M165: =1/L165 -> 0.72337437 | N165: =INDEX('ROA2'!$D$2:$AQ$224,MATCH(A165,'ROA2'!$B$2:$B$224,0),MATCH(G165,'ROA2'!$D$1:$AQ$1,0)) -> 0.27947101 | O165: 6805.6079 | P165: 0.008265879
A166: AEM CN Equity | B166: =VLOOKUP(A166,Sheet3!L:L,1,FALSE) -> #N/A | C166: =VLOOKUP(A166,'ALL - prices'!B:C,2,FALSE) -> Agnico Eagle Mines Ltd | D166: =VLOOKUP(A166,'ALL - prices'!B:I,8,FALSE) -> Materials | E166: 2016 | F166: Q1 | G166: =E166&"-"&F166 -> 2016-Q1 | H166: =INDEX('ALL - prices'!$J$3:$DY$219,MATCH('COMBINED DATA'!A166,'ALL - prices'!$B$3:$B$219,0),MATCH('COMBINED DATA'!G166,'ALL - prices'!$J$1:$DY$1,0)) -> 39.3428 | I166: =STDEV(H167:H170) -> 6.510667 | J166: =INDEX(MarketCap2!$E$2:$AR$224,MATCH(A166,MarketCap2!$B$2:$B$224,0),MATCH(G166,MarketCap2!$E$1:$AR$1,0)) -> 10380139520 | K166: =LN(J166) -> 23.06316 | L166: =INDEX('PB2'!$D$2:$AQ$224,MATCH(A166,'PB2'!$B$2:$B$224,0),MATCH(G166,'PB2'!$D$1:$AQ$1,0)) -> 1.8763731 | M166: =1/L166 -> 0.53294306 | N166: =INDEX('ROA2'!$D$2:$AQ$224,MATCH(A166,'ROA2'!$B$2:$B$224,0),MATCH(G166,'ROA2'!$D$1:$AQ$1,0)) -> 0.36439699 | O166: 6683.18 | P166: -0.017989268
A167: AEM CN Equity | B167: =VLOOKUP(A167,Sheet3!L:L,1,FALSE) -> #N/A | C167: =VLOOKUP(A167,'ALL - prices'!B:C,2,FALSE) -> Agnico Eagle Mines Ltd | D167: =VLOOKUP(A167,'ALL - prices'!B:I,8,FALSE) -> Materials | E167: 2016 | F167: Q2 | G167: =E167&"-"&F167 -> 2016-Q2 | H167: =INDEX('ALL - prices'!$J$3:$DY$219,MATCH('COMBINED DATA'!A167,'ALL - prices'!$B$3:$B$219,0),MATCH('COMBINED DATA'!G167,'ALL - prices'!$J$1:$DY$1,0)) -> 57.9926 | I167: =STDEV(H168:H171) -> 5.7714552 | J167: =INDEX(MarketCap2!$E$2:$AR$224,MATCH(A167,MarketCap2!$B$2:$B$224,0),MATCH(G167,MarketCap2!$E$1:$AR$1,0)) -> 15424679936 | K167: =LN(J167) -> 23.459235 | L167: =INDEX('PB2'!$D$2:$AQ$224,MATCH(A167,'PB2'!$B$2:$B$224,0),MATCH(G167,'PB2'!$D$1:$AQ$1,0)) -> 2.7184329 | M167: =1/L167 -> 0.367859 | N167: =INDEX('ROA2'!$D$2:$AQ$224,MATCH(A167,'ROA2'!$B$2:$B$224,0),MATCH(G167,'ROA2'!$D$1:$AQ$1,0)) -> 0.35046801 | O167: 6716.564 | P167: 0.0049952172
A168: AEM CN Equity | B168: =VLOOKUP(A168,Sheet3!L:L,1,FALSE) -> #N/A | C168: =VLOOKUP(A168,'ALL - prices'!B:C,2,FALSE) -> Agnico Eagle Mines Ltd | D168: =VLOOKUP(A168,'ALL - prices'!B:I,8,FALSE) -> Materials | E168: 2016 | F168: Q3 | G168: =E168&"-"&F168 -> 2016-Q3 | H168: =INDEX('ALL - prices'!$J$3:$DY$219,MATCH('COMBINED DATA'!A168,'ALL - prices'!$B$3:$B$219,0),MATCH('COMBINED DATA'!G168,'ALL - prices'!$J$1:$DY$1,0)) -> 59.6227 | I168: =STDEV(H169:H172) -> 0.9118123 | J168: =INDEX(MarketCap2!$E$2:$AR$224,MATCH(A168,MarketCap2!$B$2:$B$224,0),MATCH(G168,MarketCap2!$E$1:$AR$1,0)) -> 15931622400 | K168: =LN(J168) -> 23.491572 | L168: =INDEX('PB2'!$D$2:$AQ$224,MATCH(A168,'PB2'!$B$2:$B$224,0),MATCH(G168,'PB2'!$D$1:$AQ$1,0)) -> 2.7253511 | M168: =1/L168 -> 0.3669252 | N168: =INDEX('ROA2'!$D$2:$AQ$224,MATCH(A168,'ROA2'!$B$2:$B$224,0),MATCH(G168,'ROA2'!$D$1:$AQ$1,0)) -> 0.47241101 | O168: 7024.1951 | P168: 0.045801857
A169: AEM CN Equity | B169: =VLOOKUP(A169,Sheet3!L:L,1,FALSE) -> #N/A | C169: =VLOOKUP(A169,'ALL - prices'!B:C,2,FALSE) -> Agnico Eagle Mines Ltd | D169: =VLOOKUP(A169,'ALL - prices'!B:I,8,FALSE) -> Materials | E169: 2016 | F169: Q4 | G169: =E169&"-"&F169 -> 2016-Q4 | H169: =INDEX('ALL - prices'!$J$3:$DY$219,MATCH('COMBINED DATA'!A169,'ALL - prices'!$B$3:$B$219,0),MATCH('COMBINED DATA'!G169,'ALL - prices'!$J$1:$DY$1,0)) -> 47.5501 | I169: =STDEV(H170:H173) -> 0.97543682 | J169: =INDEX(MarketCap2!$E$2:$AR$224,MATCH(A169,MarketCap2!$B$2:$B$224,0),MATCH(G169,MarketCap2!$E$1:$AR$1,0)) -> 12717728768 | K169: =LN(J169) -> 23.266263 | L169: =INDEX('PB2'!$D$2:$AQ$224,MATCH(A169,'PB2'!$B$2:$B$224,0),MATCH(G169,'PB2'!$D$1:$AQ$1,0)) -> 2.106379 | M169: =1/L169 -> 0.47474836 | N169: =INDEX('ROA2'!$D$2:$AQ$224,MATCH(A169,'ROA2'!$B$2:$B$224,0),MATCH(G169,'ROA2'!$D$1:$AQ$1,0)) -> 1.1536731 | O169: 7172.8788 | P169: 0.021167376
A170: AEM CN Equity | B170: =VLOOKUP(A170,Sheet3!L:L,1,FALSE) -> #N/A | C170: =VLOOKUP(A170,'ALL - prices'!B:C,2,FALSE) -> Agnico Eagle Mines Ltd | D170: =VLOOKUP(A170,'ALL - prices'!B:I,8,FALSE) -> Materials | E170: 2017 | F170: Q1 | G170: =E170&"-"&F170 -> 2017-Q1 | H170: =INDEX('ALL - prices'!$J$3:$DY$219,MATCH('COMBINED DATA'!A170,'ALL - prices'!$B$3:$B$219,0),MATCH('COMBINED DATA'!G170,'ALL - prices'!$J$1:$DY$1,0)) -> 47.63 | I170: =STDEV(H171:H174) -> 1.536261 | J170: =INDEX(MarketCap2!$E$2:$AR$224,MATCH(A170,MarketCap2!$B$2:$B$224,0),MATCH(G170,MarketCap2!$E$1:$AR$1,0)) -> 12744101888 | K170: =LN(J170) -> 23.268334 | L170: =INDEX('PB2'!$D$2:$AQ$224,MATCH(A170,'PB2'!$B$2:$B$224,0),MATCH(G170,'PB2'!$D$1:$AQ$1,0)) -> 2.0432501 | M170: =1/L170 -> 0.48941635 | N170: =INDEX('ROA2'!$D$2:$AQ$224,MATCH(A170,'ROA2'!$B$2:$B$224,0),MATCH(G170,'ROA2'!$D$1:$AQ$1,0)) -> 2.303277 | O170: 7107.9511 | P170: -0.0090518389
A171: AEM CN Equity | B171: =VLOOKUP(A171,Sheet3!L:L,1,FALSE) -> #N/A | C171: =VLOOKUP(A171,'ALL - prices'!B:C,2,FALSE) -> Agnico Eagle Mines Ltd | D171: =VLOOKUP(A171,'ALL - prices'!B:I,8,FALSE) -> Materials | E171: 2017 | F171: Q2 | G171: =E171&"-"&F171 -> 2017-Q2 | H171: =INDEX('ALL - prices'!$J$3:$DY$219,MATCH('COMBINED DATA'!A171,'ALL - prices'!$B$3:$B$219,0),MATCH('COMBINED DATA'!G171,'ALL - prices'!$J$1:$DY$1,0)) -> 49.4709 | I171: =STDEV(H172:H175) -> 2.2560049 | J171: =INDEX(MarketCap2!$E$2:$AR$224,MATCH(A171,MarketCap2!$B$2:$B$224,0),MATCH(G171,MarketCap2!$E$1:$AR$1,0)) -> 13550573568 | K171: =LN(J171) -> 23.329695 | L171: =INDEX('PB2'!$D$2:$AQ$224,MATCH(A171,'PB2'!$B$2:$B$224,0),MATCH(G171,'PB2'!$D$1:$AQ$1,0)) -> 2.145957 | M171: =1/L171 -> 0.46599256 | N171: =INDEX('ROA2'!$D$2:$AQ$224,MATCH(A171,'ROA2'!$B$2:$B$224,0),MATCH(G171,'ROA2'!$D$1:$AQ$1,0)) -> 2.933094 | O171: 7397.269 | P171: 0.040703416
A172: AEM CN Equity | B172: =VLOOKUP(A172,Sheet3!L:L,1,FALSE) -> #N/A | C172: =VLOOKUP(A172,'ALL - prices'!B:C,2,FALSE) -> Agnico Eagle Mines Ltd | D172: =VLOOKUP(A172,'ALL - prices'!B:I,8,FALSE) -> Materials | E172: 2017 | F172: Q3 | G172: =E172&"-"&F172 -> 2017-Q3 | H172: =INDEX('ALL - prices'!$J$3:$DY$219,MATCH('COMBINED DATA'!A172,'ALL - prices'!$B$3:$B$219,0),MATCH('COMBINED DATA'!G172,'ALL - prices'!$J$1:$DY$1,0)) -> 47.7965 | I172: =STDEV(H173:H176) -> 6.0035075 | J172: =INDEX(MarketCap2!$E$2:$AR$224,MATCH(A172,MarketCap2!$B$2:$B$224,0),MATCH(G172,MarketCap2!$E$1:$AR$1,0)) -> 13082985472 | K172: =LN(J172) -> 23.294578 | L172: =INDEX('PB2'!$D$2:$AQ$224,MATCH(A172,'PB2'!$B$2:$B$224,0),MATCH(G172,'PB2'!$D$1:$AQ$1,0)) -> 2.127152 | M172: =1/L172 -> 0.47011216 | N172: =INDEX('ROA2'!$D$2:$AQ$224,MATCH(A172,'ROA2'!$B$2:$B$224,0),MATCH(G172,'ROA2'!$D$1:$AQ$1,0)) -> 3.3000619 | O172: 7695.042 | P172: 0.040254458
A173: AEM CN Equity | B173: =VLOOKUP(A173,Sheet3!L:L,1,FALSE) -> #N/A | C173: =VLOOKUP(A173,'ALL - prices'!B:C,2,FALSE) -> Agnico Eagle Mines Ltd | D173: =VLOOKUP(A173,'ALL - prices'!B:I,8,FALSE) -> Materials | E173: 2017 | F173: Q4 | G173: =E173&"-"&F173 -> 2017-Q4 | H173: =INDEX('ALL - prices'!$J$3:$DY$219,MATCH('COMBINED DATA'!A173,'ALL - prices'!$B$3:$B$219,0),MATCH('COMBINED DATA'!G173,'ALL - prices'!$J$1:$DY$1,0)) -> 49.3196 | I173: =STDEV(H174:H177) -> 5.7382581 | J173: =INDEX(MarketCap2!$E$2:$AR$224,MATCH(A173,MarketCap2!$B$2:$B$224,0),MATCH(G173,MarketCap2!$E$1:$AR$1,0)) -> 13488970752 | K173: =LN(J173) -> 23.325138 | L173: =INDEX('PB2'!$D$2:$AQ$224,MATCH(A173,'PB2'!$B$2:$B$224,0),MATCH(G173,'PB2'!$D$1:$AQ$1,0)) -> 2.1802671 | M173: =1/L173 -> 0.4586594 | N173: =INDEX('ROA2'!$D$2:$AQ$224,MATCH(A173,'ROA2'!$B$2:$B$224,0),MATCH(G173,'ROA2'!$D$1:$AQ$1,0)) -> 3.534657 | O173: 7875.2 | P173: 0.023412212
... A197: AEM CN Equity | B197: =VLOOKUP(A197,Sheet3!L:L,1,FALSE) -> #N/A | C197: =VLOOKUP(A197,'ALL - prices'!B:C,2,FALSE) -> Agnico Eagle Mines Ltd | D197: =VLOOKUP(A197,'ALL - prices'!B:I,8,FALSE) -> Materials | E197: 2023 | F197: Q4 | G197: =E197&"-"&F197 -> 2023-Q4 | H197: =INDEX('ALL - prices'!$J$3:$DY$219,MATCH('COMBINED DATA'!A197,'ALL - prices'!$B$3:$B$219,0),MATCH('COMBINED DATA'!G197,'ALL - prices'!$J$1:$DY$1,0)) -> 70.0433 | I197: =STDEV(H198:H201) -> 15.558953 | J197: =INDEX(MarketCap2!$E$2:$AR$224,MATCH(A197,MarketCap2!$B$2:$B$224,0),MATCH(G197,MarketCap2!$E$1:$AR$1,0)) -> 36073746432 | K197: =LN(J197) -> 24.308831 | L197: =INDEX('PB2'!$D$2:$AQ$224,MATCH(A197,'PB2'!$B$2:$B$224,0),MATCH(G197,'PB2'!$D$1:$AQ$1,0)) -> 1.408429 | M197: =1/L197 -> 0.71001093 | N197: =INDEX('ROA2'!$D$2:$AQ$224,MATCH(A197,'ROA2'!$B$2:$B$224,0),MATCH(G197,'ROA2'!$D$1:$AQ$1,0)) -> 9.5744724 | O197: 29225.681 | P197: -0.0029329955
A198: AEM CN Equity | B198: =VLOOKUP(A198,Sheet3!L:L,1,FALSE) -> #N/A | C198: =VLOOKUP(A198,'ALL - prices'!B:C,2,FALSE) -> Agnico Eagle Mines Ltd | D198: =VLOOKUP(A198,'ALL - prices'!B:I,8,FALSE) -> Materials | E198: 2024 | F198: Q1 | G198: =E198&"-"&F198 -> 2024-Q1 | H198: =INDEX('ALL - prices'!$J$3:$DY$219,MATCH('COMBINED DATA'!A198,'ALL - prices'!$B$3:$B$219,0),MATCH('COMBINED DATA'!G198,'ALL - prices'!$J$1:$DY$1,0)) -> 78.5261 | I198: N/A | J198: =INDEX(MarketCap2!$E$2:$AR$224,MATCH(A198,MarketCap2!$B$2:$B$224,0),MATCH(G198,MarketCap2!$E$1:$AR$1,0)) -> 40299433984 | K198: =LN(J198) -> 24.419603 | L198: =INDEX('PB2'!$D$2:$AQ$224,MATCH(A198,'PB2'!$B$2:$B$224,0),MATCH(G198,'PB2'!$D$1:$AQ$1,0)) -> 1.513322 | M198: =1/L198 -> 0.6607979 | N198: =INDEX('ROA2'!$D$2:$AQ$224,MATCH(A198,'ROA2'!$B$2:$B$224,0),MATCH(G198,'ROA2'!$D$1:$AQ$1,0)) -> 7.4287658 | O198: 28684.95 | P198: -0.018501926
A199: AEM CN Equity | B199: =VLOOKUP(A199,Sheet3!L:L,1,FALSE) -> #N/A | C199: =VLOOKUP(A199,'ALL - prices'!B:C,2,FALSE) -> Agnico Eagle Mines Ltd | D199: =VLOOKUP(A199,'ALL - prices'!B:I,8,FALSE) -> Materials | E199: 2024 | F199: Q2 | G199: =E199&"-"&F199 -> 2024-Q2 | H199: =INDEX('ALL - prices'!$J$3:$DY$219,MATCH('COMBINED DATA'!A199,'ALL - prices'!$B$3:$B$219,0),MATCH('COMBINED DATA'!G199,'ALL - prices'!$J$1:$DY$1,0)) -> 87.5036 | I199: N/A | J199: =INDEX(MarketCap2!$E$2:$AR$224,MATCH(A199,MarketCap2!$B$2:$B$224,0),MATCH(G199,MarketCap2!$E$1:$AR$1,0)) -> 44764639232 | K199: =LN(J199) -> 24.524684 | L199: =INDEX('PB2'!$D$2:$AQ$224,MATCH(A199,'PB2'!$B$2:$B$224,0),MATCH(G199,'PB2'!$D$1:$AQ$1,0)) -> 1.635753 | M199: =1/L199 -> 0.61133923 | N199: =INDEX('ROA2'!$D$2:$AQ$224,MATCH(A199,'ROA2'!$B$2:$B$224,0),MATCH(G199,'ROA2'!$D$1:$AQ$1,0)) -> 1.602964 | O199: 28802.441 | P199: 0.0040959358
A200: AEM CN Equity | B200: =VLOOKUP(A200,Sheet3!L:L,1,FALSE) -> #N/A | C200: =VLOOKUP(A200,'ALL - prices'!B:C,2,FALSE) -> Agnico Eagle Mines Ltd | D200: =VLOOKUP(A200,'ALL - prices'!B:I,8,FALSE) -> Materials | E200: 2024 | F200: Q3 | G200: =E200&"-"&F200 -> 2024-Q3 | H200: =INDEX('ALL - prices'!$J$3:$DY$219,MATCH('COMBINED DATA'!A200,'ALL - prices'!$B$3:$B$219,0),MATCH('COMBINED DATA'!G200,'ALL - prices'!$J$1:$DY$1,0)) -> 107.0644 | I200: N/A | J200: =INDEX(MarketCap2!$E$2:$AR$224,MATCH(A200,MarketCap2!$B$2:$B$224,0),MATCH(G200,MarketCap2!$E$1:$AR$1,0)) -> 54646591488 | K200: =LN(J200) -> 24.724153 | L200: =INDEX('PB2'!$D$2:$AQ$224,MATCH(A200,'PB2'!$B$2:$B$224,0),MATCH(G200,'PB2'!$D$1:$AQ$1,0)) -> 1.972854 | M200: =1/L200 -> 0.50687988 | N200: =INDEX('ROA2'!$D$2:$AQ$224,MATCH(A200,'ROA2'!$B$2:$B$224,0),MATCH(G200,'ROA2'!$D$1:$AQ$1,0)) -> 2.105027 | O200: 29291.207 | P200: 0.016969584
A201: AEM CN Equity | B201: =VLOOKUP(A201,Sheet3!L:L,1,FALSE) -> #N/A | C201: =VLOOKUP(A201,'ALL - prices'!B:C,2,FALSE) -> Agnico Eagle Mines Ltd | D201: =VLOOKUP(A201,'ALL - prices'!B:I,8,FALSE) -> Materials | E201: 2024 | F201: Q4 | G201: =E201&"-"&F201 -> 2024-Q4 | H201: =INDEX('ALL - prices'!$J$3:$DY$219,MATCH('COMBINED DATA'!A201,'ALL - prices'!$B$3:$B$219,0),MATCH('COMBINED DATA'!G201,'ALL - prices'!$J$1:$DY$1,0)) -> 111.0433 | I201: N/A | J201: =INDEX(MarketCap2!$E$2:$AR$224,MATCH(A201,MarketCap2!$B$2:$B$224,0),MATCH(G201,MarketCap2!$E$1:$AR$1,0)) -> 56443891712 | K201: =LN(J201) -> 24.756513 | L201: =INDEX('PB2'!$D$2:$AQ$224,MATCH(A201,'PB2'!$B$2:$B$224,0),MATCH(G201,'PB2'!$D$1:$AQ$1,0)) -> 1.9114541 | M201: =1/L201 -> 0.52316192 | N201: =INDEX('ROA2'!$D$2:$AQ$224,MATCH(A201,'ROA2'!$B$2:$B$224,0),MATCH(G201,'ROA2'!$D$1:$AQ$1,0)) -> 3.4054129 | O201: 29816.49 | P201: 0.017933141
A202: AG CN Equity | B202: =VLOOKUP(A202,Sheet3!L:L,1,FALSE) -> AG CN EQUITY | C202: =VLOOKUP(A202,'ALL - prices'!B:C,2,FALSE) -> First Majestic Silver Corp | D202: =VLOOKUP(A202,'ALL - prices'!B:I,8,FALSE) -> Materials | E202: 2015 | F202: Q1 | G202: =E202&"-"&F202 -> 2015-Q1 | H202: =INDEX('ALL - prices'!$J$3:$DY$219,MATCH('COMBINED DATA'!A202,'ALL - prices'!$B$3:$B$219,0),MATCH('COMBINED DATA'!G202,'ALL - prices'!$J$1:$DY$1,0)) -> 6.7302 | I202: =STDEV(H203:H206) -> 1.8837593 | J202: =INDEX('market cap'!$B$3:$DQ$219,MATCH(A202,'market cap'!$A$3:$A$219,0),MATCH(G202,'market cap'!$B$1:$DQ$1,0)) -> 801.9955 | K202: =LN(J202) -> 6.687103 | L202: =INDEX('PB2'!$D$2:$AQ$224,MATCH(A202,'PB2'!$B$2:$B$224,0),MATCH(G202,'PB2'!$D$1:$AQ$1,0)) -> 1.214095 | M202: =1/L202 -> 0.82365878 | N202: =INDEX('ROA2'!$D$2:$AQ$224,MATCH(A202,'ROA2'!$B$2:$B$224,0),MATCH(G202,'ROA2'!$D$1:$AQ$1,0)) -> -7.5568128 | O202: 771.34202 | P202: -0.11888112
A203: AG CN Equity | B203: =VLOOKUP(A203,Sheet3!L:L,1,FALSE) -> AG CN EQUITY | C203: =VLOOKUP(A203,'ALL - prices'!B:C,2,FALSE) -> First Majestic Silver Corp | D203: =VLOOKUP(A203,'ALL - prices'!B:I,8,FALSE) -> Materials | E203: 2015 | F203: Q2 | G203: =E203&"-"&F203 -> 2015-Q2 | H203: =INDEX('ALL - prices'!$J$3:$DY$219,MATCH('COMBINED DATA'!A203,'ALL - prices'!$B$3:$B$219,0),MATCH('COMBINED DATA'!G203,'ALL - prices'!$J$1:$DY$1,0)) -> 5.9704 | I203: =STDEV(H204:H207) -> 6.1253275 | J203: =INDEX('market cap'!$B$3:$DQ$219,MATCH(A203,'market cap'!$A$3:$A$219,0),MATCH(G203,'market cap'!$B$1:$DQ$1,0)) -> 739.3986 | K203: =LN(J203) -> 6.6058372 | L203: =INDEX('PB2'!$D$2:$AQ$224,MATCH(A203,'PB2'!$B$2:$B$224,0),MATCH(G203,'PB2'!$D$1:$AQ$1,0)) -> 1.0908951 | M203: =1/L203 -> 0.91667846 | N203: =INDEX('ROA2'!$D$2:$AQ$224,MATCH(A203,'ROA2'!$B$2:$B$224,0),MATCH(G203,'ROA2'!$D$1:$AQ$1,0)) -> -8.4330349 | O203: 757.11699 | P203: -0.018441915
A204: AG CN Equity | B204: =VLOOKUP(A204,Sheet3!L:L,1,FALSE) -> AG CN EQUITY | C204: =VLOOKUP(A204,'ALL - prices'!B:C,2,FALSE) -> First Majestic Silver Corp | D204: =VLOOKUP(A204,'ALL - prices'!B:I,8,FALSE) -> Materials | E204: 2015 | F204: Q3 | G204: =E204&"-"&F204 -> 2015-Q3 | H204: =INDEX('ALL - prices'!$J$3:$DY$219,MATCH('COMBINED DATA'!A204,'ALL - prices'!$B$3:$B$219,0),MATCH('COMBINED DATA'!G204,'ALL - prices'!$J$1:$DY$1,0)) -> 4.2138 | I204: =STDEV(H205:H208) -> 5.642553 | J204: =INDEX('market cap'!$B$3:$DQ$219,MATCH(A204,'market cap'!$A$3:$A$219,0),MATCH(G204,'market cap'!$B$1:$DQ$1,0)) -> 522.668 | K204: =LN(J204) -> 6.2589465 | L204: =INDEX('PB2'!$D$2:$AQ$224,MATCH(A204,'PB2'!$B$2:$B$224,0),MATCH(G204,'PB2'!$D$1:$AQ$1,0)) -> 0.718786 | M204: =1/L204 -> 1.3912347 | N204: =INDEX('ROA2'!$D$2:$AQ$224,MATCH(A204,'ROA2'!$B$2:$B$224,0),MATCH(G204,'ROA2'!$D$1:$AQ$1,0)) -> -9.4984417 | O204: 766.23898 | P204: 0.012048315
A205: AG CN Equity | B205: =VLOOKUP(A205,Sheet3!L:L,1,FALSE) -> AG CN EQUITY | C205: =VLOOKUP(A205,'ALL - prices'!B:C,2,FALSE) -> First Majestic Silver Corp | D205: =VLOOKUP(A205,'ALL - prices'!B:I,8,FALSE) -> Materials | E205: 2015 | F205: Q4 | G205: =E205&"-"&F205 -> 2015-Q4 | H205: =INDEX('ALL - prices'!$J$3:$DY$219,MATCH('COMBINED DATA'!A205,'ALL - prices'!$B$3:$B$219,0),MATCH('COMBINED DATA'!G205,'ALL - prices'!$J$1:$DY$1,0)) -> 4.4506 | I205: =STDEV(H206:H209) -> 3.9560802 | J205: =INDEX('market cap'!$B$3:$DQ$219,MATCH(A205,'market cap'!$A$3:$A$219,0),MATCH(G205,'market cap'!$B$1:$DQ$1,0)) -> 701.4221 | K205: =LN(J205) -> 6.5531098 | L205: =INDEX('PB2'!$D$2:$AQ$224,MATCH(A205,'PB2'!$B$2:$B$224,0),MATCH(G205,'PB2'!$D$1:$AQ$1,0)) -> 0.93158299 | M205: =1/L205 -> 1.0734417 | N205: =INDEX('ROA2'!$D$2:$AQ$224,MATCH(A205,'ROA2'!$B$2:$B$224,0),MATCH(G205,'ROA2'!$D$1:$AQ$1,0)) -> -8.6144981 | O205: 750.47501 | P205: -0.020573174
A206: AG CN Equity | B206: =VLOOKUP(A206,Sheet3!L:L,1,FALSE) -> AG CN EQUITY | C206: =VLOOKUP(A206,'ALL - prices'!B:C,2,FALSE) -> First Majestic Silver Corp | D206: =VLOOKUP(A206,'ALL - prices'!B:I,8,FALSE) -> Materials | E206: 2016 | F206: Q1 | G206: =E206&"-"&F206 -> 2016-Q1 | H206: =INDEX('ALL - prices'!$J$3:$DY$219,MATCH('COMBINED DATA'!A206,'ALL - prices'!$B$3:$B$219,0),MATCH('COMBINED DATA'!G206,'ALL - prices'!$J$1:$DY$1,0)) -> 8.3092 | I206: =STDEV(H207:H210) -> 3.2912921 | J206: =INDEX('market cap'!$B$3:$DQ$219,MATCH(A206,'market cap'!$A$3:$A$219,0),MATCH(G206,'market cap'!$B$1:$DQ$1,0)) -> 1310.6869 | K206: =LN(J206) -> 7.1783066 | L206: =INDEX('PB2'!$D$2:$AQ$224,MATCH(A206,'PB2'!$B$2:$B$224,0),MATCH(G206,'PB2'!$D$1:$AQ$1,0)) -> 1.873919 | M206: =1/L206 -> 0.53364099 | N206: =INDEX('ROA2'!$D$2:$AQ$224,MATCH(A206,'ROA2'!$B$2:$B$224,0),MATCH(G206,'ROA2'!$D$1:$AQ$1,0)) -> -13.891234 | O206: 789.69997 | P206: 0.052266844
A207: AG CN Equity | B207: =VLOOKUP(A207,Sheet3!L:L,1,FALSE) -> AG CN EQUITY | C207: =VLOOKUP(A207,'ALL - prices'!B:C,2,FALSE) -> First Majestic Silver Corp | D207: =VLOOKUP(A207,'ALL - prices'!B:I,8,FALSE) -> Materials | E207: 2016 | F207: Q2 | G207: =E207&"-"&F207 -> 2016-Q2 | H207: =INDEX('ALL - prices'!$J$3:$DY$219,MATCH('COMBINED DATA'!A207,'ALL - prices'!$B$3:$B$219,0),MATCH('COMBINED DATA'!G207,'ALL - prices'!$J$1:$DY$1,0)) -> 17.319 | I207: =STDEV(H208:H211) -> 1.4638371 | J207: =INDEX('market cap'!$B$3:$DQ$219,MATCH(A207,'market cap'!$A$3:$A$219,0),MATCH(G207,'market cap'!$B$1:$DQ$1,0)) -> 2847.2805 | K207: =LN(J207) -> 7.9541196 | L207: =INDEX('PB2'!$D$2:$AQ$224,MATCH(A207,'PB2'!$B$2:$B$224,0),MATCH(G207,'PB2'!$D$1:$AQ$1,0)) -> 3.6747971 | M207: =1/L207 -> 0.27212387 | N207: =INDEX('ROA2'!$D$2:$AQ$224,MATCH(A207,'ROA2'!$B$2:$B$224,0),MATCH(G207,'ROA2'!$D$1:$AQ$1,0)) -> -14.790516 | O207: 794.57997 | P207: 0.0061795621
A208: AG CN Equity | B208: =VLOOKUP(A208,Sheet3!L:L,1,FALSE) -> AG CN EQUITY | C208: =VLOOKUP(A208,'ALL - prices'!B:C,2,FALSE) -> First Majestic Silver Corp | D208: =VLOOKUP(A208,'ALL - prices'!B:I,8,FALSE) -> Materials | E208: 2016 | F208: Q3 | G208: =E208&"-"&F208 -> 2016-Q3 | H208: =INDEX('ALL - prices'!$J$3:$DY$219,MATCH('COMBINED DATA'!A208,'ALL - prices'!$B$3:$B$219,0),MATCH('COMBINED DATA'!G208,'ALL - prices'!$J$1:$DY$1,0)) -> 13.3519 | I208: =STDEV(H209:H212) -> 1.0555662 | J208: =INDEX('market cap'!$B$3:$DQ$219,MATCH(A208,'market cap'!$A$3:$A$219,0),MATCH(G208,'market cap'!$B$1:$DQ$1,0)) -> 2213.5339 | K208: =LN(J208) -> 7.7023456 | L208: =INDEX('PB2'!$D$2:$AQ$224,MATCH(A208,'PB2'!$B$2:$B$224,0),MATCH(G208,'PB2'!$D$1:$AQ$1,0)) -> 2.7302999 | M208: =1/L208 -> 0.36626012 | N208: =INDEX('ROA2'!$D$2:$AQ$224,MATCH(A208,'ROA2'!$B$2:$B$224,0),MATCH(G208,'ROA2'!$D$1:$AQ$1,0)) -> -13.204084 | O208: 840.36998 | P208: 0.057627952
A209: AG CN Equity | B209: =VLOOKUP(A209,Sheet3!L:L,1,FALSE) -> AG CN EQUITY | C209: =VLOOKUP(A209,'ALL - prices'!B:C,2,FALSE) -> First Majestic Silver Corp | D209: =VLOOKUP(A209,'ALL - prices'!B:I,8,FALSE) -> Materials | E209: 2016 | F209: Q4 | G209: =E209&"-"&F209 -> 2016-Q4 | H209: =INDEX('ALL - prices'!$J$3:$DY$219,MATCH('COMBINED DATA'!A209,'ALL - prices'!$B$3:$B$219,0),MATCH('COMBINED DATA'!G209,'ALL - prices'!$J$1:$DY$1,0)) -> 10.125 | I209: =STDEV(H210:H213) -> 1.2963369 | J209: =INDEX('market cap'!$B$3:$DQ$219,MATCH(A209,'market cap'!$A$3:$A$219,0),MATCH(G209,'market cap'!$B$1:$DQ$1,0)) -> 1687.1449 | K209: =LN(J209) -> 7.430793 | L209: =INDEX('PB2'!$D$2:$AQ$224,MATCH(A209,'PB2'!$B$2:$B$224,0),MATCH(G209,'PB2'!$D$1:$AQ$1,0)) -> 2.0179391 | M209: =1/L209 -> 0.4955551 | N209: =INDEX('ROA2'!$D$2:$AQ$224,MATCH(A209,'ROA2'!$B$2:$B$224,0),MATCH(G209,'ROA2'!$D$1:$AQ$1,0)) -> -11.960929 | O209: 857.66099 | P209: 0.020575471
A210: AG CN Equity | B210: =VLOOKUP(A210,Sheet3!L:L,1,FALSE) -> AG CN EQUITY | C210: =VLOOKUP(A210,'ALL - prices'!B:C,2,FALSE) -> First Majestic Silver Corp | D210: =VLOOKUP(A210,'ALL - prices'!B:I,8,FALSE) -> Materials | E210: 2017 | F210: Q1 | G210: =E210&"-"&F210 -> 2017-Q1 | H210: =INDEX('ALL - prices'!$J$3:$DY$219,MATCH('COMBINED DATA'!A210,'ALL - prices'!$B$3:$B$219,0),MATCH('COMBINED DATA'!G210,'ALL - prices'!$J$1:$DY$1,0)) -> 10.648 | I210: =STDEV(H211:H214) -> 1.2482386 | J210: =INDEX('market cap'!$B$3:$DQ$219,MATCH(A210,'market cap'!$A$3:$A$219,0),MATCH(G210,'market cap'!$B$1:$DQ$1,0)) -> 1774.5403 | K210: =LN(J210) -> 7.4812967 | L210: =INDEX('PB2'!$D$2:$AQ$224,MATCH(A210,'PB2'!$B$2:$B$224,0),MATCH(G210,'PB2'!$D$1:$AQ$1,0)) -> 2.128149 | M210: =1/L210 -> 0.4698919 | N210: =INDEX('ROA2'!$D$2:$AQ$224,MATCH(A210,'ROA2'!$B$2:$B$224,0),MATCH(G210,'ROA2'!$D$1:$AQ$1,0)) -> 1.044524 | O210: 857.17498 | P210: -0.00056667612
A211: AG CN Equity | B211: =VLOOKUP(A211,Sheet3!L:L,1,FALSE) -> AG CN EQUITY | C211: =VLOOKUP(A211,'ALL - prices'!B:C,2,FALSE) -> First Majestic Silver Corp | D211: =VLOOKUP(A211,'ALL - prices'!B:I,8,FALSE) -> Materials | E211: 2017 | F211: Q2 | G211: =E211&"-"&F211 -> 2017-Q2 | H211: =INDEX('ALL - prices'!$J$3:$DY$219,MATCH('COMBINED DATA'!A211,'ALL - prices'!$B$3:$B$219,0),MATCH('COMBINED DATA'!G211,'ALL - prices'!$J$1:$DY$1,0)) -> 10.6184 | I211: =STDEV(H212:H215) -> 0.90123995 | J211: =INDEX('market cap'!$B$3:$DQ$219,MATCH(A211,'market cap'!$A$3:$A$219,0),MATCH(G211,'market cap'!$B$1:$DQ$1,0)) -> 1776.9392 | K211: =LN(J211) -> 7.4826476 | L211: =INDEX('PB2'!$D$2:$AQ$224,MATCH(A211,'PB2'!$B$2:$B$224,0),MATCH(G211,'PB2'!$D$1:$AQ$1,0)) -> 2.1606929 | M211: =1/L211 -> 0.46281449 | N211: =INDEX('ROA2'!$D$2:$AQ$224,MATCH(A211,'ROA2'!$B$2:$B$224,0),MATCH(G211,'ROA2'!$D$1:$AQ$1,0)) -> 2.283844 | O211: 847.73901 | P211: -0.011008217
A212: AG CN Equity | B212: =VLOOKUP(A212,Sheet3!L:L,1,FALSE) -> AG CN EQUITY | C212: =VLOOKUP(A212,'ALL - prices'!B:C,2,FALSE) -> First Majestic Silver Corp | D212: =VLOOKUP(A212,'ALL - prices'!B:I,8,FALSE) -> Materials | E212: 2017 | F212: Q3 | G212: =E212&"-"&F212 -> 2017-Q3 | H212: =INDEX('ALL - prices'!$J$3:$DY$219,MATCH('COMBINED DATA'!A212,'ALL - prices'!$B$3:$B$219,0),MATCH('COMBINED DATA'!G212,'ALL - prices'!$J$1:$DY$1,0)) -> 8.4079 | I212: =STDEV(H213:H216) -> 1.1485994 | J212: =INDEX('market cap'!$B$3:$DQ$219,MATCH(A212,'market cap'!$A$3:$A$219,0),MATCH(G212,'market cap'!$B$1:$DQ$1,0)) -> 1411.038 | K212: =LN(J212) -> 7.2520809 | L212: =INDEX('PB2'!$D$2:$AQ$224,MATCH(A212,'PB2'!$B$2:$B$224,0),MATCH(G212,'PB2'!$D$1:$AQ$1,0)) -> 1.778047 | M212: =1/L212 -> 0.56241484 | N212: =INDEX('ROA2'!$D$2:$AQ$224,MATCH(A212,'ROA2'!$B$2:$B$224,0),MATCH(G212,'ROA2'!$D$1:$AQ$1,0)) -> 1.67793 | O212: 835.624 | P212: -0.014290964
A213: AG CN Equity | B213: =VLOOKUP(A213,Sheet3!L:L,1,FALSE) -> AG CN EQUITY | C213: =VLOOKUP(A213,'ALL - prices'!B:C,2,FALSE) -> First Majestic Silver Corp | D213: =VLOOKUP(A213,'ALL - prices'!B:I,8,FALSE) -> Materials | E213: 2017 | F213: Q4 | G213: =E213&"-"&F213 -> 2017-Q4 | H213: =INDEX('ALL - prices'!$J$3:$DY$219,MATCH('COMBINED DATA'!A213,'ALL - prices'!$B$3:$B$219,0),MATCH('COMBINED DATA'!G213,'ALL - prices'!$J$1:$DY$1,0)) -> 8.3684 | I213: =STDEV(H214:H217) -> 1.1647328 | J213: =INDEX('market cap'!$B$3:$DQ$219,MATCH(A213,'market cap'!$A$3:$A$219,0),MATCH(G213,'market cap'!$B$1:$DQ$1,0)) -> 1405.0992 | K213: =LN(J213) -> 7.2478632 | L213: =INDEX('PB2'!$D$2:$AQ$224,MATCH(A213,'PB2'!$B$2:$B$224,0),MATCH(G213,'PB2'!$D$1:$AQ$1,0)) -> 1.927134 | M213: =1/L213 -> 0.51890527 | N213: =INDEX('ROA2'!$D$2:$AQ$224,MATCH(A213,'ROA2'!$B$2:$B$224,0),MATCH(G213,'ROA2'!$D$1:$AQ$1,0)) -> 0.54576302 | O213: 837.58003 | P213: 0.002340804
... A237: AG CN Equity | B237: =VLOOKUP(A237,Sheet3!L:L,1,FALSE) -> AG CN EQUITY | C237: =VLOOKUP(A237,'ALL - prices'!B:C,2,FALSE) -> First Majestic Silver Corp | D237: =VLOOKUP(A237,'ALL - prices'!B:I,8,FALSE) -> Materials | E237: 2023 | F237: Q4 | G237: =E237&"-"&F237 -> 2023-Q4 | H237: =INDEX('ALL - prices'!$J$3:$DY$219,MATCH('COMBINED DATA'!A237,'ALL - prices'!$B$3:$B$219,0),MATCH('COMBINED DATA'!G237,'ALL - prices'!$J$1:$DY$1,0)) -> 8.0831 | I237: =STDEV(H238:H241) -> 0.10728797 | J237: =INDEX('market cap'!$B$3:$DQ$219,MATCH(A237,'market cap'!$A$3:$A$219,0),MATCH(G237,'market cap'!$B$1:$DQ$1,0)) -> 2332.7662 | K237: =LN(J237) -> 7.7548101 | L237: =INDEX('PB2'!$D$2:$AQ$224,MATCH(A237,'PB2'!$B$2:$B$224,0),MATCH(G237,'PB2'!$D$1:$AQ$1,0)) -> 1.301881 | M237: =1/L237 -> 0.76811939 | N237: =INDEX('ROA2'!$D$2:$AQ$224,MATCH(A237,'ROA2'!$B$2:$B$224,0),MATCH(G237,'ROA2'!$D$1:$AQ$1,0)) -> -8.0970459 | O237: 1952.3549 | P237: -0.030600076
A238: AG CN Equity | B238: =VLOOKUP(A238,Sheet3!L:L,1,FALSE) -> AG CN EQUITY | C238: =VLOOKUP(A238,'ALL - prices'!B:C,2,FALSE) -> First Majestic Silver Corp | D238: =VLOOKUP(A238,'ALL - prices'!B:I,8,FALSE) -> Materials | E238: 2024 | F238: Q1 | G238: =E238&"-"&F238 -> 2024-Q1 | H238: =INDEX('ALL - prices'!$J$3:$DY$219,MATCH('COMBINED DATA'!A238,'ALL - prices'!$B$3:$B$219,0),MATCH('COMBINED DATA'!G238,'ALL - prices'!$J$1:$DY$1,0)) -> 7.9112 | I238: N/A | J238: =INDEX('market cap'!$B$3:$DQ$219,MATCH(A238,'market cap'!$A$3:$A$219,0),MATCH(G238,'market cap'!$B$1:$DQ$1,0)) -> 2282.8164 | K238: =LN(J238) -> 7.7331652 | L238: =INDEX('PB2'!$D$2:$AQ$224,MATCH(A238,'PB2'!$B$2:$B$224,0),MATCH(G238,'PB2'!$D$1:$AQ$1,0)) -> 1.258952 | M238: =1/L238 -> 0.79431145 | N238: =INDEX('ROA2'!$D$2:$AQ$224,MATCH(A238,'ROA2'!$B$2:$B$224,0),MATCH(G238,'ROA2'!$D$1:$AQ$1,0)) -> -6.612823 | O238: 1976.3549 | P238: 0.012292847
...

Sheet RAW DATA -->
B2: Page intentionally left blank

Sheet securities
A1: Ticker
A2: AAUC CN Equity
A3: AAV CN Equity
A4: ABX CN Equity
A5: AC CN Equity
A6: ACO/X CN Equity
A7: AEM CN Equity
A8: AG CN Equity
A9: AGI CN Equity
A10: AIF CN Equity
A11: ALA CN Equity
A12: AP-U CN Equity
... A219: X CN Equity

Sheet ALL - prices
A1: Ticker | B1: Ticker | C1: Name | D1: Weight | E1: Shares | F1: Price | G1: Start | H1: End | I1: SECTOR | J1: 1/31/2015 | K1: 2/28/2015 | L1: 2015-Q1 | M1: 4/30/2015 | N1: 5/31/2015 | O1: 2015-Q2 | P1: 42216 | Q1: 42247 | R1: 2015-Q3 | S1: 42308 | T1: 42338 | U1: 2015-Q4 | V1: 42400 | W1: 42429 | X1: 2016-Q1 | Y1: 42490 | Z1: 42521 | AA1: 2016-Q2 | AB1: 42582 | AC1: 42613 | AD1: 2016-Q3 | AE1: 42674 | AF1: 42704 | AG1: 2016-Q4 | AH1: 42766 | AI1: 42794 | AJ1: 2017-Q1 | AK1: 42855 | AL1: 42886 | AM1: 2017-Q2 | AN1: 42947 | AO1: 42978 | AP1: 2017-Q3 | AQ1: 43039 | AR1: 43069 | AS1: 2017-Q4 | AT1: 43131 | AU1: 43159 | AV1: 2018-Q1 | AW1: 43220 | AX1: 43251 | AY1: 2018-Q2 | AZ1: 43312 | BA1: 43343 | BB1: 2018-Q3 | BC1: 43404 | BD1: 43434 | BE1: 2018-Q4 | BF1: 43496 | BG1: 43524 | BH1: 2019-Q1 | BI1: 43585 | BJ1: 43616 | BK1: 2019-Q2 | BL1: 43677 | BM1: 43708 | BN1: 2019-Q3 | BO1: 43769 | BP1: 43799 | BQ1: 2019-Q4 | BR1: 43861 | BS1: 43890 | BT1: 2020-Q1 | BU1: 43951 | BV1: 43982 | BW1: 2020-Q2 | BX1: 44043 | BY1: 44074 | BZ1: 2020-Q3 | CA1: 44135 | CB1: 44165 | CC1: 2020-Q4 | CD1: 44227 | CE1: 44255 | CF1: 2021-Q1 | CG1: 44316 | CH1: 44347 | CI1: 2021-Q2 | CJ1: 44408 | CK1: 44439 | CL1: 2021-Q3 | CM1: 44500 | CN1: 44530 | CO1: 2021-Q4 | CP1: 44592 | CQ1: 44620 | CR1: 2022-Q1 | CS1: 44681 | CT1: 44712 | CU1: 2022-Q2 | CV1: 44773 | CW1: 44804 | CX1: 2022-Q3 | CY1: 44865 | CZ1: 44895 | DA1: 2022-Q4 | DB1: 44957 | DC1: 44985 | DD1: 2023-Q1 | DE1: 45046 | DF1: 45077 | DG1: 2023-Q2 | DH1: 45138 | DI1: 45169 | DJ1: 2023-Q3 | DK1: 45230 | DL1: 45260 | DM1: 2023-Q4 | DN1: 45322 | DO1: 45351 | DP1: 2024-Q1 | DQ1: 45412 | DR1: 45443 | DS1: 2024-Q2 | DT1: 45504 | DU1: 45535 | DV1: 2024-Q3 | DW1: 45596 | DX1: 45626 | DY1: 2024-Q4
A2: AAUC | B2: =A2&" CN Equity" -> AAUC CN Equity | C2: Allied Gold Corp | D2: -- | E2: -- | F2: 42.97 | G2: 42005 | H2: 45657 | I2: Materials | DJ2: =_xll.BDH(B2, "PX_LAST", "2015-01-01", "2024-12-31", "Period=M", "Orientation=H", "CshAdjNormal = Y","CapChg = Y", "DTS=H","cols=16;rows=1") -> #N/A Requesting Data... | DK2: 13.2 | DL2: 11.25 | DM2: 10.53 | DN2: 9.48 | DO2: 8.88 | DP2: 10.2 | DQ2: 11.1 | DR2: 9.24 | DS2: 8.82 | DT2: 9.81 | DU2: 9.18 | DV2: 9.66 | DW2: 11.1 | DX2: 10.29 | DY2: 10.23
A3: AAV | B3: =A3&" CN Equity" -> AAV CN Equity | C3: Advantage Energy Ltd | D3: -- | E3: -- | F3: 11.01 | G3: 42005 | H3: 45657 | I3: Energy | J3: 5.82 | K3: 6.49 | L3: 6.82 | M3: 7.47 | N3: 7.54 | O3: 7.9 | P3: 7.14 | Q3: 7.33 | R3: 6.97 | S3: 7.27 | T3: 7.04 | U3: 7.03 | V3: 7.65 | W3: 6.88 | X3: 7.13 | Y3: 7.19 | Z3: 7.71 | AA3: 7.22 | AB3: 8.26 | AC3: 8.95 | AD3: 9.2 | AE3: 9.05 | AF3: 9.74 | AG3: 9.12 | AH3: 8.39 | AI3: 8 | AJ3: 8.78 | AK3: 8.59 | AL3: 8.51 | AM3: 8.77 | AN3: 8.57 | AO3: 7.96 | AP3: 7.82 | AQ3: 6.83 | AR3: 6.03 | AS3: 5.4 | AT3: 3.95 | AU3: 3.63 | AV3: 3.81 | AW3: 4.09 | AX3: 3.87 | AY3: 4.11 | AZ3: 4.5 | BA3: 3.88 | BB3: 3.6 | BC3: 2.95 | BD3: 2.38 | BE3: 1.98 | BF3: 2.05 | BG3: 2.24 | BH3: 2.2 | BI3: 2.22 | BJ3: 1.75 | BK3: 1.63 | BL3: 1.89 | BM3: 1.48 | BN3: 2.15 | BO3: 1.9 | BP3: 2.44 | BQ3: 2.75 | BR3: 2.21 | BS3: 2.02 | BT3: 1.43 | BU3: 2.26 | BV3: 2.1 | BW3: 1.66 | BX3: 1.6 | BY3: 2.17 | BZ3: 1.75 | CA3: 2.2 | CB3: 2.06 | CC3: 1.71 | CD3: 1.91 | CE3: 2.6 | CF3: 2.37 | CG3: 3.26 | CH3: 4.03 | CI3: 5.06 | CJ3: 4.69 | CK3: 5.25 | CL3: 6.4 | CM3: 7.01 | CN3: 7.09 | CO3: 7.41 | CP3: 6.88 | CQ3: 7.41 | CR3: 8.71 | CS3: 10.73 | CT3: 10.98 | CU3: 8 | CV3: 11.01 | CW3: 11.22 | CX3: 9.93 | CY3: 10.3 | CZ3: 11.56 | DA3: 9.47 | DB3: 8.3 | DC3: 7.98 | DD3: 7.81 | DE3: 7.62 | DF3: 7.31 | DG3: 8.65 | DH3: 9.3 | DI3: 9.63 | DJ3: 9.27 | DK3: 10.07 | DL3: 9.3 | DM3: 8.53 | DN3: 8.82 | DO3: 10.04 | DP3: 9.88 | DQ3: 10.74 | DR3: 11.59 | DS3: 10.38 | DT3: 9.63 | DU3: 9.72 | DV3: 9.45 | DW3: 8.71 | DX3: 9 | DY3: 9.86
A4: ABX | B4: =A4&" CN Equity" -> ABX CN Equity | C4: Barrick Mining Corp | D4: -- | E4: -- | F4: 62.24 | G4: 42005 | H4: 45657 | I4: Materials | J4: 13.5 | K4: 13.5648 | L4: 11.5543 | M4: 13.0809 | N4: 12.3327 | O4: 11.1849 | P4: 7.6996 | Q4: 7.6895 | R4: 7.1349 | S4: 8.5383 | T4: 8.2834 | U4: 8.6289 | V4: 11.7384 | W4: 15.8659 | X4: 14.8869 | Y4: 20.4991 | Z4: 18.5206 | AA4: 23.3029 | AB4: 24.0886 | AC4: 18.8539 | AD4: 19.649 | AE4: 19.962 | AF4: 17.0668 | AG4: 18.2018 | AH4: 20.3108 | AI4: 20.7913 | AJ4: 21.4276 | AK4: 19.3577 | AL4: 18.9853 | AM4: 17.5321 | AN4: 17.9145 | AO4: 19.1453 | AP4: 17.0937 | AQ4: 15.8679 | AR4: 15.2019 | AS4: 15.5091 | AT4: 15.091 | AU4: 12.6396 | AV4: 13.7257 | AW4: 14.7776 | AX4: 14.631 | AY4: 14.8024 | AZ4: 12.4967 | BA4: 11.4749 | BB4: 12.2829 | BC4: 14.1739 | BD4: 14.5856 | BE4: 15.9594 | BF4: 15.232 | BG4: 14.3747 | BH4: 15.8642 | BI4: 14.7471 | BJ4: 14.6063 | BK4: 17.9603 | BL4: 18.6381 | BM4: 22.4715 | BN4: 19.9553 | BO4: 19.9205 | BP4: 19.3687 | BQ4: 21.0628 | BR4: 21.4034 | BS4: 22.4297 | BT4: 22.6575 | BU4: 31.3928 | BV4: 29.0951 | BW4: 32.1004 | BX4: 34.016 | BY4: 34.05 | BZ4: 32.9573 | CA4: 31.3887 | CB4: 26.371 | CC4: 25.6545 | CD4: 25.2652 | CE4: 21.1075 | CF4: 22.1562 | CG4: 23.276 | CH4: 25.5469 | CI4: 22.8709 | CJ4: 24.2267 | CK4: 22.722 | CL4: 20.491 | CM4: 20.3477 | CN4: 21.8572 | CO4: 21.6501 | CP4: 21.9022 | CQ4: 25.8522 | CR4: 27.5974 | CS4: 25.9065 | CT4: 23.6523 | CU4: 20.7768 | CV4: 18.4216 | CW4: 18.0359 | CX4: 19.8024 | CY4: 19.0255 | CZ4: 20.4993 | DA4: 21.6761 | DB4: 24.3003 | DC4: 20.7225 | DD4: 23.5794 | DE4: 24.2091 | DF4: 21.6867 | DG4: 21.2046 | DH4: 21.5355 | DI4: 20.8312 | DJ4: 18.7671 | DK4: 21.069 | DL4: 22.8647 | DM4: 22.903 | DN4: 20.0903 | DO4: 19.064 | DP4: 21.7035 | DQ4: 22.0792 | DR4: 22.5963 | DS4: 22.1118 | DT4: 24.7862 | DU4: 26.4957 | DV4: 26.1841 | DW4: 26.2036 | DX4: 24.0126 | DY4: 21.8288
A5: AC | B5: =A5&" CN Equity" -> AC CN Equity | C5: Air Canada | D5: -- | E5: -- | F5: 18.85 | G5: 42005 | H5: 45657 | I5: Industrials | J5: 11.75 | K5: 12.34 | L5: 12.39 | M5: 11.52 | N5: 13.76 | O5: 13.21 | P5: 11.77 | Q5: 11.23 | R5: 10.73 | S5: 10.76 | T5: 10.43 | U5: 10.21 | V5: 7.83 | W5: 7.22 | X5: 8.96 | Y5: 9.33 | Z5: 9.63 | AA5: 8.89 | AB5: 8.99 | AC5: 8.96 | AD5: 10.6 | AE5: 12.65 | AF5: 13.5 | AG5: 13.67 | AH5: 13.37 | AI5: 13.38 | AJ5: 13.8 | AK5: 12.99 | AL5: 17.8 | AM5: 17.38 | AN5: 19.83 | AO5: 23.34 | AP5: 26.24 | AQ5: 25.56 | AR5: 24.59 | AS5: 25.88 | AT5: 23.91 | AU5: 27.06 | AV5: 26.77 | AW5: 25.25 | AX5: 22.97 | AY5: 21.25 | AZ5: 23.53 | BA5: 26.82 | BB5: 27.6 | BC5: 24.98 | BD5: 29 | BE5: 25.96 | BF5: 29.67 | BG5: 33.11 | BH5: 32.21 | BI5: 32.16 | BJ5: 39.9 | BK5: 39.69 | BL5: 45.41 | BM5: 44.75 | BN5: 43.21 | BO5: 46.9 | BP5: 50.05 | BQ5: 48.51 | BR5: 44.33 | BS5: 34.25 | BT5: 15.75 | BU5: 20.24 | BV5: 15.9 | BW5: 16.95 | BX5: 15.11 | BY5: 17.6 | BZ5: 15.69 | CA5: 15.1 | CB5: 24.7 | CC5: 22.77 | CD5: 20.02 | CE5: 25.1 | CF5: 26.15 | CG5: 24.77 | CH5: 27.36 | CI5: 25.5 | CJ5: 24.98 | CK5: 24.51 | CL5: 23.13 | CM5: 22.19 | CN5: 20.8 | CO5: 21.12 | CP5: 22.86 | CQ5: 23.95 | CR5: 24.25 | CS5: 22.5 | CT5: 22.19 | CU5: 16.04 | CV5: 17.39 | CW5: 17.69 | CX5: 16.6 | CY5: 19.61 | CZ5: 19.29 | DA5: 19.39 | DB5: 22.58 | DC5: 20.12 | DD5: 19.15 | DE5: 18.96 | DF5: 21.43 | DG5: 24.99 | DH5: 24.3 | DI5: 22.82 | DJ5: 19.38 | DK5: 16.73 | DL5: 17.63 | DM5: 18.69 | DN5: 18.22 | DO5: 18.12 | DP5: 19.61 | DQ5: 20.32 | DR5: 18.2 | DS5: 17.9 | DT5: 15.91 | DU5: 15.44 | DV5: 16.39 | DW5: 18.87 | DX5: 24.96 | DY5: 22.26
A6: ACO/X | B6: =A6&" CN Equity" -> ACO/X CN Equity | C6: Atco Ltd/Canada | D6: -- | E6: -- | F6: 59.12 | G6: 42005 | H6: 45657 | I6: Utilities | J6: 32.57 | K6: 31.9351 | L6: 30.0313 | M6: 30.4373 | N6: 28.9597 | O6: 26.4378 | P6: 26.2771 | Q6: 26.5784 | R6: 26.4174 | S6: 25.1706 | T6: 24.3148 | U6: 24.2275 | V6: 26.3517 | W6: 24.3429 | X6: 26.8634 | Y6: 28.0261 | Z6: 29.517 | AA6: 31.1943 | AB6: 33.8719 | AC6: 33.1147 | AD6: 32.2778 | AE6: 32.5548 | AF6: 29.633 | AG6: 31.1272 | AH6: 31.9357 | AI6: 31.6291 | AJ6: 36.2967 | AK6: 34.8647 | AL6: 35.7632 | AM6: 35.8231 | AN6: 32.7854 | AO6: 32.5029 | AP6: 32.5903 | AQ6: 33.2877 | AR6: 32.7896 | AS6: 32.2532 | AT6: 31.8805 | AU6: 30.275 | AV6: 29.9241 | AW6: 28.0945 | AX6: 28.4995 | AY6: 29.6328 | AZ6: 29.1289 | BA6: 28.4863 | BB6: 27.8395 | BC6: 28.3041 | BD6: 29.9634 | BE6: 28.7335 | BF6: 30.9214 | BG6: 32.9605 | BH6: 33.7935 | BI6: 34.5069 | BJ6: 34.9125 | BK6: 33.4396 | BL6: 33.3259 | BM6: 36.0456 | BN6: 37.0407 | BO6: 35.3751 | BP6: 38.5001 | BQ6: 38.3325 | BR6: 39.7573 | BS6: 38.5712 | BT6: 30.2715 | BU6: 30.3647 | BV6: 30.1472 | BW6: 31.6367 | BX6: 32.7444 | BY6: 31.2204 | BZ6: 30.5676 | CA6: 29.4558 | CB6: 31.0044 | CC6: 29.3054 | CD6: 29.4018 | CE6: 29.8114 | CF6: 33.9039 | CG6: 34.2858 | CH6: 35.4561 | CI6: 36.0949 | CJ6: 37.0145 | CK6: 34.8551 | CL6: 33.7168 | CM6: 34.8537 | CN6: 34.5467 | CO6: 35.8203 | CP6: 35.921 | CQ6: 34.9227 | CR6: 36.4159 | CS6: 38.825 | CT6: 38.9183 | CU6: 37.7886 | CV6: 40.5564 | CW6: 40.2381 | CX6: 36.7335 | CY6: 36.6037 | CZ6: 37.6763 | DA6: 37.0727 | DB6: 37.0377 | DC6: 37.0115 | DD6: 38.3258 | DE6: 39.6087 | DF6: 37.3364 | DG6: 35.2875 | DH6: 33.677 | DI6: 33.3728 | DJ6: 31.1757 | DK6: 32.218 | DL6: 33.5774 | DM6: 35.4947 | DN6: 34.5126 | DO6: 34.5691 | DP6: 35.0713 | DQ6: 34.9411 | DR6: 37.2136 | DS6: 36.6957 | DT6: 40.3305 | DU6: 42.8164 | DV6: 45.5895 | DW6: 45.9892 | DX6: 46.7696 | DY6: 45.7286
A7: AEM | B7: =A7&" CN Equity" -> AEM CN Equity | C7: Agnico Eagle Mines Ltd | D7: -- | E7: -- | F7: 258.84 | G7: 42005 | H7: 45657 | I7: Materials | J7: 35.38 | K7: 33.2588 | L7: 29.2018 | M7: 30.2367 | N7: 33.2195 | O7: 29.4344 | P7: 24.0223 | Q7: 26.8356 | R7: 28.1766 | S7: 30.7835 | T7: 29.639 | U7: 30.3825 | V7: 34.551 | W7: 39.8619 | X7: 39.3428 | Y7: 49.6578 | Z7: 49.37 | AA7: 57.9926 | AB7: 63.7298 | AC7: 55.8579 | AD7: 59.6227 | AE7: 57.2445 | AF7: 46.4972 | AG7: 47.5501 | AH7: 52.2841 | AI7: 47.1488 | AJ7: 47.63 | AK7: 55.0843 | AL7: 55.2318 | AM7: 49.4709 | AN7: 49.2425 | AO7: 54.2553 | AP7: 47.7965 | AQ7: 48.8221 | AR7: 48.0534 | AS7: 49.3196 | AT7: 49.447 | AU7: 41.6627 | AV7: 46.1878 | AW7: 46.0429 | AX7: 49.7083 | AY7: 51.4852 | AZ7: 46.5562 | BA7: 38.5428 | BB7: 37.8059 | BC7: 39.8453 | BD7: 40.1668 | BE7: 47.3613 | BF7: 49.1233 | BG7: 48.2509 | BH7: 50.0872 | BI7: 47.8285 | BJ7: 50.9743 | BK7: 58.0562 | BL7: 59.6213 | BM7: 72.1189 | BN7: 61.5142 | BO7: 70.1348 | BP7: 68.5825 | BQ7: 69.5037 | BR7: 71.0853 | BS7: 55.5647 | BT7: 49.0128 | BU7: 70.9543 | BV7: 77.0942 | BW7: 76.079 | BX7: 93.0924 | BY7: 94.3545 | BZ7: 92.8278 | CA7: 92.5383 | CB7: 75.0811 | CC7: 79.0332 | CD7: 78.7509 | CE7: 63.0431 | CF7: 64.4719 | CG7: 68.1724 | CH7: 76.255 | CI7: 66.8469 | CJ7: 71.9746 | CK7: 65.1403 | CL7: 58.9583 | CM7: 58.9403 | CN7: 57.535 | CO7: 60.7063 | CP7: 54.8516 | CQ7: 58.041 | CR7: 69.6458 | CS7: 68.0799 | CT7: 61.4833 | CU7: 54.0363 | CV7: 50.4963 | CW7: 50.1452 | CX7: 54.0338 | CY7: 55.4875 | CZ7: 63.2353 | DA7: 65.6714 | DB7: 70.1329 | DC7: 59.1488 | DD7: 64.8264 | DE7: 72.3683 | DF7: 65.5648 | DG7: 62.7839 | DH7: 65.6123 | DI7: 62.7825 | DJ7: 59.0601 | DK7: 62.237 | DL7: 70.2362 | DM7: 70.0433 | DN7: 63.7091 | DO7: 63.4178 | DP7: 78.5261 | DQ7: 84.758 | DR7: 90.9556 | DS7: 87.5036 | DT7: 104.177 | DU7: 107.8997 | DV7: 107.0644 | DW7: 118.1 | DX7: 116.5728 | DY7: 111.0433
A8: AG | B8: =A8&" CN Equity" -> AG CN Equity | C8: First Majestic Silver Corp | D8: -- | E8: -- | F8: 28.35 | G8: 42005 | H8: 45657 | I8: Materials | J8: 7.75 | K8: 7.6085 | L8: 6.7302 | M8: 5.8026 | N8: 6.0691 | O8: 5.9704 | P8: 3.9572 | Q8: 4.4803 | R8: 4.2138 | S8: 4.2631 | T8: 4.4013 | U8: 4.4506 | V8: 4.1447 | W8: 6.1974 | X8: 8.3092 | Y8: 13.1842 | Z8: 13.4605 | AA8: 17.319 | AB8: 22.342 | AC8: 15.6019 | AD8: 13.3519 | AE8: 10.6283 | AF8: 11.7533 | AG8: 10.125 | AH8: 12.3059 | AI8: 11.8815 | AJ8: 10.648 | AK8: 10.9539 | AL8: 11.1513 | AM8: 10.6184 | AN8: 10.125 | AO8: 8.7039 | AP8: 8.4079 | AQ8: 8.5756 | AR8: 8.5263 | AS8: 8.3684 | AT8: 7.421 | AU8: 6.7105 | AV8: 7.7862 | AW8: 8.2302 | AX8: 9.0691 | AY8: 9.898 | AZ8: 8.5164 | BA8: 7.1645 | BB8: 7.2335 | BC8: 7.2138 | BD8: 6.296 | BE8: 7.9145 | BF8: 7.9342 | BG8: 8.7631 | BH8: 8.6743 | BI8: 8.1217 | BJ8: 8.102 | BK8: 10.2039 | BL8: 12.2861 | BM8: 14.2894 | BN8: 11.8914 | BO8: 13.8947 | BP8: 14.0526 | BQ8: 15.7204 | BR8: 13.1644 | BS8: 9.9967 | BT8: 8.6052 | BU8: 11.0921 | BV8: 13.5789 | BW8: 13.3223 | BX8: 17.6447 | BY8: 15.9967 | BZ8: 12.4934 | CA8: 13.4506 | CB8: 13.3421 | CC8: 16.8552 | CD8: 22.7664 | CE8: 22.6381 | CF8: 19.3421 | CG8: 18.3749 | CH8: 21.3614 | CI8: 19.328 | CJ8: 16.8404 | CK8: 16.0485 | CL8: 14.1622 | CM8: 15.4855 | CN8: 15.0366 | CO8: 13.9005 | CP8: 12.7544 | CQ8: 14.0981 | CR8: 16.2412 | CS8: 13.1175 | CT8: 9.9714 | CU8: 9.1305 | CV8: 9.7043 | CW8: 9.4936 | CX8: 10.4538 | CY8: 11.3448 | CZ8: 12.3628 | DA8: 11.1741 | DB8: 10.4113 | DC8: 8.2518 | DD8: 9.6672 | DE8: 9.4888 | DF8: 7.8004 | DG8: 7.4332 | DH8: 8.7233 | DI8: 8.2339 | DJ8: 6.9129 | DK8: 7.0917 | DL8: 8.0632 | DM8: 8.0831 | DN8: 6.1642 | DO8: 6.0748 | DP8: 7.9112 | DQ8: 9.1352 | DR8: 9.7172 | DS8: 8.0645 | DT8: 8.5025 | DU8: 7.5232 | DV8: 8.0911 | DW8: 10.2534 | DX8: 8.5658 | DY8: 7.8777
A9: AGI | B9: =A9&" CN Equity" -> AGI CN Equity | C9: Alamos Gold Inc | D9: -- | E9: -- | F9: 50.46 | G9: 42005 | H9: 45657 | I9: Materials | J9: 6.29 | K9: 7.0124 | L9: 6.8826 | M9: 7.7359 | N9: 7.5815 | O9: 6.6129 | P9: 3.9584 | Q9: 5.0481 | R9: 4.6011 | S9: 4.6958 | T9: 3.7902 | U9: 4.2477 | V9: 4.2663 | W9: 5.788 | X9: 6.4228 | Y9: 8.4622 | Z9: 7.8451 | AA9: 10.3884 | AB9: 11.417 | AC9: 8.6305 | AD9: 10.0985 | AE9: 9.8504 | AF9: 8.0058 | AG9: 8.7361 | AH9: 9.1387 | AI9: 8.9983 | AJ9: 10.0002 | AK9: 9.1595 | AL9: 8.522 | AM9: 8.6157 | AN9: 8.2782 | AO9: 9.7501 | AP9: 7.9032 | AQ9: 7.6795 | AR9: 7.6983 | AS9: 7.6889 | AT9: 6.9191 | AU9: 6.1211 | AV9: 6.2901 | AW9: 6.5273 | AX9: 6.7436 | AY9: 7.0446 | AZ9: 6.6402 | BA9: 5.3987 | BB9: 5.5774 | BC9: 4.957 | BD9: 4.0241 | BE9: 4.6272 | BF9: 5.5131 | BG9: 5.9937 | BH9: 6.4015 | BI9: 5.8728 | BJ9: 6.2315 | BK9: 7.4734 | BL9: 8.1924 | BM9: 8.8735 | BN9: 7.2957 | BO9: 6.7935 | BP9: 7.1346 | BQ9: 7.4319 | BR9: 7.9255 | BS9: 7.4129 | BT9: 6.7364 | BU9: 10.681 | BV9: 10.6239 | BW9: 12.0859 | BX9: 13.5275 | BY9: 13.031 | BZ9: 11.2147 | CA9: 11.6353 | CB9: 10.2777 | CC9: 10.656 | CD9: 9.8318 | CE9: 8.6436 | CF9: 9.4396 | CG9: 9.4684 | CH9: 10.5354 | CI9: 9.1293 | CJ9: 9.7752 | CK9: 9.6016 | CL9: 8.8105 | CM9: 8.8782 | CN9: 9.4489 | CO9: 9.4424 | CP9: 8.4138 | CQ9: 9.064 | CR9: 10.221 | CS9: 9.7148 | CT9: 9.1891 | CU9: 8.8207 | CV9: 9.8855 | CW9: 9.231 | CX9: 10.0365 | CY9: 10.5364 | CZ9: 12.7808 | DA9: 13.4515 | DB9: 14.4243 | DC9: 13.6677 | DD9: 16.2504 | DE9: 17.2452 | DF9: 16.5065 | DG9: 15.5727 | DH9: 16.076 | DI9: 17.1517 | DJ9: 15.1505 | DK9: 16.9801 | DL9: 19.8876 | DM9: 17.6533 | DN9: 16.1277 | DO9: 15.8602 | DP9: 19.8196 | DQ9: 20.0975 | DR9: 22.6183 | DS9: 21.3317 | DT9: 23.3893 | DU9: 25.8247 | DV9: 26.8244 | DW9: 27.9989 | DX9: 26.486 | DY9: 26.4302
A10: AIF | B10: =A10&" CN Equity" -> AIF CN Equity | C10: Altus Group Ltd/Canada | D10: -- | E10: -- | F10: 46.2 | G10: 42005 | H10: 45657 | I10: Real Estate | J10: 15.61 | K10: 18.2763 | L10: 16.3731 | M10: 16.8921 | N10: 15.988 | O10: 15.0233 | P10: 14.0273 | Q10: 17.7747 | R10: 17.4114 | S10: 16.1956 | T10: 17.1648 | U10: 16.6173 | V10: 15.2889 | W10: 17.1829 | X10: 17.9326 | Y10: 19.0895 | Z10: 19.8147 | AA10: 19.3658 | AB10: 20.5224 | AC10: 24.2964 | AD10: 25.5673 | AE10: 25.2876 | AF10: 26.8698 | AG10: 27.1969 | AH10: 26.2218 | AI10: 26.6171 | AJ10: 25.695 | AK10: 27.1961 | AL10: 26.6751 | AM10: 24.8831 | AN10: 22.6904 | AO10: 27.6972 | AP10: 28.3376 | AQ10: 31.4238 | AR10: 32.1106 | AS10: 33.074 | AT10: 30.7007 | AU10: 28.1214 | AV10: 29.3512 | AW10: 29.0633 | AX10: 26.3189 | AY10: 26.5079 | AZ10: 25.3231 | BA10: 27.9911 | BB10: 27.8204 | BC10: 26.1845 | BD10: 23.9396 | BE10: 21.6561 | BF10: 22.5619 | BG10: 24.0898 | BH10: 23.9903 | BI10: 24.9014 | BJ10: 27.2111 | BK10: 29.6541 | BL10: 30.9856 | BM10: 36.0621 | BN10: 37.0832 | BO10: 33.8808 | BP10: 34.215 | BQ10: 35.3734 | BR10: 40.3961 | BS10: 41.8219 | BT10: 34.1518 | BU10: 39.326 | BV10: 40.3179 | BW10: 38.3056 | BX10: 40.0617 | BY10: 50.3448 | BZ10: 52.1077 | CA10: 51.3354 | CB10: 46.3535 | CC10: 46.4183 | CD10: 46.2388 | CE10: 52.7283 | CF10: 57.2328 | CG10: 58.8142 | CH10: 55.9071 | CI10: 54.5392 | CJ10: 55.7448 | CK10: 62.9882 | CL10: 58.8126 | CM10: 61.7722 | CN10: 62.2576 | CO10: 67.6833 | CP10: 58.1846 | CQ10: 46.8452 | CR10: 48.3054 | CS10: 46.0192 | CT10: 45.1392 | CU10: 42.7942 | CV10: 50.4528 | CW10: 49.234 | CX10: 43.118 | CY10: 46.6133 | CZ10: 51.2544 | DA10: 52.1801 | DB10: 54.9803 | DC10: 58.9006 | DD10: 55.5626 | DE10: 52.087 | DF10: 42.7636 | DG10: 42.6762 | DH10: 42.7733 | DI10: 50.5547 | DJ10: 45.8216 | DK10: 45.8995 | DL10: 38.9805 | DM10: 41.21 | DN10: 44.3198 | DO10: 48.9846 | DP10: 50.8802 | DQ10: 49.5464 | DR10: 46.0746 | DS10: 49.696 | DT10: 56.8179 | DU10: 53.4439 | DV10: 54.1419 | DW10: 51.962 | DX10: 58.7088 | DY10: 55.387
A11: ALA | B11: =A11&" CN Equity" -> ALA CN Equity | C11: AltaGas Ltd | D11: -- | E11: -- | F11: 41.07 | G11: 42005 | H11: 45657 | I11: Utilities | J11: 24.09 | K11: 25.3244 | L11: 23.8703 | M11: 23.2406 | N11: 22.5708 | O11: 21.738 | P11: 20.5484 | Q11: 20.8638 | R11: 19.0555 | S11: 19.6599 | T11: 18.3218 | U11: 18.1841 | V11: 19.4007 | W11: 19.1344 | X11: 19.9642 | Y11: 18.3263 | Z11: 18.3136 | AA11: 19.0735 | AB11: 20.2983 | AC11: 20.8301 | AD11: 20.8157 | AE11: 20.5794 | AF11: 20.3461 | AG11: 21.2408 | AH11: 19.4976 | AI11: 19.6393 | AJ11: 19.6241 | AK11: 19.6003 | AL11: 19.4023 | AM11: 19.2468 | AN11: 18.9242 | AO11: 18.1716 | AP11: 18.9767 | AQ11: 19.5356 | AR11: 19.6031 | AS11: 19.2511 | AT11: 18.6613 | AU11: 18.0067 | AV11: 16.371 | AW11: 17.1175 | AX11: 17.7271 | AY11: 19.0427 | AZ11: 18.6199 | BA11: 17.2474 | BB11: 14.7362 | BC11: 11.9683 | BD11: 10.5704 | BE11: 10.2322 | BF11: 9.9581 | BG11: 13.1566 | BH11: 13.148 | BI11: 13.3721 | BJ11: 14.7102 | BK11: 14.997 | BL11: 15.3597 | BM11: 13.8001 | BN11: 14.9062 | BO11: 14.7448 | BP11: 15.2211 | BQ11: 15.3443 | BR11: 16.5967 | BS11: 15.6869 | BT11: 10.0518 | BU11: 13.1906 | BV11: 11.7771 | BW11: 12.5317 | BX11: 13.5002 | BY11: 13.6341 | BZ11: 13.0593 | CA11: 13.7802 | CB11: 15.2746 | CC11: 15.4079 | CD11: 15.6957 | CE11: 16.0106 | CF11: 17.4504 | CG11: 19.2165 | CH11: 20.0638 | CI11: 21.9128 | CJ11: 22.3113 | CK11: 21.4179 | CL11: 21.2506 | CM11: 21.8546 | CN11: 20.7965 | CO11: 23.4455 | CP11: 22.4153 | CQ11: 23.9692 | CR11: 24.264 | CS11: 25.4599 | CT11: 26.4651 | CU11: 23.7635 | CV11: 24.9622 | CW11: 24.7785 | CX11: 23.3516 | CY11: 21.6918 | CZ11: 19.9261 | DA11: 20.8678 | DB11: 22.2066 | DC11: 20.9035 | DD11: 20.3609 | DE11: 21.4183 | DF11: 20.8037 | DG11: 21.7569 | DH11: 23.7955 | DI11: 24.152 | DJ11: 24.0663 | DK11: 23.7984 | DL11: 25.4983 | DM11: 25.9638 | DN11: 26.0851 | DO11: 27.149 | DP11: 28.2106 | DQ11: 28.4557 | DR11: 28.9932 | DS11: 29.429 | DT11: 31.3427 | DU11: 32.8661 | DV11: 32.1456 | DW11: 31.944 | DX11: 32.8753 | DY11: 32.4396
A12: AP-U | B12: =A12&" CN Equity" -> AP-U CN Equity | C12: Allied Properties Real Estate | D12: -- | E12: -- | F12: 14.05 | G12: 42005 | H12: 45657 | I12: Real Estate | J12: 21.61 | K12: 22.0001 | L12: 21.8995 | M12: 21.8126 | N12: 19.8491 | O12: 19.4554 | P12: 20.0618 | Q12: 19.2694 | R12: 19.3767 | S12: 19.9706 | T12: 18.2968 | U12: 17.7064 | V12: 18.7516 | W12: 17.8428 | X12: 19.8424 | Y12: 20.1313 | Z12: 20.7367 | AA12: 22.1754 | AB12: 22.7862 | AC12: 21.2516 | AD12: 21.8143 | AE12: 20.948 | AF12: 19.762 | AG12: 21.0392 | AH12: 19.9144 | AI12: 20.6461 | AJ12: 21.3516 | AK12: 21.7455 | AL12: 22.7843 | AM12: 23.2583 | AN12: 22.8742 | AO12: 23.2871 | AP12: 24.0444 | AQ12: 25.0263 | AR12: 25.1882 | AS12: 25.6324 | AT12: 25.2667 | AU12: 25.413 | AV12: 24.9437 | AW12: 25.5909 | AX12: 26.3059 | AY12: 25.9784 | AZ12: 26.4321 | BA12: 27.2235 | BB12: 26.9982 | BC12: 26.5802 | BD12: 28.4216 | BE12: 28.0139 | BF12: 29.9194 | BG12: 30.5176 | BH12: 31.4223 | BI12: 30.3151 | BJ12: 31.1547 | BK12: 30.4459 | BL12: 31.5339 | BM12: 33.921 | BN12: 34.6979 | BO12: 34.7915 | BP12: 34.7613 | BQ12: 33.9816 | BR12: 36.1271 | BS12: 35.7213 | BT12: 29.4307 | BU12: 29.4033 | BV12: 26.4852 | BW12: 27.2119 | BX12: 26.7348 | BY12: 24.6173 | BZ12: 24.074 | CA12: 21.7906 | CB12: 27.622 | CC12: 25.6903 | CD12: 24.7395 | CE12: 26.2469 | CF12: 27.9026 | CG12: 29.3803 | CH12: 30.6495 | CI12: 31.2309 | CJ12: 31.787 | CK12: 30.2023 | CL12: 28.1571 | CM12: 30.0398 | CN12: 29.0677 | CO12: 31.0705 | CP12: 31.727 | CQ12: 31.3707 | CR12: 33.2889 | CS12: 29.892 | CT12: 27.8837 | CU12: 23.9688 | CV12: 24.7863 | CW12: 22.8659 | CX12: 20.0458 | CY12: 19.4366 | CZ12: 19.448 | DA12: 19.0704 | DB12: 22.2218 | DC12: 21.5413 | DD12: 18.449 | DE12: 17.3614 | DF12: 17.0476 | DG12: 16.7807 | DH12: 17.0689 | DI12: 16.2742 | DJ12: 14.1673 | DK12: 12.6435 | DL12: 14.3751 | DM12: 16.3546 | DN12: 15.9353 | DO12: 13.9888 | DP12: 14.675 | DQ12: 14.1849 | DR12: 14.2792 | DS12: 13.0703 | DT12: 14.2504 | DU12: 15.1126 | DV12: 17.6954 | DW12: 16.2012 | DX12: 16.158 | DY12: 15.3866
A13: AQN | B13: =A13&" CN Equity" -> AQN CN Equity | C13: Algonquin Power & Utilities Co | D13: -- | E13: -- | F13: 8.94 | G13: 42005 | H13: 45657 | I13: Utilities | J13: 5.78 | K13: 5.8404 | L13: 5.4061 | M13: 5.6776 | N13: 5.6371 | O13: 5.473 | P13: 5.6017 | Q13: 5.7186 | R13: 5.5949 | S13: 5.9802 | T13: 6.1284 | U13: 6.5436 | V13: 6.8975 | W13: 6.2437 | X13: 6.5967 | Y13: 6.6514 | Z13: 7.0883 | AA13: 7.3003 | AB13: 7.4967 | AC13: 7.2696 | AD13: 7.2996 | AE13: 7.3617 | AF13: 6.9144 | AG13: 7.166 | AH13: 7.1283 | AI13: 7.5938 | AJ13: 8.0878 | AK13: 8.2343 | AL13: 8.8966 | AM13: 8.7884 | AN13: 8.5824 | AO13: 8.724 | AP13: 8.5859 | AQ13: 8.9895 | AR13: 9.2369 | AS13: 9.2486 | AT13: 8.7882 | AU13: 8.3475 | AV13: 8.4996 | AW13: 8.3199 | AX13: 8.4064 | AY13: 8.5668 | AZ13: 8.6207 | BA13: 9.1199 | BB13: 9.1243 | BC13: 8.974 | BD13: 9.6297 | BE13: 9.4981 | BF13: 10.0377 | BG13: 10.1 | BH13: 10.516 | BI13: 10.6979 | BJ13: 11.0337 | BK13: 11.2322 | BL13: 11.6357 | BM13: 12.3151 | BN13: 12.9714 | BO13: 12.9356 | BP13: 13.3218 | BQ13: 13.2668 | BR13: 14.6318 | BS13: 14.7329 | BT13: 13.8413 | BU13: 14.097 | BV13: 14.0824 | BW13: 12.9778 | BX13: 13.6655 | BY13: 13.3698 | BZ13: 14.4576 | CA13: 15.1005 | CB13: 15.2127 | CC13: 15.8088 | CD13: 16.0805 | CE13: 14.8731 | CF13: 15.1718 | CG13: 15.1109 | CH13: 14.1126 | CI13: 14.2323 | CJ13: 15.3573 | CK13: 15.0953 | CL13: 14.4719 | CM13: 13.903 | CN13: 13.4744 | CO13: 14.4083 | CP13: 14.3136 | CQ13: 14.4635 | CR13: 15.4614 | CS13: 14.8314 | CT13: 14.6719 | CU13: 13.9776 | CV13: 14.4705 | CW13: 14.5755 | CX13: 12.3837 | CY13: 12.3755 | CZ13: 8.3379 | DA13: 7.4844 | DB13: 8.1848 | DC13: 8.7923 | DD13: 9.6963 | DE13: 9.8502 | DF13: 9.7818 | DG13: 9.4875 | DH13: 9.4269 | DI13: 8.8637 | DJ13: 7.0824 | DK13: 6.1487 | DL13: 7.3731 | DM13: 7.4902 | DN13: 7.1408 | DO13: 7.087 | DP13: 7.81 | DQ13: 7.6732 | DR13: 7.8192 | DS13: 7.4711 | DT13: 8.01 | DU13: 6.7927 | DV13: 6.95 | DW13: 6.3293 | DX13: 6.5362 | DY13: 6.0888
A14: ARE | B14: =A14&" CN Equity" -> ARE CN Equity | C14: Aecon Group Inc | D14: -- | E14: -- | F14: 35.3 | G14: 42005 | H14: 45657 | I14: Industrials | J14: 6.38 | K14: 7.6583 | L14: 7.3807 | M14: 8.624 | N14: 8.7226 | O14: 8.4546 | P14: 7.2809 | Q14: 8.4612 | R14: 9.0793 | S14: 10.0948 | T14: 9.4534 | U14: 10.3494 | V14: 9.7577 | W14: 9.3811 | X14: 10.9226 | Y14: 11.3289 | Z14: 11.9519 | AA14: 11.983 | AB14: 11.8535 | AC14: 12.5079 | AD14: 12.4301 | AE14: 11.895 | AF14: 10.722 | AG14: 10.5412 | AH14: 11.2325 | AI14: 11.0113 | AJ14: 11.9565 | AK14: 11.2741 | AL14: 10.2644 | AM14: 11.3312 | AN14: 10.573 | AO14: 11.9982 | AP14: 12.4233 | AQ14: 13.7384 | AR14: 13.9081 | AS14: 14.1882 | AT14: 14.1669 | AU14: 13.5549 | AV14: 13.1525 | AW14: 12.9305 | AX14: 10.7312 | AY14: 11.1639 | AZ14: 11.8932 | BA14: 12.5287 | BB14: 11.8133 | BC14: 13.7786 | BD14: 13.6257 | BE14: 12.9083 | BF14: 13.3921 | BG14: 13.4581 | BH14: 12.8877 | BI14: 14.1513 | BJ14: 12.9246 | BK14: 14.2714 | BL14: 15.1275 | BM14: 13.7651 | BN14: 13.6835 | BO14: 13.6535 | BP14: 13.7585 | BQ14: 13.2499 | BR14: 13.0155 | BS14: 11.8811 | BT14: 9.6189 | BU14: 11.7096 | BV14: 11.1812 | BW14: 11.4271 | BX14: 10.8852 | BY14: 11.2568 | BZ14: 10.7108 | CA14: 11.1336 | CB14: 12.7465 | CC14: 12.9344 | CD14: 13.045 | CE14: 14.5472 | CF14: 15.5001 | CG14: 14.8858 | CH14: 14.5428 | CI14: 14.5004 | CJ14: 16.3935 | CK14: 16.603 | CL14: 15.5756 | CM14: 14.9987 | CN14: 13.2275 | CO14: 13.8579 | CP14: 14.2519 | CQ14: 14.4572 | CR14: 14.0895 | CS14: 12.429 | CT14: 12.2796 | CU14: 11.0542 | CV14: 9.3451 | CW14: 9.1599 | CX14: 8.1515 | CY14: 8.2714 | CZ14: 8.4084 | DA14: 7.9651 | DB14: 9.8012 | DC14: 8.8656 | DD14: 12.1724 | DE14: 11.2326 | DF14: 11.7114 | DG14: 11.1274 | DH14: 9.868 | DI14: 10.2908 | DJ14: 10.3789 | DK14: 9.3273 | DL14: 10.5343 | DM14: 12.1371 | DN14: 12.8336 | DO14: 13.2143 | DP14: 15.98 | DQ14: 15.8861 | DR14: 15.4351 | DS14: 16.1389 | DT14: 15.9963 | DU14: 17.5836 | DV14: 20.072 | DW14: 22.25 | DX14: 27.6134 | DY14: 26.3005
... A20: ATS | B20: =A20&" CN Equity" -> ATS CN Equity | C20: ATS Corp | D20: -- | E20: -- | F20: 38.7 | G20: 42005 | H20: 45657 | I20: Industrials | J20: 14.5 | K20: 14.35 | L20: 13.58 | M20: 13.31 | N20: 15.72 | O20: 15.29 | P20: 16.15 | Q20: 13.61 | R20: 12.91 | S20: 13.77 | T20: 12.8 | U20: 11.38 | V20: 10.64 | W20: 9.96 | X20: 10.59 | Y20: 11.61 | Z20: 10.71 | AA20: 9.72 | AB20: 9.97 | AC20: 10.81 | AD20: 11 | AE20: 11.5 | AF20: 10.5 | AG20: 12.52 | AH20: 13.13 | AI20: 13.5 | AJ20: 13.57 | AK20: 13.02 | AL20: 12.93 | AM20: 13.29 | AN20: 13.4 | AO20: 12.61 | AP20: 13.26 | AQ20: 14.85 | AR20: 16.04 | AS20: 15.55 | AT20: 16.64 | AU20: 17.6 | AV20: 17.69 | AW20: 17.57 | AX20: 20.27 | AY20: 19.7 | AZ20: 19.56 | BA20: 22.12 | BB20: 24.02 | BC20: 19.36 | BD20: 17.02 | BE20: 14.39 | BF20: 16.92 | BG20: 18.53 | BH20: 19.64 | BI20: 21.45 | BJ20: 20.36 | BK20: 21.3 | BL20: 21.15 | BM20: 18.37 | BN20: 18.11 | BO20: 17.88 | BP20: 19.67 | BQ20: 21.43 | BR20: 20.33 | BS20: 17.93 | BT20: 16.46 | BU20: 20.65 | BV20: 20.01 | BW20: 19.12 | BX20: 17.34 | BY20: 18.38 | BZ20: 17.31 | CA20: 16.5 | CB20: 21.69 | CC20: 22.35 | CD20: 21.94 | CE20: 28.05 | CF20: 26.47 | CG20: 29.65 | CH20: 29.76 | CI20: 35.58 | CJ20: 37.56 | CK20: 45.62 | CL20: 40.18 | CM20: 42.11 | CN20: 47.67 | CO20: 50.24 | CP20: 51.9 | CQ20: 49.15 | CR20: 45.1 | CS20: 37.49 | CT20: 37.13 | CU20: 35.35 | CV20: 40.55 | CW20: 40.12 | CX20: 36.46 | CY20: 43.1 | CZ20: 44.82 | DA20: 42.09 | DB20: 53.88 | DC20: 55.05 | DD20: 56.59 | DE20: 58.08 | DF20: 59.45 | DG20: 60.95 | DH20: 59.8 | DI20: 60.62 | DJ20: 57.9 | DK20: 46.7 | DL20: 53.41 | DM20: 57.11 | DN20: 57.51 | DO20: 51.14 | DP20: 45.58 | DQ20: 45.29 | DR20: 43.42 | DS20: 44.27 | DT20: 41.49 | DU20: 36.2 | DV20: 39.24 | DW20: 41.73 | DX20: 45.86 | DY20: 43.84
A21: ATZ | B21: =A21&" CN Equity" -> ATZ CN Equity | C21: Aritzia Inc | D21: -- | E21: -- | F21: 107.33 | G21: 42005 | H21: 45657 | I21: Consumer Discretionary | AD21: =_xll.BDH(B21, "PX_LAST", "2015-01-01", "2024-12-31", "Period=M", "Orientation=H", "CshAdjNormal = Y","CapChg = Y", "DTS=H","cols=100;rows=1") -> #N/A Requesting Data... | AE21: 18.3 | AF21: 17.69 | AG21: 17.5 | AH21: 16.38 | AI21: 15.88 | AJ21: 15.53 | AK21: 15 | AL21: 15.3 | AM21: 15.02 | AN21: 13.29 | AO21: 12.55 | AP21: 14.85 | AQ21: 10.95 | AR21: 12.07 | AS21: 12.69 | AT21: 13.32 | AU21: 12.55 | AV21: 12.06 | AW21: 12.23 | AX21: 13.8 | AY21: 15.6 | AZ21: 16.05 | BA21: 16.31 | BB21: 17.11 | BC21: 19.37 | BD21: 18.27 | BE21: 16.4 | BF21: 17.03 | BG21: 16.16 | BH21: 17.76 | BI21: 19.43 | BJ21: 17.75 | BK21: 16.78 | BL21: 18.29 | BM21: 16.96 | BN21: 16.79 | BO21: 18.77 | BP21: 18.87 | BQ21: 19.05 | BR21: 25.03 | BS21: 22.12 | BT21: 12.31 | BU21: 16.57 | BV21: 18.14 | BW21: 19.01 | BX21: 17.73 | BY21: 18.68 | BZ21: 17.43 | CA21: 20.12 | CB21: 23.33 | CC21: 25.79 | CD21: 26.6 | CE21: 29.99 | CF21: 29.2 | CG21: 30.67 | CH21: 29.49 | CI21: 37.08 | CJ21: 36.59 | CK21: 41.23 | CL21: 40.32 | CM21: 48.74 | CN21: 50.62 | CO21: 52.35 | CP21: 58.97 | CQ21: 48.19 | CR21: 51.03 | CS21: 45.75 | CT21: 36.92 | CU21: 34.85 | CV21: 40.4 | CW21: 42.72 | CX21: 45.39 | CY21: 52.84 | CZ21: 51.17 | DA21: 47.35 | DB21: 47.99 | DC21: 41.54 | DD21: 43.37 | DE21: 43.06 | DF21: 34.77 | DG21: 36.78 | DH21: 25.09 | DI21: 24.8 | DJ21: 23.63 | DK21: 21.57 | DL21: 26.32 | DM21: 27.5 | DN21: 32.71 | DO21: 35.89 | DP21: 37.4 | DQ21: 35.64 | DR21: 34.05 | DS21: 38.72 | DT21: 45.32 | DU21: 46.1 | DV21: 50.83 | DW21: 44.83 | DX21: 46.64 | DY21: 53.44
A22: AYA | B22: =A22&" CN Equity" -> AYA CN Equity | C22: Aya Gold & Silver Inc | D22: -- | E22: -- | F22: 22.1 | G22: 42005 | H22: 45657 | I22: Materials | J22: 1.02 | K22: 0.92 | L22: 0.94 | M22: 0.84 | N22: 0.86 | O22: 0.98 | P22: 0.9 | Q22: 0.74 | R22: 0.72 | S22: 0.62 | T22: 0.6 | U22: 0.48 | V22: 0.46 | W22: 0.52 | X22: 0.56 | Y22: 0.68 | Z22: 0.6 | AA22: 0.62 | AB22: 0.6 | AC22: 0.7 | AD22: 0.68 | AE22: 0.56 | AF22: 0.48 | AG22: 0.56 | AH22: 0.58 | AI22: 0.52 | AJ22: 0.56 | AK22: 0.56 | AL22: 0.58 | AM22: 0.74 | AN22: 0.82 | AO22: 1.6 | AP22: 1.52 | AQ22: 1.28 | AR22: 1.58 | AS22: 1.64 | AT22: 2.8 | AU22: 2.4 | AV22: 2.1 | AW22: 2.9 | AX22: 2.5 | AY22: 2.6 | AZ22: 2.58 | BA22: 2.25 | BB22: 2.35 | BC22: 2.43 | BD22: 2.08 | BE22: 1.91 | BF22: 1.92 | BG22: 2.6 | BH22: 2.2 | BI22: 2.3 | BJ22: 2.15 | BK22: 1.91 | BL22: 1.92 | BM22: 1.98 | BN22: 1.75 | BO22: 1.83 | BP22: 1.71 | BQ22: 1.95 | BR22: 1.77 | BS22: 0.82 | BT22: 0.97 | BU22: 1.97 | BV22: 2.1 | BW22: 1.43 | BX22: 2 | BY22: 2.5 | BZ22: 2.61 | CA22: 3.04 | CB22: 2.87 | CC22: 3.85 | CD22: 4.55 | CE22: 4.77 | CF22: 4.93 | CG22: 7.55 | CH22: 7.35 | CI22: 9.18 | CJ22: 10.28 | CK22: 10.04 | CL22: 7.79 | CM22: 9.22 | CN22: 9.72 | CO22: 9.55 | CP22: 8.59 | CQ22: 10.13 | CR22: 8.92 | CS22: 8.04 | CT22: 7.03 | CU22: 6.56 | CV22: 7.38 | CW22: 7.67 | CX22: 8.01 | CY22: 7.9 | CZ22: 8.28 | DA22: 9.02 | DB22: 8.09 | DC22: 8 | DD22: 10.88 | DE22: 10.78 | DF22: 9.39 | DG22: 8.49 | DH22: 8.4 | DI22: 8.27 | DJ22: 7.29 | DK22: 7.51 | DL22: 9.97 | DM22: 9.71 | DN22: 10.31 | DO22: 9.76 | DP22: 11.66 | DQ22: 13.24 | DR22: 15.01 | DS22: 13.58 | DT22: 15.58 | DU22: 14.97 | DV22: 17.6 | DW22: 17.89 | DX22: 13.18 | DY22: 10.74
A23: BAM | B23: =A23&" CN Equity" -> BAM CN Equity | C23: Brookfield Asset Management Lt | D23: -- | E23: -- | F23: 67.65 | G23: 42005 | H23: 45657 | I23: Financials | DA23: =_xll.BDH(B23, "PX_LAST", "2015-01-01", "2024-12-31", "Period=M", "Orientation=H", "CshAdjNormal = Y","CapChg = Y", "DTS=H","cols=25;rows=1") -> #N/A Requesting Data... | DB23: 39.1259 | DC23: 41.7445 | DD23: 40.2533 | DE23: 41.2989 | DF23: 38.1228 | DG23: 39.7212 | DH23: 40.8603 | DI23: 43.2928 | DJ23: 41.9668 | DK23: 36.8577 | DL23: 44.468 | DM23: 49.7937 | DN23: 50.5986 | DO23: 52.2528 | DP23: 53.7549 | DQ23: 49.6831 | DR23: 51.0323 | DS23: 49.6778 | DT23: 57.4805 | DU23: 52.8958 | DV23: 61.532 | DW23: 71.1214 | DX23: 77.8361 | DY23: 75.5585
A24: BB | B24: =A24&" CN Equity" -> BB CN Equity | C24: BlackBerry Ltd | D24: -- | E24: -- | F24: 4.85 | G24: 42005 | H24: 45657 | I24: Information Technology | J24: 12.91 | K24: 13.54 | L24: 11.29 | M24: 12.25 | N24: 12.21 | O24: 10.21 | P24: 10.13 | Q24: 9.98 | R24: 8.19 | S24: 9.53 | T24: 10.62 | U24: 12.84 | V24: 9.97 | W24: 10.56 | X24: 10.54 | Y24: 8.86 | Z24: 9.54 | AA24: 8.67 | AB24: 9.9 | AC24: 9.95 | AD24: 10.46 | AE24: 9.47 | AF24: 10.34 | AG24: 9.24 | AH24: 9.18 | AI24: 9.23 | AJ24: 10.3 | AK24: 12.75 | AL24: 14.28 | AM24: 12.96 | AN24: 11.69 | AO24: 11.57 | AP24: 13.95 | AQ24: 14.12 | AR24: 13.92 | AS24: 14.04 | AT24: 15.6 | AU24: 15.57 | AV24: 14.81 | AW24: 13.44 | AX24: 15.35 | AY24: 12.68 | AZ24: 12.77 | BA24: 13.89 | BB24: 14.62 | BC24: 12.15 | BD24: 11.68 | BE24: 9.71 | BF24: 10.58 | BG24: 11.44 | BH24: 13.47 | BI24: 12.29 | BJ24: 10.61 | BK24: 9.76 | BL24: 9.63 | BM24: 9.14 | BN24: 6.94 | BO24: 6.92 | BP24: 7.33 | BQ24: 8.35 | BR24: 8.06 | BS24: 6.93 | BT24: 5.77 | BU24: 5.94 | BV24: 6.4 | BW24: 6.65 | BX24: 6.35 | BY24: 6.8 | BZ24: 6.11 | CA24: 5.98 | CB24: 7.65 | CC24: 8.44 | CD24: 17.96 | CE24: 12.87 | CF24: 10.54 | CG24: 10.87 | CH24: 12.4 | CI24: 15.15 | CJ24: 12.7 | CK24: 14.38 | CL24: 12.33 | CM24: 13.37 | CN24: 12.17 | CO24: 11.82 | CP24: 10.46 | CQ24: 8.7 | CR24: 9.27 | CS24: 7.35 | CT24: 7.62 | CU24: 6.94 | CV24: 7.87 | CW24: 7.8 | CX24: 6.51 | CY24: 6.33 | CZ24: 6.52 | DA24: 4.41 | DB24: 5.69 | DC24: 5.3 | DD24: 6.2 | DE24: 5.28 | DF24: 7.29 | DG24: 7.34 | DH24: 6.71 | DI24: 7.54 | DJ24: 6.43 | DK24: 4.99 | DL24: 4.98 | DM24: 4.61 | DN24: 3.77 | DO24: 3.8 | DP24: 3.71 | DQ24: 3.85 | DR24: 3.8 | DS24: 3.42 | DT24: 3.33 | DU24: 3.17 | DV24: 3.56 | DW24: 3.15 | DX24: 3.68 | DY24: 5.46
A25: BBD/B | B25: =A25&" CN Equity" -> BBD/B CN Equity | C25: Bombardier Inc | D25: -- | E25: -- | F25: 232.61 | G25: 42005 | H25: 45657 | I25: Industrials | J25: 72.5 | K25: 65 | L25: 62.5 | M25: 61 | N25: 64.5 | O25: 56.75 | P25: 40.75 | Q25: 32.25 | R25: 41.75 | S25: 35.5 | T25: 32.5 | U25: 33.5 | V25: 23.5 | W25: 26.5 | X25: 32.75 | Y25: 47.25 | Z25: 49.25 | AA25: 48.5 | AB25: 49 | AC25: 53.75 | AD25: 45 | AE25: 44.5 | AF25: 47 | AG25: 54.25 | AH25: 62.25 | AI25: 57.5 | AJ25: 51 | AK25: 52.75 | AL25: 61 | AM25: 59 | AN25: 62.75 | AO25: 62.5 | AP25: 56.5 | AQ25: 68.25 | AR25: 75 | AS25: 75.75 | AT25: 87 | AU25: 101.5 | AV25: 93.75 | AW25: 99.25 | AX25: 122 | AY25: 130 | AZ25: 122.5 | BA25: 107.75 | BB25: 115 | BC25: 79.75 | BD25: 55.5 | BE25: 50.75 | BF25: 49.75 | BG25: 70 | BH25: 64.25 | BI25: 57.25 | BJ25: 50.75 | BK25: 55 | BL25: 56.75 | BM25: 43 | BN25: 44.75 | BO25: 41.5 | BP25: 49.25 | BQ25: 48.25 | BR25: 30.75 | BS25: 24 | BT25: 11.375 | BU25: 12.25 | BV25: 11.375 | BW25: 10.5 | BX25: 11.625 | BY25: 10.25 | BZ25: 8.25 | CA25: 7.125 | CB25: 13.25 | CC25: 12 | CD25: 15.25 | CE25: 14 | CF25: 24.25 | CG25: 23 | CH25: 24.5 | CI25: 29.75 | CJ25: 37.25 | CK25: 46 | CL25: 54 | CM25: 49.75 | CN25: 43.25 | CO25: 42 | CP25: 42.25 | CQ25: 39.5 | CR25: 36 | CS25: 31.5 | CT25: 29.75 | CU25: 19.32 | CV25: 21.41 | CW25: 32.68 | CX25: 24.73 | CY25: 40.01 | CZ25: 47.39 | DA25: 52.27 | DB25: 64.27 | DC25: 68.09 | DD25: 73.78 | DE25: 58.52 | DF25: 53.82 | DG25: 65.31 | DH25: 66 | DI25: 55.12 | DJ25: 47.36 | DK25: 44.49 | DL25: 46.86 | DM25: 53.21 | DN25: 49.69 | DO25: 49.16 | DP25: 58.15 | DQ25: 62.72 | DR25: 91.75 | DS25: 87.73 | DT25: 93.18 | DU25: 92.56 | DV25: 102.91 | DW25: 102.42 | DX25: 96.77 | DY25: 97.75
A26: BBU-U | B26: =A26&" CN Equity" -> BBU-U CN Equity | C26: Brookfield Business Partners L | D26: -- | E26: -- | F26: 47.65 | G26: 42005 | H26: 45657 | I26: Industrials | Z26: =_xll.BDH(B26, "PX_LAST", "2015-01-01", "2024-12-31", "Period=M", "Orientation=H", "CshAdjNormal = Y","CapChg = Y", "DTS=H","cols=104;rows=1") -> #N/A Requesting Data... | AA26: 14.2564 | AB26: 16.1701 | AC26: 17.5154 | AD26: 20.1292 | AE26: 18.1572 | AF26: 20.716 | AG26: 18.8678 | AH26: 18.9556 | AI26: 19.7046 | AJ26: 19.3177 | AK26: 21.0941 | AL26: 21.0378 | AM26: 20.6088 | AN26: 20.4207 | AO26: 22.1955 | AP26: 21.7892 | AQ26: 22.2309 | AR26: 23.4502 | AS26: 25.545 | AT26: 28.3066 | AU26: 25.9329 | AV26: 27.4522 | AW26: 26.53 | AX26: 30.5447 | AY26: 29.8342 | AZ26: 30.1776 | BA26: 33.3984 | BB26: 35.1059 | BC26: 31.4299 | BD26: 27.8207 | BE26: 24.6965 | BF26: 24.7678 | BG26: 29.07 | BH26: 31.5034 | BI26: 30.7776 | BJ26: 29.9182 | BK26: 30.3891 | BL26: 29.8706 | BM26: 25.4983 | BN26: 30.992 | BO26: 30.7353 | BP26: 33.2153 | BQ26: 32.1329 | BR26: 33.2811 | BS26: 31.192 | BT26: 21.3157 | BU26: 26.155 | BV26: 25.506 | BW26: 25.0799 | BX26: 21.3591 | BY26: 24.5207 | BZ26: 24.4245 | CA26: 23.3782 | CB26: 27.805 | CC26: 29.0881 | CD26: 27.8894 | CE26: 31.4522 | CF26: 30.6017 | CG26: 32.4295 | CH26: 33.5727 | CI26: 34.6117 | CJ26: 33.2828 | CK26: 32.5751 | CL26: 34.9646 | CM26: 36.3801 | CN26: 34.9202 | CO26: 35.1625 | CP26: 33.7088 | CQ26: 33.0281 | CR26: 36.4979 | CS26: 29.3743 | CT26: 28.0606 | CU26: 26.124 | CV26: 23.9574 | CW26: 27.0927 | CX26: 26.0159 | CY26: 29.0348 | CZ26: 24.4734 | DA26: 22.0811 | DB26: 26.6246 | DC26: 23.7878 | DD26: 24.1169 | DE26: 21.9676 | DF26: 24.3828 | DG26: 22.3526 | DH26: 21.964 | DI26: 19.7703 | DJ26: 20.1116 | DK26: 16.6784 | DL26: 22.3273 | DM26: 26.7829 | DN26: 28.4281 | DO26: 28.6971 | DP26: 29.4631 | DQ26: 25.3088 | DR26: 24.1544 | DS26: 25.5341 | DT26: 27.3967 | DU26: 27.55 | DV26: 31.3459 | DW26: 30.822 | DX26: 36.0572 | DY26: 33.59
A27: BCE | B27: =A27&" CN Equity" -> BCE CN Equity | C27: BCE Inc | D27: -- | E27: -- | F27: 35.2 | G27: 42005 | H27: 45657 | I27: Communication Services | J27: 30.49 | K27: 28.587 | L27: 28.362 | M27: 28.135 | N27: 28.828 | O27: 28.416 | P27: 28.817 | Q27: 28.48 | R27: 29.595 | S27: 30.625 | T27: 31.145 | U27: 29.31 | V27: 30.939 | W27: 32.041 | X27: 32.833 | Y27: 32.639 | Z27: 33.532 | AA27: 34.306 | AB27: 35.086 | AC27: 34.379 | AD27: 34.38 | AE27: 34.579 | AF27: 32.848 | AG27: 33.314 | AH27: 33.676 | AI27: 33.262 | AJ27: 34.221 | AK27: 36.122 | AL27: 35.575 | AM27: 34.349 | AN27: 34.419 | AO27: 34.96 | AP27: 34.813 | AQ27: 35.474 | AR27: 36.766 | AS27: 36.372 | AT27: 34.649 | AU27: 33.733 | AV27: 33.841 | AW27: 33.261 | AX27: 32.968 | AY27: 32.95 | AZ27: 34.212 | BA27: 32.944 | BB27: 32.856 | BC27: 31.99 | BD27: 35.757 | BE27: 34.317 | BF27: 36.353 | BG27: 37.237 | BH27: 38.268 | BI27: 38.655 | BJ27: 39.248 | BK27: 38.916 | BL27: 38.955 | BM27: 41.15 | BN27: 42.378 | BO27: 41.319 | BP27: 42.285 | BQ27: 40.282 | BR27: 41.755 | BS27: 39.472 | BT27: 39.3 | BU27: 38.319 | BV27: 38.959 | BW27: 39.107 | BX27: 38.789 | BY27: 38.72 | BZ27: 38.706 | CA27: 37.528 | CB27: 39.463 | CC27: 38.702 | CD27: 38.567 | CE27: 38.702 | CF27: 40.961 | CG27: 42.239 | CH27: 43.192 | CI27: 44.773 | CJ27: 45.608 | CK27: 48.193 | CL27: 47.09 | CM27: 47.283 | CN27: 47.714 | CO27: 49.5 | CP27: 49.944 | CQ27: 50.072 | CR27: 52.816 | CS27: 52.054 | CT27: 52.519 | CU27: 48.902 | CV27: 50.007 | CW27: 48.894 | CX27: 45.435 | CY27: 48.205 | CZ27: 50.252 | DA27: 47.294 | DB27: 50.072 | DC27: 48.058 | DD27: 48.982 | DE27: 52.687 | DF27: 49.54 | DG27: 49.646 | DH27: 46.818 | DI27: 47.048 | DJ27: 43.369 | DK27: 43.059 | DL27: 44.69 | DM27: 44.413 | DN27: 46.184 | DO27: 42.906 | DP27: 40.014 | DQ27: 39.319 | DR27: 40.527 | DS27: 39.36 | DT27: 41.368 | DU27: 41.936 | DV27: 42.652 | DW27: 40.72 | DX27: 34.379 | DY27: 31.078
A28: BDGI | B28: =A28&" CN Equity" -> BDGI CN Equity | C28: Badger Infrastructure Solution | D28: -- | E28: -- | F28: 76.99 | G28: 42005 | H28: 45657 | I28: Industrials | J28: 18.7 | K28: 20.323 | L28: 22.4274 | M28: 24.8593 | N28: 23.9375 | O28: 21.7919 | P28: 20.3035 | Q28: 17.306 | R28: 16.2961 | S28: 17.1417 | T28: 20.6238 | U28: 20.4896 | V28: 20.2556 | W28: 20.6514 | X28: 18.5233 | Y28: 19.7117 | Z28: 20.2547 | AA28: 19.0342 | AB28: 17.3868 | AC28: 22.202 | AD28: 24.0799 | AE28: 24.6425 | AF28: 26.6018 | AG28: 27.3539 | AH28: 28.1312 | AI28: 28.2688 | AJ28: 29.8692 | AK28: 27.7839 | AL28: 20.0023 | AM28: 22.8329 | AN28: 22.7413 | AO28: 24.8702 | AP28: 22.8826 | AQ28: 25.3269 | AR28: 24.5062 | AS28: 23.5029 | AT28: 21.8924 | AU28: 20.8328 | AV28: 22.3874 | AW28: 21.5229 | AX28: 25.4269 | AY28: 27.6448 | AZ28: 25.8156 | BA28: 25.4004 | BB28: 25.957 | BC28: 23.3668 | BD28: 28.036 | BE28: 28.4116 | BF28: 30.8383 | BG28: 33.7627 | BH28: 35.9157 | BI28: 39.9991 | BJ28: 42.3601 | BK28: 42.3765 | BL28: 42.3132 | BM28: 37.4993 | BN28: 36.2083 | BO28: 34.7671 | BP28: 32.413 | BQ28: 31.3926 | BR28: 30.8891 | BS28: 28.1316 | BT28: 20.4468 | BU28: 27.2126 | BV28: 25.9163 | BW28: 26.8283 | BX28: 26.1959 | BY28: 33.8365 | BZ28: 34.5242 | CA28: 35.0952 | CB28: 35.213 | CC28: 34.6141 | CD28: 34.0211 | CE28: 36.9563 | CF28: 39.1671 | CG28: 38.0361 | CH28: 35.3668 | CI28: 34.5086 | CJ28: 32.0164 | CK28: 31.7248 | CL28: 31.1905 | CM28: 31.5145 | CN28: 28.9781 | CO28: 29.4334 | CP28: 28.5075 | CQ28: 28.1279 | CR28: 29.2814 | CS28: 27.6898 | CT28: 27.5409 | CU28: 26.4374 | CV28: 28.7685 | CW28: 28.9557 | CX28: 26.4992 | CY28: 27.0923 | CZ28: 26.5651 | DA28: 25.267 | DB28: 30.0436 | DC28: 28.8684 | DD28: 31.1426 | DE28: 28.2933 | DF28: 25.6345 | DG28: 25.8064 | DH28: 30.795 | DI28: 34.0472 | DJ28: 33.4496 | DK28: 35.4166 | DL28: 39.4954 | DM28: 39.42 | DN28: 45.2396 | DO28: 45.0847 | DP28: 48.7814 | DQ28: 43.6797 | DR28: 39.7733 | DS28: 40.1987 | DT28: 38.0614 | DU28: 35.114 | DV28: 36.0581 | DW28: 35.5187 | DX28: 37.0976 | DY28: 35.3644
A29: BDT | B29: =A29&" CN Equity" -> BDT CN Equity | C29: Bird Construction Inc | D29: -- | E29: -- | F29: 30.16 | G29: 42005 | H29: 45657 | I29: Industrials | J29: 6.48 | K29: 7.188 | L29: 5.5643 | M29: 6.7899 | N29: 6.7923 | O29: 6.6885 | P29: 6.62 | Q29: 7.3189 | R29: 7.3267 | S29: 8.0453 | T29: 8.7778 | U29: 8.0518 | V29: 7.1993 | W29: 7.4185 | X29: 6.975 | Y29: 7.3595 | Z29: 8.48 | AA29: 8.5402 | AB29: 8.6455 | AC29: 7.3648 | AD29: 7.3676 | AE29: 7.1813 | AF29: 6.1122 | AG29: 5.9962 | AH29: 6.018 | AI29: 5.9129 | AJ29: 6.6943 | AK29: 6.3947 | AL29: 5.6446 | AM29: 5.7611 | AN29: 5.7488 | AO29: 6.0487 | AP29: 6.7996 | AQ29: 6.7059 | AR29: 6.8316 | AS29: 6.9989 | AT29: 6.4687 | AU29: 6.1723 | AV29: 5.9665 | AW29: 6.081 | AX29: 5.123 | AY29: 5.1318 | AZ29: 5.515 | BA29: 5.4947 | BB29: 5.6464 | BC29: 4.897 | BD29: 4.8415 | BE29: 4.4422 | BF29: 4.6549 | BG29: 4.9344 | BH29: 5.8104 | BI29: 5.8636 | BJ29: 4.1926 | BK29: 4.2319 | BL29: 4.0913 | BM29: 4.0941 | BN29: 4.3309 | BO29: 4.7142 | BP29: 5.1377 | BQ29: 5.5075 | BR29: 5.0465 | BS29: 4.5592 | BT29: 3.5736 | BU29: 4.0701 | BV29: 4.5131 | BW29: 4.7449 | BX29: 5.4974 | BY29: 5.4992 | BZ29: 5.2042 | CA29: 5.1906 | CB29: 5.9082 | CC29: 6.5641 | CD29: 6.754 | CE29: 7.1017 | CF29: 7.4271 | CG29: 7.5449 | CH29: 7.9795 | CI29: 7.4059 | CJ29: 7.1901 | CK29: 8.3463 | CL29: 8.3396 | CM29: 8.5707 | CN29: 8.0787 | CO29: 8.4051 | CP29: 8.2627 | CQ29: 8.1884 | CR29: 7.897 | CS29: 7.4668 | CT29: 7.3041 | CU29: 6.5385 | CV29: 6.4014 | CW29: 5.8577 | CX29: 5.2946 | CY29: 5.4831 | CZ29: 6.6563 | DA29: 7.3143 | DB29: 7.6854 | DC29: 8.2214 | DD29: 8.281 | DE29: 7.8397 | DF29: 7.6794 | DG29: 7.786 | DH29: 8.2148 | DI29: 10.1561 | DJ29: 9.5949 | DK29: 9.9749 | DL29: 11.1693 | DM29: 13.5493 | DN29: 14.439 | DO29: 16.1041 | DP29: 17.6607 | DQ29: 17.9793 | DR29: 20.6168 | DS29: 25.5732 | DT29: 24.7311 | DU29: 21.9481 | DV29: 23.1621 | DW29: 29.1144 | DX29: 29.7009 | DY29: 25.1579
A30: BEI-U | B30: =A30&" CN Equity" -> BEI-U CN Equity | C30: Boardwalk Real Estate Investme | D30: -- | E30: -- | F30: 68.85 | G30: 42005 | H30: 45657 | I30: Real Estate | J30: 45.12 | K30: 43.2796 | L30: 43.1845 | M30: 44.6343 | N30: 42.9587 | O30: 41.8434 | P30: 42.6569 | Q30: 40.5424 | R30: 40.8875 | S30: 40.193 | T30: 35.6013 | U30: 35.7564 | V30: 33.3236 | W30: 37.6 | X30: 39.4852 | Y30: 41.0846 | Z30: 40.7799 | AA30: 44.3498 | AB30: 43.3641 | AC30: 39.1033 | AD30: 40.308 | AE30: 38.4802 | AF30: 35.0183 | AG30: 38.3497 | AH30: 37.3453 | AI30: 35.3435 | AJ30: 37.6389 | AK30: 36.8941 | AL30: 38.5673 | AM30: 38.3936 | AN30: 38.7568 | AO30: 32.8878 | AP30: 31.1087 | AQ30: 32.7366 | AR30: 33.2897 | AS30: 35.7608 | AT30: 37.0002 | AU30: 37.9507 | AV30: 36.9465 | AW30: 38.5538 | AX30: 39.7779 | AY30: 38.3242 | AZ30: 38.4703 | BA30: 41.7343 | BB30: 42.3179 | BC30: 41.4112 | BD30: 35.1272 | BE30: 32.0817 | BF30: 34.1211 | BG30: 35.0768 | BH30: 34.8154 | BI30: 33.2734 | BJ30: 34.875 | BK30: 34.2269 | BL30: 36.1465 | BM30: 38.1121 | BN30: 38.3744 | BO30: 37.8157 | BP30: 42.0868 | BQ30: 39.9034 | BR30: 41.0957 | BS30: 39.7004 | BT30: 20.0493 | BU30: 23.3415 | BV30: 25.7043 | BW30: 26.2306 | BX30: 27.1153 | BY30: 26.8438 | BZ30: 24.44 | CA30: 23.9197 | CB30: 31.0036 | CC30: 30.2815 | CD30: 31.1448 | CE30: 33.1259 | CF30: 32.8133 | CG30: 33.2037 | CH30: 35.2547 | CI30: 37.1833 | CJ30: 41.6265 | CK30: 42.9879 | CL30: 43.2447 | CM30: 48.9003 | CN30: 48.7998 | CO30: 50.3719 | CP30: 51.4706 | CQ30: 52.0198 | CR30: 54.2596 | CS30: 52.11 | CT30: 46.4511 | CU30: 38.8664 | CV30: 45.4125 | CW30: 44.9939 | CX30: 43.1804 | CY30: 45.3365 | CZ30: 46.6925 | DA30: 46.3945 | DB30: 52.854 | DC30: 55.5816 | DD30: 52.0124 | DE30: 54.8032 | DF30: 57.2019 | DG30: 58.9511 | DH30: 62.1894 | DI30: 64.9982 | DJ30: 63.6097 | DK30: 61.7519 | DL30: 63.7726 | DM30: 68.2206 | DN30: 66.8395 | DO30: 72.8967 | DP30: 74.979 | DQ30: 68.1673 | DR30: 67.8037 | DS30: 68.0274 | DT30: 75.4002 | DU30: 83.5422 | DV30: 83.0389 | DW30: 70.2017 | DX30: 69.4453 | DY30: 62.6097
A31: BEP-U | B31: =A31&" CN Equity" -> BEP-U CN Equity | C31: Brookfield Renewable Partners | D31: -- | E31: -- | F31: 40.62 | G31: 42005 | H31: 45657 | I31: Utilities | J31: 12.34 | K31: 11.6847 | L31: 12.1684 | M31: 12.0011 | N31: 11.6402 | O31: 11.4552 | P31: 11.6896 | Q31: 11.6502 | R31: 11.4937 | S31: 10.7892 | T31: 10.6956 | U31: 11.5455 | V31: 11.7906 | W31: 11.484 | X31: 12.7075 | Y31: 11.7591 | Z31: 12.4651 | AA31: 12.6392 | AB31: 13.3458 | AC31: 13.1641 | AD31: 13.4408 | AE31: 13.6476 | AF31: 13.2211 | AG31: 13.492 | AH31: 13.2719 | AI31: 13.4102 | AJ31: 13.5478 | AK31: 14.3283 | AL31: 14.7951 | AM31: 14.4287 | AN31: 14.6904 | AO31: 15.3 | AP31: 14.7837 | AQ31: 15.3813 | AR31: 15.2378 | AS31: 15.7111 | AT31: 14.7321 | AU31: 14.437 | AV31: 14.59 | AW31: 14.2003 | AX31: 14.8001 | AY31: 14.5966 | AZ31: 14.604 | BA31: 15.0687 | BB31: 14.7043 | BC31: 13.4796 | BD31: 14.5377 | BE31: 13.5097 | BF31: 14.4307 | BG31: 15.3992 | BH31: 16.5616 | BI31: 16.41 | BJ31: 17.18 | BK31: 17.8908 | BL31: 18.6649 | BM31: 19.9498 | BN31: 21.5436 | BO31: 22.4405 | BP31: 25.0888 | BQ31: 24.4166 | BR31: 26.1619 | BS31: 27.4191 | BT31: 24.2157 | BU31: 26.8872 | BV31: 27.8844 | BW31: 26.8915 | BX31: 29.878 | BY31: 30.9717 | BZ31: 36.659 | CA31: 37.8112 | CB31: 43.5283 | CC31: 43.4676 | CD31: 45.9199 | CE31: 42.9827 | CF31: 42.7437 | CG31: 38.5052 | CH31: 38.6519 | CI31: 38.4512 | CJ31: 39.4306 | CK31: 41.3435 | CL31: 37.8497 | CM31: 40.1223 | CN31: 37.8528 | CO31: 36.9556 | CP31: 34.7371 | CQ31: 37.5101 | CR31: 42.2442 | CS31: 37.2384 | CT31: 37.3672 | CU31: 37.1513 | CV31: 40.1496 | CW31: 40.9434 | CX31: 36.1438 | CY31: 33.1116 | CZ31: 32.1591 | DA31: 29.0338 | DB31: 32.8197 | DC31: 30.598 | DD31: 36.5426 | DE31: 35.865 | DF31: 35.6345 | DG31: 33.874 | DH31: 33.319 | DI31: 30.0047 | DJ31: 25.9204 | DK31: 25.5866 | DL31: 29.8725 | DM31: 30.9944 | DN31: 31.0389 | DO31: 27.5314 | DP31: 28.5082 | DQ31: 26.1385 | DR31: 34.8628 | DS31: 31.0146 | DT31: 30.8222 | DU31: 30.7096 | DV31: 35.4499 | DW31: 33.2936 | DX31: 34.2637 | DY31: 30.8439
A32: BHC | B32: =A32&" CN Equity" -> BHC CN Equity | C32: Bausch Health Cos Inc | D32: -- | E32: -- | F32: 7.81 | G32: 42005 | H32: 45657 | I32: Health Care | J32: 203.17 | K32: 246.27 | L32: 250.21 | M32: 261.63 | N32: 296.44 | O32: 277.47 | P32: 335.612 | Q32: 304.99 | R32: 238.2 | S32: 120.94 | T32: 120.35 | U32: 139 | V32: 127.49 | W32: 90 | X32: 34.05 | Y32: 41.83 | Z32: 37.42 | AA32: 26.05 | AB32: 29.08 | AC32: 38.09 | AD32: 32.19 | AE32: 23.94 | AF32: 21.24 | AG32: 19.47 | AH32: 17.96 | AI32: 18.89 | AJ32: 14.69 | AK32: 12.65 | AL32: 16.4 | AM32: 22.54 | AN32: 20.54 | AO32: 16.79 | AP32: 17.88 | AQ32: 15.07 | AR32: 21.73 | AS32: 26.2 | AT32: 22.78 | AU32: 21.01 | AV32: 20.51 | AW32: 23.18 | AX32: 28.53 | AY32: 30.6 | AZ32: 28.27 | BA32: 30.14 | BB32: 33.17 | BC32: 30.12 | BD32: 32.29 | BE32: 25.25 | BF32: 32.26 | BG32: 31.26 | BH32: 32.97 | BI32: 30.94 | BJ32: 28.06 | BK32: 33.04 | BL32: 31.71 | BM32: 28.37 | BN32: 28.9 | BO32: 32.74 | BP32: 37.52 | BQ32: 38.87 | BR32: 36.31 | BS32: 29.74 | BT32: 21.81 | BU32: 25.15 | BV32: 25.36 | BW32: 24.84 | BX32: 24.49 | BY32: 21.65 | BZ32: 20.7 | CA32: 21.95 | CB32: 24.11 | CC32: 26.41 | CD32: 32.63 | CE32: 40.05 | CF32: 39.87 | CG32: 39.57 | CH32: 38.16 | CI32: 36.38 | CJ32: 36.5 | CK32: 36.76 | CL32: 35.32 | CM32: 34.69 | CN32: 30.32 | CO32: 34.94 | CP32: 31.25 | CQ32: 30.49 | CR32: 28.56 | CS32: 24.41 | CT32: 12.29 | CU32: 10.76 | CV32: 5.9 | CW32: 7.84 | CX32: 9.54 | CY32: 8.86 | CZ32: 9.43 | DA32: 8.5 | DB32: 10.21 | DC32: 12.71 | DD32: 10.95 | DE32: 9.97 | DF32: 11.14 | DG32: 10.6 | DH32: 12.82 | DI32: 11.28 | DJ32: 11.2 | DK32: 9.44 | DL32: 9.68 | DM32: 10.63 | DN32: 10.54 | DO32: 12.77 | DP32: 14.35 | DQ32: 12.05 | DR32: 8.95 | DS32: 9.54 | DT32: 8.32 | DU32: 7.99 | DV32: 11.04 | DW32: 12.77 | DX32: 11.95 | DY32: 11.62
A33: BIP-U | B33: =A33&" CN Equity" -> BIP-U CN Equity | C33: Brookfield Infrastructure Part | D33: -- | E33: -- | F33: 49.29 | G33: 42005 | H33: 45657 | I33: Utilities | J33: 12.97 | K33: 13.944 | L33: 14.1376 | M33: 12.9658 | N33: 13.3586 | O33: 13.8077 | P33: 13.5372 | Q33: 13.0894 | R33: 12.3675 | S33: 13.8113 | T33: 14.1288 | U33: 13.3442 | V33: 12.8041 | W33: 13.1904 | X33: 14.153 | Y33: 13.682 | Z33: 14.7134 | AA33: 15.3297 | AB33: 16.1034 | AC33: 16.6668 | AD33: 18.1031 | AE33: 18.0792 | AF33: 17.1467 | AG33: 18.1018 | AH33: 18.3275 | AI33: 19.5371 | AJ33: 20.9766 | AK33: 21.9267 | AL33: 22.5249 | AM33: 21.89 | AN33: 20.7976 | AO33: 22.9466 | AP33: 22.4094 | AQ33: 22.7259 | AR33: 23.1506 | AS33: 23.7099 | AT33: 22.1918 | AU33: 21.9595 | AV33: 22.7765 | AW33: 22.3254 | AX33: 21.2633 | AY33: 21.7329 | AZ33: 22.9178 | BA33: 22.1837 | BB33: 22.4801 | BC33: 21.4339 | BD33: 22.3781 | BE33: 20.803 | BF33: 22.6384 | BG33: 23.4745 | BH33: 24.9307 | BI33: 24.7833 | BJ33: 25.2233 | BK33: 25.377 | BL33: 26.4168 | BM33: 28.5873 | BN33: 29.9765 | BO33: 30.1593 | BP33: 31.9264 | BQ33: 29.9241 | BR33: 33.2367 | BS33: 31.6522 | BT33: 25.728 | BU33: 28.1773 | BV33: 29.1669 | BW33: 29.094 | BX33: 29.1565 | BY33: 29.8949 | BZ33: 33.4218 | CA33: 30.0054 | CB33: 34.3014 | CC33: 33.4723 | CD33: 35.4865 | CE33: 34.8772 | CF33: 36.0042 | CG33: 35.5158 | CH33: 35.3798 | CI33: 37.2813 | CJ33: 36.5662 | CK33: 38.9378 | CL33: 38.9378 | CM33: 39.8288 | CN33: 40.0665 | CO33: 42.4717 | CP33: 41.3353 | CQ33: 41.8814 | CR33: 46.0907 | CS33: 44.6598 | CT33: 42.4154 | CU33: 41.4435 | CV33: 42.9941 | CW33: 46.8662 | CX33: 42.1073 | CY33: 41.9714 | CZ33: 43.2883 | DA33: 35.9863 | DB33: 40.2422 | DC33: 38.9973 | DD33: 39.6307 | DE33: 40.9845 | DF33: 42.7642 | DG33: 42.352 | DH33: 41.1768 | DI33: 38.1391 | DJ33: 35.3787 | DK33: 27.932 | DL33: 31.9886 | DM33: 37.6082 | DN33: 37.8694 | DO33: 35.3181 | DP33: 38.6434 | DQ33: 33.765 | DR33: 36.4871 | DS33: 34.8193 | DT33: 40.4249 | DU33: 40.7842 | DV33: 44.537 | DW33: 44.7622 | DX33: 46.9676 | DY33: 43.3518
A34: BIR | B34: =A34&" CN Equity" -> BIR CN Equity | C34: Birchcliff Energy Ltd | D34: -- | E34: -- | F34: 7.32 | G34: 42005 | H34: 45657 | I34: Energy | J34: 4.86 | K34: 4.93 | L34: 4.8443 | M34: 6.2304 | N34: 5.6516 | O34: 4.98 | P34: 4.2369 | Q34: 4.9157 | R34: 4.5585 | S34: 4.0726 | T34: 3.9154 | U34: 2.8865 | V34: 3.5939 | W34: 3.6153 | X34: 3.7797 | Y34: 3.7296 | Z34: 4.1012 | AA34: 4.9157 | AB34: 6.7448 | AC34: 6.4876 | AD34: 6.559 | AE34: 6.1018 | AF34: 6.4876 | AG34: 6.6948 | AH34: 5.7302 | AI34: 5.1158 | AJ34: 5.45 | AK34: 5.0269 | AL34: 4.5608 | AM34: 4.3999 | AN34: 4.3927 | AO34: 4.2559 | AP34: 4.3744 | AQ34: 3.796 | AR34: 3.608 | AS34: 3.2009 | AT34: 2.4807 | AU34: 2.2407 | AV34: 2.7355 | AW34: 3.4102 | AX34: 3.3516 | AY34: 3.5539 | AZ34: 3.7972 | BA34: 3.5023 | BB34: 3.8561 | BC34: 3.0774 | BD34: 2.6177 | BE34: 2.2728 | BF34: 2.3476 | BG34: 2.699 | BH34: 2.6815 | BI34: 2.6363 | BJ34: 2.3501 | BK34: 1.9771 | BL34: 1.9999 | BM34: 1.346 | BN34: 1.6461 | BO34: 1.5461 | BP34: 1.6923 | BQ34: 2.0141 | BR34: 1.3609 | BS34: 1.1742 | BT34: 0.6264 | BU34: 1.2287 | BV34: 1.1243 | BW34: 0.9192 | BX34: 0.9676 | BY34: 1.2902 | BZ34: 1.2381 | CA34: 1.5375 | CB34: 1.6589 | CC34: 1.4361 | CD34: 1.7526 | CE34: 2.4098 | CF34: 2.1209 | CG34: 2.5354 | CH34: 2.8767 | CI34: 4.2307 | CJ34: 3.832 | CK34: 4.4178 | CL34: 5.7079 | CM34: 5.4147 | CN34: 5.2845 | CO34: 5.2681 | CP34: 5.1131 | CQ34: 5.4964 | CR34: 6.8275 | CS34: 7.6768 | CT34: 9.3102 | CU34: 7.1582 | CV34: 8.05 | CW34: 9.4652 | CX34: 8.0396 | CY34: 8.6788 | CZ34: 8.8018 | DA34: 7.7448 | DB34: 7.0056 | DC34: 6.8907 | DD34: 6.4416 | DE34: 6.9041 | DF34: 6.4416 | DG34: 6.7634 | DH34: 6.7979 | DI34: 7.2033 | DJ34: 6.8457 | DK34: 6.7749 | DL34: 5.749 | DM34: 5.28 | DN34: 4.6589 | DO34: 4.9329 | DP34: 4.9684 | DQ34: 5.2662 | DR34: 5.7779 | DS34: 5.6838 | DT34: 5.6649 | DU34: 5.5703 | DV34: 5.4855 | DW34: 4.9947 | DX34: 5.091 | DY34: 5.3212
A35: BITF | B35: =A35&" CN Equity" -> BITF CN Equity | C35: Bitfarms Ltd/Canada | D35: -- | E35: -- | F35: 3.16 | G35: 42005 | H35: 45657 | I35: Information Technology | BL35: =_xll.BDH(B35, "PX_LAST", "2015-01-01", "2024-12-31", "Period=M", "Orientation=H", "CshAdjNormal = Y","CapChg = Y", "DTS=H","cols=66;rows=1") -> #N/A Requesting Data... | BM35: 1.34 | BN35: 0.87 | BO35: 0.74 | BP35: 0.67 | BQ35: 0.5 | BR35: 0.62 | BS35: 0.56 | BT35: 0.425 | BU35: 0.5 | BV35: 0.5 | BW35: 0.37 | BX35: 0.425 | BY35: 0.425 | BZ35: 0.305 | CA35: 0.52 | CB35: 0.8 | CC35: 2.5 | CD35: 3.33 | CE35: 5.98 | CF35: 6.24 | CG35: 6.64 | CH35: 5.23 | CI35: 4.87 | CJ35: 5.15 | CK35: 7.43 | CL35: 5.37 | CM35: 6.25 | CN35: 9.7 | CO35: 6.38 | CP35: 4.62 | CQ35: 4.81 | CR35: 4.71 | CS35: 3.7 | CT35: 2.54 | CU35: 1.44 | CV35: 1.83 | CW35: 1.74 | CX35: 1.44 | CY35: 1.31 | CZ35: 0.8 | DA35: 0.56 | DB35: 1.33 | DC35: 1.27 | DD35: 1.29 | DE35: 1.6 | DF35: 1.62 | DG35: 1.96 | DH35: 2.43 | DI35: 1.84 | DJ35: 1.46 | DK35: 1.47 | DL35: 1.96 | DM35: 3.85 | DN35: 3.11 | DO35: 3.89 | DP35: 3.01 | DQ35: 2.46 | DR35: 3.08 | DS35: 3.53 | DT35: 3.61 | DU35: 2.91 | DV35: 2.85 | DW35: 2.7 | DX35: 3.1 | DY35: 2.1
A36: BLX | B36: =A36&" CN Equity" -> BLX CN Equity | C36: Boralex Inc | D36: -- | E36: -- | F36: 25.25 | G36: 42005 | H36: 45657 | I36: Utilities | J36: 10.29 | K36: 9.8832 | L36: 10.135 | M36: 10.5701 | N36: 10.8533 | O36: 10.2294 | P36: 10.6992 | Q36: 10.3953 | R36: 9.9207 | S36: 10.8311 | T36: 10.4046 | U36: 11.3633 | V36: 12.0077 | W36: 12.806 | X36: 12.7585 | Y36: 13.02 | Z36: 14.2946 | AA36: 15.5483 | AB36: 15.9317 | AC36: 14.3945 | AD36: 15.0543 | AE36: 15.4808 | AF36: 14.1783 | AG36: 15.5328 | AH36: 16.0925 | AI36: 16.507 | AJ36: 17.5366 | AK36: 17.0709 | AL36: 18.1985 | AM36: 18.0669 | AN36: 18.3219 | AO36: 18.1001 | AP36: 17.8018 | AQ36: 18.9864 | AR36: 19.5761 | AS36: 19.5927 | AT36: 19.7095 | AU36: 19.7765 | AV36: 18.7697 | AW36: 19.2563 | AX36: 18.4253 | AY36: 17.7998 | AZ36: 16.8025 | BA36: 16.3728 | BB36: 15.3671 | BC36: 14.4892 | BD36: 15.3977 | BE36: 14.4859 | BF36: 16.0773 | BG36: 16.1335 | BH36: 16.4546 | BI36: 15.8731 | BJ36: 16.1652 | BK36: 17.2423 | BL36: 17.4787 | BM36: 18.2534 | BN36: 19.9746 | BO36: 19.242 | BP36: 22.0846 | BQ36: 21.738 | BR36: 24.5285 | BS36: 25.5976 | BT36: 22.3365 | BU36: 24.0787 | BV36: 25.751 | BW36: 27.7734 | BX36: 31.4046 | BY36: 30.2608 | BZ36: 34.7683 | CA36: 35.0032 | CB36: 37.2253 | CC36: 42.849 | CD36: 45.5066 | CE36: 40.3223 | CF36: 35.9878 | CG36: 35.8785 | CH36: 33.9621 | CI36: 34.5292 | CJ36: 35.9195 | CK36: 35.5241 | CL36: 34.3574 | CM36: 35.1842 | CN36: 33.4626 | CO36: 32.0045 | CP36: 30.5003 | CQ36: 34.313 | CR36: 37.5672 | CS36: 35.7036 | CT36: 35.9418 | CU36: 39.9167 | CV36: 43.2493 | CW36: 46.2329 | CX36: 40.9745 | CY36: 36.0803 | CZ36: 35.4738 | DA36: 37.5472 | DB36: 34.9296 | DC36: 34.2637 | DD36: 38.7883 | DE36: 37.233 | DF36: 35.5145 | DG36: 34.1511 | DH36: 32.3049 | DI36: 31.1885 | DJ36: 27.7633 | DK36: 24.5569 | DL36: 29.4975 | DM36: 32.2243 | DN36: 31.0284 | DO36: 28.7061 | DP36: 27.5417 | DQ36: 26.589 | DR36: 33.4447 | DS36: 32.4005 | DT36: 33.1257 | DU36: 31.3592 | DV36: 34.9645 | DW36: 32.5253 | DX36: 29.4507 | DY36: 28.0534
A37: BMO | B37: =A37&" CN Equity" -> BMO CN Equity | C37: Bank of Montreal | D37: -- | E37: -- | F37: 185.37 | G37: 42005 | H37: 45657 | I37: Financials | J37: 45.85 | K37: 48.6464 | L37: 47.6792 | M37: 49.9459 | N37: 48.1508 | O37: 46.9583 | P37: 46.8233 | Q37: 45.5914 | R37: 46.6949 | S37: 49.3015 | T37: 49.9953 | U37: 50.6242 | V37: 49.3292 | W37: 48.9554 | X37: 51.7228 | Y37: 54.1566 | Z37: 54.5276 | AA37: 54.2361 | AB37: 56.0195 | AC37: 58.2148 | AD37: 57.5388 | AE37: 57.7013 | AF37: 59.8441 | AG37: 65.279 | AH37: 67.1222 | AI37: 68.7315 | AJ37: 67.7359 | AK37: 66.5021 | AL37: 62.381 | AM37: 65.5114 | AN37: 65.6748 | AO37: 62.2369 | AP37: 65.5845 | AQ37: 69.2638 | AR37: 69.5721 | AS37: 70.4972 | AT37: 71.6653 | AU37: 68.9141 | AV37: 68.8292 | AW37: 69.6216 | AX37: 71.7136 | AY37: 72.5561 | AZ37: 74.306 | BA37: 77.0877 | BB37: 76.7778 | BC37: 71.6269 | BD37: 72.1363 | BE37: 64.903 | BF37: 70.669 | BG37: 75.4479 | BH37: 73.5143 | BI37: 78.5387 | BJ37: 72.8238 | BK37: 73.4176 | BL37: 74.0948 | BM37: 68.4402 | BN37: 73.1799 | BO37: 73.8891 | BP37: 77.4661 | BQ37: 76.2687 | BR37: 77.281 | BS37: 69.8385 | BT37: 54.4098 | BU37: 54.9663 | BV37: 52.7528 | BW37: 56.1236 | BX37: 57.7271 | BY37: 65.2108 | BZ37: 61.3192 | CA37: 63.3208 | CB37: 74.4955 | CC37: 77.2493 | CD37: 76.7534 | CE37: 83.9026 | CF37: 90.3902 | CG37: 94.4637 | CH37: 102.753 | CI37: 103.4614 | CJ37: 101.4394 | CK37: 103.1064 | CL37: 103.8373 | CM37: 111.1915 | CN37: 110.0909 | CO37: 112.6975 | CP37: 120.1685 | CQ37: 120.8784 | CR37: 122.8662 | CS37: 114.8556 | CT37: 116.0192 | CU37: 104.3743 | CV37: 108.8278 | CW37: 103.3634 | CX37: 103.2099 | CY37: 108.1542 | CZ37: 113.2305 | DA37: 105.7151 | DB37: 116.6357 | DC37: 112.6462 | DD37: 105.2247 | DE37: 107.6497 | DF37: 99.7961 | DG37: 105.455 | DH37: 109.3131 | DI37: 103.9073 | DJ37: 102.2123 | DK37: 94.7929 | DL37: 100.8628 | DM37: 119.8684 | DN37: 115.9026 | DO37: 112.4248 | DP37: 121.037 | DQ37: 114.2256 | DR37: 112.5861 | DS37: 106.3617 | DT37: 109.2636 | DU37: 105.7544 | DV37: 114.5086 | DW37: 120.4916 | DX37: 126.7783 | DY37: 132.5237
A38: BN | B38: =A38&" CN Equity" -> BN CN Equity | C38: Brookfield Corp | D38: -- | E38: -- | F38: 62.07 | G38: 42005 | H38: 45657 | I38: Financials | J38: 13.35 | K38: 14.0329 | L38: 14.0371 | M38: 13.4373 | N38: 13.69 | O38: 13.5779 | P38: 14.2129 | Q38: 12.9393 | R38: 13.1206 | S38: 14.2736 | T38: 14.3773 | U38: 13.6875 | V38: 13.1889 | W38: 13.0783 | X38: 14.2245 | Y38: 13.3491 | Z38: 14.5462 | AA38: 13.7217 | AB38: 14.4761 | AC38: 14.2611 | AD38: 14.867 | AE38: 15.1377 | AF38: 14.4716 | AG38: 14.3325 | AH38: 14.559 | AI38: 15.5365 | AJ38: 15.7346 | AK38: 16.3873 | AL38: 16.7156 | AM38: 16.6241 | AN38: 15.8494 | AO38: 16.2013 | AP38: 16.9 | AQ38: 17.7529 | AR38: 17.648 | AS38: 18.0101 | AT38: 16.9437 | AU38: 16.4354 | AV38: 16.5907 | AW38: 16.812 | AX38: 17.1474 | AY38: 17.6847 | AZ38: 18.202 | BA38: 18.5535 | BB38: 19.1292 | BC38: 17.8747 | BD38: 19.4445 | BE38: 17.468 | BF38: 18.8769 | BG38: 19.9163 | BH38: 20.8612 | BI38: 21.6419 | BJ38: 20.846 | BK38: 21.0645 | BL38: 21.7437 | BM38: 23.1575 | BN38: 23.7275 | BO38: 24.564 | BP38: 25.9911 | BQ38: 25.3755 | BR38: 27.3879 | BS38: 27.2248 | BT38: 21.1572 | BU38: 23.9315 | BV38: 22.0753 | BW38: 22.8158 | BX38: 22.0906 | BY38: 22.5568 | BZ38: 22.5773 | CA38: 20.2868 | CB38: 26.9564 | CC38: 27.0438 | CD38: 25.466 | CE38: 26.4948 | CF38: 28.8144 | CG38: 28.8814 | CH38: 31.0089 | CI38: 32.927 | CJ38: 35.0669 | CK38: 36.6291 | CL38: 35.4184 | CM38: 38.9931 | CN38: 37.5018 | CO38: 39.9548 | CP38: 36.6126 | CQ38: 36.3265 | CR38: 37.0659 | CS38: 33.6047 | CT38: 33.6352 | CU38: 30.1118 | CV38: 33.4143 | CW38: 33.3196 | CX38: 29.802 | CY38: 28.4519 | CZ38: 33.5491 | DA38: 27.7896 | DB38: 32.3058 | DC38: 29.6916 | DD38: 28.7956 | DE38: 28.7498 | DF38: 26.7237 | DG38: 29.2341 | DH38: 30.1715 | DI38: 30.293 | DJ38: 27.8956 | DK38: 26.5359 | DL38: 31.4993 | DM38: 34.9809 | DN38: 35.1192 | DO38: 36.804 | DP38: 37.3753 | DQ38: 36.4126 | DR38: 38.6414 | DS38: 37.5919 | DT38: 44.4827 | DU38: 44.7932 | DV38: 47.5348 | DW38: 48.8584 | DX38: 56.9386 | DY38: 54.7499
A39: BNS | B39: =A39&" CN Equity" -> BNS CN Equity | C39: Bank of Nova Scotia/The | D39: -- | E39: -- | F39: 101.8 | G39: 42005 | H39: 45657 | I39: Financials | J39: 34.72 | K39: 37.9899 | L39: 36.1305 | M39: 38.2398 | N39: 37.5903 | O39: 37.05 | P39: 37.2906 | Q39: 34.9843 | R39: 34.1768 | S39: 36.1504 | T39: 35.7976 | U39: 33.3092 | V39: 34.1543 | W39: 32.5891 | X39: 37.7727 | Y39: 39.6086 | Z39: 38.6094 | AA39: 38.5399 | AB39: 40.3783 | AC39: 42.4968 | AD39: 42.7683 | AE39: 44.3432 | AF39: 45.6105 | AG39: 46.4429 | AH39: 48.3066 | AI39: 47.8593 | AJ39: 48.7985 | AK39: 47.5943 | AL39: 47.8075 | AM39: 49.402 | AN39: 49.1867 | AO39: 49.1994 | AP39: 50.7889 | AQ39: 53.264 | AR39: 52.132 | AS39: 52.3885 | AT39: 52.776 | AU39: 51.3423 | AV39: 51.2519 | AW39: 51.4999 | AX39: 51.0561 | AY39: 49.113 | AZ39: 50.8613 | BA39: 49.8321 | BB39: 50.7954 | BC39: 47.1328 | BD39: 48.2336 | BE39: 45.9662 | BF39: 50.5121 | BG39: 49.4043 | BH39: 47.3577 | BI39: 50.4628 | BJ39: 46.8926 | BK39: 48.707 | BL39: 48.7901 | BM39: 49.0255 | BN39: 52.7293 | BO39: 52.9325 | BP39: 52.5121 | BQ39: 51.3979 | BR39: 51.2753 | BS39: 49.8139 | BT39: 40.6485 | BU39: 40.2612 | BV39: 39.8067 | BW39: 40.5354 | BX39: 40.328 | BY39: 41.325 | BZ39: 40.5552 | CA39: 41.2519 | CB39: 47.1397 | CC39: 51.2761 | CD39: 51.5026 | CE39: 56.1847 | CF39: 59.3715 | CG39: 59.7578 | CH39: 62.0341 | CI39: 61.5834 | CJ39: 60.1511 | CK39: 60.3674 | CL39: 60.2206 | CM39: 63.4108 | CN39: 62.348 | CO39: 70.7586 | CP39: 72.3468 | CQ39: 72.576 | CR39: 70.7981 | CS39: 65.0092 | CT39: 68.5493 | CU39: 60.8777 | CV39: 63.1945 | CW39: 58.8282 | CX39: 53.2224 | CY39: 54.2429 | CZ39: 57.757 | DA39: 54.6297 | DB39: 60.2139 | DC39: 56.3769 | DD39: 56.9119 | DE39: 57.4042 | DF39: 55.6556 | DG39: 56.2583 | DH39: 57.2762 | DI39: 55.3094 | DJ39: 53.4281 | DK39: 49.2771 | DL39: 53.2701 | DM39: 56.605 | DN39: 56.0964 | DO39: 58.7197 | DP39: 62.5207 | DQ39: 57.2933 | DR39: 58.4529 | DS39: 56.6953 | DT39: 59.4143 | DU39: 61.9948 | DV39: 67.9113 | DW39: 67.0345 | DX39: 74.6646 | DY39: 72.1774
A40: BTE | B40: =A40&" CN Equity" -> BTE CN Equity | C40: Baytex Energy Corp | D40: -- | E40: -- | F40: 4.7 | G40: 42005 | H40: 45657 | I40: Energy | J40: 17.81 | K40: 18.5263 | L40: 18.2726 | M40: 21.5871 | N40: 19.4816 | O40: 17.985 | P40: 10.4902 | Q40: 7.1738 | R40: 4.0253 | S40: 5.0151 | T40: 5.2319 | U40: 4.2232 | V40: 2.7904 | W40: 2.9129 | X40: 4.836 | Y40: 6.052 | Z40: 6.0238 | AA40: 7.0701 | AB40: 5.7787 | AC40: 5.5807 | AD40: 5.2508 | AE40: 4.8643 | AF40: 5.4299 | AG40: 6.184 | AH40: 4.8925 | AI40: 4.5532 | AJ40: 4.2798 | AK40: 3.8933 | AL40: 3.7048 | AM40: 2.9695 | AN40: 3.2994 | AO40: 2.9789 | AP40: 3.5445 | AQ40: 3.3465 | AR40: 4.0818 | AS40: 3.5539 | AT40: 3.5351 | AU40: 3.0826 | AV40: 3.3277 | AW40: 5.4204 | AX40: 5.1376 | AY40: 4.1195 | AZ40: 3.8085 | BA40: 3.6859 | BB40: 3.5351 | BC40: 2.5358 | BD40: 2.319 | BE40: 2.2719 | BF40: 2.0833 | BG40: 2.2247 | BH40: 2.1399 | BI40: 2.5641 | BJ40: 1.9702 | BK40: 1.9137 | BL40: 1.8948 | BM40: 1.6214 | BN40: 1.8477 | BO40: 1.3857 | BP40: 1.3575 | BQ40: 1.7628 | BR40: 1.3575 | BS40: 1.1595 | BT40: 0.3158 | BU40: 0.4195 | BV40: 0.3959 | BW40: 0.6505 | BX40: 0.5845 | BY40: 0.6316 | BZ40: 0.4336 | CA40: 0.3818 | CB40: 0.6222 | CC40: 0.6505 | CD40: 0.7164 | CE40: 1.1595 | CF40: 1.2349 | CG40: 1.3763 | CH40: 1.8854 | CI40: 2.253 | CJ40: 2.0079 | CK40: 2.0551 | CL40: 3.2523 | CM40: 3.9121 | CN40: 3.4691 | CO40: 3.6859 | CP40: 4.4683 | CQ40: 5.4582 | CR40: 5.1376 | CS40: 6.1934 | CT40: 6.5705 | CU40: 5.8918 | CV40: 6.4857 | CW40: 6.4103 | CX40: 5.5147 | CY40: 6.9759 | CZ40: 6.4763 | DA40: 5.7315 | DB40: 5.8069 | DC40: 4.9585 | DD40: 4.7794 | DE40: 4.8077 | DF40: 4.0347 | DG40: 4.0724 | DH40: 5.0151 | DI40: 5.1848 | DJ40: 5.6686 | DK40: 5.6781 | DL40: 4.9494 | DM40: 4.3189 | DN40: 4.062 | DO40: 4.1857 | DP40: 4.6757 | DQ40: 4.8764 | DR40: 4.7904 | DS40: 4.5551 | DT40: 4.9299 | DU40: 4.6128 | DV40: 3.9036 | DW40: 3.7973 | DX40: 3.836 | DY40: 3.5879
A41: BTO | B41: =A41&" CN Equity" -> BTO CN Equity | C41: B2Gold Corp | D41: -- | E41: -- | F41: 6.63 | G41: 42005 | H41: 45657 | I41: Materials | J41: 1.98 | K41: 1.6708 | L41: 1.4966 | M41: 1.4966 | N41: 1.6708 | O41: 1.5125 | P41: 1.1244 | Q41: 1.2195 | R41: 1.1165 | S41: 1.1165 | T41: 1.1561 | U41: 1.1007 | V41: 0.8473 | W41: 1.1957 | X41: 1.7104 | Y41: 2.2093 | Z41: 1.9163 | AA41: 2.5656 | AB41: 3.2387 | AC41: 2.6131 | AD41: 2.724 | AE41: 3.0724 | AF41: 2.5735 | AG41: 2.5181 | AH41: 3.1278 | AI41: 3.2308 | AJ41: 3.0011 | AK41: 2.7161 | AL41: 2.6844 | AM41: 2.8903 | AN41: 2.4785 | AO41: 2.7161 | AP41: 2.724 | AQ41: 2.5973 | AR41: 2.6052 | AS41: 3.0724 | AT41: 2.9457 | AU41: 3.017 | AV41: 2.7953 | AW41: 2.922 | AX41: 2.8111 | AY41: 2.7002 | AZ41: 2.5656 | BA41: 2.4231 | BB41: 2.3281 | BC41: 2.5735 | BD41: 2.5894 | BE41: 3.1595 | BF41: 3.2941 | BG41: 3.2783 | BH41: 2.9616 | BI41: 2.8824 | BJ41: 2.922 | BK41: 3.1516 | BL41: 3.3337 | BM41: 3.7851 | BN41: 3.4129 | BO41: 3.6663 | BP41: 3.8991 | BQ41: 4.1374 | BR41: 4.5503 | BS41: 4.2565 | BT41: 3.3904 | BU41: 5.6029 | BV41: 6.0407 | BW41: 6.1919 | BX41: 7.4143 | BY41: 6.9989 | BZ41: 6.9679 | CA41: 6.8875 | CB41: 5.8186 | CC41: 5.7717 | CD41: 5.116 | CE41: 4.4846 | CF41: 4.4183 | CG41: 4.8348 | CH41: 5.0471 | CI41: 4.2859 | CJ41: 4.3107 | CK41: 4.0222 | CL41: 3.6087 | CM41: 4.2588 | CN41: 4.2755 | CO41: 4.195 | CP41: 3.8581 | CQ41: 4.3129 | CR41: 4.8792 | CS41: 4.6327 | CT41: 4.2671 | CU41: 3.7457 | CV41: 3.8488 | CW41: 3.4365 | CX41: 3.8602 | CY41: 3.6168 | CZ41: 4.0776 | DA41: 4.2312 | DB41: 4.6359 | DC41: 4.0993 | DD41: 4.7518 | DE41: 4.7518 | DF41: 4.4759 | DG41: 4.2461 | DH41: 4.1112 | DI41: 3.7423 | DJ41: 3.5533 | DK41: 4.0453 | DL41: 4.1729 | DM41: 3.8634 | DN41: 3.4577 | DO41: 3.0151 | DP41: 3.3235 | DQ41: 3.258 | DR41: 3.595 | DS41: 3.4881 | DT41: 3.9348 | DU41: 3.6021 | DV41: 4.0328 | DW41: 4.438 | DX41: 3.9171 | DY41: 3.4533
A42: BYD | B42: =A42&" CN Equity" -> BYD CN Equity | C42: BOYD GROUP INC | D42: -- | E42: -- | F42: 223.17 | G42: 42005 | H42: 45657 | I42: Industrials | J42: 43.06 | K42: 44.8449 | L42: 50.7408 | M42: 49.353 | N42: 50.6751 | O42: 50.5891 | P42: 54.4582 | Q42: 61.0104 | R42: 59.4654 | S42: 57.3211 | T42: 65.5314 | U42: 63.6856 | V42: 61.2419 | W42: 61.5836 | X42: 73.7066 | Y42: 72.8211 | Z42: 73.2863 | AA42: 71.8107 | AB42: 74.4909 | AC42: 83.4817 | AD42: 79.2916 | AE42: 80.3 | AF42: 84.0045 | AG42: 82.9892 | AH42: 82.6327 | AI42: 83.7602 | AJ42: 82.3855 | AK42: 85.7785 | AL42: 97.235 | AM42: 93.5331 | AN42: 92.3091 | AO42: 90.9887 | AP42: 89.3068 | AQ42: 93.6545 | AR42: 96.2516 | AS42: 98.4103 | AT42: 104.1895 | AU42: 103.2867 | AV42: 101.7494 | AW42: 106.2559 | AX42: 111.155 | AY42: 114.6091 | AZ42: 115.2482 | BA42: 127.3037 | BB42: 123.3147 | BC42: 117.8086 | BD42: 112.5356 | BE42: 110.6906 | BF42: 116.272 | BG42: 119.5114 | BH42: 134.9037 | BI42: 144.4446 | BJ42: 161.938 | BK42: 162.4733 | BL42: 166.8966 | BM42: 174.9854 | BN42: 172.5239 | BO42: 180.5297 | BP42: 197.3531 | BQ42: 198.6369 | BR42: 204.5272 | BS42: 206.5037 | BT42: 144.1991 | BU42: 192.774 | BV42: 207.4597 | BW42: 199.033 | BX42: 192.6504 | BY42: 204.5883 | BZ42: 202.7152 | CA42: 188.3643 | CB42: 208.7965 | CC42: 216.5414 | CD42: 233.8304 | CE42: 207.6947 | CF42: 210.1469 | CG42: 225.2955 | CH42: 204.4032 | CI42: 222.7616 | CJ42: 241.3169 | CK42: 243.2129 | CL42: 232.1527 | CM42: 237.3402 | CN42: 203.9426 | CO42: 197.3853 | CP42: 190.0483 | CQ42: 163.6176 | CR42: 163.8564 | CS42: 157.3544 | CT42: 141.3715 | CU42: 137.3704 | CV42: 159.5026 | CW42: 179.3166 | CX42: 172.4744 | CY42: 192.2156 | CZ42: 216.6465 | DA42: 207.5319 | DB42: 201.8961 | DC42: 214.1996 | DD42: 214.5059 | DE42: 224.3455 | DF42: 244.273 | DG42: 251.1044 | DH42: 240.6827 | DI42: 242.1034 | DJ42: 240.1039 | DK42: 235.034 | DL42: 257.2123 | DM42: 276.9966 | DN42: 287.4304 | DO42: 316.802 | DP42: 285.0141 | DQ42: 257.6571 | DR42: 227.0559 | DS42: 255.876 | DT42: 230.4945 | DU42: 223.604 | DV42: 204.2375 | DW42: 215.9361 | DX42: 215.2984 | DY42: 216.1698
A43: CAE | B43: =A43&" CN Equity" -> CAE CN Equity | C43: CAE Inc | D43: -- | E43: -- | F43: 43.64 | G43: 42005 | H43: 45657 | I43: Industrials | J43: 14.37 | K43: 13.8581 | L43: 13.6388 | M43: 13.8141 | N43: 13.7034 | O43: 13.7855 | P43: 13.7392 | Q43: 13.3962 | R43: 13.1777 | S43: 13.7555 | T43: 14.1283 | U43: 14.3767 | V43: 13.7023 | W43: 13.9739 | X43: 14.1383 | Y43: 13.9689 | Z43: 15.4279 | AA43: 14.761 | AB43: 16.4726 | AC43: 17.683 | AD43: 17.6941 | AE43: 17.8935 | AF43: 18.8148 | AG43: 17.912 | AH43: 17.6258 | AI43: 19.0279 | AJ43: 19.4583 | AK43: 19.9658 | AL43: 20.8947 | AM43: 21.49 | AN43: 20.3078 | AO43: 19.8081 | AP43: 21.0742 | AQ43: 22.0686 | AR43: 21.9914 | AS43: 22.6317 | AT43: 22.0017 | AU43: 22.9322 | AV43: 23.3302 | AW43: 23.6123 | AX43: 26.57 | AY43: 26.6563 | AZ43: 26.4513 | BA43: 25.4264 | BB43: 25.6878 | BC43: 22.7487 | BD43: 26.4324 | BE43: 24.6746 | BF43: 27.4578 | BG43: 27.2906 | BH43: 29.2227 | BI43: 30.7524 | BJ43: 34.0191 | BK43: 34.8518 | BL43: 35.2279 | BM43: 34.4955 | BN43: 33.4279 | BO43: 32.8022 | BP43: 35.4439 | BQ43: 34.2539 | BR43: 39.106 | BS43: 35.7783 | BT43: 17.79 | BU43: 23 | BV43: 20.66 | BW43: 22.02 | BX43: 19.99 | BY43: 20.68 | BZ43: 19.48 | CA43: 22.77 | CB43: 31.42 | CC43: 35.27 | CD43: 28.89 | CE43: 33.68 | CF43: 35.81 | CG43: 38.5 | CH43: 37.2 | CI43: 38.18 | CJ43: 38.07 | CK43: 36.43 | CL43: 37.84 | CM43: 37.53 | CN43: 30.7 | CO43: 31.91 | CP43: 32.1 | CQ43: 33.91 | CR43: 32.54 | CS43: 30.55 | CT43: 31.59 | CU43: 31.72 | CV43: 33.88 | CW43: 23.98 | CX43: 21.19 | CY43: 26 | CZ43: 29.09 | DA43: 26.19 | DB43: 30.05 | DC43: 30.77 | DD43: 30.56 | DE43: 30.49 | DF43: 27.76 | DG43: 29.65 | DH43: 30.13 | DI43: 32.59 | DJ43: 31.71 | DK43: 28.96 | DL43: 26.98 | DM43: 28.6 | DN43: 26.92 | DO43: 25.34 | DP43: 27.97 | DQ43: 26.56 | DR43: 25.59 | DS43: 25.41 | DT43: 25.12 | DU43: 24.11 | DV43: 25.39 | DW43: 24.5 | DX43: 32.91 | DY43: 36.47
A44: CAR-U | B44: =A44&" CN Equity" -> CAR-U CN Equity | C44: Canadian Apartment Properties | D44: -- | E44: -- | F44: 38.56 | G44: 42005 | H44: 45657 | I44: Real Estate | J44: 19.77 | K44: 19.725 | L44: 20.4153 | M44: 20.4629 | N44: 19.3497 | O44: 19.5051 | P44: 19.8818 | Q44: 19.9336 | R44: 20.2772 | S44: 19.306 | T44: 19.1144 | U44: 19.3951 | V44: 21.6895 | W44: 20.8633 | X44: 21.0909 | Y44: 21.8597 | Z44: 22.33 | AA44: 24.4599 | AB44: 24.1605 | AC44: 22.1855 | AD44: 22.8143 | AE44: 21.8925 | AF44: 22.913 | AG44: 23.6151 | AH44: 23.9575 | AI44: 24.3684 | AJ44: 25.3132 | AK44: 25.8262 | AL44: 25.61 | AM44: 25.7602 | AN44: 24.9518 | AO44: 26.4671 | AP44: 26.1333 | AQ44: 26.4785 | AR44: 28.8306 | AS44: 29.1722 | AT44: 28.3491 | AU44: 27.6399 | AV44: 29.2996 | AW44: 29.2967 | AX44: 32.3257 | AY44: 33.897 | AZ44: 34.5594 | BA44: 37.0476 | BB44: 38.1979 | BC44: 37.5826 | BD44: 37.6317 | BE44: 35.7418 | BF44: 37.8493 | BG44: 40.732 | BH44: 41.7327 | BI44: 39.0312 | BJ44: 39.9793 | BK44: 39.5673 | BL44: 39.947 | BM44: 44.0112 | BN44: 44.8613 | BO44: 45.2625 | BP44: 45.8525 | BQ44: 43.9368 | BR44: 47.0072 | BS44: 46.7098 | BT44: 35.5392 | BU44: 40.0671 | BV44: 39.36 | BW44: 40.8411 | BX44: 40.9209 | BY44: 38.0064 | BZ44: 39.3285 | CA44: 36.3615 | CB44: 43.5309 | CC44: 42.6327 | CD44: 43.7624 | CE44: 43.7264 | CF44: 46.2405 | CG44: 47.0085 | CH44: 47.7443 | CI44: 50.2065 | CJ44: 53.9611 | CK44: 52.9924 | CL44: 51.3616 | CM44: 52.6134 | CN44: 49.6084 | CO44: 52.4192 | CP44: 48.9896 | CQ44: 46.3344 | CR44: 47.2202 | CS44: 44.3956 | CT44: 43.7804 | CU44: 39.7492 | CV44: 43.1348 | CW44: 39.826 | CX44: 37.6468 | CY44: 37.8348 | CZ44: 39.3005 | DA44: 38.495 | DB44: 44.4848 | DC44: 44.7937 | DD44: 43.0827 | DE44: 45.2128 | DF44: 44.7956 | DG44: 46.5627 | DH44: 47.1777 | DI44: 44.5899 | DJ44: 41.5836 | DK44: 37.7651 | DL44: 42.8843 | DM44: 45.3805 | DN44: 43.5105 | DO44: 44.4976 | DP44: 43.5648 | DQ44: 40.2664 | DR44: 42.027 | DS44: 41.9997 | DT44: 45.4661 | DU44: 49.735 | DV44: 52.3332 | DW44: 44.2659 | DX44: 43.8709 | DY44: 40.9112
A45: CCA | B45: =A45&" CN Equity" -> CCA CN Equity | C45: Cogeco Communications Inc | D45: -- | E45: -- | F45: 65.63 | G45: 42005 | H45: 45657 | I45: Communication Services | J45: 50.1 | K45: 51.1079 | L45: 46.6059 | M45: 47.6723 | N45: 45.4166 | O45: 49.8314 | P45: 50.7366 | Q45: 46.0366 | R45: 44.7125 | S45: 46.813 | T45: 45.2436 | U45: 43.0616 | V45: 44.4258 | W45: 44.4959 | X45: 48.5856 | Y45: 44.1271 | Z45: 48.4396 | AA45: 47.8538 | AB45: 45.6435 | AC45: 45.0681 | AD45: 45.9986 | AE45: 44.436 | AF45: 46.1703 | AG45: 47.379 | AH45: 51.0926 | AI45: 51.6683 | AJ45: 51.1286 | AK45: 56.5289 | AL45: 57.1585 | AM45: 57.325 | AN45: 63.3456 | AO45: 67.9638 | AP45: 66.9238 | AQ45: 67.4547 | AR45: 67.3184 | AS45: 63.238 | AT45: 56.0597 | AU45: 53.2052 | AV45: 51.8957 | AW45: 50.6798 | AX45: 50.4132 | AY45: 48.2425 | AZ45: 52.6593 | BA45: 48.3108 | BB45: 48.2586 | BC45: 48.1467 | BD45: 48.5802 | BE45: 49.4675 | BF45: 56.7413 | BG45: 62.3313 | BH45: 64.6416 | BI45: 67.7844 | BJ45: 70.6262 | BK45: 71.7538 | BL45: 79.8116 | BM45: 80.1255 | BN45: 81.7565 | BO45: 87.1778 | BP45: 88.3097 | BQ45: 87.132 | BR45: 80.416 | BS45: 82.2116 | BT45: 73.8914 | BU45: 80.1268 | BV45: 80.0567 | BW45: 76.1559 | BX45: 79.966 | BY45: 76.5825 | BZ45: 85.519 | CA45: 72.6821 | CB45: 74.1449 | CC45: 77.1814 | CD45: 86.4688 | CE45: 91.2925 | CF45: 93.617 | CG45: 93.1292 | CH45: 92.5469 | CI45: 96.6868 | CJ45: 94.6335 | CK45: 93.0376 | CL45: 90.2707 | CM45: 85.2423 | CN45: 78.8563 | CO45: 81.3602 | CP45: 84.8878 | CQ45: 82.3332 | CR45: 84.1881 | CS45: 86.3806 | CT45: 86.1759 | CU45: 71.2906 | CV45: 68.4299 | CW45: 66.3825 | CX45: 59.5305 | CY45: 57.3593 | CZ45: 62.8174 | DA45: 64.0945 | DB45: 58.0516 | DC45: 59.1493 | DD45: 55.586 | DE45: 56.1161 | DF45: 54.8085 | DG45: 60.415 | DH45: 57.7625 | DI45: 57.6674 | DJ45: 54.3561 | DK45: 47.2233 | DL45: 45.7819 | DM45: 52.1628 | DN45: 55.2957 | DO45: 53.2193 | DP45: 53.5402 | DQ45: 49.3748 | DR45: 47.33 | DS45: 46.6785 | DT45: 58.0747 | DU45: 59.2398 | DV45: 65.5977 | DW45: 64.3592 | DX45: 65.069 | DY45: 62.6056
A46: CCL/B | B46: =A46&" CN Equity" -> CCL/B CN Equity | C46: CCL Industries Inc | D46: -- | E46: -- | F46: 82.06 | G46: 42005 | H46: 45657 | I46: Materials | J46: 22.89 | K46: 24.0993 | L46: 24.8952 | M46: 24.2331 | N46: 25.2498 | O46: 26.8337 | P46: 32.0481 | Q46: 30.1266 | R46: 32.8472 | S46: 32.5137 | T46: 38.9252 | U46: 39.4453 | V46: 34.6871 | W46: 36.381 | X46: 43.4301 | Y46: 40.4789 | Z46: 41.1255 | AA46: 39.7 | AB46: 41.2644 | AC46: 44.1866 | AD46: 44.6955 | AE46: 42.206 | AF46: 41.3585 | AG46: 46.7775 | AH46: 47.4868 | AI46: 50.0597 | AJ46: 51.5469 | AK46: 56.1412 | AL46: 56.7062 | AM46: 58.381 | AN46: 53.1844 | AO46: 51.5472 | AP46: 53.8356 | AQ46: 55.4405 | AR46: 53.3096 | AS46: 51.886 | AT46: 52.556 | AU46: 57.0585 | AV46: 58.218 | AW46: 55.7475 | AX46: 57.4393 | AY46: 57.8043 | AZ46: 59.1945 | BA46: 56.3872 | BB46: 52.3248 | BC46: 49.7723 | BD46: 49.5297 | BE46: 45.099 | BF46: 49.9098 | BG46: 48.4324 | BH46: 48.8925 | BI46: 51.649 | BJ46: 55.6435 | BK46: 58.1925 | BL46: 59.8054 | BM46: 54.6676 | BN46: 48.5693 | BO46: 49.2691 | BP46: 51.6321 | BQ46: 50.4279 | BR46: 50.8746 | BS46: 40.3915 | BT46: 39.1683 | BU46: 39.8273 | BV46: 42.4636 | BW46: 40.3271 | BX46: 40.952 | BY46: 44.3065 | BZ46: 47.3609 | CA46: 46.8628 | CB46: 52.8221 | CC46: 53.4723 | CD46: 54.2865 | CE46: 62.0219 | CF46: 64.5217 | CG46: 64.7537 | CH46: 62.814 | CI46: 63.5556 | CJ46: 66.6091 | CK46: 67.0466 | CL46: 61.2479 | CM46: 63.1619 | CN46: 58.5309 | CO46: 63.5399 | CP46: 62.2565 | CQ46: 53.526 | CR46: 53.057 | CS46: 52.6901 | CT46: 57.1209 | CU46: 57.4728 | CV46: 60.7697 | CW46: 60.8547 | CX46: 63.4809 | CY46: 60.6747 | CZ46: 60.6178 | DA46: 55.0544 | DB46: 59.233 | DC46: 62.4692 | DD46: 64.1759 | DE46: 60.8973 | DF46: 60.4576 | DG46: 62.5089 | DH46: 60.6851 | DI46: 57.9686 | DJ46: 54.9797 | DK46: 52.2891 | DL46: 53.9382 | DM46: 57.7179 | DN46: 55.7323 | DO46: 67.0067 | DP46: 67.3219 | DQ46: 68.3624 | DR46: 68.3138 | DS46: 70.2415 | DT46: 73.3366 | DU46: 75.2308 | DV46: 80.7926 | DW46: 79.5874 | DX46: 76.0499 | DY46: 72.7459
A47: CCO | B47: =A47&" CN Equity" -> CCO CN Equity | C47: Cameco Corp | D47: -- | E47: -- | F47: 168.41 | G47: 42005 | H47: 45657 | I47: Energy | J47: 15.99 | K47: 17.2364 | L47: 15.8486 | M47: 19.0542 | N47: 16.7375 | O47: 16.1163 | P47: 16.2156 | Q47: 16.7122 | R47: 14.7792 | S47: 16.8231 | T47: 14.8246 | U47: 15.5957 | V47: 15.5408 | W47: 14.9653 | X47: 15.3221 | Y47: 14.4305 | Z47: 14.0445 | AA47: 13.1365 | AB47: 11.5534 | AC47: 11.2017 | AD47: 10.4704 | AE47: 9.6485 | AF47: 11.5445 | AG47: 13.2066 | AH47: 15.5864 | AI47: 13.8274 | AJ47: 13.9394 | AK47: 12.3958 | AL47: 11.7898 | AM47: 11.2739 | AN47: 12.1903 | AO47: 11.9517 | AP47: 11.5974 | AQ47: 10.0863 | AR47: 11.6455 | AS47: 11.2698 | AT47: 10.9883 | AU47: 10.9883 | AV47: 11.3669 | AW47: 13.1238 | AX47: 13.0171 | AY47: 14.3566 | AZ47: 13.648 | BA47: 13.1627 | BB47: 14.2984 | BC47: 13.6868 | BD47: 15.3841 | BE47: 15.1012 | BF47: 15.5305 | BG47: 14.8964 | BH47: 15.3646 | BI47: 14.4183 | BJ47: 13.3062 | BK47: 13.6965 | BL47: 11.8234 | BM47: 11.3942 | BN47: 12.2722 | BO47: 11.4722 | BP47: 11.88 | BQ47: 11.3302 | BR47: 10.476 | BS47: 11.3989 | BT47: 10.5349 | BU47: 13.5884 | BV47: 14.688 | BW47: 13.6669 | BX47: 13.3724 | BY47: 14.8353 | BZ47: 13.2055 | CA47: 12.4298 | CB47: 12.8315 | CC47: 16.842 | CD47: 15.7159 | CE47: 19.7264 | CF47: 20.5858 | CG47: 20.408 | CH47: 23.4603 | CI47: 23.4702 | CJ47: 21.9193 | CK47: 23.0257 | CL47: 27.1843 | CM47: 29.7032 | CN47: 29.5028 | CO47: 27.3141 | CP47: 24.4718 | CQ47: 30.8695 | CR47: 36.059 | CS47: 32.8503 | CT47: 30.6913 | CU47: 26.7397 | CV47: 32.6621 | CW47: 37.8615 | CX47: 36.3066 | CY47: 31.9986 | CZ47: 32.5793 | DA47: 30.5114 | DB47: 37.0133 | DC47: 37.0829 | DD47: 35.184 | DE47: 37.0332 | DF47: 37.5701 | DG47: 41.2485 | DH47: 46.0902 | DI47: 49.709 | DJ47: 53.5764 | DK47: 56.3998 | DL47: 62.0687 | DM47: 56.9088 | DN47: 63.9414 | DO47: 54.7273 | DP47: 58.4129 | DQ47: 62.5668 | DR47: 75.3371 | DS47: 67.129 | DT47: 62.5967 | DU47: 54.7771 | DV47: 64.2901 | DW47: 72.4783 | DX47: 83.6877 | DY47: 73.7669
... A60: CRT-U | B60: =A60&" CN Equity" -> CRT-U CN Equity | C60: CT Real Estate Investment Trus | D60: -- | E60: -- | F60: 16.32 | G60: 42005 | H60: 45657 | I60: Real Estate | J60: 7.1 | K60: 7.3966 | L60: 7.1509 | M60: 6.9927 | N60: 7.0185 | O60: 6.7976 | P60: 7.184 | Q60: 7.347 | R60: 7.3216 | S60: 7.4329 | T60: 7.6366 | U60: 7.4968 | V60: 8.0785 | W60: 8.176 | X60: 8.4365 | Y60: 8.4635 | Z60: 8.7252 | AA60: 8.741 | AB60: 9.0107 | AC60: 8.8651 | AD60: 9.1969 | AE60: 8.8121 | AF60: 9.0853 | AG60: 9.0608 | AH60: 8.9087 | AI60: 9.1312 | AJ60: 9.1908 | AK60: 8.988 | AL60: 9.3003 | AM60: 8.8929 | AN60: 9.0216 | AO60: 8.7105 | AP60: 8.6975 | AQ60: 8.8906 | AR60: 9.2543 | AS60: 9.1919 | AT60: 8.8175 | AU60: 8.314 | AV60: 8.5454 | AW60: 8.4566 | AX60: 8.4503 | AY60: 8.4052 | AZ60: 8.8423 | BA60: 8.8361 | BB60: 8.4881 | BC60: 8.6291 | BD60: 8.1253 | BE60: 7.7347 | BF60: 8.6296 | BG60: 9.2053 | BH60: 9.7696 | BI60: 9.6356 | BJ60: 9.4729 | BK60: 9.8046 | BL60: 10.0892 | BM60: 10.2102 | BN60: 10.4985 | BO60: 10.3894 | BP60: 10.7353 | BQ60: 11.4157 | BR60: 11.4543 | BS60: 11.015 | BT60: 8.3891 | BU60: 9.3317 | BV60: 9.5374 | BW60: 9.8822 | BX60: 10.2068 | BY60: 10.4093 | BZ60: 10.3117 | CA60: 10.2282 | CB60: 11.1081 | CC60: 11.7248 | CD60: 11.6853 | CE60: 11.6686 | CF60: 12.3909 | CG60: 12.5934 | CH60: 12.5765 | CI60: 12.5688 | CJ60: 13.1599 | CK60: 13.5144 | CL60: 13.2266 | CM60: 13.8406 | CN60: 12.9726 | CO60: 13.615 | CP60: 13.3806 | CQ60: 13.4281 | CR60: 14.0697 | CS60: 14.181 | CT60: 14.0537 | CU60: 13.3505 | CV60: 13.7569 | CW60: 13.1186 | CX60: 12.2609 | CY60: 12.7201 | CZ60: 12.8453 | DA60: 12.914 | DB60: 13.6863 | DC60: 13.8212 | DD60: 13.4575 | DE60: 13.5691 | DF60: 12.7264 | DG60: 12.876 | DH60: 13.0329 | DI60: 12.5228 | DJ60: 11.8389 | DK60: 11.0043 | DL60: 11.9134 | DM60: 12.8802 | DN60: 12.8216 | DO60: 12.3036 | DP60: 12.7444 | DQ60: 12.0606 | DR60: 12.2464 | DS60: 11.9731 | DT60: 13.1509 | DU60: 14.1615 | DV60: 14.6541 | DW60: 14.1159 | DX60: 14.3362 | DY60: 13.3838
A61: CS | B61: =A61&" CN Equity" -> CS CN Equity | C61: Capstone Copper Corp | D61: -- | E61: -- | F61: 15.09 | G61: 42005 | H61: 45657 | I61: Materials | CR61: =_xll.BDH(B61, "PX_LAST", "2015-01-01", "2024-12-31", "Period=M", "Orientation=H", "CshAdjNormal = Y","CapChg = Y", "DTS=H","cols=34;rows=1") -> #N/A Requesting Data... | CS61: 5.85 | CT61: 4.79 | CU61: 3.25 | CV61: 2.89 | CW61: 2.95 | CX61: 3.26 | CY61: 3.16 | CZ61: 4.7 | DA61: 4.94 | DB61: 6.53 | DC61: 6 | DD61: 6.1 | DE61: 6.37 | DF61: 5.36 | DG61: 6.01 | DH61: 6.89 | DI61: 6.29 | DJ61: 5.76 | DK61: 4.72 | DL61: 5.56 | DM61: 6.45 | DN61: 6.62 | DO61: 7.12 | DP61: 8.62 | DQ61: 9.53 | DR61: 9.6 | DS61: 9.7 | DT61: 9.28 | DU61: 9.67 | DV61: 10.57 | DW61: 9.63 | DX61: 9.71 | DY61: 8.89
A62: CSH-U | B62: =A62&" CN Equity" -> CSH-U CN Equity | C62: Chartwell Retirement Residence | D62: -- | E62: -- | F62: 20.22 | G62: 42005 | H62: 45657 | I62: Health Care | J62: 7.59 | K62: 7.7087 | L62: 7.4717 | M62: 7.3482 | N62: 6.7078 | O62: 7.0222 | P62: 7.3447 | Q62: 7.1889 | R62: 7.6059 | S62: 7.8574 | T62: 8.2281 | U62: 7.9449 | V62: 8.0056 | W62: 8.1668 | X62: 8.9153 | Y62: 8.7743 | Z62: 9.4317 | AA62: 10.0667 | AB62: 10.1544 | AC62: 9.9085 | AD62: 10.1773 | AE62: 9.6533 | AF62: 9.4254 | AG62: 9.5278 | AH62: 9.9225 | AI62: 10.2528 | AJ62: 10.2324 | AK62: 10.2315 | AL62: 10.619 | AM62: 10.2608 | AN62: 10.1733 | AO62: 9.8071 | AP62: 9.9663 | AQ62: 10.2991 | AR62: 10.4255 | AS62: 10.9763 | AT62: 10.5629 | AU62: 10.406 | AV62: 10.6637 | AW62: 10.1244 | AX62: 9.9593 | AY62: 10.5489 | AZ62: 10.5759 | BA62: 10.4578 | BB62: 10.173 | BC62: 9.8531 | BD62: 10.5425 | BE62: 9.5978 | BF62: 10.3412 | BG62: 10.6009 | BH62: 10.622 | BI62: 10.4521 | BJ62: 10.3524 | BK62: 10.9024 | BL62: 11.0521 | BM62: 10.7581 | BN62: 10.6497 | BO62: 10.7006 | BP62: 10.6064 | BQ62: 10.1617 | BR62: 10.3296 | BS62: 9.5948 | BT62: 6.6303 | BU62: 6.662 | BV62: 6.1324 | BW62: 7.0639 | BX62: 7.4791 | BY62: 7.9494 | BZ62: 7.7292 | CA62: 7.355 | CB62: 8.7545 | CC62: 8.6859 | CD62: 8.3369 | CE62: 8.5796 | CF62: 9.2154 | CG62: 9.8859 | CH62: 10.3847 | CI62: 10.5511 | CJ62: 10.4801 | CK62: 10.3369 | CL62: 9.719 | CM62: 9.6636 | CN62: 8.9664 | CO62: 9.6504 | CP62: 10.1913 | CQ62: 10.02 | CR62: 10.251 | CS62: 10.1271 | CT62: 10.3437 | CU62: 9.3354 | CV62: 9.5719 | CW62: 8.7813 | CX62: 7.8955 | CY62: 6.7555 | CZ62: 7.1591 | DA62: 7.3088 | DB62: 8.5387 | DC62: 8.0598 | DD62: 7.5274 | DE62: 7.8453 | DF62: 8.0232 | DG62: 8.4789 | DH62: 9.0082 | DI62: 9.2881 | DJ62: 9.3435 | DK62: 9.2814 | DL62: 9.9676 | DM62: 10.804 | DN62: 11.1009 | DO62: 11.305 | DP62: 11.5392 | DQ62: 11.7084 | DR62: 11.7384 | DS62: 12.1445 | DT62: 12.9962 | DU62: 13.8892 | DV62: 14.8811 | DW62: 14.9972 | DX62: 15.525 | DY62: 14.5459
A63: CSU | B63: =A63&" CN Equity" -> CSU CN Equity | C63: Constellation Software Inc/Can | D63: -- | E63: -- | F63: 2512.96 | G63: 42005 | H63: 45657 | I63: Information Technology | J63: 326.29 | K63: 390.144 | L63: 406.854 | M63: 439.607 | N63: 473.065 | O63: 461.937 | P63: 541.737 | Q63: 523.748 | R63: 522.311 | S63: 527.587 | T63: 535.197 | U63: 539.957 | V63: 471.405 | W63: 528.388 | X63: 499.062 | Y63: 460.163 | Z63: 500.197 | AA63: 470.418 | AB63: 500.054 | AC63: 538.317 | AD63: 557.758 | AE63: 592.587 | AF63: 590.785 | AG63: 576.653 | AH63: 555.491 | AI63: 589.299 | AJ63: 618.935 | AK63: 591.307 | AL63: 661.64 | AM63: 643.712 | AN63: 637.344 | AO63: 658.895 | AP63: 647.126 | AQ63: 697.737 | AR63: 718.366 | AS63: 725.59 | AT63: 757.098 | AU63: 790.882 | AV63: 833.559 | AW63: 875.02 | AX63: 973.8 | AY63: 973.421 | AZ63: 900.363 | BA63: 950.067 | BB63: 908.139 | BC63: 866.206 | BD63: 871.235 | BE63: 836.681 | BF63: 938.899 | BG63: 1075.92 | BH63: 1085.614 | BI63: 1133.132 | BJ63: 1121.907 | BK63: 1184.469 | BL63: 1205.044 | BM63: 1244.41 | BN63: 1271.082 | BO63: 1249.641 | BP63: 1364.131 | BQ63: 1212.783 | BR63: 1337.691 | BS63: 1314.977 | BT63: 1231.337 | BU63: 1288.629 | BV63: 1506.781 | BW63: 1477.08 | BX63: 1526.685 | BY63: 1455.013 | BZ63: 1427.019 | CA63: 1348.86 | CB63: 1551.094 | CC63: 1603.483 | CD63: 1511.188 | CE63: 1598.438 | CF63: 1703.796 | CG63: 1751.258 | CH63: 1666.614 | CI63: 1823.82 | CJ63: 1941.386 | CK63: 2077.156 | CL63: 2016.951 | CM63: 2114.124 | CN63: 2112.86 | CO63: 2282.595 | CP63: 2129.325 | CQ63: 2077.594 | CR63: 2079.719 | CS63: 1967.675 | CT63: 1937.379 | CU63: 1860.969 | CV63: 2121.474 | CW63: 1925.392 | CX63: 1873.179 | CY63: 1919.763 | CZ63: 2113.339 | DA63: 2061.501 | DB63: 2292.434 | DC63: 2335.449 | DD63: 2529.31 | DE63: 2631.62 | DF63: 2756.812 | DG63: 2734.982 | DH63: 2776.036 | DI63: 2765.573 | DJ63: 2795.406 | DK63: 2771.42 | DL63: 3177.452 | DM63: 3276.466 | DN63: 3705.902 | DO63: 3768.264 | DP63: 3671.471 | DQ63: 3536.065 | DR63: 3782.283 | DS63: 3934.176 | DT63: 4347.776 | DU63: 4411.711 | DV63: 4392.754 | DW63: 4192.125 | DX63: 4726.363 | DY63: 4439.032
A64: CTC/A | B64: =A64&" CN Equity" -> CTC/A CN Equity | C64: Canadian Tire Corp Ltd | D64: -- | E64: -- | F64: 167.52 | G64: 42005 | H64: 45657 | I64: Consumer Discretionary | J64: 83.43 | K64: 93.7721 | L64: 91.857 | M64: 91.3396 | N64: 92.1687 | O64: 95.478 | P64: 93.5809 | Q64: 89.1383 | R64: 86.1599 | S64: 82.9255 | T64: 90.2072 | U64: 85.1893 | V64: 82.7393 | W64: 95.3441 | X64: 97.9897 | Y64: 99.4792 | Z64: 104.2323 | AA64: 102.4489 | AB64: 100.2695 | AC64: 98.1792 | AD64: 96.0231 | AE64: 95.7152 | AF64: 102.7187 | AG64: 102.2415 | AH64: 102.0617 | AI64: 112.3203 | AJ64: 116.5092 | AK64: 123.346 | AL64: 113.8396 | AM64: 109.2493 | AN64: 105.8443 | AO64: 109.9275 | AP64: 115.5354 | AQ64: 118.2214 | AR64: 121.7539 | AS64: 122.4036 | AT64: 128.8446 | AU64: 130.9166 | AV64: 127.1705 | AW64: 132.046 | AX64: 124.5751 | AY64: 129.4953 | AZ64: 134.3878 | BA64: 123.8443 | BB64: 114.7951 | BC64: 113.0474 | BD64: 113.2077 | BE64: 108.9266 | BF64: 114.8514 | BG64: 111.5853 | BH64: 110.6555 | BI64: 114.119 | BJ64: 104.631 | BK64: 110.4198 | BL64: 112.3215 | BM64: 104.8157 | BN64: 115.8756 | BO64: 111.479 | BP64: 121.505 | BQ64: 109.7203 | BR64: 112.3171 | BS64: 104.451 | BT64: 67.2177 | BU64: 78.1698 | BV64: 94.1367 | BW64: 94.1527 | BX64: 99.7534 | BY64: 110.2223 | BZ64: 108.3402 | CA64: 121.101 | CB64: 135.093 | CC64: 136.1999 | CD64: 135.9121 | CE64: 134.7891 | CF64: 146.1745 | CG64: 161.5462 | CH64: 168.5055 | CI64: 161.7441 | CJ64: 159.2429 | CK64: 159.2927 | CL64: 147.0471 | CM64: 146.8144 | CN64: 141.018 | CO64: 151.5418 | CP64: 154.4246 | CQ64: 157.2349 | CR64: 158.8252 | CS64: 149.9959 | CT64: 147.3088 | CU64: 137.6623 | CV64: 140.8566 | CW64: 132.2602 | CX64: 125.907 | CY64: 132.1361 | CZ64: 131.8332 | DA64: 122.4524 | DB64: 138.3788 | DC64: 148.7791 | DD64: 154.2722 | DE64: 156.852 | DF64: 144.0025 | DG64: 159.9518 | DH64: 161.446 | DI64: 142.8954 | DJ64: 130.1926 | DK64: 120.7679 | DL64: 127.4401 | DM64: 127.0518 | DN64: 130.5648 | DO64: 126.1792 | DP64: 123.4381 | DQ64: 123.0877 | DR64: 125.9106 | DS64: 125.633 | DT64: 132.8484 | DU64: 143.9613 | DV64: 151.8789 | DW64: 140.4488 | DX64: 146.3257 | DY64: 143.3398
A65: CU | B65: =A65&" CN Equity" -> CU CN Equity | C65: Canadian Utilities Ltd | D65: -- | E65: -- | F65: 44.07 | G65: 42005 | H65: 45657 | I65: Utilities | J65: 25.45 | K65: 25.2775 | L65: 24.1946 | M65: 23.8478 | N65: 22.6427 | O65: 22.0419 | P65: 22.5262 | Q65: 22.4826 | R65: 22.3219 | S65: 21.2648 | T65: 20.3382 | U65: 19.9142 | V65: 22.5266 | W65: 20.4775 | X65: 22.8681 | Y65: 22.7045 | Z65: 23.0093 | AA65: 23.7583 | AB65: 25.5101 | AC65: 24.0602 | AD65: 23.6891 | AE65: 24.5274 | AF65: 22.829 | AG65: 23.3583 | AH65: 23.9069 | AI65: 23.2956 | AJ65: 25.3944 | AK65: 25.6486 | AL65: 26.8892 | AM65: 27.4089 | AN65: 26.0276 | AO65: 25.8308 | AP65: 25.7179 | AQ65: 25.8573 | AR65: 26.1496 | AS65: 25.0578 | AT65: 24.388 | AU65: 22.9529 | AV65: 23.2915 | AW65: 22.1469 | AX65: 21.5713 | AY65: 22.7572 | AZ65: 22.2431 | BA65: 22.032 | BB65: 22.039 | BC65: 21.6712 | BD65: 22.0055 | BE65: 22.0055 | BF65: 23.7339 | BG65: 24.8906 | BH65: 25.9505 | BI65: 26.2706 | BJ65: 27.4158 | BK65: 26.5955 | BL65: 25.8615 | BM65: 27.9944 | BN65: 28.4313 | BO65: 27.9653 | BP65: 28.7466 | BQ65: 28.8275 | BR65: 29.8063 | BS65: 29.5475 | BT65: 25.0246 | BU65: 25.2626 | BV65: 24.8988 | BW65: 25.4715 | BX65: 25.8935 | BY65: 24.9918 | BZ65: 24.2437 | CA65: 23.7705 | CB65: 25.108 | CC65: 24.0631 | CD65: 24.4656 | CE65: 23.6311 | CF65: 26.4712 | CG65: 27.5617 | CH65: 28.1076 | CI65: 27.329 | CJ65: 29.0371 | CK65: 28.7175 | CL65: 27.4469 | CM65: 28.8301 | CN65: 27.9255 | CO65: 29.8713 | CP65: 30.0667 | CQ65: 29.0938 | CR65: 31.5828 | CS65: 31.9207 | CT65: 33.4655 | CU65: 32.0144 | CV65: 34.5662 | CW65: 33.872 | CX65: 30.2892 | CY65: 30.559 | CZ65: 31.4027 | DA65: 31.2832 | DB65: 31.5479 | DC65: 30.9245 | DD65: 32.5403 | DE65: 33.845 | DF65: 31.8618 | DG65: 29.9912 | DH65: 28.7062 | DI65: 28.3824 | DJ65: 25.4396 | DK65: 26.0069 | DL65: 27.3649 | DM65: 28.7061 | DN65: 27.9834 | DO65: 27.9104 | DP65: 28.1752 | DQ65: 28.1113 | DR65: 28.8279 | DS65: 27.3912 | DT65: 29.9681 | DU65: 31.9575 | DV65: 33.7528 | DW65: 33.5084 | DX65: 34.2256 | DY65: 33.1876
A66: CURA | B66: =A66&" CN Equity" -> CURA CN Equity | C66: Curaleaf Holdings Inc | D66: -- | E66: -- | F66: 3.01 | G66: 42005 | H66: 45657 | I66: Health Care | S66: 1.1 | T66: 1.35 | U66: 1 | V66: 0.9 | W66: 0.8 | X66: 0.75 | Y66: 1.2 | Z66: 0.8 | AA66: 1 | AB66: 0.75 | AC66: 0.7 | AD66: 0.7 | AE66: 0.6 | AF66: 0.8 | AG66: 0.5 | AH66: 0.6 | AI66: 0.55 | AJ66: 0.45 | AK66: 0.4 | AL66: 0.35 | AM66: 0.65 | AN66: 0.55 | AO66: 0.4 | AP66: 0.25 | AQ66: 0.25 | AR66: 0.25 | AS66: 0.4 | AT66: 0.45 | AU66: 0.65 | AV66: 0.225 | AW66: 0.14 | AX66: 0.19 | AY66: 0.25 | AZ66: 9.5 | BA66: 7 | BB66: 6.46 | BC66: 8.51 | BD66: 10.41 | BE66: 12.2 | BF66: 13.32 | BG66: 11.15 | BH66: 9.33 | BI66: 10.4 | BJ66: 9.41 | BK66: 7.17 | BL66: 6.27 | BM66: 8 | BN66: 8.18 | BO66: 9.39 | BP66: 7.12 | BQ66: 5.52 | BR66: 6.62 | BS66: 8.15 | BT66: 8.29 | BU66: 11.26 | BV66: 10.93 | BW66: 9.71 | BX66: 12.49 | BY66: 14.18 | BZ66: 15.24 | CA66: 17.07 | CB66: 20.5 | CC66: 19.25 | CD66: 17.35 | CE66: 17.52 | CF66: 17.47 | CG66: 14.97 | CH66: 15.1 | CI66: 15.41 | CJ66: 12.08 | CK66: 12.2 | CL66: 11.3 | CM66: 9.21 | CN66: 8.88 | CO66: 9.1 | CP66: 7.54 | CQ66: 7.83 | CR66: 6.51 | CS66: 7.11 | CT66: 8.32 | CU66: 6.85 | CV66: 7.5 | CW66: 8.97 | CX66: 5.83 | CY66: 5.18 | CZ66: 5.02 | DA66: 3.795 | DB66: 3.43 | DC66: 3.87 | DD66: 4.09 | DE66: 4.89 | DF66: 5 | DG66: 6.15 | DH66: 4 | DI66: 4.68 | DJ66: 5.5 | DK66: 7.16 | DL66: 6.48 | DM66: 7.24 | DN66: 8.6 | DO66: 6.3 | DP66: 5.25 | DQ66: 5.48 | DR66: 3.91 | DS66: 4.12 | DT66: 4.03 | DU66: 2.69 | DV66: 2.24
A67: CVE | B67: =A67&" CN Equity" -> CVE CN Equity | C67: Cenovus Energy Inc | D67: -- | E67: -- | F67: 26.87 | G67: 42005 | H67: 45657 | I67: Energy | J67: 19.15 | K67: 17.145 | L67: 17.172 | M67: 18.259 | N67: 16.513 | O67: 16.285 | P67: 15.539 | Q67: 15.547 | R67: 16.648 | S67: 16.023 | T67: 16.294 | U67: 14.521 | V67: 14.321 | W67: 12.845 | X67: 14.065 | Y67: 16.553 | Z67: 16.454 | AA67: 14.912 | AB67: 15.596 | AC67: 15.813 | AD67: 15.755 | AE67: 16.19 | AF67: 17.378 | AG67: 17.025 | AH67: 14.895 | AI67: 14.09 | AJ67: 12.661 | AK67: 11.45 | AL67: 10.137 | AM67: 8.078 | AN67: 8.864 | AO67: 8.256 | AP67: 10.619 | AQ67: 10.628 | AR67: 10.441 | AS67: 9.786 | AT67: 9.999 | AU67: 7.962 | AV67: 9.396 | AW67: 11.015 | AX67: 11.717 | AY67: 11.738 | AZ67: 11.222 | BA67: 10.405 | BB67: 11.2 | BC67: 9.62 | BD67: 8.48 | BE67: 8.33 | BF67: 8.902 | BG67: 10.464 | BH67: 10.108 | BI67: 11.572 | BJ67: 9.655 | BK67: 10.11 | BL67: 10.741 | BM67: 10.172 | BN67: 10.925 | BO67: 9.861 | BP67: 10.318 | BQ67: 11.66 | BR67: 10.176 | BS67: 8.719 | BT67: 2.547 | BU67: 4.529 | BV67: 5.381 | BW67: 5.695 | BX67: 5.345 | BY67: 5.525 | BZ67: 4.655 | CA67: 3.91 | CB67: 5.776 | CC67: 6.951 | CD67: 6.771 | CE67: 8.448 | CF67: 8.48 | CG67: 8.597 | CH67: 9.064 | CI67: 10.67 | CJ67: 9.365 | CK67: 9.419 | CL67: 11.506 | CM67: 13.335 | CN67: 13.741 | CO67: 14.007 | CP67: 16.698 | CQ67: 17.999 | CR67: 18.853 | CS67: 21.485 | CT67: 26.524 | CU67: 22.235 | CV67: 22.153 | CW67: 22.371 | CX67: 19.35 | CY67: 25.113 | CZ67: 24.392 | DA67: 24.056 | DB67: 24.34 | DC67: 23.04 | DD67: 21.688 | DE67: 20.915 | DF67: 19.95 | DG67: 20.824 | DH67: 23.212 | DI67: 24.97 | DJ67: 26.306 | DK67: 24.576 | DL67: 22.39 | DM67: 20.671 | DN67: 20.39 | DO67: 22.141 | DP67: 25.467 | DQ67: 26.625 | DR67: 26.748 | DS67: 25.489 | DT67: 26.323 | DU67: 23.697 | DV67: 21.626 | DW67: 21.406 | DX67: 21.205 | DY67: 21.008
A68: DFY | B68: =A68&" CN Equity" -> DFY CN Equity | C68: Definity Financial Corp | D68: -- | E68: -- | F68: 66.64 | G68: 42005 | H68: 45657 | I68: Financials | CN68: =_xll.BDH(B68, "PX_LAST", "2015-01-01", "2024-12-31", "Period=M", "Orientation=H", "CshAdjNormal = Y","CapChg = Y", "DTS=H","cols=38;rows=1") -> #N/A Requesting Data... | CO68: 27.9999 | CP68: 27.3267 | CQ68: 26.1225 | CR68: 30.3995 | CS68: 31.9133 | CT68: 32.1514 | CU68: 31.7934 | CV68: 35.2623 | CW68: 35.549 | CX68: 37.2145 | CY68: 38.6812 | CZ68: 38.2019 | DA68: 37.0074 | DB68: 34.478 | DC68: 34.5454 | DD68: 34.058 | DE68: 35.3133 | DF68: 35.0526 | DG68: 34.0735 | DH68: 32.1736 | DI68: 36.0414 | DJ68: 36.4856 | DK68: 37.3029 | DL68: 35.97 | DM68: 36.6602 | DN68: 38.2032 | DO68: 44.8145 | DP68: 42.2735 | DQ68: 44.9683 | DR68: 42.3617 | DS68: 44.241 | DT68: 47.2311 | DU68: 49.1786 | DV68: 53.7849 | DW68: 53.0153 | DX68: 57.7514 | DY68: 57.8309
A69: DIR-U | B69: =A69&" CN Equity" -> DIR-U CN Equity | C69: Dream Industrial Real Estate I | D69: -- | E69: -- | F69: 12.86 | G69: 42005 | H69: 45657 | I69: Real Estate | J69: 4.43 | K69: 4.6402 | L69: 4.5102 | M69: 4.5692 | N69: 4.3267 | O69: 4.1783 | P69: 4.0651 | Q69: 4.1838 | R69: 4.1104 | S69: 4.2296 | T69: 4.1974 | U69: 3.8361 | V69: 3.8636 | W69: 4.2562 | X69: 4.3971 | Y69: 4.5438 | Z69: 4.4764 | AA69: 4.8757 | AB69: 4.9638 | AC69: 4.5918 | AD69: 4.4771 | AE69: 4.3618 | AF69: 4.4819 | AG69: 4.9738 | AH69: 5.0192 | AI69: 5.018 | AJ69: 4.893 | AK69: 5.058 | AL69: 5.2372 | AM69: 5.2841 | AN69: 5.4894 | AO69: 5.5679 | AP69: 5.6345 | AQ69: 5.6268 | AR69: 5.5388 | AS69: 5.5566 | AT69: 5.8964 | AU69: 5.9974 | AV69: 6.1312 | AW69: 6.5165 | AX69: 7.0789 | AY69: 6.7528 | AZ69: 6.8305 | BA69: 6.6577 | BB69: 6.7296 | BC69: 6.5492 | BD69: 6.7964 | BE69: 6.4517 | BF69: 7.3657 | BG69: 7.7061 | BH69: 8.2119 | BI69: 7.97 | BJ69: 8.0517 | BK69: 8.2454 | BL69: 8.5165 | BM69: 8.8807 | BN69: 9.3737 | BO69: 9.5643 | BP69: 10.0115 | BQ69: 9.4312 | BR69: 10.0755 | BS69: 9.1559 | BT69: 6.8409 | BU69: 7.4589 | BV69: 7.4874 | BW69: 7.9149 | BX69: 8.1956 | BY69: 8.3733 | BZ69: 8.5136 | CA69: 8.9502 | CB69: 9.6822 | CC69: 10.0383 | CD69: 9.7242 | CE69: 9.922 | CF69: 10.3831 | CG69: 10.5905 | CH69: 10.7916 | CI69: 11.9685 | CJ69: 12.6174 | CK69: 13.0799 | CL69: 12.8254 | CM69: 13.4659 | CN69: 12.9551 | CO69: 13.7757 | CP69: 12.6634 | CQ69: 13.5698 | CR69: 13.0522 | CS69: 12.1433 | CT69: 11.5821 | CU69: 9.8939 | CV69: 10.386 | CW69: 10.0883 | CX69: 8.9224 | CY69: 9.153 | CZ69: 10.1558 | DA69: 9.8698 | DB69: 11.8704 | DC69: 12.5555 | DD69: 12.5643 | DE69: 12.735 | DF69: 11.9269 | DG69: 12.2116 | DH69: 12.3317 | DI69: 12.0346 | DJ69: 11.2566 | DK69: 10.3176 | DL69: 11.0569 | DM69: 12.4007 | DN69: 11.9801 | DO69: 11.3962 | DP69: 11.8719 | DQ69: 11.2309 | DR69: 11.1575 | DS69: 11.5746 | DT69: 12.3669 | DU69: 12.5677 | DV69: 13.3587 | DW69: 12.2833 | DX69: 11.8642 | DY69: 11.079
A70: DML | B70: =A70&" CN Equity" -> DML CN Equity | C70: Denison Mines Corp | D70: -- | E70: -- | F70: 5.38 | G70: 42005 | H70: 45657 | I70: Energy | J70: 1.09 | K70: 1.12 | L70: 1.01 | M70: 1.07 | N70: 1.05 | O70: 0.9 | P70: 0.68 | Q70: 0.64 | R70: 0.5 | S70: 0.53 | T70: 0.52 | U70: 0.7 | V70: 0.64 | W70: 0.62 | X70: 0.73 | Y70: 0.76 | Z70: 0.63 | AA70: 0.71 | AB70: 0.7 | AC70: 0.65 | AD70: 0.61 | AE70: 0.54 | AF70: 0.57 | AG70: 0.7 | AH70: 0.97 | AI70: 0.86 | AJ70: 0.82 | AK70: 0.7 | AL70: 0.6 | AM70: 0.56 | AN70: 0.65 | AO70: 0.61 | AP70: 0.58 | AQ70: 0.53 | AR70: 0.63 | AS70: 0.69 | AT70: 0.63 | AU70: 0.59 | AV70: 0.58 | AW70: 0.59 | AX70: 0.59 | AY70: 0.64 | AZ70: 0.67 | BA70: 0.68 | BB70: 0.85 | BC70: 0.83 | BD70: 0.77 | BE70: 0.63 | BF70: 0.66 | BG70: 0.71 | BH70: 0.68 | BI70: 0.73 | BJ70: 0.72 | BK70: 0.7 | BL70: 0.62 | BM70: 0.61 | BN70: 0.64 | BO70: 0.61 | BP70: 0.57 | BQ70: 0.54 | BR70: 0.46 | BS70: 0.5 | BT70: 0.37 | BU70: 0.6 | BV70: 0.58 | BW70: 0.48 | BX70: 0.62 | BY70: 0.7 | BZ70: 0.56 | CA70: 0.47 | CB70: 0.47 | CC70: 0.84 | CD70: 0.85 | CE70: 1.36 | CF70: 1.37 | CG70: 1.32 | CH70: 1.56 | CI70: 1.51 | CJ70: 1.38 | CK70: 1.61 | CL70: 1.84 | CM70: 2.1 | CN70: 2.05 | CO70: 1.74 | CP70: 1.54 | CQ70: 1.88 | CR70: 2.04 | CS70: 1.66 | CT70: 1.58 | CU70: 1.27 | CV70: 1.53 | CW70: 1.86 | CX70: 1.61 | CY70: 1.72 | CZ70: 1.66 | DA70: 1.55 | DB70: 1.89 | DC70: 1.72 | DD70: 1.47 | DE70: 1.49 | DF70: 1.46 | DG70: 1.66 | DH70: 1.72 | DI70: 1.9 | DJ70: 2.23 | DK70: 2.22 | DL70: 2.48 | DM70: 2.32 | DN70: 2.7 | DO70: 2.43 | DP70: 2.65 | DQ70: 2.74 | DR70: 3.29 | DS70: 2.74 | DT70: 2.7 | DU70: 2.23 | DV70: 2.46 | DW70: 2.93 | DX70: 3.37 | DY70: 2.61
A71: DOL | B71: =A71&" CN Equity" -> DOL CN Equity | C71: Dollarama Inc | D71: -- | E71: -- | F71: 183.5 | G71: 42005 | H71: 45657 | I71: Consumer Discretionary | J71: 19.36 | K71: 20.0583 | L71: 22.7147 | M71: 22.2558 | N71: 22.1273 | O71: 24.3182 | P71: 25.0387 | Q71: 24.1606 | R71: 29.0179 | S71: 28.4384 | T71: 28.7507 | U71: 25.7372 | V71: 24.2291 | W71: 25.3863 | X71: 29.4572 | Y71: 29.1897 | Z71: 29.138 | AA71: 29.1058 | AB71: 31.1858 | AC71: 31.3021 | AD71: 33.1208 | AE71: 32.4094 | AF71: 32.3059 | AG71: 31.8112 | AH71: 31.8984 | AI71: 33.1058 | AJ71: 35.6725 | AK71: 38.7156 | AL71: 40.5396 | AM71: 40.1443 | AN71: 39.5186 | AO71: 39.9077 | AP71: 44.2724 | AQ71: 46.6056 | AR71: 51.1815 | AS71: 50.9673 | AT71: 54.6179 | AU71: 48.5027 | AV71: 50.8507 | AW71: 48.038 | AX71: 48.6393 | AY71: 49.6891 | AZ71: 45.8642 | BA71: 48.1574 | BB71: 39.7067 | BC71: 35.8003 | BD71: 34.3058 | BE71: 31.7172 | BF71: 34.5897 | BG71: 34.8341 | BH71: 34.8635 | BI71: 39.397 | BJ71: 41.7956 | BK71: 45.1048 | BL71: 47.9184 | BM71: 49.9272 | BN71: 46.4779 | BO71: 43.4606 | BP71: 47.6585 | BQ71: 43.7744 | BR71: 44.2683 | BS71: 38.7409 | BT71: 38.3286 | BU71: 42.9085 | BV71: 45.8765 | BW71: 44.3827 | BX71: 48.1827 | BY71: 50.0912 | BZ71: 50.2092 | CA71: 45.171 | CB71: 52.3385 | CC71: 51.0783 | CD71: 49.2612 | CE71: 47.7239 | CF71: 54.7106 | CG71: 56.4948 | CH71: 51.7803 | CI71: 55.9622 | CJ71: 57.9956 | CK71: 56.7912 | CL71: 54.2345 | CM71: 55.2727 | CN71: 54.5217 | CO71: 62.5547 | CP71: 64.86 | CQ71: 64.771 | CR71: 70.1109 | CS71: 70.6789 | CT71: 72.5988 | CU71: 73.3509 | CV71: 76.8618 | CW71: 79.2089 | CX71: 78.5355 | CY71: 80.2227 | CZ71: 81.5903 | DA71: 78.4785 | DB71: 78.9096 | DC71: 78.1658 | DD71: 80.0997 | DE71: 83.2955 | DF71: 81.9655 | DG71: 89.0523 | DH71: 86.2819 | DI71: 87.0269 | DJ71: 92.9571 | DK71: 94.1408 | DL71: 97.9681 | DM71: 94.9262 | DN71: 98.1607 | DO71: 104.4382 | DP71: 102.6574 | DQ71: 114.34 | DR71: 128.4384 | DS71: 124.3662 | DT71: 128.9596 | DU71: 136.0039 | DV71: 138.0365 | DW71: 144.4598 | DX71: 145.4069 | DY71: 139.8634
A72: DOO | B72: =A72&" CN Equity" -> DOO CN Equity | C72: BRP Inc | D72: -- | E72: -- | F72: 102.77 | G72: 42005 | H72: 45657 | I72: Consumer Discretionary | J72: 20.54 | K72: 21.6727 | L72: 22.7418 | M72: 25.1051 | N72: 25.7803 | O72: 27.3745 | P72: 26.3992 | Q72: 25.4896 | R72: 23.7452 | S72: 22.0759 | T72: 20.4911 | U72: 18.6436 | V72: 14.5547 | W72: 15.455 | X72: 18.2216 | Y72: 18.7092 | Z72: 18.8968 | AA72: 19.3844 | AB72: 19.8815 | AC72: 22.8543 | AD72: 24.0735 | AE72: 24.3173 | AF72: 22.0478 | AG72: 26.5868 | AH72: 24.6549 | AI72: 24.4111 | AJ72: 29.3533 | AK72: 30.263 | AL72: 30.8163 | AM72: 35.7005 | AN72: 37.5423 | AO72: 38.9989 | AP72: 38.0006 | AQ72: 40.8252 | AR72: 44.4125 | AS72: 43.8661 | AT72: 47.9688 | AU72: 42.4325 | AV72: 46.7543 | AW72: 49.0788 | AX72: 57.0727 | AY72: 59.9736 | AZ72: 57.4187 | BA72: 64.4589 | BB72: 57.4183 | BC72: 50.1877 | BD72: 44.8619 | BE72: 33.581 | BF72: 35.9375 | BG72: 37.4389 | BH72: 35.3318 | BI72: 39.6768 | BJ72: 38.5334 | BK72: 44.6893 | BL72: 44.3933 | BM72: 45.5869 | BN72: 49.3213 | BO72: 56.5353 | BP72: 62.209 | BQ72: 56.6962 | BR72: 64.7464 | BS72: 52.7382 | BT72: 22.0038 | BU72: 39.925 | BV72: 45.6943 | BW72: 55.4887 | BX72: 57.5012 | BY72: 67.8898 | BZ72: 67.4202 | CA72: 68.9631 | CB72: 71.0044 | CC72: 80.6942 | CD72: 80.7709 | CE72: 88.2368 | CF72: 104.5694 | CG72: 108.4893 | CH72: 97.0947 | CI72: 93.3196 | CJ72: 100.5639 | CK72: 101.6991 | CL72: 112.9095 | CM72: 104.8005 | CN72: 97.2309 | CO72: 106.8325 | CP72: 101.8669 | CQ72: 87.5872 | CR72: 98.6947 | CS72: 100.5006 | CT72: 94.9478 | CU72: 76.6506 | CV72: 94.2409 | CW72: 88.1356 | CX72: 82.4849 | CY72: 88.3012 | CZ72: 97.5782 | DA72: 100.2261 | DB72: 107.7992 | DC72: 114.7897 | DD72: 102.8595 | DE72: 98.4441 | DF72: 93.8632 | DG72: 109.1026 | DH72: 118.1823 | DI72: 100.6659 | DJ72: 100.3444 | DK72: 91.4821 | DL72: 81.7903 | DM72: 92.7205 | DN72: 82.9615 | DO72: 87.5965 | DP72: 88.9362 | DQ72: 90.7651 | DR72: 83.4545 | DS72: 86.1028 | DT72: 98.2643 | DU72: 96.0147 | DV72: 79.2733 | DW72: 67.6123 | DX72: 67.3562 | DY72: 72.3136
A73: DPM | B73: =A73&" CN Equity" -> DPM CN Equity | C73: DPM Metals Inc | D73: -- | E73: -- | F73: 47.51 | G73: 42005 | H73: 45657 | I73: Materials | J73: 3.17 | K73: 2.6411 | L73: 2.4106 | M73: 2.579 | N73: 2.3131 | O73: 2.2511 | P73: 1.808 | Q73: 2.0295 | R73: 1.9321 | S73: 1.5332 | T73: 1.161 | U73: 1.1344 | V73: 0.9483 | W73: 0.9838 | X73: 1.8612 | Y73: 2.4727 | Z73: 2.2157 | AA73: 2.7297 | AB73: 3.483 | AC73: 2.774 | AD73: 2.8715 | AE73: 2.4284 | AF73: 1.8168 | AG73: 1.9941 | AH73: 2.6056 | AI73: 2.6677 | AJ73: 2.4993 | AK73: 2.4195 | AL73: 2.003 | AM73: 2.1448 | AN73: 2.3309 | AO73: 2.5613 | AP73: 2.3752 | AQ73: 2.2866 | AR73: 2.6233 | AS73: 2.6588 | AT73: 2.6056 | AU73: 2.712 | AV73: 2.7297 | AW73: 2.8892 | AX73: 3.0133 | AY73: 2.7829 | AZ73: 2.7386 | BA73: 2.5259 | BB73: 2.6942 | BC73: 3.0487 | BD73: 3.031 | BE73: 3.1905 | BF73: 3.7666 | BG73: 4.1477 | BH73: 3.9261 | BI73: 3.7312 | BJ73: 3.3146 | BK73: 4.325 | BL73: 3.9527 | BM73: 4.6529 | BN73: 3.9527 | BO73: 4.068 | BP73: 4.4934 | BQ73: 4.9454 | BR73: 5.4151 | BS73: 4.6529 | BT73: 3.9595 | BU73: 5.7877 | BV73: 6.6795 | BW73: 7.9974 | BX73: 8.9994 | BY73: 8.4447 | BZ73: 8.5593 | CA73: 7.9312 | CB73: 7.6262 | CC73: 8.2441 | CD73: 7.3251 | CE73: 7.1269 | CF73: 6.945 | CG73: 8.0134 | CH73: 7.7961 | CI73: 6.8342 | CJ73: 6.8706 | CK73: 7.0708 | CL73: 6.9678 | CM73: 7.4433 | CN73: 7.4341 | CO73: 7.1867 | CP73: 6.8651 | CQ73: 6.8926 | CR73: 6.9015 | CS73: 6.883 | CT73: 6.9293 | CU73: 5.9759 | CV73: 5.7708 | CW73: 5.5751 | CX73: 5.7824 | CY73: 5.8201 | CZ73: 5.9802 | DA73: 6.1819 | DB73: 8.252 | DC73: 8.3185 | DD73: 9.3858 | DE73: 9.4908 | DF73: 8.9275 | DG73: 8.4063 | DH73: 8.8098 | DI73: 8.3775 | DJ73: 8.1234 | DK73: 8.7907 | DL73: 9.6901 | DM73: 8.2502 | DN73: 8.3767 | DO73: 8.9312 | DP73: 10.0752 | DQ73: 10.1925 | DR73: 11.0044 | DS73: 10.5301 | DT73: 11.474 | DU73: 12.9095 | DV73: 13.5213 | DW73: 13.9753 | DX73: 12.9488 | DY73: 12.927
A74: DSG | B74: =A74&" CN Equity" -> DSG CN Equity | C74: Descartes Systems Group Inc/Th | D74: -- | E74: -- | F74: 101.69 | G74: 42005 | H74: 45657 | I74: Information Technology | J74: 19.41 | K74: 18.94 | L74: 19.1 | M74: 18.13 | N74: 18.92 | O74: 20.05 | P74: 22.06 | Q74: 22.76 | R74: 23.64 | S74: 22.88 | T74: 26.67 | U74: 27.84 | V74: 24.94 | W74: 23.17 | X74: 25.28 | Y74: 23.13 | Z74: 27.34 | AA74: 24.71 | AB74: 26.33 | AC74: 27.96 | AD74: 28.23 | AE74: 27.95 | AF74: 29.83 | AG74: 28.63 | AH74: 28.41 | AI74: 27.86 | AJ74: 30.47 | AK74: 31.5 | AL74: 33.78 | AM74: 31.55 | AN74: 31.28 | AO74: 35.06 | AP74: 34.03 | AQ74: 37.4 | AR74: 35.81 | AS74: 35.74 | AT74: 34.8 | AU74: 34 | AV74: 36.82 | AW74: 37.95 | AX74: 38.69 | AY74: 42.83 | AZ74: 41.58 | BA74: 45.56 | BB74: 43.81 | BC74: 40.28 | BD74: 39.13 | BE74: 36.03 | BF74: 40.84 | BG74: 45.45 | BH74: 48.58 | BI74: 53.5 | BJ74: 54.21 | BK74: 48.45 | BL74: 47.95 | BM74: 47.22 | BN74: 53.48 | BO74: 51.25 | BP74: 57.03 | BQ74: 55.5 | BR74: 59.33 | BS74: 55.73 | BT74: 48.41 | BU74: 58.51 | BV74: 65.64 | BW74: 71.67 | BX74: 75.41 | BY74: 79.59 | BZ74: 75.85 | CA74: 71.44 | CB74: 77.01 | CC74: 74.45 | CD74: 77.98 | CE74: 74.51 | CF74: 76.67 | CG74: 78.63 | CH74: 70.65 | CI74: 85.73 | CJ74: 90.49 | CK74: 98.91 | CL74: 103.1 | CM74: 101.07 | CN74: 102.71 | CO74: 104.62 | CP74: 92.48 | CQ74: 90.32 | CR74: 91.5 | CS74: 79.79 | CT74: 75.05 | CU74: 79.99 | CV74: 88.46 | CW74: 92.52 | CX74: 87.71 | CY74: 94 | CZ74: 93.39 | DA74: 94.39 | DB74: 97.1 | DC74: 100.64 | DD74: 109.08 | DE74: 107.36 | DF74: 104.96 | DG74: 106.12 | DH74: 102.85 | DI74: 101.31 | DJ74: 99.69 | DK74: 100.23 | DL74: 110.22 | DM74: 111.33 | DN74: 117.72 | DO74: 117.63 | DP74: 123.9 | DQ74: 127.7 | DR74: 125.86 | DS74: 132.55 | DT74: 140.42 | DU74: 135.81 | DV74: 139.17 | DW74: 144.65 | DX74: 165.1 | DY74: 163.4
A75: DSV | B75: =A75&" CN Equity" -> DSV CN Equity | C75: Discovery Silver Corp | D75: -- | E75: -- | F75: 9.58 | G75: 42005 | H75: 45657 | I75: Materials | J75: 0.06 | K75: 0.06 | L75: 0.05 | M75: 0.05 | N75: 0.05 | O75: 0.05 | P75: 0.01 | Q75: 0.01 | R75: 0.075 | S75: 0.4 | T75: 0.45 | U75: 0.45 | V75: 0.45 | W75: 0.5 | X75: 0.65 | Y75: 0.6 | Z75: 0.6 | AA75: 0.9 | AB75: 0.81 | AC75: 0.72 | AD75: 0.5 | AE75: 0.5 | AF75: 0.46 | AG75: 0.335 | AH75: 0.35 | AI75: 0.3 | AJ75: 0.4 | AK75: 0.35 | AL75: 0.33 | AM75: 0.305 | AN75: 0.3 | AO75: 0.27 | AP75: 0.19 | AQ75: 0.19 | AR75: 0.2 | AS75: 0.2 | AT75: 0.25 | AU75: 0.22 | AV75: 0.22 | AW75: 0.225 | AX75: 0.44 | AY75: 0.57 | AZ75: 0.445 | BA75: 0.47 | BB75: 0.42 | BC75: 0.66 | BD75: 0.68 | BE75: 0.43 | BF75: 0.34 | BG75: 0.46 | BH75: 0.76 | BI75: 1.02 | BJ75: 1.77 | BK75: 2.26 | BL75: 1.79 | BM75: 1.52 | BN75: 1.73 | BO75: 1.96 | BP75: 1.88 | BQ75: 2.33 | BR75: 2.2 | BS75: 2.22 | BT75: 2.52 | BU75: 2.12 | BV75: 1.89 | BW75: 1.74 | BX75: 1.23 | BY75: 1.77 | BZ75: 1.89 | CA75: 2.07 | CB75: 1.75 | CC75: 1.8 | CD75: 1.83 | CE75: 1.52 | CF75: 1.32 | CG75: 1.13 | CH75: 1.19 | CI75: 1.07 | CJ75: 0.94 | CK75: 1.02 | CL75: 1.19 | CM75: 1.36 | CN75: 1.33 | CO75: 1.17 | CP75: 1.31 | CQ75: 1.06 | CR75: 0.98 | CS75: 0.83 | CT75: 0.82 | CU75: 0.85 | CV75: 0.68 | CW75: 0.63 | CX75: 0.89 | CY75: 0.76 | CZ75: 0.62 | DA75: 0.61 | DB75: 0.71 | DC75: 0.86 | DD75: 1.08 | DE75: 0.88 | DF75: 0.98 | DG75: 0.6 | DH75: 0.69 | DI75: 0.95 | DJ75: 0.87 | DK75: 0.71
A76: EDR | B76: =A76&" CN Equity" -> EDR CN Equity | C76: Endeavour Silver Corp | D76: -- | E76: -- | F76: 14.86 | G76: 42005 | H76: 45657 | I76: Materials | J76: 3.49 | K76: 2.97 | L76: 2.39 | M76: 2.45 | N76: 2.49 | O76: 2.51 | P76: 1.81 | Q76: 2.22 | R76: 2.06 | S76: 2.16 | T76: 1.9 | U76: 1.98 | V76: 1.74 | W76: 2.27 | X76: 3.19 | Y76: 5.21 | Z76: 4.08 | AA76: 5.08 | AB76: 6.32 | AC76: 5.66 | AD76: 6.72 | AE76: 5.89 | AF76: 5.12 | AG76: 4.75 | AH76: 5.51 | AI76: 5.75 | AJ76: 4.23 | AK76: 4.18 | AL76: 3.93 | AM76: 3.95 | AN76: 3.78 | AO76: 3.09 | AP76: 2.97 | AQ76: 2.67 | AR76: 2.75 | AS76: 3.02 | AT76: 2.94 | AU76: 2.83 | AV76: 3.13 | AW76: 3.86 | AX76: 3.63 | AY76: 4.13 | AZ76: 3.82 | BA76: 2.91 | BB76: 2.97 | BC76: 2.65 | BD76: 2.47 | BE76: 2.94 | BF76: 2.92 | BG76: 3.41 | BH76: 3.37 | BI76: 2.92 | BJ76: 2.4 | BK76: 2.7 | BL76: 3.04 | BM76: 3.51 | BN76: 2.96 | BO76: 3.27 | BP76: 2.91 | BQ76: 3.13 | BR76: 2.81 | BS76: 2.14 | BT76: 1.89 | BU76: 2.26 | BV76: 2.67 | BW76: 3.08 | BX76: 5.83 | BY76: 5.45 | BZ76: 4.68 | CA76: 4.22 | CB76: 4.43 | CC76: 6.43 | CD76: 6.34 | CE76: 7.5 | CF76: 6.22 | CG76: 6.48 | CH76: 9.1 | CI76: 7.59 | CJ76: 6.58 | CK76: 5.93 | CL76: 5.19 | CM76: 6.24 | CN76: 6.07 | CO76: 5.35 | CP76: 4.61 | CQ76: 5.35 | CR76: 5.8 | CS76: 4.9 | CT76: 4.41 | CU76: 4.04 | CV76: 4.68 | CW76: 3.81 | CX76: 4.16 | CY76: 4.64 | CZ76: 4.55 | DA76: 4.38 | DB76: 4.63 | DC76: 4 | DD76: 5.22 | DE76: 5.28 | DF76: 4.29 | DG76: 3.85 | DH76: 4.66 | DI76: 3.85 | DJ76: 3.32 | DK76: 2.98 | DL76: 2.98 | DM76: 2.6 | DN76: 2.04 | DO76: 1.96 | DP76: 3.26 | DQ76: 3.62 | DR76: 5.43 | DS76: 4.81 | DT76: 6.22 | DU76: 4.14 | DV76: 5.34 | DW76: 7.05 | DX76: 5.86 | DY76: 5.27
